Workbook
Name _xlfn_IFERROR: none
Name _xlfn_QUARTILE_INC: none
Name Excel_BuiltIn_Print_Area: DCF!$A$1:$O$66,#REF!
Name TrialPrice: 'Monte Carlo'!$BF$27:$BF$526

Sheet DCF
B1: A DCF does not tell you the “true” value of a company. It tells you what the company could be worth if your assumptions about future cash flows are reasonably correct. The basic logic of DCF is straightforward: A company is worth the cash it can generate in the future. Those future cash flows are uncertain, so we estimate cash flows on the basis of ASSUMPTIONS and discount those cash flows back to present value to find intrinsic value. DCF is not about intrinsic value it is about margin of error around intrinsic value. Thus we perform scenario and sensitivity analysis.
A2: Granules India Limited: Discounted Cash Flow Analysis
A3: (Rs. in crore, fiscal year ending March 31) | M3: =B4 -> Operating Scenario | O3: =+CHOOSE(D4,'A1'!B10,'A1'!B11,'A1'!B12,'A1'!B13,'A1'!B14) -> Base
B4: Operating Scenario | D4: 1
B5: Mid-Year Convention | D5: N | E5: Historical Period | I5: CAGR | J5: Projection Period | O5: CAGR
E6: 2023 | F6: 2024 | G6: 2025 | H6: 2026 | I6: ('23 - '26) | J6: 2027 | K6: 2028 | L6: 2029 | M6: 2030 | N6: 2031 | O6: ('26 - '31)
B7: Sales | E7: 4511.92 | F7: 4506.37 | G7: 4481.61 | H7: 5365.64 | I7: =+IF(ISERROR((H7/E7)^(1/($H$6-$E$6))-1),"-",(H7/E7)^(1/($H$6-$E$6))-1) -> 0.059465242 | J7: =H7*(1+J35) -> 6277.7988 | K7: =J7*(1+K35) -> 7219.4686 | L7: =K7*(1+L35) -> 8085.8049 | M7: =L7*(1+M35) -> 8894.3853 | N7: =M7*(1+N35) -> 9694.88 | O7: =+IF(ISERROR((N7/H7)^(1/($N$6-$H$6))-1),"-",(N7/H7)^(1/($N$6-$H$6))-1) -> 0.12560025
B8: % growth | E8: NA | F8: =+IF(ISERROR(F7/E7-1),0,F7/E7-1) -> -0.001230075 | G8: =+IF(ISERROR(G7/F7-1),0,G7/F7-1) -> -0.0054944445 | H8: =+IF(ISERROR(H7/G7-1),0,H7/G7-1) -> 0.19725724 | J8: =+IF(ISERROR(J7/H7-1),0,J7/H7-1) -> 0.17 | K8: =+IF(ISERROR(K7/J7-1),0,K7/J7-1) -> 0.15 | L8: =+IF(ISERROR(L7/K7-1),0,L7/K7-1) -> 0.12 | M8: =+IF(ISERROR(M7/L7-1),0,M7/L7-1) -> 0.1 | N8: =+IF(ISERROR(N7/M7-1),0,N7/M7-1) -> 0.09
B9: COGS | E9: 2307.28 | F9: 2021.25 | G9: 1725.7 | H9: 1875.7 | J9: =J7*J36 -> 2165.8406 | K9: =K7*K36 -> 2454.6193 | L9: =L7*L36 -> 2708.7446 | M9: =M7*M36 -> 2935.1472 | N9: =N7*N36 -> 3179.9206
B10: Gross Profit | E10: =+E7-E9 -> 2204.64 | F10: =+F7-F9 -> 2485.12 | G10: =+G7-G9 -> 2755.91 | H10: =+H7-H9 -> 3489.94 | I10: =+IF(ISERROR((H10/E10)^(1/($H$6-$E$6))-1),"-",(H10/E10)^(1/($H$6-$E$6))-1) -> 0.16544941 | J10: =+J7-J9 -> 4111.9582 | K10: =+K7-K9 -> 4764.8493 | L10: =+L7-L9 -> 5377.0602 | M10: =+M7-M9 -> 5959.2382 | N10: =+N7-N9 -> 6514.9594 | O10: =+IF(ISERROR((N10/H10)^(1/($N$6-$H$6))-1),"-",(N10/H10)^(1/($N$6-$H$6))-1) -> 0.13297089
B11: % margin | E11: =+IF(ISERROR(E10/E7),0,E10/E7) -> 0.48862568 | F11: =+IF(ISERROR(F10/F7),0,F10/F7) -> 0.55146825 | G11: =+IF(ISERROR(G10/G7),0,G10/G7) -> 0.61493749 | H11: =+IF(ISERROR(H10/H7),0,H10/H7) -> 0.65042381 | J11: =+IF(ISERROR(J10/J7),0,J10/J7) -> 0.655 | K11: =+IF(ISERROR(K10/K7),0,K10/K7) -> 0.66 | L11: =+IF(ISERROR(L10/L7),0,L10/L7) -> 0.665 | M11: =+IF(ISERROR(M10/M7),0,M10/M7) -> 0.67 | N11: =+IF(ISERROR(N10/N7),0,N10/N7) -> 0.672
B12: SG&A | E12: 1290.81 | F12: 1629.14 | G12: 1810.67 | H12: 2304.8 | J12: =J7*J37 -> 2699.4535 | K12: =K7*K37 -> 3104.3715 | L12: =L7*L37 -> 3436.4671 | M12: =M7*M37 -> 3735.6418 | N12: =N7*N37 -> 4042.765
B13: EBITDA | E13: =E10-E12 -> 913.83 | F13: =F10-F12 -> 855.98 | G13: =G10-G12 -> 945.24 | H13: =H10-H12 -> 1185.14 | I13: =+IF(ISERROR((H13/E13)^(1/($H$6-$E$6))-1),"-",(H13/E13)^(1/($H$6-$E$6))-1) -> 0.090522796 | J13: =J10-J12 -> 1412.5047 | K13: =K10-K12 -> 1660.4778 | L13: =L10-L12 -> 1940.5932 | M13: =M10-M12 -> 2223.5963 | N13: =N10-N12 -> 2472.1944 | O13: =+IF(ISERROR((N13/H13)^(1/($N$6-$H$6))-1),"-",(N13/H13)^(1/($N$6-$H$6))-1) -> 0.15841079
B14: % margin | E14: =+IF(ISERROR(E13/E7),0,E13/E7) -> 0.20253684 | F14: =+IF(ISERROR(F13/F7),0,F13/F7) -> 0.18994889 | G14: =+IF(ISERROR(G13/G7),0,G13/G7) -> 0.21091527 | H14: =+IF(ISERROR(H13/H7),0,H13/H7) -> 0.22087579 | J14: =+IF(ISERROR(J13/J7),0,J13/J7) -> 0.225 | K14: =+IF(ISERROR(K13/K7),0,K13/K7) -> 0.23 | L14: =+IF(ISERROR(L13/L7),0,L13/L7) -> 0.24 | M14: =+IF(ISERROR(M13/M7),0,M13/M7) -> 0.25 | N14: =+IF(ISERROR(N13/N7),0,N13/N7) -> 0.255
B15: Depreciation & Amortization | E15: 184.49 | F15: 207.33 | G15: 225.5 | H15: 296.14 | J15: =J7*J38 -> 351.55673 | K15: =K7*K38 -> 397.07077 | L15: =L7*L38 -> 428.54766 | M15: =M7*M38 -> 444.71927 | N15: =N7*N38 -> 465.35424
B16: EBIT | E16: =+E13-E15 -> 729.34 | F16: =+F13-F15 -> 648.65 | G16: =+G13-G15 -> 719.74 | H16: =+H13-H15 -> 889 | I16: =+IF(ISERROR((H16/E16)^(1/($H$6-$E$6))-1),"-",(H16/E16)^(1/($H$6-$E$6))-1) -> 0.068211484 | J16: =+J13-J15 -> 1060.948 | K16: =+K13-K15 -> 1263.407 | L16: =+L13-L15 -> 1512.0455 | M16: =+M13-M15 -> 1778.8771 | N16: =+N13-N15 -> 2006.8402 | O16: =+IF(ISERROR((N16/H16)^(1/($N$6-$H$6))-1),"-",(N16/H16)^(1/($N$6-$H$6))-1) -> 0.17685296
B17: % margin | E17: =+IF(ISERROR(E16/E7),0,E16/E7) -> 0.16164737 | F17: =+IF(ISERROR(F16/F7),0,F16/F7) -> 0.14394069 | G17: =+IF(ISERROR(G16/G7),0,G16/G7) -> 0.16059853 | H17: =+IF(ISERROR(H16/H7),0,H16/H7) -> 0.16568387 | J17: =+IF(ISERROR(J16/J7),0,J16/J7) -> 0.169 | K17: =+IF(ISERROR(K16/K7),0,K16/K7) -> 0.175 | L17: =+IF(ISERROR(L16/L7),0,L16/L7) -> 0.187 | M17: =+IF(ISERROR(M16/M7),0,M16/M7) -> 0.2 | N17: =+IF(ISERROR(N16/N7),0,N16/N7) -> 0.207
B18: Taxes | E18: =+E16*E40 -> 181.02219 | F18: =+F16*F40 -> 168.25981 | G18: =+G16*G40 -> 172.95352 | H18: =+H16*H40 -> 215.138 | J18: =+J16*J40 -> 256.74942 | K18: =+K16*K40 -> 305.7445 | L18: =+L16*L40 -> 365.91501 | M18: =+M16*M40 -> 430.48825 | N18: =+N16*N40 -> 485.65532
B19: EBIAT | E19: =+E16-E18 -> 548.31781 | F19: =+F16-F18 -> 480.39019 | G19: =+G16-G18 -> 546.78648 | H19: =+H16-H18 -> 673.862 | I19: =+IF(ISERROR((H19/E19)^(1/($H$6-$E$6))-1),"-",(H19/E19)^(1/($H$6-$E$6))-1) -> 0.071139917 | J19: =+J16-J18 -> 804.19858 | K19: =+K16-K18 -> 957.66251 | L19: =+L16-L18 -> 1146.1305 | M19: =+M16-M18 -> 1348.3888 | N19: =+N16-N18 -> 1521.1848 | O19: =+IF(ISERROR((N19/H19)^(1/($N$6-$H$6))-1),"-",(N19/H19)^(1/($N$6-$H$6))-1) -> 0.17685296
B21: Plus: Depreciation & Amortization | E21: =E15 -> 184.49 | F21: =F15 -> 207.33 | G21: =G15 -> 225.5 | H21: =H15 -> 296.14 | J21: =J15 -> 351.55673 | K21: =K15 -> 397.07077 | L21: =L15 -> 428.54766 | M21: =M15 -> 444.71927 | N21: =N15 -> 465.35424
B22: Less: Capital Expenditures | E22: -410.68 | F22: -380.58 | G22: -571.69 | H22: -558.21 | J22: =-(J7*J39) -> -596.39089 | K22: =-(K7*K39) -> -649.75218 | L22: =-(L7*L39) -> -646.86439 | M22: =-(M7*M39) -> -622.60697 | N22: =-(N7*N39) -> -630.1672
B23: Less: Increase in Net Working Capital | F23: =NWC!D25 -> -333.51 | G23: =NWC!E25 -> 99.24 | H23: =NWC!F25 -> -280.51 | J23: =NWC!H25 -> -275.24411 | K23: =NWC!I25 -> -197.30348 | L23: =NWC!J25 -> -88.935942 | M23: =NWC!K25 -> -54.850556 | N23: =NWC!L25 -> -41.899622
B25: Unlevered Free Cash Flow | F25: =+F19+SUM(F21:F23) -> -26.36981 | G25: =+G19+SUM(G21:G23) -> 299.83648 | H25: =+H19+SUM(H21:H23) -> 131.282 | J25: =+J19+SUM(J21:J23) -> 284.12031 | K25: =+K19+SUM(K21:K23) -> 507.67763 | L25: =+L19+SUM(L21:L23) -> 838.87782 | M25: =+M19+SUM(M21:M23) -> 1115.6506 | N25: =+N19+SUM(N21:N23) -> 1314.4723
B26: WACC | E26: =WACC!D26 -> 0.10254788
B27: Discount Period | J27: =IF($D$5="Y",J6-$H$6-0.5,J6-$H$6) -> 1 | K27: =IF($D$5="Y",K6-$H$6-0.5,K6-$H$6) -> 2 | L27: =IF($D$5="Y",L6-$H$6-0.5,L6-$H$6) -> 3 | M27: =IF($D$5="Y",M6-$H$6-0.5,M6-$H$6) -> 4 | N27: =IF($D$5="Y",N6-$H$6-0.5,N6-$H$6) -> 5
B28: Discount Factor | J28: =1/((1+$E$26)^(J27)) -> 0.90699009 | K28: =1/((1+$E$26)^(K27)) -> 0.82263102 | L28: =1/((1+$E$26)^(L27)) -> 0.74611818 | M28: =1/((1+$E$26)^(M27)) -> 0.6767218 | N28: =1/((1+$E$26)^(N27)) -> 0.61377996
B29: Present Value of Free Cash Flow | J29: =+J25*J28 -> 257.69431 | K29: =+K25*K28 -> 417.63137 | L29: =+L25*L28 -> 625.902 | M29: =+M25*M28 -> 754.98505 | N29: =+N25*N28 -> 806.79674
B34: Assumptions
B35: Sales (% growth) | E35: NA | F35: =+IF(ISERROR(F7/E7-1),0,F7/E7-1) -> -0.001230075 | G35: =+IF(ISERROR(G7/F7-1),0,G7/F7-1) -> -0.0054944445 | H35: =+IF(ISERROR(H7/G7-1),0,H7/G7-1) -> 0.19725724 | J35: ='A1'!F9 -> 0.17 | K35: ='A1'!G9 -> 0.15 | L35: ='A1'!H9 -> 0.12 | M35: ='A1'!I9 -> 0.1 | N35: ='A1'!J9 -> 0.09
B36: COGS (% sales) | E36: =+IF(ISERROR(E9/E7),0,E9/E7) -> 0.51137432 | F36: =+IF(ISERROR(F9/F7),0,F9/F7) -> 0.44853175 | G36: =+IF(ISERROR(G9/G7),0,G9/G7) -> 0.38506251 | H36: =+IF(ISERROR(H9/H7),0,H9/H7) -> 0.34957619 | J36: ='A1'!F16 -> 0.345 | K36: ='A1'!G16 -> 0.34 | L36: ='A1'!H16 -> 0.335 | M36: ='A1'!I16 -> 0.33 | N36: ='A1'!J16 -> 0.328
B37: SG&A (% sales) | E37: =+IF(ISERROR(E12/E7),0,E12/E7) -> 0.28608885 | F37: =+IF(ISERROR(F12/F7),0,F12/F7) -> 0.36151936 | G37: =+IF(ISERROR(G12/G7),0,G12/G7) -> 0.40402222 | H37: =+IF(ISERROR(H12/H7),0,H12/H7) -> 0.42954801 | J37: ='A1'!F23 -> 0.43 | K37: ='A1'!G23 -> 0.43 | L37: ='A1'!H23 -> 0.425 | M37: ='A1'!I23 -> 0.42 | N37: ='A1'!J23 -> 0.417
B38: Depreciation & Amortization (% sales) | E38: =+IF(ISERROR(E15/E7),0,E15/E7) -> 0.040889466 | F38: =+IF(ISERROR(F15/F7),0,F15/F7) -> 0.046008206 | G38: =+IF(ISERROR(G15/G7),0,G15/G7) -> 0.050316739 | H38: =+IF(ISERROR(H15/H7),0,H15/H7) -> 0.055191925 | J38: ='A1'!F30 -> 0.056 | K38: ='A1'!G30 -> 0.055 | L38: ='A1'!H30 -> 0.053 | M38: ='A1'!I30 -> 0.05 | N38: ='A1'!J30 -> 0.048
B39: Capital Expenditures (% sales) | E39: =+IF(ISERROR(-E22/E7),0,-E22/E7) -> 0.091021117 | F39: =+IF(ISERROR(-F22/F7),0,-F22/F7) -> 0.084453784 | G39: =+IF(ISERROR(-G22/G7),0,-G22/G7) -> 0.12756353 | H39: =+IF(ISERROR(-H22/H7),0,-H22/H7) -> 0.10403419 | J39: ='A1'!F38 -> 0.095 | K39: ='A1'!G38 -> 0.09 | L39: ='A1'!H38 -> 0.08 | M39: ='A1'!I38 -> 0.07 | N39: ='A1'!J38 -> 0.065
B40: Tax Rate | E40: 0.2482 | F40: 0.2594 | G40: 0.2403 | H40: 0.242 | J40: =H40 -> 0.242 | K40: =J40 -> 0.242 | L40: =K40 -> 0.242 | M40: =L40 -> 0.242 | N40: =M40 -> 0.242
B41: Working Capital (% sales) | E41: =NWC!C23 -> 0.28053246 | F41: =NWC!D23 -> 0.35488653 | G41: =NWC!E23 -> 0.33470338 | H41: =NWC!F23 -> 0.33183739 | J41: =NWC!H23 -> 0.32746575 | K41: =NWC!I23 -> 0.31208219 | L41: =NWC!J23 -> 0.28964384 | M41: =NWC!K23 -> 0.26947945 | N41: =NWC!L23 -> 0.25155068
B46: Enterprise Value | G46: Implied Equity Value and Share Price | L46: Implied Perpetuity Growth Rate
B47: Cumulative Present Value of FCF | E47: =+SUM(J29:N29) -> 2863.0095 | G47: Enterprise Value | J47: =+E57 -> 21071.61 | L47: ="Terminal Year Free Cash Flow ("&N6&"E)" -> Terminal Year Free Cash Flow (2031E) | O47: =+N25 -> 1314.4723
G48: Less: Net Financial Obligations (Financial Obligations - Investments) | J48: =1512.04-0.84 -> 1511.2 | L48: WACC | O48: =+E26 -> 0.10254788
B49: Terminal Value | G49: Less: Preferred Securities | J49: 0 | L49: =+B49 -> Terminal Value | O49: =+E52 -> 29666.333
B50: ="Terminal Year EBITDA ("&N6&"E)" -> Terminal Year EBITDA (2031E) | E50: =+N13 -> 2472.1944 | G50: Less: Noncontrolling Interest | J50: 0
B51: Exit Multiple (Industry average or target existing multiple) | E51: 12 | G51: Plus: Cash and Cash Equivalents | J51: 949.06 | L51: Implied Perpetuity Growth Rate | O51: =+IF(ISERROR(IF(D5="Y",((E52*E26)-N25*(1+E26)^0.5)/(E52+N25*(1+E26)^0.5),((O49*O48)-O47)/(O49+O47))),"- %",IF(D5="Y",((E52*E26)-N25*(1+E26)^0.5)/(E52+N25*(1+E26)^0.5),((O49*O48)-O47)/(O49+O47))) -> 0.055768314
B52: Terminal Value | E52: =+E50*E51 -> 29666.333
B53: Discount Factor | E53: =1/((1+$E$26)^(N6-H6)) -> 0.61377996 | G53: Implied Equity Value | J53: =+J47-J48-J49-J50+J51 -> 20509.47
B54: Present Value of Terminal Value | E54: =+E52*E53 -> 18208.601
B55: % of Enterprise Value | E55: =+IF(ISERROR(E54/E57),"- %",E54/E57) -> 0.86412954 | G55: Fully Diluted Shares Outstanding | J55: 24.779692
B57: Enterprise Value | E57: =+E54+E47 -> 21071.61 | G57: Implied Share Price | J57: =J53/J55 -> 827.67252
C59: Enterprise Value | J59: Implied Perpetuity Growth Rate
D60: Exit Multiple | K60: Exit Multiple
C61: =+E57 -> 21071.61 | D61: =+E61-0.5 -> 11 | E61: =+F61-0.5 -> 11.5 | F61: =E51 -> 12 | G61: =+F61+0.5 -> 12.5 | H61: =+G61+0.5 -> 13 | J61: =+O51 -> 0.055768314 | K61: =+L61-0.5 -> 11 | L61: =+M61-0.5 -> 11.5 | M61: =E51 -> 12 | N61: =+M61+0.5 -> 12.5 | O61: =+N61+0.5 -> 13
B62: WACC | C62: =+C63-0.005 -> 0.09254788 | D62: =SUMPRODUCT($J$25:$N$25,(1+$C62)^(-$J$27:$N$27))+($E$50*D$61)*(1+$C62)^(-$N$27) -> 20425.216 | E62: =SUMPRODUCT($J$25:$N$25,(1+$C62)^(-$J$27:$N$27))+($E$50*E$61)*(1+$C62)^(-$N$27) -> 21219.27 | F62: =SUMPRODUCT($J$25:$N$25,(1+$C62)^(-$J$27:$N$27))+($E$50*F$61)*(1+$C62)^(-$N$27) -> 22013.325 | G62: =SUMPRODUCT($J$25:$N$25,(1+$C62)^(-$J$27:$N$27))+($E$50*G$61)*(1+$C62)^(-$N$27) -> 22807.379 | H62: =SUMPRODUCT($J$25:$N$25,(1+$C62)^(-$J$27:$N$27))+($E$50*H$61)*(1+$C62)^(-$N$27) -> 23601.434 | I62: WACC | J62: =+J63-0.005 -> 0.09254788 | K62: =IFERROR(IF($D$5="Y",((($E$50*K$61)*$J62)-$N$25*(1+$J62)^0.5)/(($E$50*K$61)+$N$25*(1+$J62)^0.5),((($E$50*K$61)*$J62)-$N$25)/(($E$50*K$61)+$N$25)),"- %") -> 0.042172788 | L62: =IFERROR(IF($D$5="Y",((($E$50*L$61)*$J62)-$N$25*(1+$J62)^0.5)/(($E$50*L$61)+$N$25*(1+$J62)^0.5),((($E$50*L$61)*$J62)-$N$25)/(($E$50*L$61)+$N$25)),"- %") -> 0.04426622 | M62: =IFERROR(IF($D$5="Y",((($E$50*M$61)*$J62)-$N$25*(1+$J62)^0.5)/(($E$50*M$61)+$N$25*(1+$J62)^0.5),((($E$50*M$61)*$J62)-$N$25)/(($E$50*M$61)+$N$25)),"- %") -> 0.0461926 | N62: =IFERROR(IF($D$5="Y",((($E$50*N$61)*$J62)-$N$25*(1+$J62)^0.5)/(($E$50*N$61)+$N$25*(1+$J62)^0.5),((($E$50*N$61)*$J62)-$N$25)/(($E$50*N$61)+$N$25)),"- %") -> 0.047971158 | O62: =IFERROR(IF($D$5="Y",((($E$50*O$61)*$J62)-$N$25*(1+$J62)^0.5)/(($E$50*O$61)+$N$25*(1+$J62)^0.5),((($E$50*O$61)*$J62)-$N$25)/(($E$50*O$61)+$N$25)),"- %") -> 0.04961828
C63: =+C64-0.005 -> 0.09754788 | D63: =SUMPRODUCT($J$25:$N$25,(1+$C63)^(-$J$27:$N$27))+($E$50*D$61)*(1+$C63)^(-$N$27) -> 19983.878 | E63: =SUMPRODUCT($J$25:$N$25,(1+$C63)^(-$J$27:$N$27))+($E$50*E$61)*(1+$C63)^(-$N$27) -> 20760.01 | F63: =SUMPRODUCT($J$25:$N$25,(1+$C63)^(-$J$27:$N$27))+($E$50*F$61)*(1+$C63)^(-$N$27) -> 21536.141 | G63: =SUMPRODUCT($J$25:$N$25,(1+$C63)^(-$J$27:$N$27))+($E$50*G$61)*(1+$C63)^(-$N$27) -> 22312.272 | H63: =SUMPRODUCT($J$25:$N$25,(1+$C63)^(-$J$27:$N$27))+($E$50*H$61)*(1+$C63)^(-$N$27) -> 23088.404 | J63: =+J64-0.005 -> 0.09754788 | K63: =IFERROR(IF($D$5="Y",((($E$50*K$61)*$J63)-$N$25*(1+$J63)^0.5)/(($E$50*K$61)+$N$25*(1+$J63)^0.5),((($E$50*K$61)*$J63)-$N$25)/(($E$50*K$61)+$N$25)),"- %") -> 0.046942249 | L63: =IFERROR(IF($D$5="Y",((($E$50*L$61)*$J63)-$N$25*(1+$J63)^0.5)/(($E$50*L$61)+$N$25*(1+$J63)^0.5),((($E$50*L$61)*$J63)-$N$25)/(($E$50*L$61)+$N$25)),"- %") -> 0.049045261 | M63: =IFERROR(IF($D$5="Y",((($E$50*M$61)*$J63)-$N$25*(1+$J63)^0.5)/(($E$50*M$61)+$N$25*(1+$J63)^0.5),((($E$50*M$61)*$J63)-$N$25)/(($E$50*M$61)+$N$25)),"- %") -> 0.050980457 | N63: =IFERROR(IF($D$5="Y",((($E$50*N$61)*$J63)-$N$25*(1+$J63)^0.5)/(($E$50*N$61)+$N$25*(1+$J63)^0.5),((($E$50*N$61)*$J63)-$N$25)/(($E$50*N$61)+$N$25)),"- %") -> 0.052767155 | O63: =IFERROR(IF($D$5="Y",((($E$50*O$61)*$J63)-$N$25*(1+$J63)^0.5)/(($E$50*O$61)+$N$25*(1+$J63)^0.5),((($E$50*O$61)*$J63)-$N$25)/(($E$50*O$61)+$N$25)),"- %") -> 0.054421815
C64: =E26 -> 0.10254788 | D64: =SUMPRODUCT($J$25:$N$25,(1+$C64)^(-$J$27:$N$27))+($E$50*D$61)*(1+$C64)^(-$N$27) -> 19554.227 | E64: =SUMPRODUCT($J$25:$N$25,(1+$C64)^(-$J$27:$N$27))+($E$50*E$61)*(1+$C64)^(-$N$27) -> 20312.918 | F64: =SUMPRODUCT($J$25:$N$25,(1+$C64)^(-$J$27:$N$27))+($E$50*F$61)*(1+$C64)^(-$N$27) -> 21071.61 | G64: =SUMPRODUCT($J$25:$N$25,(1+$C64)^(-$J$27:$N$27))+($E$50*G$61)*(1+$C64)^(-$N$27) -> 21830.302 | H64: =SUMPRODUCT($J$25:$N$25,(1+$C64)^(-$J$27:$N$27))+($E$50*H$61)*(1+$C64)^(-$N$27) -> 22588.994 | J64: =E26 -> 0.10254788 | K64: =IFERROR(IF($D$5="Y",((($E$50*K$61)*$J64)-$N$25*(1+$J64)^0.5)/(($E$50*K$61)+$N$25*(1+$J64)^0.5),((($E$50*K$61)*$J64)-$N$25)/(($E$50*K$61)+$N$25)),"- %") -> 0.051711709 | L64: =IFERROR(IF($D$5="Y",((($E$50*L$61)*$J64)-$N$25*(1+$J64)^0.5)/(($E$50*L$61)+$N$25*(1+$J64)^0.5),((($E$50*L$61)*$J64)-$N$25)/(($E$50*L$61)+$N$25)),"- %") -> 0.053824302 | M64: =IFERROR(IF($D$5="Y",((($E$50*M$61)*$J64)-$N$25*(1+$J64)^0.5)/(($E$50*M$61)+$N$25*(1+$J64)^0.5),((($E$50*M$61)*$J64)-$N$25)/(($E$50*M$61)+$N$25)),"- %") -> 0.055768314 | N64: =IFERROR(IF($D$5="Y",((($E$50*N$61)*$J64)-$N$25*(1+$J64)^0.5)/(($E$50*N$61)+$N$25*(1+$J64)^0.5),((($E$50*N$61)*$J64)-$N$25)/(($E$50*N$61)+$N$25)),"- %") -> 0.057563151 | O64: =IFERROR(IF($D$5="Y",((($E$50*O$61)*$J64)-$N$25*(1+$J64)^0.5)/(($E$50*O$61)+$N$25*(1+$J64)^0.5),((($E$50*O$61)*$J64)-$N$25)/(($E$50*O$61)+$N$25)),"- %") -> 0.059225349
C65: =+C64+0.005 -> 0.10754788 | D65: =SUMPRODUCT($J$25:$N$25,(1+$C65)^(-$J$27:$N$27))+($E$50*D$61)*(1+$C65)^(-$N$27) -> 19135.899 | E65: =SUMPRODUCT($J$25:$N$25,(1+$C65)^(-$J$27:$N$27))+($E$50*E$61)*(1+$C65)^(-$N$27) -> 19877.619 | F65: =SUMPRODUCT($J$25:$N$25,(1+$C65)^(-$J$27:$N$27))+($E$50*F$61)*(1+$C65)^(-$N$27) -> 20619.34 | G65: =SUMPRODUCT($J$25:$N$25,(1+$C65)^(-$J$27:$N$27))+($E$50*G$61)*(1+$C65)^(-$N$27) -> 21361.06 | H65: =SUMPRODUCT($J$25:$N$25,(1+$C65)^(-$J$27:$N$27))+($E$50*H$61)*(1+$C65)^(-$N$27) -> 22102.78 | J65: =+J64+0.005 -> 0.10754788 | K65: =IFERROR(IF($D$5="Y",((($E$50*K$61)*$J65)-$N$25*(1+$J65)^0.5)/(($E$50*K$61)+$N$25*(1+$J65)^0.5),((($E$50*K$61)*$J65)-$N$25)/(($E$50*K$61)+$N$25)),"- %") -> 0.05648117 | L65: =IFERROR(IF($D$5="Y",((($E$50*L$61)*$J65)-$N$25*(1+$J65)^0.5)/(($E$50*L$61)+$N$25*(1+$J65)^0.5),((($E$50*L$61)*$J65)-$N$25)/(($E$50*L$61)+$N$25)),"- %") -> 0.058603343 | M65: =IFERROR(IF($D$5="Y",((($E$50*M$61)*$J65)-$N$25*(1+$J65)^0.5)/(($E$50*M$61)+$N$25*(1+$J65)^0.5),((($E$50*M$61)*$J65)-$N$25)/(($E$50*M$61)+$N$25)),"- %") -> 0.060556171 | N65: =IFERROR(IF($D$5="Y",((($E$50*N$61)*$J65)-$N$25*(1+$J65)^0.5)/(($E$50*N$61)+$N$25*(1+$J65)^0.5),((($E$50*N$61)*$J65)-$N$25)/(($E$50*N$61)+$N$25)),"- %") -> 0.062359148 | O65: =IFERROR(IF($D$5="Y",((($E$50*O$61)*$J65)-$N$25*(1+$J65)^0.5)/(($E$50*O$61)+$N$25*(1+$J65)^0.5),((($E$50*O$61)*$J65)-$N$25)/(($E$50*O$61)+$N$25)),"- %") -> 0.064028884
C66: =+C65+0.005 -> 0.11254788 | D66: =SUMPRODUCT($J$25:$N$25,(1+$C66)^(-$J$27:$N$27))+($E$50*D$61)*(1+$C66)^(-$N$27) -> 18728.546 | E66: =SUMPRODUCT($J$25:$N$25,(1+$C66)^(-$J$27:$N$27))+($E$50*E$61)*(1+$C66)^(-$N$27) -> 19453.748 | F66: =SUMPRODUCT($J$25:$N$25,(1+$C66)^(-$J$27:$N$27))+($E$50*F$61)*(1+$C66)^(-$N$27) -> 20178.951 | G66: =SUMPRODUCT($J$25:$N$25,(1+$C66)^(-$J$27:$N$27))+($E$50*G$61)*(1+$C66)^(-$N$27) -> 20904.153 | H66: =SUMPRODUCT($J$25:$N$25,(1+$C66)^(-$J$27:$N$27))+($E$50*H$61)*(1+$C66)^(-$N$27) -> 21629.355 | J66: =+J65+0.005 -> 0.11254788 | K66: =IFERROR(IF($D$5="Y",((($E$50*K$61)*$J66)-$N$25*(1+$J66)^0.5)/(($E$50*K$61)+$N$25*(1+$J66)^0.5),((($E$50*K$61)*$J66)-$N$25)/(($E$50*K$61)+$N$25)),"- %") -> 0.06125063 | L66: =IFERROR(IF($D$5="Y",((($E$50*L$61)*$J66)-$N$25*(1+$J66)^0.5)/(($E$50*L$61)+$N$25*(1+$J66)^0.5),((($E$50*L$61)*$J66)-$N$25)/(($E$50*L$61)+$N$25)),"- %") -> 0.063382384 | M66: =IFERROR(IF($D$5="Y",((($E$50*M$61)*$J66)-$N$25*(1+$J66)^0.5)/(($E$50*M$61)+$N$25*(1+$J66)^0.5),((($E$50*M$61)*$J66)-$N$25)/(($E$50*M$61)+$N$25)),"- %") -> 0.065344028 | N66: =IFERROR(IF($D$5="Y",((($E$50*N$61)*$J66)-$N$25*(1+$J66)^0.5)/(($E$50*N$61)+$N$25*(1+$J66)^0.5),((($E$50*N$61)*$J66)-$N$25)/(($E$50*N$61)+$N$25)),"- %") -> 0.067155144 | O66: =IFERROR(IF($D$5="Y",((($E$50*O$61)*$J66)-$N$25*(1+$J66)^0.5)/(($E$50*O$61)+$N$25*(1+$J66)^0.5),((($E$50*O$61)*$J66)-$N$25)/(($E$50*O$61)+$N$25)),"- %") -> 0.068832418
C68: Implied Equity Value | J68: Implied Share Price
D69: Exit Multiple | K69: Exit Multiple
C70: =J53 -> 20509.47 | D70: =+E70-0.5 -> 11 | E70: =+F70-0.5 -> 11.5 | F70: =E51 -> 12 | G70: =+F70+0.5 -> 12.5 | H70: =+G70+0.5 -> 13 | J70: =+J57 -> 827.67252 | K70: =+L70-0.5 -> 11 | L70: =+M70-0.5 -> 11.5 | M70: =E51 -> 12 | N70: =+M70+0.5 -> 12.5 | O70: =+N70+0.5 -> 13
B71: WACC | C71: =+C72-0.005 -> 0.09254788 | D71: =SUMPRODUCT($J$25:$N$25,(1+$C71)^(-$J$27:$N$27))+($E$50*D$70)*(1+$C71)^(-$N$27)-$J$48-$J$49-$J$50+$J$51 -> 19863.076 | E71: =SUMPRODUCT($J$25:$N$25,(1+$C71)^(-$J$27:$N$27))+($E$50*E$70)*(1+$C71)^(-$N$27)-$J$48-$J$49-$J$50+$J$51 -> 20657.13 | F71: =SUMPRODUCT($J$25:$N$25,(1+$C71)^(-$J$27:$N$27))+($E$50*F$70)*(1+$C71)^(-$N$27)-$J$48-$J$49-$J$50+$J$51 -> 21451.185 | G71: =SUMPRODUCT($J$25:$N$25,(1+$C71)^(-$J$27:$N$27))+($E$50*G$70)*(1+$C71)^(-$N$27)-$J$48-$J$49-$J$50+$J$51 -> 22245.239 | H71: =SUMPRODUCT($J$25:$N$25,(1+$C71)^(-$J$27:$N$27))+($E$50*H$70)*(1+$C71)^(-$N$27)-$J$48-$J$49-$J$50+$J$51 -> 23039.294 | I71: WACC | J71: =+J72-0.005 -> 0.09254788 | K71: =(SUMPRODUCT($J$25:$N$25,(1+$J71)^(-$J$27:$N$27))+($E$50*K$70)*(1+$J71)^(-$N$27)-$J$48-$J$49-$J$50+$J$51)/$J$55 -> 801.58688 | L71: =(SUMPRODUCT($J$25:$N$25,(1+$J71)^(-$J$27:$N$27))+($E$50*L$70)*(1+$J71)^(-$N$27)-$J$48-$J$49-$J$50+$J$51)/$J$55 -> 833.63144 | M71: =(SUMPRODUCT($J$25:$N$25,(1+$J71)^(-$J$27:$N$27))+($E$50*M$70)*(1+$J71)^(-$N$27)-$J$48-$J$49-$J$50+$J$51)/$J$55 -> 865.676 | N71: =(SUMPRODUCT($J$25:$N$25,(1+$J71)^(-$J$27:$N$27))+($E$50*N$70)*(1+$J71)^(-$N$27)-$J$48-$J$49-$J$50+$J$51)/$J$55 -> 897.72056 | O71: =(SUMPRODUCT($J$25:$N$25,(1+$J71)^(-$J$27:$N$27))+($E$50*O$70)*(1+$J71)^(-$N$27)-$J$48-$J$49-$J$50+$J$51)/$J$55 -> 929.76513
C72: =+C73-0.005 -> 0.09754788 | D72: =SUMPRODUCT($J$25:$N$25,(1+$C72)^(-$J$27:$N$27))+($E$50*D$70)*(1+$C72)^(-$N$27)-$J$48-$J$49-$J$50+$J$51 -> 19421.738 | E72: =SUMPRODUCT($J$25:$N$25,(1+$C72)^(-$J$27:$N$27))+($E$50*E$70)*(1+$C72)^(-$N$27)-$J$48-$J$49-$J$50+$J$51 -> 20197.87 | F72: =SUMPRODUCT($J$25:$N$25,(1+$C72)^(-$J$27:$N$27))+($E$50*F$70)*(1+$C72)^(-$N$27)-$J$48-$J$49-$J$50+$J$51 -> 20974.001 | G72: =SUMPRODUCT($J$25:$N$25,(1+$C72)^(-$J$27:$N$27))+($E$50*G$70)*(1+$C72)^(-$N$27)-$J$48-$J$49-$J$50+$J$51 -> 21750.132 | H72: =SUMPRODUCT($J$25:$N$25,(1+$C72)^(-$J$27:$N$27))+($E$50*H$70)*(1+$C72)^(-$N$27)-$J$48-$J$49-$J$50+$J$51 -> 22526.264 | J72: =+J73-0.005 -> 0.09754788 | K72: =(SUMPRODUCT($J$25:$N$25,(1+$J72)^(-$J$27:$N$27))+($E$50*K$70)*(1+$J72)^(-$N$27)-$J$48-$J$49-$J$50+$J$51)/$J$55 -> 783.77642 | L72: =(SUMPRODUCT($J$25:$N$25,(1+$J72)^(-$J$27:$N$27))+($E$50*L$70)*(1+$J72)^(-$N$27)-$J$48-$J$49-$J$50+$J$51)/$J$55 -> 815.09769 | M72: =(SUMPRODUCT($J$25:$N$25,(1+$J72)^(-$J$27:$N$27))+($E$50*M$70)*(1+$J72)^(-$N$27)-$J$48-$J$49-$J$50+$J$51)/$J$55 -> 846.41895 | N72: =(SUMPRODUCT($J$25:$N$25,(1+$J72)^(-$J$27:$N$27))+($E$50*N$70)*(1+$J72)^(-$N$27)-$J$48-$J$49-$J$50+$J$51)/$J$55 -> 877.74022 | O72: =(SUMPRODUCT($J$25:$N$25,(1+$J72)^(-$J$27:$N$27))+($E$50*O$70)*(1+$J72)^(-$N$27)-$J$48-$J$49-$J$50+$J$51)/$J$55 -> 909.06149
C73: =E26 -> 0.10254788 | D73: =SUMPRODUCT($J$25:$N$25,(1+$C73)^(-$J$27:$N$27))+($E$50*D$70)*(1+$C73)^(-$N$27)-$J$48-$J$49-$J$50+$J$51 -> 18992.087 | E73: =SUMPRODUCT($J$25:$N$25,(1+$C73)^(-$J$27:$N$27))+($E$50*E$70)*(1+$C73)^(-$N$27)-$J$48-$J$49-$J$50+$J$51 -> 19750.778 | F73: =SUMPRODUCT($J$25:$N$25,(1+$C73)^(-$J$27:$N$27))+($E$50*F$70)*(1+$C73)^(-$N$27)-$J$48-$J$49-$J$50+$J$51 -> 20509.47 | G73: =SUMPRODUCT($J$25:$N$25,(1+$C73)^(-$J$27:$N$27))+($E$50*G$70)*(1+$C73)^(-$N$27)-$J$48-$J$49-$J$50+$J$51 -> 21268.162 | H73: =SUMPRODUCT($J$25:$N$25,(1+$C73)^(-$J$27:$N$27))+($E$50*H$70)*(1+$C73)^(-$N$27)-$J$48-$J$49-$J$50+$J$51 -> 22026.854 | J73: =E26 -> 0.10254788 | K73: =(SUMPRODUCT($J$25:$N$25,(1+$J73)^(-$J$27:$N$27))+($E$50*K$70)*(1+$J73)^(-$N$27)-$J$48-$J$49-$J$50+$J$51)/$J$55 -> 766.43756 | L73: =(SUMPRODUCT($J$25:$N$25,(1+$J73)^(-$J$27:$N$27))+($E$50*L$70)*(1+$J73)^(-$N$27)-$J$48-$J$49-$J$50+$J$51)/$J$55 -> 797.05504 | M73: =(SUMPRODUCT($J$25:$N$25,(1+$J73)^(-$J$27:$N$27))+($E$50*M$70)*(1+$J73)^(-$N$27)-$J$48-$J$49-$J$50+$J$51)/$J$55 -> 827.67252 | N73: =(SUMPRODUCT($J$25:$N$25,(1+$J73)^(-$J$27:$N$27))+($E$50*N$70)*(1+$J73)^(-$N$27)-$J$48-$J$49-$J$50+$J$51)/$J$55 -> 858.29 | O73: =(SUMPRODUCT($J$25:$N$25,(1+$J73)^(-$J$27:$N$27))+($E$50*O$70)*(1+$J73)^(-$N$27)-$J$48-$J$49-$J$50+$J$51)/$J$55 -> 888.90748
C74: =+C73+0.005 -> 0.10754788 | D74: =SUMPRODUCT($J$25:$N$25,(1+$C74)^(-$J$27:$N$27))+($E$50*D$70)*(1+$C74)^(-$N$27)-$J$48-$J$49-$J$50+$J$51 -> 18573.759 | E74: =SUMPRODUCT($J$25:$N$25,(1+$C74)^(-$J$27:$N$27))+($E$50*E$70)*(1+$C74)^(-$N$27)-$J$48-$J$49-$J$50+$J$51 -> 19315.479 | F74: =SUMPRODUCT($J$25:$N$25,(1+$C74)^(-$J$27:$N$27))+($E$50*F$70)*(1+$C74)^(-$N$27)-$J$48-$J$49-$J$50+$J$51 -> 20057.2 | G74: =SUMPRODUCT($J$25:$N$25,(1+$C74)^(-$J$27:$N$27))+($E$50*G$70)*(1+$C74)^(-$N$27)-$J$48-$J$49-$J$50+$J$51 -> 20798.92 | H74: =SUMPRODUCT($J$25:$N$25,(1+$C74)^(-$J$27:$N$27))+($E$50*H$70)*(1+$C74)^(-$N$27)-$J$48-$J$49-$J$50+$J$51 -> 21540.64 | J74: =+J73+0.005 -> 0.10754788 | K74: =(SUMPRODUCT($J$25:$N$25,(1+$J74)^(-$J$27:$N$27))+($E$50*K$70)*(1+$J74)^(-$N$27)-$J$48-$J$49-$J$50+$J$51)/$J$55 -> 749.55569 | L74: =(SUMPRODUCT($J$25:$N$25,(1+$J74)^(-$J$27:$N$27))+($E$50*L$70)*(1+$J74)^(-$N$27)-$J$48-$J$49-$J$50+$J$51)/$J$55 -> 779.48827 | M74: =(SUMPRODUCT($J$25:$N$25,(1+$J74)^(-$J$27:$N$27))+($E$50*M$70)*(1+$J74)^(-$N$27)-$J$48-$J$49-$J$50+$J$51)/$J$55 -> 809.42086 | N74: =(SUMPRODUCT($J$25:$N$25,(1+$J74)^(-$J$27:$N$27))+($E$50*N$70)*(1+$J74)^(-$N$27)-$J$48-$J$49-$J$50+$J$51)/$J$55 -> 839.35344 | O74: =(SUMPRODUCT($J$25:$N$25,(1+$J74)^(-$J$27:$N$27))+($E$50*O$70)*(1+$J74)^(-$N$27)-$J$48-$J$49-$J$50+$J$51)/$J$55 -> 869.28602
C75: =+C74+0.005 -> 0.11254788 | D75: =SUMPRODUCT($J$25:$N$25,(1+$C75)^(-$J$27:$N$27))+($E$50*D$70)*(1+$C75)^(-$N$27)-$J$48-$J$49-$J$50+$J$51 -> 18166.406 | E75: =SUMPRODUCT($J$25:$N$25,(1+$C75)^(-$J$27:$N$27))+($E$50*E$70)*(1+$C75)^(-$N$27)-$J$48-$J$49-$J$50+$J$51 -> 18891.608 | F75: =SUMPRODUCT($J$25:$N$25,(1+$C75)^(-$J$27:$N$27))+($E$50*F$70)*(1+$C75)^(-$N$27)-$J$48-$J$49-$J$50+$J$51 -> 19616.811 | G75: =SUMPRODUCT($J$25:$N$25,(1+$C75)^(-$J$27:$N$27))+($E$50*G$70)*(1+$C75)^(-$N$27)-$J$48-$J$49-$J$50+$J$51 -> 20342.013 | H75: =SUMPRODUCT($J$25:$N$25,(1+$C75)^(-$J$27:$N$27))+($E$50*H$70)*(1+$C75)^(-$N$27)-$J$48-$J$49-$J$50+$J$51 -> 21067.215 | J75: =+J74+0.005 -> 0.11254788 | K75: =(SUMPRODUCT($J$25:$N$25,(1+$J75)^(-$J$27:$N$27))+($E$50*K$70)*(1+$J75)^(-$N$27)-$J$48-$J$49-$J$50+$J$51)/$J$55 -> 733.11671 | L75: =(SUMPRODUCT($J$25:$N$25,(1+$J75)^(-$J$27:$N$27))+($E$50*L$70)*(1+$J75)^(-$N$27)-$J$48-$J$49-$J$50+$J$51)/$J$55 -> 762.3827 | M75: =(SUMPRODUCT($J$25:$N$25,(1+$J75)^(-$J$27:$N$27))+($E$50*M$70)*(1+$J75)^(-$N$27)-$J$48-$J$49-$J$50+$J$51)/$J$55 -> 791.64868 | N75: =(SUMPRODUCT($J$25:$N$25,(1+$J75)^(-$J$27:$N$27))+($E$50*N$70)*(1+$J75)^(-$N$27)-$J$48-$J$49-$J$50+$J$51)/$J$55 -> 820.91467 | O75: =(SUMPRODUCT($J$25:$N$25,(1+$J75)^(-$J$27:$N$27))+($E$50*O$70)*(1+$J75)^(-$N$27)-$J$48-$J$49-$J$50+$J$51)/$J$55 -> 850.18065

Sheet NWC
A1: =+DCF!A1 -> 0
A2: Granules India Limited: Working Capital Projections
A3: (Rs. in crore)
C5: Historical Period | H5: Projection Period
C6: =+DCF!E6 -> 2023 | D6: =+DCF!F6 -> 2024 | E6: =+DCF!G6 -> 2025 | F6: =+DCF!H6 -> 2026 | H6: =+DCF!J6 -> 2027 | I6: =+DCF!K6 -> 2028 | J6: =+DCF!L6 -> 2029 | K6: =+DCF!M6 -> 2030 | L6: =+DCF!N6 -> 2031
B8: Sales | C8: =+DCF!E7 -> 4511.92 | D8: =+DCF!F7 -> 4506.37 | E8: =+DCF!G7 -> 4481.61 | F8: =+DCF!H7 -> 5365.64 | H8: =+DCF!J7 -> 6277.7988 | I8: =+DCF!K7 -> 7219.4686 | J8: =+DCF!L7 -> 8085.8049 | K8: =+DCF!M7 -> 8894.3853 | L8: =+DCF!N7 -> 9694.88
B9: Cost of Goods Sold | C9: =+DCF!E9 -> 2307.28 | D9: =+DCF!F9 -> 2021.25 | E9: =+DCF!G9 -> 1725.7 | F9: =+DCF!H9 -> 1875.7 | H9: =+DCF!J9 -> 2165.8406 | I9: =+DCF!K9 -> 2454.6193 | J9: =+DCF!L9 -> 2708.7446 | K9: =+DCF!M9 -> 2935.1472 | L9: =+DCF!N9 -> 3179.9206
B11: Current Assets
B12: Accounts Receivable | C12: 948.54 | D12: 985.83 | E12: 942.22 | F12: 909.37 | H12: =+H8/365*H28 -> 1083.5653 | I12: =+I8/365*I28 -> 1226.3207 | J12: =+J8/365*J28 -> 1329.1734 | K12: =+K8/365*K28 -> 1413.3544 | L12: =+L8/365*L28 -> 1487.4336
B13: Inventories | C13: 1149.41 | D13: 1300.55 | E13: 1342.82 | F13: 1673.03 | H13: =+H9/365*H29 -> 1898.8191 | I13: =+I9/365*I29 -> 2084.7452 | J13: =+J9/365*J29 -> 2189.2594 | K13: =+K9/365*K29 -> 2251.6197 | L13: =+L9/365*L29 -> 2308.7095
B14: Advances and other current assets | C14: 163.41 | D14: 232.28 | E14: 234.07 | F14: 236.2 | H14: =+H8*H30 -> 282.50095 | I14: =+I8*I30 -> 324.87609 | J14: =+J8*J30 -> 347.68961 | K14: =+K8*K30 -> 373.56418 | L14: =+L8*L30 -> 387.7952
B15: Total Current Assets | C15: =SUM(C12:C14) -> 2261.36 | D15: =SUM(D12:D14) -> 2518.66 | E15: =SUM(E12:E14) -> 2519.11 | F15: =SUM(F12:F14) -> 2818.6 | H15: =SUM(H12:H14) -> 3264.8854 | I15: =SUM(I12:I14) -> 3635.942 | J15: =SUM(J12:J14) -> 3866.1224 | K15: =SUM(K12:K14) -> 4038.5383 | L15: =SUM(L12:L14) -> 4183.9384
B17: Current Liabilities
B18: Accounts Payable | C18: 782.13 | D18: 749.53 | E18: 726.07 | F18: 672.8 | H18: =+H9/365*H31 -> 801.06433 | I18: =+I9/365*I31 -> 928.04786 | J18: =+J9/365*J31 -> 1038.9705 | K18: =+K9/365*K31 -> 1125.8099 | L18: =+L9/365*L31 -> 1202.2714
B19: Other Current Liabilities | C19: 213.49 | D19: 169.88 | E19: 293.03 | F19: 365.28 | H19: =+H8*H32 -> 408.05692 | I19: =+I8*I32 -> 454.82652 | J19: =+J8*J32 -> 485.14829 | K19: =+K8*K32 -> 515.87435 | L19: =+L8*L32 -> 542.91328
B20: Total Current Liabilities | C20: =SUM(C18:C19) -> 995.62 | D20: =SUM(D18:D19) -> 919.41 | E20: =SUM(E18:E19) -> 1019.1 | F20: =SUM(F18:F19) -> 1038.08 | H20: =SUM(H18:H19) -> 1209.1212 | I20: =SUM(I18:I19) -> 1382.8744 | J20: =SUM(J18:J19) -> 1524.1188 | K20: =SUM(K18:K19) -> 1641.6842 | L20: =SUM(L18:L19) -> 1745.1846
B22: Net Working Capital | C22: =+C15-C20 -> 1265.74 | D22: =+D15-D20 -> 1599.25 | E22: =+E15-E20 -> 1500.01 | F22: =+F15-F20 -> 1780.52 | H22: =+H15-H20 -> 2055.7641 | I22: =+I15-I20 -> 2253.0676 | J22: =+J15-J20 -> 2342.0035 | K22: =+K15-K20 -> 2396.8541 | L22: =+L15-L20 -> 2438.7537
B23: % sales | C23: =+IF(ISERROR(C22/C8),0,C22/C8) -> 0.28053246 | D23: =+IF(ISERROR(D22/D8),0,D22/D8) -> 0.35488653 | E23: =+IF(ISERROR(E22/E8),0,E22/E8) -> 0.33470338 | F23: =+IF(ISERROR(F22/F8),0,F22/F8) -> 0.33183739 | H23: =+IF(ISERROR(H22/H8),0,H22/H8) -> 0.32746575 | I23: =+IF(ISERROR(I22/I8),0,I22/I8) -> 0.31208219 | J23: =+IF(ISERROR(J22/J8),0,J22/J8) -> 0.28964384 | K23: =+IF(ISERROR(K22/K8),0,K22/K8) -> 0.26947945 | L23: =+IF(ISERROR(L22/L8),0,L22/L8) -> 0.25155068
B25: (Increase) / Decrease in NWC | D25: =+C22-D22 -> -333.51 | E25: =+D22-E22 -> 99.24 | F25: =+E22-F22 -> -280.51 | H25: =+F22-H22 -> -275.24411 | I25: =+H22-I22 -> -197.30348 | J25: =+I22-J22 -> -88.935942 | K25: =+J22-K22 -> -54.850556 | L25: =+K22-L22 -> -41.899622
B27: Assumptions
B28: Days Sales Outstanding | C28: =+IF(ISERROR(C12/C8*365),0,C12/C8*365) -> 76.733874 | D28: =+IF(ISERROR(D12/D8*365),0,D12/D8*365) -> 79.848736 | E28: =+IF(ISERROR(E12/E8*365),0,E12/E8*365) -> 76.738114 | F28: =E28 -> 76.738114 | H28: ='A2'!F9 -> 63 | I28: ='A2'!G9 -> 62 | J28: ='A2'!H9 -> 60 | K28: ='A2'!I9 -> 58 | L28: ='A2'!J9 -> 56
B29: Days Inventory Held | C29: =+IF(ISERROR(C13/C9*365),0,C13/C9*365) -> 181.83084 | D29: =+IF(ISERROR(D13/D9*365),0,D13/D9*365) -> 234.85504 | E29: =+IF(ISERROR(E13/E9*365),0,E13/E9*365) -> 284.01767 | F29: =E29 -> 284.01767 | H29: ='A2'!F16 -> 320 | I29: ='A2'!G16 -> 310 | J29: ='A2'!H16 -> 295 | K29: ='A2'!I16 -> 280 | L29: ='A2'!J16 -> 265
B30: Advanvces and Other CA (% of sales) | C30: =+IF(ISERROR(C14/C8),0,C14/C8) -> 0.036217397 | D30: =+IF(ISERROR(D14/D8),0,D14/D8) -> 0.051544813 | E30: =+IF(ISERROR(E14/E8),0,E14/E8) -> 0.052228998 | F30: =E30 -> 0.052228998 | H30: ='A2'!F23 -> 0.045 | I30: ='A2'!G23 -> 0.045 | J30: ='A2'!H23 -> 0.043 | K30: ='A2'!I23 -> 0.042 | L30: ='A2'!J23 -> 0.04
B31: Days Payable Outstanding | C31: =+IF(ISERROR(C18/C9*365),0,C18/C9*365) -> 123.729 | D31: =+IF(ISERROR(D18/D9*365),0,D18/D9*365) -> 135.35112 | E31: =+IF(ISERROR(E18/E9*365),0,E18/E9*365) -> 153.56988 | F31: =E31 -> 153.56988 | H31: ='A2'!F31 -> 135 | I31: ='A2'!G31 -> 138 | J31: ='A2'!H31 -> 140 | K31: ='A2'!I31 -> 140 | L31: ='A2'!J31 -> 138
B32: Other Current Liabilities (% of sales) | C32: =+IF(ISERROR(C19/C8),0,C19/C8) -> 0.047316885 | D32: =+IF(ISERROR(D19/D8),0,D19/D8) -> 0.037697748 | E32: =+IF(ISERROR(E19/E8),0,E19/E8) -> 0.065384984 | F32: =E32 -> 0.065384984 | H32: ='A2'!F38 -> 0.065 | I32: ='A2'!G38 -> 0.063 | J32: ='A2'!H38 -> 0.06 | K32: ='A2'!I38 -> 0.058 | L32: ='A2'!J38 -> 0.056

Sheet WACC
A1: =+DCF!A1 -> 0
A2: Granules India Limited: Weighted Average Cost of Capital Analysis
A3: (Rs. in crore)
B6: WACC Calculation | F6: Comparable Companies Unlevered Beta
B7: Target Capital Structure | G7: Predicted | H7: Market | I7: Market | J7: Debt/ | K7: Marginal | L7: Unlevered
B8: Debt-to-Total Capitalization | D8: 0.0685 | F8: Company | G8: Levered Beta(3) | H8: Value of Debt | I8: Value of Equity | J8: Equity | K8: Tax Rate | L8: Beta
B9: Equity-to-Total Capitalization | D9: =1-D8 -> 0.9315 | F9: Strides Pharma | G9: 0.5708 | H9: 1757.99 | I9: 9061.5 | J9: =+IF(ISERROR(H9/I9),0,H9/I9) -> 0.19400651 | K9: =$D$14 -> 0.2522 | L9: =+G9/(1+(J9)*(1-K9)) -> 0.4984813
B10: Memo: Book-value Debt/(Debt+Equity) | D10: =1512.04/(1512.04+5085) -> 0.22919976 | F10: FDC | G10: 0.4282 | H10: 21.17 | I10: 5673.93 | J10: =+IF(ISERROR(H10/I10),0,H10/I10) -> 0.0037311 | K10: =$D$14 -> 0.2522 | L10: =+G10/(1+(J10)*(1-K10)) -> 0.4270086
F11: Orchid Pharma | G11: 1.0266 | H11: 174.61 | I11: 5819.34 | J11: =+IF(ISERROR(H11/I11),0,H11/I11) -> 0.030005121 | K11: =$D$14 -> 0.2522 | L11: =+G11/(1+(J11)*(1-K11)) -> 1.0040708
B12: Cost of Debt | F12: RPG LifeScience. | G12: 0.7832 | H12: 20 | I12: 4295.93 | J12: =+IF(ISERROR(H12/I12),0,H12/I12) -> 0.0046555693 | K12: =$D$14 -> 0.2522 | L12: =+G12/(1+(J12)*(1-K12)) -> 0.7804828
B13: Cost of Debt | D13: 0.07387 | F13: Unichem Labs. | G13: 0.6236 | H13: 500.15 | I13: 3737.49 | J13: =+IF(ISERROR(H13/I13),0,H13/I13) -> 0.13381976 | K13: =$D$14 -> 0.2522 | L13: =+G13/(1+(J13)*(1-K13)) -> 0.5668728
B14: Tax Rate | D14: 0.2522
B15: After-tax Cost of Debt | D15: =+D13*(1-D14) -> 0.055239986 | F15: Mean | G15: =AVERAGE(G9:G14) -> 0.68648 | J15: =AVERAGE(J9:J14) -> 0.073243611 | L15: =AVERAGE(L9:L13) -> 0.65538327
F16: Median | G16: =MEDIAN(G9:G14) -> 0.6236 | J16: =MEDIAN(J9:J14) -> 0.030005121 | L16: =MEDIAN(L9:L12) -> 0.63948205
B18: Cost of Equity | F18: ValueCo Relevered Beta
B19: Risk-free Rate(1) | D19: 0.067771 | I19: Mean | J19: Target | K19: Target
B20: Market Risk Premium(2) | D20: 0.055329 | I20: Unlevered | J20: Debt/ | K20: Marginal | L20: Relevered
B21: Levered Beta | D21: =L22 -> 0.69142358 | I21: Beta | J21: Equity | K21: Tax Rate | L21: Beta
F22: Relevered Beta | I22: =L15 -> 0.65538327 | J22: =D8/D9 -> 0.073537305 | K22: =D14 -> 0.2522 | L22: =+I22*(1+(J22)*(1-K22)) -> 0.69142358
B23: Cost of Equity | D23: =+D19+(D21*D20) -> 0.10602678
I24: Adjusted Regression levered beta | L24: 0.99
I25: Domodaran Industry levered beta | L25: 0.98
B26: WACC | D26: =(D8*D15)+(D9*D23) -> 0.10254788
B28: (1) 10 year Indian government bond | F28: WACC Sensitivity Analysis
B29: (2) 10 year Indian government bond minus BSE 10 years return | H29: Pre-tax Cost of Debt
B30: (3) Levered beta directly taken from capitaline on 15-07-2026 | F30: Debt-to-Total Capitalization | G30: =+D26 -> 0.10254788 | H30: =I30-0.005 -> 0.06387 | I30: =J30-0.005 -> 0.06887 | J30: =D13 -> 0.07387 | K30: =J30+0.005 -> 0.07887 | L30: =K30+0.005 -> 0.08387
G31: =G32-0.02 -> 0.0285 | H31: =$G31*H$30*(1-$D$14)+(1-$G31)*$D$23-$D$26 -> 0.0018183486 | I31: =$G31*I$30*(1-$D$14)+(1-$G31)*$D$23-$D$26 -> 0.0019249101 | J31: =$G31*J$30*(1-$D$14)+(1-$G31)*$D$23-$D$26 -> 0.0020314716 | K31: =$G31*K$30*(1-$D$14)+(1-$G31)*$D$23-$D$26 -> 0.0021380331 | L31: =$G31*L$30*(1-$D$14)+(1-$G31)*$D$23-$D$26 -> 0.0022445946
G32: =G33-0.02 -> 0.0485 | H32: =$G32*H$30*(1-$D$14)+(1-$G32)*$D$23-$D$26 -> 0.00065305278 | I32: =$G32*I$30*(1-$D$14)+(1-$G32)*$D$23-$D$26 -> 0.00083439428 | J32: =$G32*J$30*(1-$D$14)+(1-$G32)*$D$23-$D$26 -> 0.0010157358 | K32: =$G32*K$30*(1-$D$14)+(1-$G32)*$D$23-$D$26 -> 0.0011970773 | L32: =$G32*L$30*(1-$D$14)+(1-$G32)*$D$23-$D$26 -> 0.0013784188
G33: =D8 -> 0.0685 | H33: =$G33*H$30*(1-$D$14)+(1-$G33)*$D$23-$D$26 -> -0.000512243 | I33: =$G33*I$30*(1-$D$14)+(1-$G33)*$D$23-$D$26 -> -0.0002561215 | J33: =$G33*J$30*(1-$D$14)+(1-$G33)*$D$23-$D$26 -> 0 | K33: =$G33*K$30*(1-$D$14)+(1-$G33)*$D$23-$D$26 -> 0.0002561215 | L33: =$G33*L$30*(1-$D$14)+(1-$G33)*$D$23-$D$26 -> 0.000512243
G34: =G33+0.02 -> 0.0885 | H34: =$G34*H$30*(1-$D$14)+(1-$G34)*$D$23-$D$26 -> -0.0016775388 | I34: =$G34*I$30*(1-$D$14)+(1-$G34)*$D$23-$D$26 -> -0.0013466373 | J34: =$G34*J$30*(1-$D$14)+(1-$G34)*$D$23-$D$26 -> -0.0010157358 | K34: =$G34*K$30*(1-$D$14)+(1-$G34)*$D$23-$D$26 -> -0.00068483428 | L34: =$G34*L$30*(1-$D$14)+(1-$G34)*$D$23-$D$26 -> -0.00035393278
G35: =G34+0.02 -> 0.1085 | H35: =$G35*H$30*(1-$D$14)+(1-$G35)*$D$23-$D$26 -> -0.0028428346 | I35: =$G35*I$30*(1-$D$14)+(1-$G35)*$D$23-$D$26 -> -0.0024371531 | J35: =$G35*J$30*(1-$D$14)+(1-$G35)*$D$23-$D$26 -> -0.0020314716 | K35: =$G35*K$30*(1-$D$14)+(1-$G35)*$D$23-$D$26 -> -0.0016257901 | L35: =$G35*L$30*(1-$D$14)+(1-$G35)*$D$23-$D$26 -> -0.0012201086

Sheet A1
A1: `
B2: Assumptions Page 1 - Income Statement and Cash Flow Statement
F4: Projection Period | Q4: What is base cae? Base (Analyst) Case assumption should preferably have three anchors: Historical evidence + External/industry evidence + Company/management evidence. FY26 Sales Growth Historical Average Industry expected Management expects Analyst conclusion Groups need them to prove that their conculed number is correct. Groups need to explain why their estimation is more reasonable than min or maxium number.
F5: 1 | G5: 2 | H5: 3 | I5: 4 | J5: 5
F6: 2027 | G6: 2028 | H6: 2029 | I6: 2030 | J6: 2031
B8: Income Statement Assumptions
B9: Sales (% growth) | F9: =CHOOSE(DCF!$D$4,F10,F11,F12,F13,F14) -> 0.17 | G9: =CHOOSE(DCF!$D$4,G10,G11,G12,G13,G14) -> 0.15 | H9: =CHOOSE(DCF!$D$4,H10,H11,H12,H13,H14) -> 0.12 | I9: =CHOOSE(DCF!$D$4,I10,I11,I12,I13,I14) -> 0.1 | J9: =CHOOSE(DCF!$D$4,J10,J11,J12,J13,J14) -> 0.09 | M9: Previous year | N9: =DCF!H35 -> 0.19725724
B10: Base | E10: 1 | F10: 0.17 | G10: 0.15 | H10: 0.12 | I10: 0.1 | J10: 0.09 | M10: Historical Average | N10: =AVERAGE(DCF!F35:H35) -> 0.063510905
B11: Management | E11: 2 | F11: 0.21 | G11: 0.18 | H11: 0.15 | I11: 0.12 | J11: 0.1 | M11: Industry average | N11: 0.09
B12: Upside | E12: 3 | F12: 0.23 | G12: 0.21 | H12: 0.18 | I12: 0.14 | J12: 0.12 | M12: Industry expectation | N12: 0.1
B13: Downside 1 | E13: 4 | F13: 0.14 | G13: 0.11 | H13: 0.09 | I13: 0.08 | J13: 0.07 | M13: Earnings call or MD&A (if avilable) | N13: 0.22
B14: Downside 2 | E14: 5 | F14: 0.12 | G14: 0.06 | H14: 0.05 | I14: 0.05 | J14: 0.05
B16: Cost of Goods Sold (% sales) | F16: =CHOOSE(DCF!$D$4,F17,F18,F19,F20,F21) -> 0.345 | G16: =CHOOSE(DCF!$D$4,G17,G18,G19,G20,G21) -> 0.34 | H16: =CHOOSE(DCF!$D$4,H17,H18,H19,H20,H21) -> 0.335 | I16: =CHOOSE(DCF!$D$4,I17,I18,I19,I20,I21) -> 0.33 | J16: =CHOOSE(DCF!$D$4,J17,J18,J19,J20,J21) -> 0.328 | M16: Previous year | N16: =DCF!H36 -> 0.34957619
B17: Base | E17: 1 | F17: 0.345 | G17: 0.34 | H17: 0.335 | I17: 0.33 | J17: 0.328 | M17: Historical Average | N17: =AVERAGE(DCF!E36:H36) -> 0.42363619
B18: Management | E18: 2 | F18: 0.335 | G18: 0.325 | H18: 0.315 | I18: 0.31 | J18: 0.305 | M18: Industry average | N18: 0.44
B19: Upside | E19: 3 | F19: 0.325 | G19: 0.31 | H19: 0.295 | I19: 0.29 | J19: 0.285 | M19: Earnings call or MD&A (if avilable) | N19: 0.344
B20: Downside 1 | E20: 4 | F20: 0.36 | G20: 0.36 | H20: 0.355 | I20: 0.355 | J20: 0.35
B21: Downside 2 | E21: 5 | F21: 0.38 | G21: 0.385 | H21: 0.38 | I21: 0.375 | J21: 0.37 | Q21: What is Management cae? What happens if management broadly delivers what it is communicating? Management Case = Management's story converted into numbers.
B23: SG&A (% sales) | F23: =CHOOSE(DCF!$D$4,F24,F25,F26,F27,F28) -> 0.43 | G23: =CHOOSE(DCF!$D$4,G24,G25,G26,G27,G28) -> 0.43 | H23: =CHOOSE(DCF!$D$4,H24,H25,H26,H27,H28) -> 0.425 | I23: =CHOOSE(DCF!$D$4,I24,I25,I26,I27,I28) -> 0.42 | J23: =CHOOSE(DCF!$D$4,J24,J25,J26,J27,J28) -> 0.417 | M23: Previous year | N23: =DCF!H37 -> 0.42954801
B24: Base | E24: 1 | F24: 0.43 | G24: 0.43 | H24: 0.425 | I24: 0.42 | J24: 0.417 | M24: Historical Average | N24: =AVERAGE(DCF!E37:H37) -> 0.37029461
B25: Management | E25: 2 | F25: 0.435 | G25: 0.425 | H25: 0.415 | I25: 0.41 | J25: 0.405 | M25: Industry average | N25: 0.38
B26: Upside | E26: 3 | F26: 0.435 | G26: 0.42 | H26: 0.405 | I26: 0.4 | J26: 0.395 | M26: Earnings call or MD&A (if avilable) | N26: 0.431
B27: Downside 1 | E27: 4 | F27: 0.45 | G27: 0.45 | H27: 0.45 | I27: 0.445 | J27: 0.445
B28: Downside 2 | E28: 5 | F28: 0.46 | G28: 0.465 | H28: 0.465 | I28: 0.465 | J28: 0.465
B30: Depreciation & Amortization (% sales) | F30: =CHOOSE(DCF!$D$4,F31,F32,F33,F34,F35) -> 0.056 | G30: =CHOOSE(DCF!$D$4,G31,G32,G33,G34,G35) -> 0.055 | H30: =CHOOSE(DCF!$D$4,H31,H32,H33,H34,H35) -> 0.053 | I30: =CHOOSE(DCF!$D$4,I31,I32,I33,I34,I35) -> 0.05 | J30: =CHOOSE(DCF!$D$4,J31,J32,J33,J34,J35) -> 0.048 | M30: Previous year | N30: =DCF!H38 -> 0.055191925 | Q30: What is upside cae? If all the positive findings of qualitative analysis (SWOT, PORTER 5, PORTER GENERIC, etc) will be activated than what will happen to specific deriver? Upside Case = Base case positive adjustments (Generally 1-2%)
B31: Base | E31: 1 | F31: 0.056 | G31: 0.055 | H31: 0.053 | I31: 0.05 | J31: 0.048 | M31: Historical Average | N31: =AVERAGE(DCF!E38:H38) -> 0.048101584
B32: Management | E32: 2 | F32: 0.057 | G32: 0.056 | H32: 0.053 | I32: 0.05 | J32: 0.047 | M32: Industry average | N32: 0.05
B33: Upside | E33: 3 | F33: 0.055 | G33: 0.052 | H33: 0.049 | I33: 0.046 | J33: 0.044 | M33: Earnings call or MD&A (if avilable) | N33: Not separately guided
B34: Downside 1 | E34: 4 | F34: 0.058 | G34: 0.058 | H34: 0.056 | I34: 0.054 | J34: 0.052
B35: Downside 2 | E35: 5 | F35: 0.06 | G35: 0.062 | H35: 0.06 | I35: 0.058 | J35: 0.056
B37: Cash Flow Statement Assumptions
B38: Capital Expenditures (% of sales) | F38: =CHOOSE(DCF!$D$4,F39,F40,F41,F42,F43) -> 0.095 | G38: =CHOOSE(DCF!$D$4,G39,G40,G41,G42,G43) -> 0.09 | H38: =CHOOSE(DCF!$D$4,H39,H40,H41,H42,H43) -> 0.08 | I38: =CHOOSE(DCF!$D$4,I39,I40,I41,I42,I43) -> 0.07 | J38: =CHOOSE(DCF!$D$4,J39,J40,J41,J42,J43) -> 0.065 | M38: Previous year | N38: =DCF!H39 -> 0.10403419 | Q38: What is downside1 cae? If all the negative findings of qualitative analysis (SWOT, PORTER 5, PORTER GENERIC, etc) will be activated (Moderate Stress) than what will happen to specific deriver? Downside1 Case = Base case negative adjustments (Generally 1-2%)
B39: Base | E39: 1 | F39: 0.095 | G39: 0.09 | H39: 0.08 | I39: 0.07 | J39: 0.065 | M39: Historical Average | N39: =AVERAGE(DCF!E39:H39) -> 0.10176816
B40: Management | E40: 2 | F40: 0.1 | G40: 0.095 | H40: 0.08 | I40: 0.065 | J40: 0.06 | M40: Industry average | N40: 0.08
B41: Upside | E41: 3 | F41: 0.09 | G41: 0.08 | H41: 0.07 | I41: 0.06 | J41: 0.055 | M41: Earnings call or MD&A (if avilable) | N41: 0.0956
B42: Downside 1 | E42: 4 | F42: 0.105 | G42: 0.105 | H42: 0.095 | I42: 0.085 | J42: 0.08
B43: Downside 2 | E43: 5 | F43: 0.11 | G43: 0.115 | H43: 0.105 | I43: 0.095 | J43: 0.09
Q46: What is downside2 cae? If all the negative findings of qualitative analysis (SWOT, PORTER 5, PORTER GENERIC, etc) will be activated (Severe Stress) than what will happen to specific deriver? Downside2 Case = Base case negative adjustments (Generally 3-4%)

Sheet A2
B2: Assumptions Page 2 - Balance Sheet
F4: Projection Period
F5: 1 | G5: 2 | H5: 3 | I5: 4 | J5: 5
F6: ='A1'!F6 -> 2027 | G6: ='A1'!G6 -> 2028 | H6: ='A1'!H6 -> 2029 | I6: ='A1'!I6 -> 2030 | J6: ='A1'!J6 -> 2031
B8: Current Assets
B9: Days Sales Outstanding (DSO) | F9: =CHOOSE(DCF!$D$4,F10,F11,F12,F13,F14) -> 63 | G9: =CHOOSE(DCF!$D$4,G10,G11,G12,G13,G14) -> 62 | H9: =CHOOSE(DCF!$D$4,H10,H11,H12,H13,H14) -> 60 | I9: =CHOOSE(DCF!$D$4,I10,I11,I12,I13,I14) -> 58 | J9: =CHOOSE(DCF!$D$4,J10,J11,J12,J13,J14) -> 56 | M9: Previous year | N9: =NWC!F28 -> 76.738114
B10: Base | E10: 1 | F10: 63 | G10: 62 | H10: 60 | I10: 58 | J10: 56 | M10: Historical Average | N10: =AVERAGE(NWC!C28:F28) -> 77.51471
B11: Management | E11: 2 | F11: 64 | G11: 63 | H11: 61 | I11: 59 | J11: 57 | M11: Industry average | N11: 65
B12: Upside | E12: 3 | F12: 55 | G12: 52 | H12: 50 | I12: 48 | J12: 47 | M12: Earnings call or MD&A (if avilable) | N12: Rises slightly (qualitative)
B13: Downside 1 | E13: 4 | F13: 65 | G13: 64 | H13: 62 | I13: 61 | J13: 60
B14: Downside 2 | E14: 5 | F14: 72 | G14: 72 | H14: 70 | I14: 68 | J14: 66
B16: Days Inventory Held (DIH) | F16: =CHOOSE(DCF!$D$4,F17,F18,F19,F20,F21) -> 320 | G16: =CHOOSE(DCF!$D$4,G17,G18,G19,G20,G21) -> 310 | H16: =CHOOSE(DCF!$D$4,H17,H18,H19,H20,H21) -> 295 | I16: =CHOOSE(DCF!$D$4,I17,I18,I19,I20,I21) -> 280 | J16: =CHOOSE(DCF!$D$4,J17,J18,J19,J20,J21) -> 265 | M16: Previous year | N16: =NWC!F29 -> 284.01767
B17: Base | E17: 1 | F17: 320 | G17: 310 | H17: 295 | I17: 280 | J17: 265 | M17: Historical Average | N17: =AVERAGE(NWC!C29:F29) -> 246.18031
B18: Management | E18: 2 | F18: 322 | G18: 312 | H18: 297 | I18: 282 | J18: 267 | M18: Industry average | N18: 150
B19: Upside | E19: 3 | F19: 285 | G19: 265 | H19: 250 | I19: 240 | J19: 230 | M19: Earnings call or MD&A (if avilable) | N19: Held deliberately elevated
B20: Downside 1 | E20: 4 | F20: 330 | G20: 325 | H20: 315 | I20: 305 | J20: 295
B21: Downside 2 | E21: 5 | F21: 350 | G21: 355 | H21: 345 | I21: 335 | J21: 325
B23: Advances and other current assets (% of sales) | F23: =CHOOSE(DCF!$D$4,F24,F25,F26,F27,F28) -> 0.045 | G23: =CHOOSE(DCF!$D$4,G24,G25,G26,G27,G28) -> 0.045 | H23: =CHOOSE(DCF!$D$4,H24,H25,H26,H27,H28) -> 0.043 | I23: =CHOOSE(DCF!$D$4,I24,I25,I26,I27,I28) -> 0.042 | J23: =CHOOSE(DCF!$D$4,J24,J25,J26,J27,J28) -> 0.04 | M23: Previous year | N23: =NWC!F30 -> 0.052228998
B24: Base | E24: 1 | F24: 0.045 | G24: 0.045 | H24: 0.043 | I24: 0.042 | J24: 0.04 | M24: Historical Average | N24: =AVERAGE(NWC!C30:F30) -> 0.048055052
B25: Management | E25: 2 | F25: 0.043 | G25: 0.042 | H25: 0.04 | I25: 0.039 | J25: 0.038 | M25: Industry average | N25: 0.04
B26: Upside | E26: 3 | F26: 0.04 | G26: 0.039 | H26: 0.037 | I26: 0.036 | J26: 0.035 | M26: Earnings call or MD&A (if avilable) | N26: Not guided
B27: Downside 1 | E27: 4 | F27: 0.05 | G27: 0.05 | H27: 0.048 | I27: 0.047 | J27: 0.046
B28: Downside 2 | E28: 5 | F28: 0.055 | G28: 0.055 | H28: 0.053 | I28: 0.052 | J28: 0.05
B30: Current Liabilities
B31: Days Payable Outstanding (DPO) | F31: =CHOOSE(DCF!$D$4,F32,F33,F34,F35,F36) -> 135 | G31: =CHOOSE(DCF!$D$4,G32,G33,G34,G35,G36) -> 138 | H31: =CHOOSE(DCF!$D$4,H32,H33,H34,H35,H36) -> 140 | I31: =CHOOSE(DCF!$D$4,I32,I33,I34,I35,I36) -> 140 | J31: =CHOOSE(DCF!$D$4,J32,J33,J34,J35,J36) -> 138 | M31: Previous year | N31: =NWC!F31 -> 153.56988
B32: Base | E32: 1 | F32: 135 | G32: 138 | H32: 140 | I32: 140 | J32: 138 | M32: Historical Average | N32: =AVERAGE(NWC!C31:F31) -> 141.55497
B33: Management | E33: 2 | F33: 140 | G33: 145 | H33: 148 | I33: 148 | J33: 145 | M33: Industry average | N33: 90
B34: Upside | E34: 3 | F34: 145 | G34: 150 | H34: 152 | I34: 152 | J34: 150 | M34: Earnings call or MD&A (if avilable) | N34: General comment only
B35: Downside 1 | E35: 4 | F35: 128 | G35: 128 | H35: 130 | I35: 130 | J35: 128
B36: Downside 2 | E36: 5 | F36: 120 | G36: 118 | H36: 120 | I36: 120 | J36: 118
B38: Other Current Liabilities (% of sales) | F38: =CHOOSE(DCF!$D$4,F39,F40,F41,F42,F43) -> 0.065 | G38: =CHOOSE(DCF!$D$4,G39,G40,G41,G42,G43) -> 0.063 | H38: =CHOOSE(DCF!$D$4,H39,H40,H41,H42,H43) -> 0.06 | I38: =CHOOSE(DCF!$D$4,I39,I40,I41,I42,I43) -> 0.058 | J38: =CHOOSE(DCF!$D$4,J39,J40,J41,J42,J43) -> 0.056 | M38: Previous year | N38: =NWC!F32 -> 0.065384984
B39: Base | E39: 1 | F39: 0.065 | G39: 0.063 | H39: 0.06 | I39: 0.058 | J39: 0.056 | M39: Historical Average | N39: =AVERAGE(NWC!C32:F32) -> 0.05394615
B40: Management | E40: 2 | F40: 0.06 | G40: 0.057 | H40: 0.054 | I40: 0.052 | J40: 0.05 | M40: Industry average | N40: 0.02
B41: Upside | E41: 3 | F41: 0.055 | G41: 0.052 | H41: 0.049 | I41: 0.047 | J41: 0.045 | M41: Earnings call or MD&A (if avilable) | N41: Not guided
B42: Downside 1 | E42: 4 | F42: 0.07 | G42: 0.072 | H42: 0.07 | I42: 0.068 | J42: 0.066
B43: Downside 2 | E43: 5 | F43: 0.075 | G43: 0.078 | H43: 0.076 | I43: 0.074 | J43: 0.072

Sheet Rights
A1: Copyright © 2009 by Joshua Rosenbaum and Joshua Pearl. All rights reserved.
A3: Published by John Wiley & Sons, Inc., Hoboken, New Jersey.
A4: Published simultaneously in Canada.
A6: No part of this publication may be reproduced, stored in a retrieval system, or transmitted in
A7: any form or by any means, electronic, mechanical, photocopying, recording, scanning, or
A8: otherwise, except as permitted under Section 107 or 108 of the 1976 United States Copyright
A9: Act, without either the prior written permission of the Publisher, or authorization through
A10: payment of the appropriate per-copy fee to the Copyright Clearance Center, Inc., 222
A11: Rosewood Drive, Danvers, MA 01923, (978) 750-8400, fax (978) 750-4470, or on the web
A12: at www.copyright.com. Requests to the Publisher for permission should be addressed to the
A13: Permissions Department, John Wiley & Sons, Inc., 111 River Street, Hoboken, NJ 07030,
A14: (201) 748-6011, fax (201) 748-6008, or online at http://www.wiley.com/go/permissions.
... A42: 10 9 8 7 6 5 4 3 2 1

Sheet Monte Carlo
A1: Granules India Limited: Monte Carlo Simulation of Intrinsic Value
A2: (Rs. in crore, except per-share data; 500 trials, present-year (FY27-31) DCF)
A4: Methodology: each trial draws two independent uniform random numbers and converts them to a symmetric triangular(0, 0.5, 1) weight:
A5: w1 (Operating Scenario weight) - interpolates Sales Growth, COGS%, SG&A%, D&A% and CapEx% linearly between the Downside 2 case (w1=0) and the Upside case (w1=1) built in the A1 sheet, for each forecast year FY27-31.
A6: w2 (Market/Discount-Rate weight) - interpolates WACC and the Exit Multiple linearly between the low and high ends of the sensitivity ranges already used on the DCF sheet.
A7: A triangular(0,0.5,1) shape is used (not uniform) so trials cluster around the Base case, matching how the case was built (three-anchor Base case, with Upside/Downside as deliberate stress scenarios rather than equally likely outcomes).
A8: Simplifications (for tractability, disclosed rather than hidden): (1) Net debt is held fixed at Rs562.14cr (J48-J51 on the DCF sheet) in every trial - financing risk is not separately randomized. (2) The change in Net Working Capital is approximated as (change in Sales) x the FY26 actual NWC-to-Sales ratio (33.2%), held constant across trials, rather than re-deriving DSO/DIH/DPO per trial. (3) Shares outstanding are held fixed at 24.78cr.
A9: Everything else (Sales, COGS, SG&A, EBITDA, D&A, CapEx, Tax, FCF, discounting, terminal value, Enterprise/Equity Value, Share Price) is computed fresh for every trial from the randomized drivers - this is a full re-run of the DCF logic per trial, not a shortcut sensitivity table.
A11: Simulation Results (Implied Share Price, Rs.)
A12: Mean | C12: =AVERAGE(TrialPrice) -> 724.39311
A13: Median | C13: =MEDIAN(TrialPrice) -> 708.09222
A14: Std. Deviation | C14: =STDEV(TrialPrice) -> 185.4125
A15: Minimum | C15: =MIN(TrialPrice) -> 352.94634
A16: 5th percentile | C16: =PERCENTILE(TrialPrice,0.05) -> 452.42765
A17: 25th percentile | C17: =PERCENTILE(TrialPrice,0.25) -> 583.6506
A18: 75th percentile | C18: =PERCENTILE(TrialPrice,0.75) -> 850.16146
A19: 95th percentile | C19: =PERCENTILE(TrialPrice,0.95) -> 1042.2078
A20: Maximum | C20: =MAX(TrialPrice) -> 1322.6717
A21: P(price < current market price ~Rs847) | C21: =COUNTIF(TrialPrice,"<847")/COUNT(TrialPrice) -> 0.74
A22: P(price < Downside 2 single-point estimate, Rs336) | C22: =COUNTIF(TrialPrice,"<336")/COUNT(TrialPrice) -> 0
A23: P(price > Upside single-point estimate, Rs1,335) | C23: =COUNTIF(TrialPrice,">1335")/COUNT(TrialPrice) -> 0
A26: Trial# | B26: u1 | C26: w1 (Op.) | D26: u2 | E26: w2 (Mkt.) | F26: Sales FY27 | G26: Sales FY28 | H26: Sales FY29 | I26: Sales FY30 | J26: Sales FY31 | K26: COGS% FY27 | L26: COGS% FY28 | M26: COGS% FY29 | N26: COGS% FY30 | O26: COGS% FY31 | P26: SG&A% FY27 | Q26: SG&A% FY28 | R26: SG&A% FY29 | S26: SG&A% FY30 | T26: SG&A% FY31 | U26: EBITDA FY27 | V26: EBITDA FY28 | W26: EBITDA FY29 | X26: EBITDA FY30 | Y26: EBITDA FY31 | Z26: D&A FY27 | AA26: D&A FY28 | AB26: D&A FY29 | AC26: D&A FY30 | AD26: D&A FY31 | AE26: CapEx FY27 | AF26: CapEx FY28 | AG26: CapEx FY29 | AH26: CapEx FY30 | AI26: CapEx FY31 | AJ26: Tax FY27 | AK26: Tax FY28 | AL26: Tax FY29 | AM26: Tax FY30 | AN26: Tax FY31 | AO26: ΔNWC FY27 | AP26: ΔNWC FY28 | AQ26: ΔNWC FY29 | AR26: ΔNWC FY30 | AS26: ΔNWC FY31 | AT26: FCF FY27 | AU26: FCF FY28 | AV26: FCF FY29 | AW26: FCF FY30 | AX26: FCF FY31 | AY26: WACC | AZ26: Exit Mult. | BA26: PV of FCF | BB26: Terminal Value | BC26: PV of TV | BD26: Enterprise Value | BE26: Equity Value | BF26: Share Price
A27: 1 | B27: =RAND() -> 0.33647521 | C27: =IF(B27<0.5,SQRT(0.5*B27),1-SQRT(0.5*(1-B27))) -> 0.41016778 | D27: =RAND() -> 0.28332894 | E27: =IF(D27<0.5,SQRT(0.5*D27),1-SQRT(0.5*(1-D27))) -> 0.37638341 | F27: =DCF!$H$7*(1+('A1'!F14+$C27*('A1'!F12-'A1'!F14))) -> 6251.6062 | G27: =F27*(1+('A1'!G14+$C27*('A1'!G12-'A1'!G14))) -> 7011.3337 | H27: =G27*(1+('A1'!H14+$C27*('A1'!H12-'A1'!H14))) -> 7735.7574 | I27: =H27*(1+('A1'!I14+$C27*('A1'!I12-'A1'!I14))) -> 8408.1115 | J27: =I27*(1+('A1'!J14+$C27*('A1'!J12-'A1'!J14))) -> 9069.9286 | K27: ='A1'!F21+$C27*('A1'!F19-'A1'!F21) -> 0.35744077 | L27: ='A1'!G21+$C27*('A1'!G19-'A1'!G21) -> 0.35423742 | M27: ='A1'!H21+$C27*('A1'!H19-'A1'!H21) -> 0.34513574 | N27: ='A1'!I21+$C27*('A1'!I19-'A1'!I21) -> 0.34013574 | O27: ='A1'!J21+$C27*('A1'!J19-'A1'!J21) -> 0.33513574 | P27: ='A1'!F28+$C27*('A1'!F26-'A1'!F28) -> 0.44974581 | Q27: ='A1'!G28+$C27*('A1'!G26-'A1'!G28) -> 0.44654245 | R27: ='A1'!H28+$C27*('A1'!H26-'A1'!H28) -> 0.44038993 | S27: ='A1'!I28+$C27*('A1'!I26-'A1'!I28) -> 0.43833909 | T27: ='A1'!J28+$C27*('A1'!J26-'A1'!J28) -> 0.43628826 | U27: =F27*(1-K27-P27) -> 1205.3936 | V27: =G27*(1-L27-Q27) -> 1396.7988 | W27: =H27*(1-M27-R27) -> 1659.1214 | X27: =I27*(1-N27-S27) -> 1862.6083 | Y27: =J27*(1-O27-T27) -> 2073.1681 | Z27: =F27*('A1'!F35+$C27*('A1'!F33-'A1'!F35)) -> 362.27533 | AA27: =G27*('A1'!G35+$C27*('A1'!G33-'A1'!G35)) -> 405.94446 | AB27: =H27*('A1'!H35+$C27*('A1'!H33-'A1'!H35)) -> 429.2429 | AC27: =I27*('A1'!I35+$C27*('A1'!I33-'A1'!I35)) -> 446.28563 | AD27: =J27*('A1'!J35+$C27*('A1'!J33-'A1'!J35)) -> 463.27369 | AE27: =F27*('A1'!F43+$C27*('A1'!F41-'A1'!F43)) -> 636.39253 | AF27: =G27*('A1'!G43+$C27*('A1'!G41-'A1'!G43)) -> 705.64956 | AG27: =H27*('A1'!H43+$C27*('A1'!H41-'A1'!H43)) -> 701.20098 | AH27: =I27*('A1'!I43+$C27*('A1'!I41-'A1'!I43)) -> 678.06482 | AI27: =J27*('A1'!J43+$C27*('A1'!J41-'A1'!J43)) -> 686.08684 | AJ27: =(U27-Z27)*DCF!$H$40 -> 204.03462 | AK27: =(V27-AA27)*DCF!$H$40 -> 239.78676 | AL27: =(W27-AB27)*DCF!$H$40 -> 297.63059 | AM27: =(X27-AC27)*DCF!$H$40 -> 342.75009 | AN27: =(Y27-AD27)*DCF!$H$40 -> 389.59444 | AO27: =(F27-DCF!$H$7)*DCF!$H$41 -> 293.99671 | AP27: =(G27-F27)*DCF!$H$41 -> 252.10599 | AQ27: =(H27-G27)*DCF!$H$41 -> 240.39087 | AR27: =(I27-H27)*DCF!$H$41 -> 223.11224 | AS27: =(J27-I27)*DCF!$H$41 -> 219.61567 | AT27: =(U27-Z27)*(1-DCF!$H$40)+Z27-AE27-AO27 -> 70.969722 | AU27: =(V27-AA27)*(1-DCF!$H$40)+AA27-AF27-AP27 -> 199.25652 | AV27: =(W27-AB27)*(1-DCF!$H$40)+AB27-AG27-AQ27 -> 419.89892 | AW27: =(X27-AC27)*(1-DCF!$H$40)+AC27-AH27-AR27 -> 618.68115 | AX27: =(Y27-AD27)*(1-DCF!$H$40)+AD27-AI27-AS27 -> 777.87111 | AY27: =0.0925+$E27*(0.1125-0.0925) -> 0.10002767 | AZ27: =10+$E27*(14-10) -> 11.505534 | BA27: =SUMPRODUCT(AT27:AX27,(1+$AY27)^(-{1,2,3,4,5})) -> 1450.0964 | BB27: =Y27*$AZ27 -> 23852.905 | BC27: =BB27*(1+$AY27)^(-5) -> 14808.915 | BD27: =BA27+BC27 -> 16259.011 | BE27: =BD27-(DCF!$J$48-DCF!$J$51) -> 15696.871 | BF27: =BE27/DCF!$J$55 -> 633.45707
A28: 2 | B28: =RAND() -> 0.37503102 | C28: =IF(B28<0.5,SQRT(0.5*B28),1-SQRT(0.5*(1-B28))) -> 0.43303061 | D28: =RAND() -> 0.093130366 | E28: =IF(D28<0.5,SQRT(0.5*D28),1-SQRT(0.5*(1-D28))) -> 0.21578967 | F28: =DCF!$H$7*(1+('A1'!F14+$C28*('A1'!F12-'A1'!F14))) -> 6265.1003 | G28: =F28*(1+('A1'!G14+$C28*('A1'!G12-'A1'!G14))) -> 7047.9533 | H28: =G28*(1+('A1'!H14+$C28*('A1'!H12-'A1'!H14))) -> 7797.1084 | I28: =H28*(1+('A1'!I14+$C28*('A1'!I12-'A1'!I14))) -> 8490.8386 | J28: =I28*(1+('A1'!J14+$C28*('A1'!J12-'A1'!J14))) -> 9172.756 | K28: ='A1'!F21+$C28*('A1'!F19-'A1'!F21) -> 0.35618332 | L28: ='A1'!G21+$C28*('A1'!G19-'A1'!G21) -> 0.3525227 | M28: ='A1'!H21+$C28*('A1'!H19-'A1'!H21) -> 0.3431924 | N28: ='A1'!I21+$C28*('A1'!I19-'A1'!I21) -> 0.3381924 | O28: ='A1'!J21+$C28*('A1'!J19-'A1'!J21) -> 0.3331924 | P28: ='A1'!F28+$C28*('A1'!F26-'A1'!F28) -> 0.44917423 | Q28: ='A1'!G28+$C28*('A1'!G26-'A1'!G28) -> 0.44551362 | R28: ='A1'!H28+$C28*('A1'!H26-'A1'!H28) -> 0.43901816 | S28: ='A1'!I28+$C28*('A1'!I26-'A1'!I28) -> 0.43685301 | T28: ='A1'!J28+$C28*('A1'!J26-'A1'!J28) -> 0.43468786 | U28: =F28*(1-K28-P28) -> 1219.4545 | V28: =G28*(1-L28-Q28) -> 1423.4305 | W28: =H28*(1-M28-R28) -> 1698.1278 | X28: =I28*(1-N28-S28) -> 1910.0531 | Y28: =J28*(1-O28-T28) -> 2129.1778 | Z28: =F28*('A1'!F35+$C28*('A1'!F33-'A1'!F35)) -> 362.34112 | AA28: =G28*('A1'!G35+$C28*('A1'!G33-'A1'!G35)) -> 406.45331 | AB28: =H28*('A1'!H35+$C28*('A1'!H33-'A1'!H35)) -> 430.68625 | AC28: =I28*('A1'!I35+$C28*('A1'!I33-'A1'!I35)) -> 448.34712 | AD28: =J28*('A1'!J35+$C28*('A1'!J33-'A1'!J35)) -> 466.00933 | AE28: =F28*('A1'!F43+$C28*('A1'!F41-'A1'!F43)) -> 634.90143 | AF28: =G28*('A1'!G43+$C28*('A1'!G41-'A1'!G43)) -> 703.69535 | AG28: =H28*('A1'!H43+$C28*('A1'!H41-'A1'!H43)) -> 700.52285 | AH28: =I28*('A1'!I43+$C28*('A1'!I41-'A1'!I43)) -> 677.94191 | AI28: =J28*('A1'!J43+$C28*('A1'!J41-'A1'!J43)) -> 686.5251 | AJ28: =(U28-Z28)*DCF!$H$40 -> 207.42143 | AK28: =(V28-AA28)*DCF!$H$40 -> 246.10849 | AL28: =(W28-AB28)*DCF!$H$40 -> 306.72087 | AM28: =(X28-AC28)*DCF!$H$40 -> 353.73285 | AN28: =(Y28-AD28)*DCF!$H$40 -> 402.48677 | AO28: =(F28-DCF!$H$7)*DCF!$H$41 -> 298.47456 | AP28: =(G28-F28)*DCF!$H$41 -> 259.77992 | AQ28: =(H28-G28)*DCF!$H$41 -> 248.59765 | AR28: =(I28-H28)*DCF!$H$41 -> 230.20563 | AS28: =(J28-I28)*DCF!$H$41 -> 226.28571 | AT28: =(U28-Z28)*(1-DCF!$H$40)+Z28-AE28-AO28 -> 78.657043 | AU28: =(V28-AA28)*(1-DCF!$H$40)+AA28-AF28-AP28 -> 213.84679 | AV28: =(W28-AB28)*(1-DCF!$H$40)+AB28-AG28-AQ28 -> 442.28649 | AW28: =(X28-AC28)*(1-DCF!$H$40)+AC28-AH28-AR28 -> 648.17273 | AX28: =(Y28-AD28)*(1-DCF!$H$40)+AD28-AI28-AS28 -> 813.88021 | AY28: =0.0925+$E28*(0.1125-0.0925) -> 0.096815793 | AZ28: =10+$E28*(14-10) -> 10.863159 | BA28: =SUMPRODUCT(AT28:AX28,(1+$AY28)^(-{1,2,3,4,5})) -> 1545.2814 | BB28: =Y28*$AZ28 -> 23129.596 | BC28: =BB28*(1+$AY28)^(-5) -> 14571.343 | BD28: =BA28+BC28 -> 16116.624 | BE28: =BD28-(DCF!$J$48-DCF!$J$51) -> 15554.484 | BF28: =BE28/DCF!$J$55 -> 627.71095
A29: 3 | B29: =RAND() -> 0.4961647 | C29: =IF(B29<0.5,SQRT(0.5*B29),1-SQRT(0.5*(1-B29))) -> 0.49807866 | D29: =RAND() -> 0.0083040635 | E29: =IF(D29<0.5,SQRT(0.5*D29),1-SQRT(0.5*(1-D29))) -> 0.064436261 | F29: =DCF!$H$7*(1+('A1'!F14+$C29*('A1'!F12-'A1'!F14))) -> 6303.493 | G29: =F29*(1+('A1'!G14+$C29*('A1'!G12-'A1'!G14))) -> 7152.6479 | H29: =G29*(1+('A1'!H14+$C29*('A1'!H12-'A1'!H14))) -> 7973.4158 | I29: =H29*(1+('A1'!I14+$C29*('A1'!I12-'A1'!I14))) -> 8729.5116 | J29: =I29*(1+('A1'!J14+$C29*('A1'!J12-'A1'!J14))) -> 9470.346 | K29: ='A1'!F21+$C29*('A1'!F19-'A1'!F21) -> 0.35260567 | L29: ='A1'!G21+$C29*('A1'!G19-'A1'!G21) -> 0.3476441 | M29: ='A1'!H21+$C29*('A1'!H19-'A1'!H21) -> 0.33766331 | N29: ='A1'!I21+$C29*('A1'!I19-'A1'!I21) -> 0.33266331 | O29: ='A1'!J21+$C29*('A1'!J19-'A1'!J21) -> 0.32766331 | P29: ='A1'!F28+$C29*('A1'!F26-'A1'!F28) -> 0.44754803 | Q29: ='A1'!G28+$C29*('A1'!G26-'A1'!G28) -> 0.44258646 | R29: ='A1'!H28+$C29*('A1'!H26-'A1'!H28) -> 0.43511528 | S29: ='A1'!I28+$C29*('A1'!I26-'A1'!I28) -> 0.43262489 | T29: ='A1'!J28+$C29*('A1'!J26-'A1'!J28) -> 0.43013449 | U29: =F29*(1-K29-P29) -> 1259.7297 | V29: =G29*(1-L29-Q29) -> 1500.4069 | W29: =H29*(1-M29-R29) -> 1811.7308 | X29: =I29*(1-N29-S29) -> 2048.9194 | Y29: =J29*(1-O29-T29) -> 2293.7386 | Z29: =F29*('A1'!F35+$C29*('A1'!F33-'A1'!F35)) -> 362.5114 | AA29: =G29*('A1'!G35+$C29*('A1'!G33-'A1'!G35)) -> 407.83836 | AB29: =H29*('A1'!H35+$C29*('A1'!H33-'A1'!H35)) -> 434.71968 | AC29: =I29*('A1'!I35+$C29*('A1'!I33-'A1'!I35)) -> 454.13587 | AD29: =J29*('A1'!J35+$C29*('A1'!J33-'A1'!J35)) -> 473.73565 | AE29: =F29*('A1'!F43+$C29*('A1'!F41-'A1'!F43)) -> 630.59152 | AF29: =G29*('A1'!G43+$C29*('A1'!G41-'A1'!G43)) -> 697.86416 | AG29: =H29*('A1'!H43+$C29*('A1'!H41-'A1'!H43)) -> 698.21007 | AH29: =I29*('A1'!I43+$C29*('A1'!I41-'A1'!I43)) -> 677.12418 | AI29: =J29*('A1'!J43+$C29*('A1'!J41-'A1'!J43)) -> 687.23693 | AJ29: =(U29-Z29)*DCF!$H$40 -> 217.12683 | AK29: =(V29-AA29)*DCF!$H$40 -> 264.4016 | AL29: =(W29-AB29)*DCF!$H$40 -> 333.23668 | AM29: =(X29-AC29)*DCF!$H$40 -> 385.93761 | AN29: =(Y29-AD29)*DCF!$H$40 -> 440.4407 | AO29: =(F29-DCF!$H$7)*DCF!$H$41 -> 311.21469 | AP29: =(G29-F29)*DCF!$H$41 -> 281.78134 | AQ29: =(H29-G29)*DCF!$H$41 -> 272.3615 | AR29: =(I29-H29)*DCF!$H$41 -> 250.90084 | AS29: =(J29-I29)*DCF!$H$41 -> 245.83656 | AT29: =(U29-Z29)*(1-DCF!$H$40)+Z29-AE29-AO29 -> 100.79666 | AU29: =(V29-AA29)*(1-DCF!$H$40)+AA29-AF29-AP29 -> 256.35983 | AV29: =(W29-AB29)*(1-DCF!$H$40)+AB29-AG29-AQ29 -> 507.9225 | AW29: =(X29-AC29)*(1-DCF!$H$40)+AC29-AH29-AR29 -> 734.95674 | AX29: =(Y29-AD29)*(1-DCF!$H$40)+AD29-AI29-AS29 -> 920.22436 | AY29: =0.0925+$E29*(0.1125-0.0925) -> 0.093788725 | AZ29: =10+$E29*(14-10) -> 10.257745 | BA29: =SUMPRODUCT(AT29:AX29,(1+$AY29)^(-{1,2,3,4,5})) -> 1795.8633 | BB29: =Y29*$AZ29 -> 23528.585 | BC29: =BB29*(1+$AY29)^(-5) -> 15028.949 | BD29: =BA29+BC29 -> 16824.812 | BE29: =BD29-(DCF!$J$48-DCF!$J$51) -> 16262.672 | BF29: =BE29/DCF!$J$55 -> 656.29032
A30: 4 | B30: =RAND() -> 0.87237964 | C30: =IF(B30<0.5,SQRT(0.5*B30),1-SQRT(0.5*(1-B30))) -> 0.74739323 | D30: =RAND() -> 0.39538373 | E30: =IF(D30<0.5,SQRT(0.5*D30),1-SQRT(0.5*(1-D30))) -> 0.44462553 | F30: =DCF!$H$7*(1+('A1'!F14+$C30*('A1'!F12-'A1'!F14))) -> 6450.6435 | G30: =F30*(1+('A1'!G14+$C30*('A1'!G12-'A1'!G14))) -> 7560.8572 | H30: =G30*(1+('A1'!H14+$C30*('A1'!H12-'A1'!H14))) -> 8673.5215 | I30: =H30*(1+('A1'!I14+$C30*('A1'!I12-'A1'!I14))) -> 9690.6254 | J30: =I30*(1+('A1'!J14+$C30*('A1'!J12-'A1'!J14))) -> 10682.146 | K30: ='A1'!F21+$C30*('A1'!F19-'A1'!F21) -> 0.33889337 | L30: ='A1'!G21+$C30*('A1'!G19-'A1'!G21) -> 0.32894551 | M30: ='A1'!H21+$C30*('A1'!H19-'A1'!H21) -> 0.31647158 | N30: ='A1'!I21+$C30*('A1'!I19-'A1'!I21) -> 0.31147158 | O30: ='A1'!J21+$C30*('A1'!J19-'A1'!J21) -> 0.30647158 | P30: ='A1'!F28+$C30*('A1'!F26-'A1'!F28) -> 0.44131517 | Q30: ='A1'!G28+$C30*('A1'!G26-'A1'!G28) -> 0.4313673 | R30: ='A1'!H28+$C30*('A1'!H26-'A1'!H28) -> 0.42015641 | S30: ='A1'!I28+$C30*('A1'!I26-'A1'!I28) -> 0.41641944 | T30: ='A1'!J28+$C30*('A1'!J26-'A1'!J28) -> 0.41268247 | U30: =F30*(1-K30-P30) -> 1417.7964 | V30: =G30*(1-L30-Q30) -> 1812.2406 | W30: =H30*(1-M30-R30) -> 2284.3629 | X30: =I30*(1-N30-S30) -> 2636.9062 | Y30: =J30*(1-O30-T30) -> 3000.0375 | Z30: =F30*('A1'!F35+$C30*('A1'!F33-'A1'!F35)) -> 362.93278 | AA30: =G30*('A1'!G35+$C30*('A1'!G33-'A1'!G35)) -> 412.26381 | AB30: =H30*('A1'!H35+$C30*('A1'!H33-'A1'!H35)) -> 449.10344 | AC30: =I30*('A1'!I35+$C30*('A1'!I33-'A1'!I35)) -> 475.14378 | AD30: =J30*('A1'!J35+$C30*('A1'!J33-'A1'!J35)) -> 502.39502 | AE30: =F30*('A1'!F43+$C30*('A1'!F41-'A1'!F43)) -> 613.14744 | AF30: =G30*('A1'!G43+$C30*('A1'!G41-'A1'!G43)) -> 671.71591 | AG30: =H30*('A1'!H43+$C30*('A1'!H41-'A1'!H43)) -> 683.83116 | AH30: =I30*('A1'!I43+$C30*('A1'!I41-'A1'!I43)) -> 667.11463 | AI30: =J30*('A1'!J43+$C30*('A1'!J41-'A1'!J43)) -> 681.96142 | AJ30: =(U30-Z30)*DCF!$H$40 -> 255.27699 | AK30: =(V30-AA30)*DCF!$H$40 -> 338.79439 | AL30: =(W30-AB30)*DCF!$H$40 -> 444.13278 | AM30: =(X30-AC30)*DCF!$H$40 -> 523.14651 | AN30: =(Y30-AD30)*DCF!$H$40 -> 604.42948 | AO30: =(F30-DCF!$H$7)*DCF!$H$41 -> 360.04475 | AP30: =(G30-F30)*DCF!$H$41 -> 368.41043 | AQ30: =(H30-G30)*DCF!$H$41 -> 369.2236 | AR30: =(I30-H30)*DCF!$H$41 -> 337.5131 | AS30: =(J30-I30)*DCF!$H$41 -> 329.02368 | AT30: =(U30-Z30)*(1-DCF!$H$40)+Z30-AE30-AO30 -> 189.32718 | AU30: =(V30-AA30)*(1-DCF!$H$40)+AA30-AF30-AP30 -> 433.31989 | AV30: =(W30-AB30)*(1-DCF!$H$40)+AB30-AG30-AQ30 -> 787.17532 | AW30: =(X30-AC30)*(1-DCF!$H$40)+AC30-AH30-AR30 -> 1109.132 | AX30: =(Y30-AD30)*(1-DCF!$H$40)+AD30-AI30-AS30 -> 1384.6229 | AY30: =0.0925+$E30*(0.1125-0.0925) -> 0.10139251 | AZ30: =10+$E30*(14-10) -> 11.778502 | BA30: =SUMPRODUCT(AT30:AX30,(1+$AY30)^(-{1,2,3,4,5})) -> 2726.3336 | BB30: =Y30*$AZ30 -> 35335.948 | BC30: =BB30*(1+$AY30)^(-5) -> 21802.493 | BD30: =BA30+BC30 -> 24528.826 | BE30: =BD30-(DCF!$J$48-DCF!$J$51) -> 23966.686 | BF30: =BE30/DCF!$J$55 -> 967.19065
A31: 5 | B31: =RAND() -> 0.16906025 | C31: =IF(B31<0.5,SQRT(0.5*B31),1-SQRT(0.5*(1-B31))) -> 0.29074065 | D31: =RAND() -> 0.11844042 | E31: =IF(D31<0.5,SQRT(0.5*D31),1-SQRT(0.5*(1-D31))) -> 0.24335203 | F31: =DCF!$H$7*(1+('A1'!F14+$C31*('A1'!F12-'A1'!F14))) -> 6181.1179 | G31: =F31*(1+('A1'!G14+$C31*('A1'!G12-'A1'!G14))) -> 6821.5503 | H31: =G31*(1+('A1'!H14+$C31*('A1'!H12-'A1'!H14))) -> 7420.457 | I31: =H31*(1+('A1'!I14+$C31*('A1'!I12-'A1'!I14))) -> 7985.6485 | J31: =I31*(1+('A1'!J14+$C31*('A1'!J12-'A1'!J14))) -> 8547.4536 | K31: ='A1'!F21+$C31*('A1'!F19-'A1'!F21) -> 0.36400926 | L31: ='A1'!G21+$C31*('A1'!G19-'A1'!G21) -> 0.36319445 | M31: ='A1'!H21+$C31*('A1'!H19-'A1'!H21) -> 0.35528704 | N31: ='A1'!I21+$C31*('A1'!I19-'A1'!I21) -> 0.35028704 | O31: ='A1'!J21+$C31*('A1'!J19-'A1'!J21) -> 0.34528704 | P31: ='A1'!F28+$C31*('A1'!F26-'A1'!F28) -> 0.45273148 | Q31: ='A1'!G28+$C31*('A1'!G26-'A1'!G28) -> 0.45191667 | R31: ='A1'!H28+$C31*('A1'!H26-'A1'!H28) -> 0.44755556 | S31: ='A1'!I28+$C31*('A1'!I26-'A1'!I28) -> 0.44610186 | T31: ='A1'!J28+$C31*('A1'!J26-'A1'!J28) -> 0.44464815 | U31: =F31*(1-K31-P31) -> 1132.747 | V31: =G31*(1-L31-Q31) -> 1261.2288 | W31: =H31*(1-M31-R31) -> 1462.998 | X31: =I31*(1-N31-S31) -> 1625.9666 | Y31: =J31*(1-O31-T31) -> 1795.5191 | Z31: =F31*('A1'!F35+$C31*('A1'!F33-'A1'!F35)) -> 361.88156 | AA31: =G31*('A1'!G35+$C31*('A1'!G33-'A1'!G35)) -> 403.1031 | AB31: =H31*('A1'!H35+$C31*('A1'!H33-'A1'!H35)) -> 421.49571 | AC31: =I31*('A1'!I35+$C31*('A1'!I33-'A1'!I35)) -> 435.30658 | AD31: =J31*('A1'!J35+$C31*('A1'!J33-'A1'!J35)) -> 448.83629 | AE31: =F31*('A1'!F43+$C31*('A1'!F41-'A1'!F43)) -> 643.98092 | AF31: =G31*('A1'!G43+$C31*('A1'!G41-'A1'!G43)) -> 715.06271 | AG31: =H31*('A1'!H43+$C31*('A1'!H41-'A1'!H43)) -> 703.63799 | AH31: =I31*('A1'!I43+$C31*('A1'!I41-'A1'!I43)) -> 677.37526 | AI31: =J31*('A1'!J43+$C31*('A1'!J41-'A1'!J43)) -> 682.29259 | AJ31: =(U31-Z31)*DCF!$H$40 -> 186.54945 | AK31: =(V31-AA31)*DCF!$H$40 -> 207.66641 | AL31: =(W31-AB31)*DCF!$H$40 -> 252.04355 | AM31: =(X31-AC31)*DCF!$H$40 -> 288.13974 | AN31: =(Y31-AD31)*DCF!$H$40 -> 325.89725 | AO31: =(F31-DCF!$H$7)*DCF!$H$41 -> 270.60605 | AP31: =(G31-F31)*DCF!$H$41 -> 212.51942 | AQ31: =(H31-G31)*DCF!$H$41 -> 198.73966 | AR31: =(I31-H31)*DCF!$H$41 -> 187.55165 | AS31: =(J31-I31)*DCF!$H$41 -> 186.42794 | AT31: =(U31-Z31)*(1-DCF!$H$40)+Z31-AE31-AO31 -> 31.610621 | AU31: =(V31-AA31)*(1-DCF!$H$40)+AA31-AF31-AP31 -> 125.98023 | AV31: =(W31-AB31)*(1-DCF!$H$40)+AB31-AG31-AQ31 -> 308.57677 | AW31: =(X31-AC31)*(1-DCF!$H$40)+AC31-AH31-AR31 -> 472.9 | AX31: =(Y31-AD31)*(1-DCF!$H$40)+AD31-AI31-AS31 -> 600.90135 | AY31: =0.0925+$E31*(0.1125-0.0925) -> 0.097367041 | AZ31: =10+$E31*(14-10) -> 10.973408 | BA31: =SUMPRODUCT(AT31:AX31,(1+$AY31)^(-{1,2,3,4,5})) -> 1070.6513 | BB31: =Y31*$AZ31 -> 19702.964 | BC31: =BB31*(1+$AY31)^(-5) -> 12381.464 | BD31: =BA31+BC31 -> 13452.116 | BE31: =BD31-(DCF!$J$48-DCF!$J$51) -> 12889.976 | BF31: =BE31/DCF!$J$55 -> 520.18304
A32: 6 | B32: =RAND() -> 0.5092443 | C32: =IF(B32<0.5,SQRT(0.5*B32),1-SQRT(0.5*(1-B32))) -> 0.50464371 | D32: =RAND() -> 0.069103085 | E32: =IF(D32<0.5,SQRT(0.5*D32),1-SQRT(0.5*(1-D32))) -> 0.18588045 | F32: =DCF!$H$7*(1+('A1'!F14+$C32*('A1'!F12-'A1'!F14))) -> 6307.3678 | G32: =F32*(1+('A1'!G14+$C32*('A1'!G12-'A1'!G14))) -> 7163.2559 | H32: =G32*(1+('A1'!H14+$C32*('A1'!H12-'A1'!H14))) -> 7991.3547 | I32: =H32*(1+('A1'!I14+$C32*('A1'!I12-'A1'!I14))) -> 8753.8732 | J32: =I32*(1+('A1'!J14+$C32*('A1'!J12-'A1'!J14))) -> 9500.798 | K32: ='A1'!F21+$C32*('A1'!F19-'A1'!F21) -> 0.3522446 | L32: ='A1'!G21+$C32*('A1'!G19-'A1'!G21) -> 0.34715172 | M32: ='A1'!H21+$C32*('A1'!H19-'A1'!H21) -> 0.33710528 | N32: ='A1'!I21+$C32*('A1'!I19-'A1'!I21) -> 0.33210528 | O32: ='A1'!J21+$C32*('A1'!J19-'A1'!J21) -> 0.32710528 | P32: ='A1'!F28+$C32*('A1'!F26-'A1'!F28) -> 0.44738391 | Q32: ='A1'!G28+$C32*('A1'!G26-'A1'!G28) -> 0.44229103 | R32: ='A1'!H28+$C32*('A1'!H26-'A1'!H28) -> 0.43472138 | S32: ='A1'!I28+$C32*('A1'!I26-'A1'!I28) -> 0.43219816 | T32: ='A1'!J28+$C32*('A1'!J26-'A1'!J28) -> 0.42967494 | U32: =F32*(1-K32-P32) -> 1263.8167 | V32: =G32*(1-L32-Q32) -> 1508.2754 | W32: =H32*(1-M32-R32) -> 1823.4141 | X32: =I32*(1-N32-S32) -> 2063.2578 | Y32: =J32*(1-O32-T32) -> 2310.782 | Z32: =F32*('A1'!F35+$C32*('A1'!F33-'A1'!F35)) -> 362.5272 | AA32: =G32*('A1'!G35+$C32*('A1'!G33-'A1'!G35)) -> 407.97295 | AB32: =H32*('A1'!H35+$C32*('A1'!H33-'A1'!H35)) -> 435.12062 | AC32: =I32*('A1'!I35+$C32*('A1'!I33-'A1'!I35)) -> 454.7136 | AD32: =J32*('A1'!J35+$C32*('A1'!J33-'A1'!J35)) -> 474.51047 | AE32: =F32*('A1'!F43+$C32*('A1'!F41-'A1'!F43)) -> 630.15099 | AF32: =G32*('A1'!G43+$C32*('A1'!G41-'A1'!G43)) -> 697.25321 | AG32: =H32*('A1'!H43+$C32*('A1'!H41-'A1'!H43)) -> 697.9447 | AH32: =I32*('A1'!I43+$C32*('A1'!I41-'A1'!I43)) -> 677.00241 | AI32: =J32*('A1'!J43+$C32*('A1'!J41-'A1'!J43)) -> 687.26369 | AJ32: =(U32-Z32)*DCF!$H$40 -> 218.11207 | AK32: =(V32-AA32)*DCF!$H$40 -> 266.2732 | AL32: =(W32-AB32)*DCF!$H$40 -> 335.96702 | AM32: =(X32-AC32)*DCF!$H$40 -> 389.26769 | AN32: =(Y32-AD32)*DCF!$H$40 -> 444.3777 | AO32: =(F32-DCF!$H$7)*DCF!$H$41 -> 312.5005 | AP32: =(G32-F32)*DCF!$H$41 -> 284.01568 | AQ32: =(H32-G32)*DCF!$H$41 -> 274.79414 | AR32: =(I32-H32)*DCF!$H$41 -> 253.03217 | AS32: =(J32-I32)*DCF!$H$41 -> 247.85757 | AT32: =(U32-Z32)*(1-DCF!$H$40)+Z32-AE32-AO32 -> 103.05317 | AU32: =(V32-AA32)*(1-DCF!$H$40)+AA32-AF32-AP32 -> 260.73335 | AV32: =(W32-AB32)*(1-DCF!$H$40)+AB32-AG32-AQ32 -> 514.70823 | AW32: =(X32-AC32)*(1-DCF!$H$40)+AC32-AH32-AR32 -> 743.95551 | AX32: =(Y32-AD32)*(1-DCF!$H$40)+AD32-AI32-AS32 -> 931.283 | AY32: =0.0925+$E32*(0.1125-0.0925) -> 0.096217609 | AZ32: =10+$E32*(14-10) -> 10.743522 | BA32: =SUMPRODUCT(AT32:AX32,(1+$AY32)^(-{1,2,3,4,5})) -> 1805.1839 | BB32: =Y32*$AZ32 -> 24825.936 | BC32: =BB32*(1+$AY32)^(-5) -> 15682.734 | BD32: =BA32+BC32 -> 17487.918 | BE32: =BD32-(DCF!$J$48-DCF!$J$51) -> 16925.778 | BF32: =BE32/DCF!$J$55 -> 683.05036
A33: 7 | B33: =RAND() -> 0.38739373 | C33: =IF(B33<0.5,SQRT(0.5*B33),1-SQRT(0.5*(1-B33))) -> 0.44011006 | D33: =RAND() -> 0.66336205 | E33: =IF(D33<0.5,SQRT(0.5*D33),1-SQRT(0.5*(1-D33))) -> 0.58973304 | F33: =DCF!$H$7*(1+('A1'!F14+$C33*('A1'!F12-'A1'!F14))) -> 6269.2787 | G33: =F33*(1+('A1'!G14+$C33*('A1'!G12-'A1'!G14))) -> 7059.3114 | H33: =G33*(1+('A1'!H14+$C33*('A1'!H12-'A1'!H14))) -> 7816.1705 | I33: =H33*(1+('A1'!I14+$C33*('A1'!I12-'A1'!I14))) -> 8516.5768 | J33: =I33*(1+('A1'!J14+$C33*('A1'!J12-'A1'!J14))) -> 9204.7819 | K33: ='A1'!F21+$C33*('A1'!F19-'A1'!F21) -> 0.35579395 | L33: ='A1'!G21+$C33*('A1'!G19-'A1'!G21) -> 0.35199175 | M33: ='A1'!H21+$C33*('A1'!H19-'A1'!H21) -> 0.34259064 | N33: ='A1'!I21+$C33*('A1'!I19-'A1'!I21) -> 0.33759064 | O33: ='A1'!J21+$C33*('A1'!J19-'A1'!J21) -> 0.33259064 | P33: ='A1'!F28+$C33*('A1'!F26-'A1'!F28) -> 0.44899725 | Q33: ='A1'!G28+$C33*('A1'!G26-'A1'!G28) -> 0.44519505 | R33: ='A1'!H28+$C33*('A1'!H26-'A1'!H28) -> 0.4385934 | S33: ='A1'!I28+$C33*('A1'!I26-'A1'!I28) -> 0.43639285 | T33: ='A1'!J28+$C33*('A1'!J26-'A1'!J28) -> 0.4341923 | U33: =F33*(1-K33-P33) -> 1223.8184 | V33: =G33*(1-L33-Q33) -> 1431.7216 | W33: =H33*(1-M33-R33) -> 1710.3029 | X33: =I33*(1-N33-S33) -> 1924.887 | Y33: =J33*(1-O33-T33) -> 2146.7122 | Z33: =F33*('A1'!F35+$C33*('A1'!F33-'A1'!F35)) -> 362.36086 | AA33: =G33*('A1'!G35+$C33*('A1'!G33-'A1'!G35)) -> 406.60856 | AB33: =H33*('A1'!H35+$C33*('A1'!H33-'A1'!H35)) -> 431.1305 | AC33: =I33*('A1'!I35+$C33*('A1'!I33-'A1'!I35)) -> 448.98268 | AD33: =J33*('A1'!J35+$C33*('A1'!J33-'A1'!J35)) -> 466.85438 | AE33: =F33*('A1'!F43+$C33*('A1'!F41-'A1'!F43)) -> 634.43721 | AF33: =G33*('A1'!G43+$C33*('A1'!G41-'A1'!G43)) -> 703.08022 | AG33: =H33*('A1'!H43+$C33*('A1'!H41-'A1'!H43)) -> 700.29877 | AH33: =I33*('A1'!I43+$C33*('A1'!I41-'A1'!I43)) -> 677.88671 | AI33: =J33*('A1'!J43+$C33*('A1'!J41-'A1'!J43)) -> 686.64127 | AJ33: =(U33-Z33)*DCF!$H$40 -> 208.47273 | AK33: =(V33-AA33)*DCF!$H$40 -> 248.07735 | AL33: =(W33-AB33)*DCF!$H$40 -> 309.55971 | AM33: =(X33-AC33)*DCF!$H$40 -> 357.16884 | AN33: =(Y33-AD33)*DCF!$H$40 -> 406.52558 | AO33: =(F33-DCF!$H$7)*DCF!$H$41 -> 299.86112 | AP33: =(G33-F33)*DCF!$H$41 -> 262.16237 | AQ33: =(H33-G33)*DCF!$H$41 -> 251.15418 | AR33: =(I33-H33)*DCF!$H$41 -> 232.421 | AS33: =(J33-I33)*DCF!$H$41 -> 228.37216 | AT33: =(U33-Z33)*(1-DCF!$H$40)+Z33-AE33-AO33 -> 81.047351 | AU33: =(V33-AA33)*(1-DCF!$H$40)+AA33-AF33-AP33 -> 218.40164 | AV33: =(W33-AB33)*(1-DCF!$H$40)+AB33-AG33-AQ33 -> 449.29019 | AW33: =(X33-AC33)*(1-DCF!$H$40)+AC33-AH33-AR33 -> 657.41042 | AX33: =(Y33-AD33)*(1-DCF!$H$40)+AD33-AI33-AS33 -> 825.17315 | AY33: =0.0925+$E33*(0.1125-0.0925) -> 0.10429466 | AZ33: =10+$E33*(14-10) -> 12.358932 | BA33: =SUMPRODUCT(AT33:AX33,(1+$AY33)^(-{1,2,3,4,5})) -> 1530.6816 | BB33: =Y33*$AZ33 -> 26531.07 | BC33: =BB33*(1+$AY33)^(-5) -> 16155.853 | BD33: =BA33+BC33 -> 17686.535 | BE33: =BD33-(DCF!$J$48-DCF!$J$51) -> 17124.395 | BF33: =BE33/DCF!$J$55 -> 691.06569
A34: 8 | B34: =RAND() -> 0.449476 | C34: =IF(B34<0.5,SQRT(0.5*B34),1-SQRT(0.5*(1-B34))) -> 0.4740654 | D34: =RAND() -> 0.50614135 | E34: =IF(D34<0.5,SQRT(0.5*D34),1-SQRT(0.5*(1-D34))) -> 0.50308016 | F34: =DCF!$H$7*(1+('A1'!F14+$C34*('A1'!F12-'A1'!F14))) -> 6289.3199 | G34: =F34*(1+('A1'!G14+$C34*('A1'!G12-'A1'!G14))) -> 7113.9114 | H34: =G34*(1+('A1'!H14+$C34*('A1'!H12-'A1'!H14))) -> 7908.0267 | I34: =H34*(1+('A1'!I14+$C34*('A1'!I12-'A1'!I14))) -> 8640.831 | J34: =I34*(1+('A1'!J14+$C34*('A1'!J12-'A1'!J14))) -> 9359.6148 | K34: ='A1'!F21+$C34*('A1'!F19-'A1'!F21) -> 0.3539264 | L34: ='A1'!G21+$C34*('A1'!G19-'A1'!G21) -> 0.3494451 | M34: ='A1'!H21+$C34*('A1'!H19-'A1'!H21) -> 0.33970444 | N34: ='A1'!I21+$C34*('A1'!I19-'A1'!I21) -> 0.33470444 | O34: ='A1'!J21+$C34*('A1'!J19-'A1'!J21) -> 0.32970444 | P34: ='A1'!F28+$C34*('A1'!F26-'A1'!F28) -> 0.44814837 | Q34: ='A1'!G28+$C34*('A1'!G26-'A1'!G28) -> 0.44366706 | R34: ='A1'!H28+$C34*('A1'!H26-'A1'!H28) -> 0.43655608 | S34: ='A1'!I28+$C34*('A1'!I26-'A1'!I28) -> 0.43418575 | T34: ='A1'!J28+$C34*('A1'!J26-'A1'!J28) -> 0.43181542 | U34: =F34*(1-K34-P34) -> 1244.8151 | V34: =G34*(1-L34-Q34) -> 1471.7818 | W34: =H34*(1-M34-R34) -> 1769.3378 | X34: =I34*(1-N34-S34) -> 1996.9808 | Y34: =J34*(1-O34-T34) -> 2232.0822 | Z34: =F34*('A1'!F35+$C34*('A1'!F33-'A1'!F35)) -> 362.45145 | AA34: =G34*('A1'!G35+$C34*('A1'!G33-'A1'!G35)) -> 407.33791 | AB34: =H34*('A1'!H35+$C34*('A1'!H33-'A1'!H35)) -> 433.24346 | AC34: =I34*('A1'!I35+$C34*('A1'!I33-'A1'!I35)) -> 452.01237 | AD34: =J34*('A1'!J35+$C34*('A1'!J33-'A1'!J35)) -> 470.8936 | AE34: =F34*('A1'!F43+$C34*('A1'!F41-'A1'!F43)) -> 632.19421 | AF34: =G34*('A1'!G43+$C34*('A1'!G41-'A1'!G43)) -> 700.06374 | AG34: =H34*('A1'!H43+$C34*('A1'!H41-'A1'!H43)) -> 699.13054 | AH34: =I34*('A1'!I43+$C34*('A1'!I41-'A1'!I43)) -> 677.50778 | AI34: =J34*('A1'!J43+$C34*('A1'!J41-'A1'!J43)) -> 687.0679 | AJ34: =(U34-Z34)*DCF!$H$40 -> 213.532 | AK34: =(V34-AA34)*DCF!$H$40 -> 257.59542 | AL34: =(W34-AB34)*DCF!$H$40 -> 323.33483 | AM34: =(X34-AC34)*DCF!$H$40 -> 373.88236 | AN34: =(Y34-AD34)*DCF!$H$40 -> 426.20765 | AO34: =(F34-DCF!$H$7)*DCF!$H$41 -> 306.51152 | AP34: =(G34-F34)*DCF!$H$41 -> 273.63031 | AQ34: =(H34-G34)*DCF!$H$41 -> 263.51714 | AR34: =(I34-H34)*DCF!$H$41 -> 243.17187 | AS34: =(J34-I34)*DCF!$H$41 -> 238.51937 | AT34: =(U34-Z34)*(1-DCF!$H$40)+Z34-AE34-AO34 -> 92.577362 | AU34: =(V34-AA34)*(1-DCF!$H$40)+AA34-AF34-AP34 -> 240.49235 | AV34: =(W34-AB34)*(1-DCF!$H$40)+AB34-AG34-AQ34 -> 483.35529 | AW34: =(X34-AC34)*(1-DCF!$H$40)+AC34-AH34-AR34 -> 702.41879 | AX34: =(Y34-AD34)*(1-DCF!$H$40)+AD34-AI34-AS34 -> 880.28731 | AY34: =0.0925+$E34*(0.1125-0.0925) -> 0.1025616 | AZ34: =10+$E34*(14-10) -> 12.012321 | BA34: =SUMPRODUCT(AT34:AX34,(1+$AY34)^(-{1,2,3,4,5})) -> 1658.0115 | BB34: =Y34*$AZ34 -> 26812.487 | BC34: =BB34*(1+$AY34)^(-5) -> 16455.943 | BD34: =BA34+BC34 -> 18113.955 | BE34: =BD34-(DCF!$J$48-DCF!$J$51) -> 17551.815 | BF34: =BE34/DCF!$J$55 -> 708.31449
A35: 9 | B35: =RAND() -> 0.71459379 | C35: =IF(B35<0.5,SQRT(0.5*B35),1-SQRT(0.5*(1-B35))) -> 0.62223935 | D35: =RAND() -> 0.68453207 | E35: =IF(D35<0.5,SQRT(0.5*D35),1-SQRT(0.5*(1-D35))) -> 0.60284265 | F35: =DCF!$H$7*(1+('A1'!F14+$C35*('A1'!F12-'A1'!F14))) -> 6376.7752 | G35: =F35*(1+('A1'!G14+$C35*('A1'!G12-'A1'!G14))) -> 7354.5637 | H35: =G35*(1+('A1'!H14+$C35*('A1'!H12-'A1'!H14))) -> 8317.2108 | I35: =H35*(1+('A1'!I14+$C35*('A1'!I12-'A1'!I14))) -> 9198.848 | J35: =I35*(1+('A1'!J14+$C35*('A1'!J12-'A1'!J14))) -> 10059.462 | K35: ='A1'!F21+$C35*('A1'!F19-'A1'!F21) -> 0.34577684 | L35: ='A1'!G21+$C35*('A1'!G19-'A1'!G21) -> 0.33833205 | M35: ='A1'!H21+$C35*('A1'!H19-'A1'!H21) -> 0.32710965 | N35: ='A1'!I21+$C35*('A1'!I19-'A1'!I21) -> 0.32210965 | O35: ='A1'!J21+$C35*('A1'!J19-'A1'!J21) -> 0.31710965 | P35: ='A1'!F28+$C35*('A1'!F26-'A1'!F28) -> 0.44444402 | Q35: ='A1'!G28+$C35*('A1'!G26-'A1'!G28) -> 0.43699923 | R35: ='A1'!H28+$C35*('A1'!H26-'A1'!H28) -> 0.42766564 | S35: ='A1'!I28+$C35*('A1'!I26-'A1'!I28) -> 0.42455444 | T35: ='A1'!J28+$C35*('A1'!J26-'A1'!J28) -> 0.42144325 | U35: =F35*(1-K35-P35) -> 1337.7145 | V35: =G35*(1-L35-Q35) -> 1652.3404 | W35: =H35*(1-M35-R35) -> 2039.5856 | X35: =I35*(1-N35-S35) -> 2330.3985 | Y35: =J35*(1-O35-T35) -> 2630.0173 | Z35: =F35*('A1'!F35+$C35*('A1'!F33-'A1'!F35)) -> 362.76711 | AA35: =G35*('A1'!G35+$C35*('A1'!G33-'A1'!G35)) -> 410.21996 | AB35: =H35*('A1'!H35+$C35*('A1'!H33-'A1'!H35)) -> 442.10439 | AC35: =I35*('A1'!I35+$C35*('A1'!I33-'A1'!I35)) -> 464.84656 | AD35: =J35*('A1'!J35+$C35*('A1'!J33-'A1'!J35)) -> 488.21717 | AE35: =F35*('A1'!F43+$C35*('A1'!F41-'A1'!F43)) -> 622.08766 | AF35: =G35*('A1'!G43+$C35*('A1'!G41-'A1'!G43)) -> 685.60437 | AG35: =H35*('A1'!H43+$C35*('A1'!H41-'A1'!H43)) -> 692.17178 | AH35: =I35*('A1'!I43+$C35*('A1'!I41-'A1'!I43)) -> 673.55457 | AI35: =J35*('A1'!J43+$C35*('A1'!J41-'A1'!J43)) -> 686.27284 | AJ35: =(U35-Z35)*DCF!$H$40 -> 235.93726 | AK35: =(V35-AA35)*DCF!$H$40 -> 300.59316 | AL35: =(W35-AB35)*DCF!$H$40 -> 386.59045 | AM35: =(X35-AC35)*DCF!$H$40 -> 451.46356 | AN35: =(Y35-AD35)*DCF!$H$40 -> 518.31562 | AO35: =(F35-DCF!$H$7)*DCF!$H$41 -> 335.53246 | AP35: =(G35-F35)*DCF!$H$41 -> 324.46681 | AQ35: =(H35-G35)*DCF!$H$41 -> 319.44229 | AR35: =(I35-H35)*DCF!$H$41 -> 292.56018 | AS35: =(J35-I35)*DCF!$H$41 -> 285.58403 | AT35: =(U35-Z35)*(1-DCF!$H$40)+Z35-AE35-AO35 -> 144.15709 | AU35: =(V35-AA35)*(1-DCF!$H$40)+AA35-AF35-AP35 -> 341.6761 | AV35: =(W35-AB35)*(1-DCF!$H$40)+AB35-AG35-AQ35 -> 641.38106 | AW35: =(X35-AC35)*(1-DCF!$H$40)+AC35-AH35-AR35 -> 912.82014 | AX35: =(Y35-AD35)*(1-DCF!$H$40)+AD35-AI35-AS35 -> 1139.8448 | AY35: =0.0925+$E35*(0.1125-0.0925) -> 0.10455685 | AZ35: =10+$E35*(14-10) -> 12.411371 | BA35: =SUMPRODUCT(AT35:AX35,(1+$AY35)^(-{1,2,3,4,5})) -> 2193.0209 | BB35: =Y35*$AZ35 -> 32642.119 | BC35: =BB35*(1+$AY35)^(-5) -> 19853.541 | BD35: =BA35+BC35 -> 22046.561 | BE35: =BD35-(DCF!$J$48-DCF!$J$51) -> 21484.421 | BF35: =BE35/DCF!$J$55 -> 867.01729
A36: 10 | B36: =RAND() -> 0.47669381 | C36: =IF(B36<0.5,SQRT(0.5*B36),1-SQRT(0.5*(1-B36))) -> 0.48820785 | D36: =RAND() -> 0.50847111 | E36: =IF(D36<0.5,SQRT(0.5*D36),1-SQRT(0.5*(1-D36))) -> 0.50425365 | F36: =DCF!$H$7*(1+('A1'!F14+$C36*('A1'!F12-'A1'!F14))) -> 6297.667 | G36: =F36*(1+('A1'!G14+$C36*('A1'!G12-'A1'!G14))) -> 7136.7126 | H36: =G36*(1+('A1'!H14+$C36*('A1'!H12-'A1'!H14))) -> 7946.4942 | I36: =H36*(1+('A1'!I14+$C36*('A1'!I12-'A1'!I14))) -> 8692.9775 | J36: =I36*(1+('A1'!J14+$C36*('A1'!J12-'A1'!J14))) -> 9424.705 | K36: ='A1'!F21+$C36*('A1'!F19-'A1'!F21) -> 0.35314857 | L36: ='A1'!G21+$C36*('A1'!G19-'A1'!G21) -> 0.34838441 | M36: ='A1'!H21+$C36*('A1'!H19-'A1'!H21) -> 0.33850233 | N36: ='A1'!I21+$C36*('A1'!I19-'A1'!I21) -> 0.33350233 | O36: ='A1'!J21+$C36*('A1'!J19-'A1'!J21) -> 0.32850233 | P36: ='A1'!F28+$C36*('A1'!F26-'A1'!F28) -> 0.4477948 | Q36: ='A1'!G28+$C36*('A1'!G26-'A1'!G28) -> 0.44303065 | R36: ='A1'!H28+$C36*('A1'!H26-'A1'!H28) -> 0.43570753 | S36: ='A1'!I28+$C36*('A1'!I26-'A1'!I28) -> 0.43326649 | T36: ='A1'!J28+$C36*('A1'!J26-'A1'!J28) -> 0.43082545 | U36: =F36*(1-K36-P36) -> 1253.5924 | V36: =G36*(1-L36-Q36) -> 1488.6108 | W36: =H36*(1-M36-R36) -> 1794.24 | X36: =I36*(1-N36-S36) -> 2027.4734 | Y36: =J36*(1-O36-T36) -> 2268.2646 | Z36: =F36*('A1'!F35+$C36*('A1'!F33-'A1'!F35)) -> 362.48717 | AA36: =G36*('A1'!G35+$C36*('A1'!G33-'A1'!G35)) -> 407.63419 | AB36: =H36*('A1'!H35+$C36*('A1'!H33-'A1'!H35)) -> 434.1147 | AC36: =I36*('A1'!I35+$C36*('A1'!I33-'A1'!I35)) -> 453.26494 | AD36: =J36*('A1'!J35+$C36*('A1'!J33-'A1'!J35)) -> 472.5689 | AE36: =F36*('A1'!F43+$C36*('A1'!F41-'A1'!F43)) -> 631.25196 | AF36: =G36*('A1'!G43+$C36*('A1'!G41-'A1'!G43)) -> 698.77498 | AG36: =H36*('A1'!H43+$C36*('A1'!H41-'A1'!H43)) -> 698.59796 | AH36: =I36*('A1'!I43+$C36*('A1'!I41-'A1'!I43)) -> 677.29357 | AI36: =J36*('A1'!J43+$C36*('A1'!J41-'A1'!J43)) -> 687.18093 | AJ36: =(U36-Z36)*DCF!$H$40 -> 215.64746 | AK36: =(V36-AA36)*DCF!$H$40 -> 261.59634 | AL36: =(W36-AB36)*DCF!$H$40 -> 329.15033 | AM36: =(X36-AC36)*DCF!$H$40 -> 380.95844 | AN36: =(Y36-AD36)*DCF!$H$40 -> 434.55837 | AO36: =(F36-DCF!$H$7)*DCF!$H$41 -> 309.28142 | AP36: =(G36-F36)*DCF!$H$41 -> 278.4267 | AQ36: =(H36-G36)*DCF!$H$41 -> 268.71579 | AR36: =(I36-H36)*DCF!$H$41 -> 247.7111 | AS36: =(J36-I36)*DCF!$H$41 -> 242.81454 | AT36: =(U36-Z36)*(1-DCF!$H$40)+Z36-AE36-AO36 -> 97.411521 | AU36: =(V36-AA36)*(1-DCF!$H$40)+AA36-AF36-AP36 -> 249.81277 | AV36: =(W36-AB36)*(1-DCF!$H$40)+AB36-AG36-AQ36 -> 497.77594 | AW36: =(X36-AC36)*(1-DCF!$H$40)+AC36-AH36-AR36 -> 721.51027 | AX36: =(Y36-AD36)*(1-DCF!$H$40)+AD36-AI36-AS36 -> 903.71081 | AY36: =0.0925+$E36*(0.1125-0.0925) -> 0.10258507 | AZ36: =10+$E36*(14-10) -> 12.017015 | BA36: =SUMPRODUCT(AT36:AX36,(1+$AY36)^(-{1,2,3,4,5})) -> 1707.9822 | BB36: =Y36*$AZ36 -> 27257.769 | BC36: =BB36*(1+$AY36)^(-5) -> 16727.451 | BD36: =BA36+BC36 -> 18435.433 | BE36: =BD36-(DCF!$J$48-DCF!$J$51) -> 17873.293 | BF36: =BE36/DCF!$J$55 -> 721.28795
A37: 11 | B37: =RAND() -> 0.84781428 | C37: =IF(B37<0.5,SQRT(0.5*B37),1-SQRT(0.5*(1-B37))) -> 0.72415066 | D37: =RAND() -> 0.31898827 | E37: =IF(D37<0.5,SQRT(0.5*D37),1-SQRT(0.5*(1-D37))) -> 0.39936717 | F37: =DCF!$H$7*(1+('A1'!F14+$C37*('A1'!F12-'A1'!F14))) -> 6436.9253 | G37: =F37*(1+('A1'!G14+$C37*('A1'!G12-'A1'!G14))) -> 7522.3364 | H37: =G37*(1+('A1'!H14+$C37*('A1'!H12-'A1'!H14))) -> 8606.6028 | I37: =H37*(1+('A1'!I14+$C37*('A1'!I12-'A1'!I14))) -> 9597.8559 | J37: =I37*(1+('A1'!J14+$C37*('A1'!J12-'A1'!J14))) -> 10564.269 | K37: ='A1'!F21+$C37*('A1'!F19-'A1'!F21) -> 0.34017171 | L37: ='A1'!G21+$C37*('A1'!G19-'A1'!G21) -> 0.3306887 | M37: ='A1'!H21+$C37*('A1'!H19-'A1'!H21) -> 0.31844719 | N37: ='A1'!I21+$C37*('A1'!I19-'A1'!I21) -> 0.31344719 | O37: ='A1'!J21+$C37*('A1'!J19-'A1'!J21) -> 0.30844719 | P37: ='A1'!F28+$C37*('A1'!F26-'A1'!F28) -> 0.44189623 | Q37: ='A1'!G28+$C37*('A1'!G26-'A1'!G28) -> 0.43241322 | R37: ='A1'!H28+$C37*('A1'!H26-'A1'!H28) -> 0.42155096 | S37: ='A1'!I28+$C37*('A1'!I26-'A1'!I28) -> 0.41793021 | T37: ='A1'!J28+$C37*('A1'!J26-'A1'!J28) -> 0.41430945 | U37: =F37*(1-K37-P37) -> 1402.8123 | V37: =G37*(1-L37-Q37) -> 1782.027 | W37: =H37*(1-M37-R37) -> 2237.7326 | X37: =I37*(1-N37-S37) -> 2578.201 | Y37: =J37*(1-O37-T37) -> 2928.8734 | Z37: =F37*('A1'!F35+$C37*('A1'!F33-'A1'!F35)) -> 362.909 | AA37: =G37*('A1'!G35+$C37*('A1'!G33-'A1'!G35)) -> 411.91181 | AB37: =H37*('A1'!H35+$C37*('A1'!H33-'A1'!H35)) -> 447.83892 | AC37: =I37*('A1'!I35+$C37*('A1'!I33-'A1'!I35)) -> 473.27212 | AD37: =J37*('A1'!J35+$C37*('A1'!J33-'A1'!J35)) -> 499.79761 | AE37: =F37*('A1'!F43+$C37*('A1'!F41-'A1'!F43)) -> 614.83571 | AF37: =G37*('A1'!G43+$C37*('A1'!G41-'A1'!G43)) -> 674.41301 | AG37: =H37*('A1'!H43+$C37*('A1'!H41-'A1'!H43)) -> 685.5566 | AH37: =I37*('A1'!I43+$C37*('A1'!I41-'A1'!I43)) -> 668.53603 | AI37: =J37*('A1'!J43+$C37*('A1'!J41-'A1'!J43)) -> 683.02994 | AJ37: =(U37-Z37)*DCF!$H$40 -> 251.65661 | AK37: =(V37-AA37)*DCF!$H$40 -> 331.56788 | AL37: =(W37-AB37)*DCF!$H$40 -> 433.15427 | AM37: =(X37-AC37)*DCF!$H$40 -> 509.39279 | AN37: =(Y37-AD37)*DCF!$H$40 -> 587.83634 | AO37: =(F37-DCF!$H$7)*DCF!$H$41 -> 355.49252 | AP37: =(G37-F37)*DCF!$H$41 -> 360.17998 | AQ37: =(H37-G37)*DCF!$H$41 -> 359.80015 | AR37: =(I37-H37)*DCF!$H$41 -> 328.93484 | AS37: =(J37-I37)*DCF!$H$41 -> 320.69209 | AT37: =(U37-Z37)*(1-DCF!$H$40)+Z37-AE37-AO37 -> 180.8275 | AU37: =(V37-AA37)*(1-DCF!$H$40)+AA37-AF37-AP37 -> 415.86615 | AV37: =(W37-AB37)*(1-DCF!$H$40)+AB37-AG37-AQ37 -> 759.22159 | AW37: =(X37-AC37)*(1-DCF!$H$40)+AC37-AH37-AR37 -> 1071.3373 | AX37: =(Y37-AD37)*(1-DCF!$H$40)+AD37-AI37-AS37 -> 1337.315 | AY37: =0.0925+$E37*(0.1125-0.0925) -> 0.10048734 | AZ37: =10+$E37*(14-10) -> 11.597469 | BA37: =SUMPRODUCT(AT37:AX37,(1+$AY37)^(-{1,2,3,4,5})) -> 2636.3324 | BB37: =Y37*$AZ37 -> 33967.518 | BC37: =BB37*(1+$AY37)^(-5) -> 21044.497 | BD37: =BA37+BC37 -> 23680.829 | BE37: =BD37-(DCF!$J$48-DCF!$J$51) -> 23118.689 | BF37: =BE37/DCF!$J$55 -> 932.96919
A38: 12 | B38: =RAND() -> 0.7094761 | C38: =IF(B38<0.5,SQRT(0.5*B38),1-SQRT(0.5*(1-B38))) -> 0.61886754 | D38: =RAND() -> 0.060134428 | E38: =IF(D38<0.5,SQRT(0.5*D38),1-SQRT(0.5*(1-D38))) -> 0.173399 | F38: =DCF!$H$7*(1+('A1'!F14+$C38*('A1'!F12-'A1'!F14))) -> 6374.785 | G38: =F38*(1+('A1'!G14+$C38*('A1'!G12-'A1'!G14))) -> 7349.0443 | H38: =G38*(1+('A1'!H14+$C38*('A1'!H12-'A1'!H14))) -> 8307.7475 | I38: =H38*(1+('A1'!I14+$C38*('A1'!I12-'A1'!I14))) -> 9185.8605 | J38: =I38*(1+('A1'!J14+$C38*('A1'!J12-'A1'!J14))) -> 10043.092 | K38: ='A1'!F21+$C38*('A1'!F19-'A1'!F21) -> 0.34596229 | L38: ='A1'!G21+$C38*('A1'!G19-'A1'!G21) -> 0.33858493 | M38: ='A1'!H21+$C38*('A1'!H19-'A1'!H21) -> 0.32739626 | N38: ='A1'!I21+$C38*('A1'!I19-'A1'!I21) -> 0.32239626 | O38: ='A1'!J21+$C38*('A1'!J19-'A1'!J21) -> 0.31739626 | P38: ='A1'!F28+$C38*('A1'!F26-'A1'!F28) -> 0.44452831 | Q38: ='A1'!G28+$C38*('A1'!G26-'A1'!G28) -> 0.43715096 | R38: ='A1'!H28+$C38*('A1'!H26-'A1'!H28) -> 0.42786795 | S38: ='A1'!I28+$C38*('A1'!I26-'A1'!I28) -> 0.42477361 | T38: ='A1'!J28+$C38*('A1'!J26-'A1'!J28) -> 0.42167927 | U38: =F38*(1-K38-P38) -> 1335.5774 | V38: =G38*(1-L38-Q38) -> 1648.1268 | W38: =H38*(1-M38-R38) -> 2033.2032 | X38: =I38*(1-N38-S38) -> 2322.4623 | Y38: =J38*(1-O38-T38) -> 2620.4884 | Z38: =F38*('A1'!F35+$C38*('A1'!F33-'A1'!F35)) -> 362.76137 | AA38: =G38*('A1'!G35+$C38*('A1'!G33-'A1'!G35)) -> 410.1599 | AB38: =H38*('A1'!H35+$C38*('A1'!H33-'A1'!H35)) -> 441.9095 | AC38: =I38*('A1'!I35+$C38*('A1'!I33-'A1'!I35)) -> 464.56194 | AD38: =J38*('A1'!J35+$C38*('A1'!J33-'A1'!J35)) -> 487.82901 | AE38: =F38*('A1'!F43+$C38*('A1'!F41-'A1'!F43)) -> 622.3234 | AF38: =G38*('A1'!G43+$C38*('A1'!G41-'A1'!G43)) -> 685.95712 | AG38: =H38*('A1'!H43+$C38*('A1'!H41-'A1'!H43)) -> 692.36466 | AH38: =I38*('A1'!I43+$C38*('A1'!I41-'A1'!I43)) -> 673.68767 | AI38: =J38*('A1'!J43+$C38*('A1'!J41-'A1'!J43)) -> 686.34123 | AJ38: =(U38-Z38)*DCF!$H$40 -> 235.42148 | AK38: =(V38-AA38)*DCF!$H$40 -> 299.588 | AL38: =(W38-AB38)*DCF!$H$40 -> 385.09307 | AM38: =(X38-AC38)*DCF!$H$40 -> 449.61189 | AN38: =(Y38-AD38)*DCF!$H$40 -> 516.10356 | AO38: =(F38-DCF!$H$7)*DCF!$H$41 -> 334.87206 | AP38: =(G38-F38)*DCF!$H$41 -> 323.29565 | AQ38: =(H38-G38)*DCF!$H$41 -> 318.13359 | AR38: =(I38-H38)*DCF!$H$41 -> 291.39071 | AS38: =(J38-I38)*DCF!$H$41 -> 284.46136 | AT38: =(U38-Z38)*(1-DCF!$H$40)+Z38-AE38-AO38 -> 142.96046 | AU38: =(V38-AA38)*(1-DCF!$H$40)+AA38-AF38-AP38 -> 339.28607 | AV38: =(W38-AB38)*(1-DCF!$H$40)+AB38-AG38-AQ38 -> 637.61187 | AW38: =(X38-AC38)*(1-DCF!$H$40)+AC38-AH38-AR38 -> 907.77204 | AX38: =(Y38-AD38)*(1-DCF!$H$40)+AD38-AI38-AS38 -> 1133.5822 | AY38: =0.0925+$E38*(0.1125-0.0925) -> 0.09596798 | AZ38: =10+$E38*(14-10) -> 10.693596 | BA38: =SUMPRODUCT(AT38:AX38,(1+$AY38)^(-{1,2,3,4,5})) -> 2243.3683 | BB38: =Y38*$AZ38 -> 28022.444 | BC38: =BB38*(1+$AY38)^(-5) -> 17722.161 | BD38: =BA38+BC38 -> 19965.529 | BE38: =BD38-(DCF!$J$48-DCF!$J$51) -> 19403.389 | BF38: =BE38/DCF!$J$55 -> 783.03593
A39: 13 | B39: =RAND() -> 0.089413991 | C39: =IF(B39<0.5,SQRT(0.5*B39),1-SQRT(0.5*(1-B39))) -> 0.21144029 | D39: =RAND() -> 0.79704211 | E39: =IF(D39<0.5,SQRT(0.5*D39),1-SQRT(0.5*(1-D39))) -> 0.6814424 | F39: =DCF!$H$7*(1+('A1'!F14+$C39*('A1'!F12-'A1'!F14))) -> 6134.3132 | G39: =F39*(1+('A1'!G14+$C39*('A1'!G12-'A1'!G14))) -> 6696.9281 | H39: =G39*(1+('A1'!H14+$C39*('A1'!H12-'A1'!H14))) -> 7215.8546 | I39: =H39*(1+('A1'!I14+$C39*('A1'!I12-'A1'!I14))) -> 7713.9623 | J39: =I39*(1+('A1'!J14+$C39*('A1'!J12-'A1'!J14))) -> 8213.8334 | K39: ='A1'!F21+$C39*('A1'!F19-'A1'!F21) -> 0.36837078 | L39: ='A1'!G21+$C39*('A1'!G19-'A1'!G21) -> 0.36914198 | M39: ='A1'!H21+$C39*('A1'!H19-'A1'!H21) -> 0.36202758 | N39: ='A1'!I21+$C39*('A1'!I19-'A1'!I21) -> 0.35702758 | O39: ='A1'!J21+$C39*('A1'!J19-'A1'!J21) -> 0.35202758 | P39: ='A1'!F28+$C39*('A1'!F26-'A1'!F28) -> 0.45471399 | Q39: ='A1'!G28+$C39*('A1'!G26-'A1'!G28) -> 0.45548519 | R39: ='A1'!H28+$C39*('A1'!H26-'A1'!H28) -> 0.45231358 | S39: ='A1'!I28+$C39*('A1'!I26-'A1'!I28) -> 0.45125638 | T39: ='A1'!J28+$C39*('A1'!J26-'A1'!J28) -> 0.45019918 | U39: =F39*(1-K39-P39) -> 1085.2534 | V39: =G39*(1-L39-Q39) -> 1174.4593 | W39: =H39*(1-M39-R39) -> 1339.6872 | X39: =I39*(1-N39-S39) -> 1478.8903 | Y39: =J39*(1-O39-T39) -> 1624.4765 | Z39: =F39*('A1'!F35+$C39*('A1'!F33-'A1'!F35)) -> 361.57359 | AA39: =G39*('A1'!G35+$C39*('A1'!G33-'A1'!G35)) -> 401.04954 | AB39: =H39*('A1'!H35+$C39*('A1'!H33-'A1'!H35)) -> 416.16833 | AC39: =I39*('A1'!I35+$C39*('A1'!I33-'A1'!I35)) -> 427.8373 | AD39: =J39*('A1'!J35+$C39*('A1'!J33-'A1'!J35)) -> 439.13385 | AE39: =F39*('A1'!F43+$C39*('A1'!F41-'A1'!F43)) -> 648.83363 | AF39: =G39*('A1'!G43+$C39*('A1'!G41-'A1'!G43)) -> 720.58672 | AG39: =H39*('A1'!H43+$C39*('A1'!H41-'A1'!H43)) -> 704.26445 | AH39: =I39*('A1'!I43+$C39*('A1'!I41-'A1'!I43)) -> 675.73993 | AI39: =J39*('A1'!J43+$C39*('A1'!J41-'A1'!J43)) -> 678.45927 | AJ39: =(U39-Z39)*DCF!$H$40 -> 175.13051 | AK39: =(V39-AA39)*DCF!$H$40 -> 187.16515 | AL39: =(W39-AB39)*DCF!$H$40 -> 223.49157 | AM39: =(X39-AC39)*DCF!$H$40 -> 254.35483 | AN39: =(Y39-AD39)*DCF!$H$40 -> 286.85292 | AO39: =(F39-DCF!$H$7)*DCF!$H$41 -> 255.0745 | AP39: =(G39-F39)*DCF!$H$41 -> 186.69667 | AQ39: =(H39-G39)*DCF!$H$41 -> 172.1992 | AR39: =(I39-H39)*DCF!$H$41 -> 165.29078 | AS39: =(J39-I39)*DCF!$H$41 -> 165.87592 | AT39: =(U39-Z39)*(1-DCF!$H$40)+Z39-AE39-AO39 -> 6.2147394 | AU39: =(V39-AA39)*(1-DCF!$H$40)+AA39-AF39-AP39 -> 80.01072 | AV39: =(W39-AB39)*(1-DCF!$H$40)+AB39-AG39-AQ39 -> 239.73198 | AW39: =(X39-AC39)*(1-DCF!$H$40)+AC39-AH39-AR39 -> 383.50479 | AX39: =(Y39-AD39)*(1-DCF!$H$40)+AD39-AI39-AS39 -> 493.28838 | AY39: =0.0925+$E39*(0.1125-0.0925) -> 0.10612885 | AZ39: =10+$E39*(14-10) -> 12.72577 | BA39: =SUMPRODUCT(AT39:AX39,(1+$AY39)^(-{1,2,3,4,5})) -> 802.23191 | BB39: =Y39*$AZ39 -> 20672.713 | BC39: =BB39*(1+$AY39)^(-5) -> 12484.435 | BD39: =BA39+BC39 -> 13286.667 | BE39: =BD39-(DCF!$J$48-DCF!$J$51) -> 12724.527 | BF39: =BE39/DCF!$J$55 -> 513.50625
A40: 14 | B40: =RAND() -> 0.26785712 | C40: =IF(B40<0.5,SQRT(0.5*B40),1-SQRT(0.5*(1-B40))) -> 0.36596251 | D40: =RAND() -> 0.20992849 | E40: =IF(D40<0.5,SQRT(0.5*D40),1-SQRT(0.5*(1-D40))) -> 0.32398186 | F40: =DCF!$H$7*(1+('A1'!F14+$C40*('A1'!F12-'A1'!F14))) -> 6225.5153 | G40: =F40*(1+('A1'!G14+$C40*('A1'!G12-'A1'!G14))) -> 6940.792 | H40: =G40*(1+('A1'!H14+$C40*('A1'!H12-'A1'!H14))) -> 7618.0407 | I40: =H40*(1+('A1'!I14+$C40*('A1'!I12-'A1'!I14))) -> 8249.8553 | J40: =I40*(1+('A1'!J14+$C40*('A1'!J12-'A1'!J14))) -> 8873.6877 | K40: ='A1'!F21+$C40*('A1'!F19-'A1'!F21) -> 0.35987206 | L40: ='A1'!G21+$C40*('A1'!G19-'A1'!G21) -> 0.35755281 | M40: ='A1'!H21+$C40*('A1'!H19-'A1'!H21) -> 0.34889319 | N40: ='A1'!I21+$C40*('A1'!I19-'A1'!I21) -> 0.34389319 | O40: ='A1'!J21+$C40*('A1'!J19-'A1'!J21) -> 0.33889319 | P40: ='A1'!F28+$C40*('A1'!F26-'A1'!F28) -> 0.45085094 | Q40: ='A1'!G28+$C40*('A1'!G26-'A1'!G28) -> 0.44853169 | R40: ='A1'!H28+$C40*('A1'!H26-'A1'!H28) -> 0.44304225 | S40: ='A1'!I28+$C40*('A1'!I26-'A1'!I28) -> 0.44121244 | T40: ='A1'!J28+$C40*('A1'!J26-'A1'!J28) -> 0.43938262 | U40: =F40*(1-K40-P40) -> 1178.3469 | V40: =G40*(1-L40-Q40) -> 1345.9272 | W40: =H40*(1-M40-R40) -> 1585.0443 | X40: =I40*(1-N40-S40) -> 1772.8475 | Y40: =J40*(1-O40-T40) -> 1967.5112 | Z40: =F40*('A1'!F35+$C40*('A1'!F33-'A1'!F35)) -> 362.13939 | AA40: =G40*('A1'!G35+$C40*('A1'!G33-'A1'!G35)) -> 404.92841 | AB40: =H40*('A1'!H35+$C40*('A1'!H33-'A1'!H35)) -> 426.41535 | AC40: =I40*('A1'!I35+$C40*('A1'!I33-'A1'!I35)) -> 442.26195 | AD40: =J40*('A1'!J35+$C40*('A1'!J33-'A1'!J35)) -> 457.95727 | AE40: =F40*('A1'!F43+$C40*('A1'!F41-'A1'!F43)) -> 639.24058 | AF40: =G40*('A1'!G43+$C40*('A1'!G41-'A1'!G43)) -> 709.28865 | AG40: =H40*('A1'!H43+$C40*('A1'!H41-'A1'!H43)) -> 702.31717 | AH40: =I40*('A1'!I43+$C40*('A1'!I41-'A1'!I43)) -> 678.06643 | AI40: =J40*('A1'!J43+$C40*('A1'!J41-'A1'!J43)) -> 684.9716 | AJ40: =(U40-Z40)*DCF!$H$40 -> 197.52221 | AK40: =(V40-AA40)*DCF!$H$40 -> 227.7217 | AL40: =(W40-AB40)*DCF!$H$40 -> 280.38821 | AM40: =(X40-AC40)*DCF!$H$40 -> 322.00171 | AN40: =(Y40-AD40)*DCF!$H$40 -> 365.31206 | AO40: =(F40-DCF!$H$7)*DCF!$H$41 -> 285.33879 | AP40: =(G40-F40)*DCF!$H$41 -> 237.35556 | AQ40: =(H40-G40)*DCF!$H$41 -> 224.73643 | AR40: =(I40-H40)*DCF!$H$41 -> 209.65971 | AS40: =(J40-I40)*DCF!$H$41 -> 207.01092 | AT40: =(U40-Z40)*(1-DCF!$H$40)+Z40-AE40-AO40 -> 56.245288 | AU40: =(V40-AA40)*(1-DCF!$H$40)+AA40-AF40-AP40 -> 171.56127 | AV40: =(W40-AB40)*(1-DCF!$H$40)+AB40-AG40-AQ40 -> 377.60251 | AW40: =(X40-AC40)*(1-DCF!$H$40)+AC40-AH40-AR40 -> 563.11967 | AX40: =(Y40-AD40)*(1-DCF!$H$40)+AD40-AI40-AS40 -> 710.21664 | AY40: =0.0925+$E40*(0.1125-0.0925) -> 0.098979637 | AZ40: =10+$E40*(14-10) -> 11.295927 | BA40: =SUMPRODUCT(AT40:AX40,(1+$AY40)^(-{1,2,3,4,5})) -> 1306.8068 | BB40: =Y40*$AZ40 -> 22224.864 | BC40: =BB40*(1+$AY40)^(-5) -> 13864.074 | BD40: =BA40+BC40 -> 15170.881 | BE40: =BD40-(DCF!$J$48-DCF!$J$51) -> 14608.741 | BF40: =BE40/DCF!$J$55 -> 589.54491
A41: 15 | B41: =RAND() -> 0.18927778 | C41: =IF(B41<0.5,SQRT(0.5*B41),1-SQRT(0.5*(1-B41))) -> 0.30763434 | D41: =RAND() -> 0.27459473 | E41: =IF(D41<0.5,SQRT(0.5*D41),1-SQRT(0.5*(1-D41))) -> 0.37053659 | F41: =DCF!$H$7*(1+('A1'!F14+$C41*('A1'!F12-'A1'!F14))) -> 6191.0889 | G41: =F41*(1+('A1'!G14+$C41*('A1'!G12-'A1'!G14))) -> 6848.2429 | H41: =G41*(1+('A1'!H14+$C41*('A1'!H12-'A1'!H14))) -> 7464.5332 | I41: =H41*(1+('A1'!I14+$C41*('A1'!I12-'A1'!I14))) -> 8044.4311 | J41: =I41*(1+('A1'!J14+$C41*('A1'!J12-'A1'!J14))) -> 8619.8846 | K41: ='A1'!F21+$C41*('A1'!F19-'A1'!F21) -> 0.36308011 | L41: ='A1'!G21+$C41*('A1'!G19-'A1'!G21) -> 0.36192742 | M41: ='A1'!H21+$C41*('A1'!H19-'A1'!H21) -> 0.35385108 | N41: ='A1'!I21+$C41*('A1'!I19-'A1'!I21) -> 0.34885108 | O41: ='A1'!J21+$C41*('A1'!J19-'A1'!J21) -> 0.34385108 | P41: ='A1'!F28+$C41*('A1'!F26-'A1'!F28) -> 0.45230914 | Q41: ='A1'!G28+$C41*('A1'!G26-'A1'!G28) -> 0.45115645 | R41: ='A1'!H28+$C41*('A1'!H26-'A1'!H28) -> 0.44654194 | S41: ='A1'!I28+$C41*('A1'!I26-'A1'!I28) -> 0.44500377 | T41: ='A1'!J28+$C41*('A1'!J26-'A1'!J28) -> 0.4434656 | U41: =F41*(1-K41-P41) -> 1142.9415 | V41: =G41*(1-L41-Q41) -> 1280.047 | W41: =H41*(1-M41-R41) -> 1489.9729 | X41: =I41*(1-N41-S41) -> 1658.3205 | Y41: =J41*(1-O41-T41) -> 1833.3057 | Z41: =F41*('A1'!F35+$C41*('A1'!F33-'A1'!F35)) -> 361.94237 | AA41: =G41*('A1'!G35+$C41*('A1'!G33-'A1'!G35)) -> 403.52351 | AB41: =H41*('A1'!H35+$C41*('A1'!H33-'A1'!H35)) -> 422.61218 | AC41: =I41*('A1'!I35+$C41*('A1'!I33-'A1'!I35)) -> 436.88008 | AD41: =J41*('A1'!J35+$C41*('A1'!J33-'A1'!J35)) -> 450.89227 | AE41: =F41*('A1'!F43+$C41*('A1'!F41-'A1'!F43)) -> 642.92794 | AF41: =G41*('A1'!G43+$C41*('A1'!G41-'A1'!G43)) -> 713.81152 | AG41: =H41*('A1'!H43+$C41*('A1'!H41-'A1'!H43)) -> 703.40385 | AH41: =I41*('A1'!I43+$C41*('A1'!I41-'A1'!I43)) -> 677.60494 | AI41: =J41*('A1'!J43+$C41*('A1'!J41-'A1'!J43)) -> 682.97758 | AJ41: =(U41-Z41)*DCF!$H$40 -> 189.0018 | AK41: =(V41-AA41)*DCF!$H$40 -> 212.11869 | AL41: =(W41-AB41)*DCF!$H$40 -> 258.3013 | AM41: =(X41-AC41)*DCF!$H$40 -> 295.58857 | AN41: =(Y41-AD41)*DCF!$H$40 -> 334.54405 | AO41: =(F41-DCF!$H$7)*DCF!$H$41 -> 273.9148 | AP41: =(G41-F41)*DCF!$H$41 -> 218.06829 | AQ41: =(H41-G41)*DCF!$H$41 -> 204.50815 | AR41: =(I41-H41)*DCF!$H$41 -> 192.4318 | AS41: =(J41-I41)*DCF!$H$41 -> 190.95702 | AT41: =(U41-Z41)*(1-DCF!$H$40)+Z41-AE41-AO41 -> 37.096999 | AU41: =(V41-AA41)*(1-DCF!$H$40)+AA41-AF41-AP41 -> 136.04851 | AV41: =(W41-AB41)*(1-DCF!$H$40)+AB41-AG41-AQ41 -> 323.75962 | AW41: =(X41-AC41)*(1-DCF!$H$40)+AC41-AH41-AR41 -> 492.69515 | AX41: =(Y41-AD41)*(1-DCF!$H$40)+AD41-AI41-AS41 -> 624.82706 | AY41: =0.0925+$E41*(0.1125-0.0925) -> 0.099910732 | AZ41: =10+$E41*(14-10) -> 11.482146 | BA41: =SUMPRODUCT(AT41:AX41,(1+$AY41)^(-{1,2,3,4,5})) -> 1114.2395 | BB41: =Y41*$AZ41 -> 21050.284 | BC41: =BB41*(1+$AY41)^(-5) -> 13075.875 | BD41: =BA41+BC41 -> 14190.115 | BE41: =BD41-(DCF!$J$48-DCF!$J$51) -> 13627.975 | BF41: =BE41/DCF!$J$55 -> 549.96547
A42: 16 | B42: =RAND() -> 0.70940129 | C42: =IF(B42<0.5,SQRT(0.5*B42),1-SQRT(0.5*(1-B42))) -> 0.61881847 | D42: =RAND() -> 0.75963922 | E42: =IF(D42<0.5,SQRT(0.5*D42),1-SQRT(0.5*(1-D42))) -> 0.65332957 | F42: =DCF!$H$7*(1+('A1'!F14+$C42*('A1'!F12-'A1'!F14))) -> 6374.7561 | G42: =F42*(1+('A1'!G14+$C42*('A1'!G12-'A1'!G14))) -> 7348.964 | H42: =G42*(1+('A1'!H14+$C42*('A1'!H12-'A1'!H14))) -> 8307.6099 | I42: =H42*(1+('A1'!I14+$C42*('A1'!I12-'A1'!I14))) -> 9185.6716 | J42: =I42*(1+('A1'!J14+$C42*('A1'!J12-'A1'!J14))) -> 10042.854 | K42: ='A1'!F21+$C42*('A1'!F19-'A1'!F21) -> 0.34596498 | L42: ='A1'!G21+$C42*('A1'!G19-'A1'!G21) -> 0.33858861 | M42: ='A1'!H21+$C42*('A1'!H19-'A1'!H21) -> 0.32740043 | N42: ='A1'!I21+$C42*('A1'!I19-'A1'!I21) -> 0.32240043 | O42: ='A1'!J21+$C42*('A1'!J19-'A1'!J21) -> 0.31740043 | P42: ='A1'!F28+$C42*('A1'!F26-'A1'!F28) -> 0.44452954 | Q42: ='A1'!G28+$C42*('A1'!G26-'A1'!G28) -> 0.43715317 | R42: ='A1'!H28+$C42*('A1'!H26-'A1'!H28) -> 0.42787089 | S42: ='A1'!I28+$C42*('A1'!I26-'A1'!I28) -> 0.4247768 | T42: ='A1'!J28+$C42*('A1'!J26-'A1'!J28) -> 0.42168271 | U42: =F42*(1-K42-P42) -> 1335.5463 | V42: =G42*(1-L42-Q42) -> 1648.0656 | W42: =H42*(1-M42-R42) -> 2033.1104 | X42: =I42*(1-N42-S42) -> 2322.3469 | Y42: =J42*(1-O42-T42) -> 2620.3499 | Z42: =F42*('A1'!F35+$C42*('A1'!F33-'A1'!F35)) -> 362.76128 | AA42: =G42*('A1'!G35+$C42*('A1'!G33-'A1'!G35)) -> 410.15902 | AB42: =H42*('A1'!H35+$C42*('A1'!H33-'A1'!H35)) -> 441.90667 | AC42: =I42*('A1'!I35+$C42*('A1'!I33-'A1'!I35)) -> 464.55779 | AD42: =J42*('A1'!J35+$C42*('A1'!J33-'A1'!J35)) -> 487.82336 | AE42: =F42*('A1'!F43+$C42*('A1'!F41-'A1'!F43)) -> 622.32683 | AF42: =G42*('A1'!G43+$C42*('A1'!G41-'A1'!G43)) -> 685.96224 | AG42: =H42*('A1'!H43+$C42*('A1'!H41-'A1'!H43)) -> 692.36745 | AH42: =I42*('A1'!I43+$C42*('A1'!I41-'A1'!I43)) -> 673.68959 | AI42: =J42*('A1'!J43+$C42*('A1'!J41-'A1'!J43)) -> 686.34221 | AJ42: =(U42-Z42)*DCF!$H$40 -> 235.41398 | AK42: =(V42-AA42)*DCF!$H$40 -> 299.57338 | AL42: =(W42-AB42)*DCF!$H$40 -> 385.0713 | AM42: =(X42-AC42)*DCF!$H$40 -> 449.58498 | AN42: =(Y42-AD42)*DCF!$H$40 -> 516.07141 | AO42: =(F42-DCF!$H$7)*DCF!$H$41 -> 334.86245 | AP42: =(G42-F42)*DCF!$H$41 -> 323.27861 | AQ42: =(H42-G42)*DCF!$H$41 -> 318.11456 | AR42: =(I42-H42)*DCF!$H$41 -> 291.37371 | AS42: =(J42-I42)*DCF!$H$41 -> 284.44504 | AT42: =(U42-Z42)*(1-DCF!$H$40)+Z42-AE42-AO42 -> 142.94305 | AU42: =(V42-AA42)*(1-DCF!$H$40)+AA42-AF42-AP42 -> 339.25132 | AV42: =(W42-AB42)*(1-DCF!$H$40)+AB42-AG42-AQ42 -> 637.55708 | AW42: =(X42-AC42)*(1-DCF!$H$40)+AC42-AH42-AR42 -> 907.69867 | AX42: =(Y42-AD42)*(1-DCF!$H$40)+AD42-AI42-AS42 -> 1133.4912 | AY42: =0.0925+$E42*(0.1125-0.0925) -> 0.10556659 | AZ42: =10+$E42*(14-10) -> 12.613318 | BA42: =SUMPRODUCT(AT42:AX42,(1+$AY42)^(-{1,2,3,4,5})) -> 2172.5035 | BB42: =Y42*$AZ42 -> 33051.307 | BC42: =BB42*(1+$AY42)^(-5) -> 20010.784 | BD42: =BA42+BC42 -> 22183.287 | BE42: =BD42-(DCF!$J$48-DCF!$J$51) -> 21621.147 | BF42: =BE42/DCF!$J$55 -> 872.53495
A43: 17 | B43: =RAND() -> 0.35198669 | C43: =IF(B43<0.5,SQRT(0.5*B43),1-SQRT(0.5*(1-B43))) -> 0.41951561 | D43: =RAND() -> 0.268918 | E43: =IF(D43<0.5,SQRT(0.5*D43),1-SQRT(0.5*(1-D43))) -> 0.36668651 | F43: =DCF!$H$7*(1+('A1'!F14+$C43*('A1'!F12-'A1'!F14))) -> 6257.1235 | G43: =F43*(1+('A1'!G14+$C43*('A1'!G12-'A1'!G14))) -> 7026.295 | H43: =G43*(1+('A1'!H14+$C43*('A1'!H12-'A1'!H14))) -> 7760.803 | I43: =H43*(1+('A1'!I14+$C43*('A1'!I12-'A1'!I14))) -> 8441.8632 | J43: =I43*(1+('A1'!J14+$C43*('A1'!J12-'A1'!J14))) -> 9111.8609 | K43: ='A1'!F21+$C43*('A1'!F19-'A1'!F21) -> 0.35692664 | L43: ='A1'!G21+$C43*('A1'!G19-'A1'!G21) -> 0.35353633 | M43: ='A1'!H21+$C43*('A1'!H19-'A1'!H21) -> 0.34434117 | N43: ='A1'!I21+$C43*('A1'!I19-'A1'!I21) -> 0.33934117 | O43: ='A1'!J21+$C43*('A1'!J19-'A1'!J21) -> 0.33434117 | P43: ='A1'!F28+$C43*('A1'!F26-'A1'!F28) -> 0.44951211 | Q43: ='A1'!G28+$C43*('A1'!G26-'A1'!G28) -> 0.4461218 | R43: ='A1'!H28+$C43*('A1'!H26-'A1'!H28) -> 0.43982906 | S43: ='A1'!I28+$C43*('A1'!I26-'A1'!I28) -> 0.43773149 | T43: ='A1'!J28+$C43*('A1'!J26-'A1'!J28) -> 0.43563391 | U43: =F43*(1-K43-P43) -> 1211.1366 | V43: =G43*(1-L43-Q43) -> 1407.6611 | W43: =H43*(1-M43-R43) -> 1675.0123 | X43: =I43*(1-N43-S43) -> 1881.9221 | Y43: =J43*(1-O43-T43) -> 2095.9551 | Z43: =F43*('A1'!F35+$C43*('A1'!F33-'A1'!F35)) -> 362.3026 | AA43: =G43*('A1'!G35+$C43*('A1'!G33-'A1'!G35)) -> 406.15389 | AB43: =H43*('A1'!H35+$C43*('A1'!H33-'A1'!H35)) -> 429.83462 | AC43: =I43*('A1'!I35+$C43*('A1'!I33-'A1'!I35)) -> 447.13015 | AD43: =J43*('A1'!J35+$C43*('A1'!J33-'A1'!J35)) -> 464.3934 | AE43: =F43*('A1'!F43+$C43*('A1'!F41-'A1'!F43)) -> 635.78436 | AF43: =G43*('A1'!G43+$C43*('A1'!G41-'A1'!G43)) -> 704.85651 | AG43: =H43*('A1'!H43+$C43*('A1'!H41-'A1'!H43)) -> 700.93209 | AH43: =I43*('A1'!I43+$C43*('A1'!I41-'A1'!I43)) -> 678.02474 | AI43: =J43*('A1'!J43+$C43*('A1'!J41-'A1'!J43)) -> 686.27761 | AJ43: =(U43-Z43)*DCF!$H$40 -> 205.41784 | AK43: =(V43-AA43)*DCF!$H$40 -> 242.36475 | AL43: =(W43-AB43)*DCF!$H$40 -> 301.33299 | AM43: =(X43-AC43)*DCF!$H$40 -> 347.21966 | AN43: =(Y43-AD43)*DCF!$H$40 -> 394.83793 | AO43: =(F43-DCF!$H$7)*DCF!$H$41 -> 295.82755 | AP43: =(G43-F43)*DCF!$H$41 -> 255.23988 | AQ43: =(H43-G43)*DCF!$H$41 -> 243.73722 | AR43: =(I43-H43)*DCF!$H$41 -> 226.00123 | AS43: =(J43-I43)*DCF!$H$41 -> 222.33029 | AT43: =(U43-Z43)*(1-DCF!$H$40)+Z43-AE43-AO43 -> 74.106882 | AU43: =(V43-AA43)*(1-DCF!$H$40)+AA43-AF43-AP43 -> 205.19996 | AV43: =(W43-AB43)*(1-DCF!$H$40)+AB43-AG43-AQ43 -> 429.00998 | AW43: =(X43-AC43)*(1-DCF!$H$40)+AC43-AH43-AR43 -> 630.67649 | AX43: =(Y43-AD43)*(1-DCF!$H$40)+AD43-AI43-AS43 -> 792.50925 | AY43: =0.0925+$E43*(0.1125-0.0925) -> 0.09983373 | AZ43: =10+$E43*(14-10) -> 11.466746 | BA43: =SUMPRODUCT(AT43:AX43,(1+$AY43)^(-{1,2,3,4,5})) -> 1482.9649 | BB43: =Y43*$AZ43 -> 24033.785 | BC43: =BB43*(1+$AY43)^(-5) -> 14934.373 | BD43: =BA43+BC43 -> 16417.338 | BE43: =BD43-(DCF!$J$48-DCF!$J$51) -> 15855.198 | BF43: =BE43/DCF!$J$55 -> 639.84644
A44: 18 | B44: =RAND() -> 0.013231737 | C44: =IF(B44<0.5,SQRT(0.5*B44),1-SQRT(0.5*(1-B44))) -> 0.081337991 | D44: =RAND() -> 0.39040464 | E44: =IF(D44<0.5,SQRT(0.5*D44),1-SQRT(0.5*(1-D44))) -> 0.44181706 | F44: =DCF!$H$7*(1+('A1'!F14+$C44*('A1'!F12-'A1'!F14))) -> 6057.5241 | G44: =F44*(1+('A1'!G14+$C44*('A1'!G12-'A1'!G14))) -> 6494.8816 | H44: =G44*(1+('A1'!H14+$C44*('A1'!H12-'A1'!H14))) -> 6888.3022 | I44: =H44*(1+('A1'!I14+$C44*('A1'!I12-'A1'!I14))) -> 7283.1425 | J44: =I44*(1+('A1'!J14+$C44*('A1'!J12-'A1'!J14))) -> 7688.7674 | K44: ='A1'!F21+$C44*('A1'!F19-'A1'!F21) -> 0.37552641 | L44: ='A1'!G21+$C44*('A1'!G19-'A1'!G21) -> 0.37889965 | M44: ='A1'!H21+$C44*('A1'!H19-'A1'!H21) -> 0.37308627 | N44: ='A1'!I21+$C44*('A1'!I19-'A1'!I21) -> 0.36808627 | O44: ='A1'!J21+$C44*('A1'!J19-'A1'!J21) -> 0.36308627 | P44: ='A1'!F28+$C44*('A1'!F26-'A1'!F28) -> 0.45796655 | Q44: ='A1'!G28+$C44*('A1'!G26-'A1'!G28) -> 0.46133979 | R44: ='A1'!H28+$C44*('A1'!H26-'A1'!H28) -> 0.46011972 | S44: ='A1'!I28+$C44*('A1'!I26-'A1'!I28) -> 0.45971303 | T44: ='A1'!J28+$C44*('A1'!J26-'A1'!J28) -> 0.45930634 | U44: =F44*(1-K44-P44) -> 1008.6204 | V44: =G44*(1-L44-Q44) -> 1037.6259 | W44: =H44*(1-M44-R44) -> 1148.9275 | X44: =I44*(1-N44-S44) -> 1254.1622 | Y44: =J44*(1-O44-T44) -> 1365.5819 | Z44: =F44*('A1'!F35+$C44*('A1'!F33-'A1'!F35)) -> 360.98791 | AA44: =G44*('A1'!G35+$C44*('A1'!G33-'A1'!G35)) -> 397.39985 | AB44: =H44*('A1'!H35+$C44*('A1'!H33-'A1'!H35)) -> 407.13504 | AC44: =I44*('A1'!I35+$C44*('A1'!I33-'A1'!I35)) -> 415.31351 | AD44: =J44*('A1'!J35+$C44*('A1'!J33-'A1'!J35)) -> 423.06631 | AE44: =F44*('A1'!F43+$C44*('A1'!F41-'A1'!F43)) -> 656.47352 | AF44: =G44*('A1'!G43+$C44*('A1'!G41-'A1'!G43)) -> 728.42156 | AG44: =H44*('A1'!H43+$C44*('A1'!H41-'A1'!H43)) -> 703.66191 | AH44: =I44*('A1'!I43+$C44*('A1'!I41-'A1'!I43)) -> 671.16468 | AI44: =J44*('A1'!J43+$C44*('A1'!J41-'A1'!J43)) -> 670.10046 | AJ44: =(U44-Z44)*DCF!$H$40 -> 156.72706 | AK44: =(V44-AA44)*DCF!$H$40 -> 154.93471 | AL44: =(W44-AB44)*DCF!$H$40 -> 179.51378 | AM44: =(X44-AC44)*DCF!$H$40 -> 203.00139 | AN44: =(Y44-AD44)*DCF!$H$40 -> 228.08877 | AO44: =(F44-DCF!$H$7)*DCF!$H$41 -> 229.59303 | AP44: =(G44-F44)*DCF!$H$41 -> 145.13157 | AQ44: =(H44-G44)*DCF!$H$41 -> 130.55165 | AR44: =(I44-H44)*DCF!$H$41 -> 131.0228 | AS44: =(J44-I44)*DCF!$H$41 -> 134.6015 | AT44: =(U44-Z44)*(1-DCF!$H$40)+Z44-AE44-AO44 -> -34.173204 | AU44: =(V44-AA44)*(1-DCF!$H$40)+AA44-AF44-AP44 -> 9.1380804 | AV44: =(W44-AB44)*(1-DCF!$H$40)+AB44-AG44-AQ44 -> 135.20019 | AW44: =(X44-AC44)*(1-DCF!$H$40)+AC44-AH44-AR44 -> 248.97337 | AX44: =(Y44-AD44)*(1-DCF!$H$40)+AD44-AI44-AS44 -> 332.79117 | AY44: =0.0925+$E44*(0.1125-0.0925) -> 0.10133634 | AZ44: =10+$E44*(14-10) -> 11.767268 | BA44: =SUMPRODUCT(AT44:AX44,(1+$AY44)^(-{1,2,3,4,5})) -> 452.32839 | BB44: =Y44*$AZ44 -> 16069.169 | BC44: =BB44*(1+$AY44)^(-5) -> 9917.3024 | BD44: =BA44+BC44 -> 10369.631 | BE44: =BD44-(DCF!$J$48-DCF!$J$51) -> 9807.4908 | BF44: =BE44/DCF!$J$55 -> 395.78744
A45: 19 | B45: =RAND() -> 0.68872549 | C45: =IF(B45<0.5,SQRT(0.5*B45),1-SQRT(0.5*(1-B45))) -> 0.60549112 | D45: =RAND() -> 0.18881143 | E45: =IF(D45<0.5,SQRT(0.5*D45),1-SQRT(0.5*(1-D45))) -> 0.30725513 | F45: =DCF!$H$7*(1+('A1'!F14+$C45*('A1'!F12-'A1'!F14))) -> 6366.89 | G45: =F45*(1+('A1'!G14+$C45*('A1'!G12-'A1'!G14))) -> 7327.1677 | H45: =G45*(1+('A1'!H14+$C45*('A1'!H12-'A1'!H14))) -> 8270.2757 | I45: =H45*(1+('A1'!I14+$C45*('A1'!I12-'A1'!I14))) -> 9134.4715 | J45: =I45*(1+('A1'!J14+$C45*('A1'!J12-'A1'!J14))) -> 9978.354 | K45: ='A1'!F21+$C45*('A1'!F19-'A1'!F21) -> 0.34669799 | L45: ='A1'!G21+$C45*('A1'!G19-'A1'!G21) -> 0.33958817 | M45: ='A1'!H21+$C45*('A1'!H19-'A1'!H21) -> 0.32853325 | N45: ='A1'!I21+$C45*('A1'!I19-'A1'!I21) -> 0.32353325 | O45: ='A1'!J21+$C45*('A1'!J19-'A1'!J21) -> 0.31853325 | P45: ='A1'!F28+$C45*('A1'!F26-'A1'!F28) -> 0.44486272 | Q45: ='A1'!G28+$C45*('A1'!G26-'A1'!G28) -> 0.4377529 | R45: ='A1'!H28+$C45*('A1'!H26-'A1'!H28) -> 0.42867053 | S45: ='A1'!I28+$C45*('A1'!I26-'A1'!I28) -> 0.42564308 | T45: ='A1'!J28+$C45*('A1'!J26-'A1'!J28) -> 0.42261562 | U45: =F45*(1-K45-P45) -> 1327.11 | V45: =G45*(1-L45-Q45) -> 1631.4594 | W45: =H45*(1-M45-R45) -> 2007.9916 | X45: =I45*(1-N45-S45) -> 2291.1417 | Y45: =J45*(1-O45-T45) -> 2582.9081 | Z45: =F45*('A1'!F35+$C45*('A1'!F33-'A1'!F35)) -> 362.73792 | AA45: =G45*('A1'!G35+$C45*('A1'!G33-'A1'!G35)) -> 409.91905 | AB45: =H45*('A1'!H35+$C45*('A1'!H33-'A1'!H35)) -> 441.13318 | AC45: =I45*('A1'!I35+$C45*('A1'!I33-'A1'!I35)) -> 463.42925 | AD45: =J45*('A1'!J35+$C45*('A1'!J33-'A1'!J35)) -> 486.28617 | AE45: =F45*('A1'!F43+$C45*('A1'!F41-'A1'!F43)) -> 623.25599 | AF45: =G45*('A1'!G43+$C45*('A1'!G41-'A1'!G43)) -> 687.34556 | AG45: =H45*('A1'!H43+$C45*('A1'!H41-'A1'!H43)) -> 693.1137 | AH45: =I45*('A1'!I43+$C45*('A1'!I41-'A1'!I43)) -> 674.19534 | AI45: =J45*('A1'!J43+$C45*('A1'!J41-'A1'!J43)) -> 686.58869 | AJ45: =(U45-Z45)*DCF!$H$40 -> 233.37805 | AK45: =(V45-AA45)*DCF!$H$40 -> 295.61276 | AL45: =(W45-AB45)*DCF!$H$40 -> 379.17974 | AM45: =(X45-AC45)*DCF!$H$40 -> 442.3064 | AN45: =(Y45-AD45)*DCF!$H$40 -> 507.38252 | AO45: =(F45-DCF!$H$7)*DCF!$H$41 -> 332.2522 | AP45: =(G45-F45)*DCF!$H$41 -> 318.65605 | AQ45: =(H45-G45)*DCF!$H$41 -> 312.95848 | AR45: =(I45-H45)*DCF!$H$41 -> 286.7725 | AS45: =(J45-I45)*DCF!$H$41 -> 280.03176 | AT45: =(U45-Z45)*(1-DCF!$H$40)+Z45-AE45-AO45 -> 138.22379 | AU45: =(V45-AA45)*(1-DCF!$H$40)+AA45-AF45-AP45 -> 329.84499 | AV45: =(W45-AB45)*(1-DCF!$H$40)+AB45-AG45-AQ45 -> 622.73969 | AW45: =(X45-AC45)*(1-DCF!$H$40)+AC45-AH45-AR45 -> 887.86741 | AX45: =(Y45-AD45)*(1-DCF!$H$40)+AD45-AI45-AS45 -> 1108.9052 | AY45: =0.0925+$E45*(0.1125-0.0925) -> 0.098645103 | AZ45: =10+$E45*(14-10) -> 11.229021 | BA45: =SUMPRODUCT(AT45:AX45,(1+$AY45)^(-{1,2,3,4,5})) -> 2170.9131 | BB45: =Y45*$AZ45 -> 29003.529 | BC45: =BB45*(1+$AY45)^(-5) -> 18120.23 | BD45: =BA45+BC45 -> 20291.144 | BE45: =BD45-(DCF!$J$48-DCF!$J$51) -> 19729.004 | BF45: =BE45/DCF!$J$55 -> 796.1763
A46: 20 | B46: =RAND() -> 0.31935455 | C46: =IF(B46<0.5,SQRT(0.5*B46),1-SQRT(0.5*(1-B46))) -> 0.39959639 | D46: =RAND() -> 0.68786954 | E46: =IF(D46<0.5,SQRT(0.5*D46),1-SQRT(0.5*(1-D46))) -> 0.60494908 | F46: =DCF!$H$7*(1+('A1'!F14+$C46*('A1'!F12-'A1'!F14))) -> 6245.3667 | G46: =F46*(1+('A1'!G14+$C46*('A1'!G12-'A1'!G14))) -> 6994.4326 | H46: =G46*(1+('A1'!H14+$C46*('A1'!H12-'A1'!H14))) -> 7707.4978 | I46: =H46*(1+('A1'!I14+$C46*('A1'!I12-'A1'!I14))) -> 8370.0626 | J46: =I46*(1+('A1'!J14+$C46*('A1'!J12-'A1'!J14))) -> 9022.691 | K46: ='A1'!F21+$C46*('A1'!F19-'A1'!F21) -> 0.3580222 | L46: ='A1'!G21+$C46*('A1'!G19-'A1'!G21) -> 0.35503027 | M46: ='A1'!H21+$C46*('A1'!H19-'A1'!H21) -> 0.34603431 | N46: ='A1'!I21+$C46*('A1'!I19-'A1'!I21) -> 0.34103431 | O46: ='A1'!J21+$C46*('A1'!J19-'A1'!J21) -> 0.33603431 | P46: ='A1'!F28+$C46*('A1'!F26-'A1'!F28) -> 0.45001009 | Q46: ='A1'!G28+$C46*('A1'!G26-'A1'!G28) -> 0.44701816 | R46: ='A1'!H28+$C46*('A1'!H26-'A1'!H28) -> 0.44102422 | S46: ='A1'!I28+$C46*('A1'!I26-'A1'!I28) -> 0.43902623 | T46: ='A1'!J28+$C46*('A1'!J26-'A1'!J28) -> 0.43702825 | U46: =F46*(1-K46-P46) -> 1198.9088 | V46: =G46*(1-L46-Q46) -> 1384.5589 | W46: =H46*(1-M46-R46) -> 1641.246 | X46: =I46*(1-N46-S46) -> 1840.907 | Y46: =J46*(1-O46-T46) -> 2047.5864 | Z46: =F46*('A1'!F35+$C46*('A1'!F33-'A1'!F35)) -> 362.24387 | AA46: =G46*('A1'!G35+$C46*('A1'!G33-'A1'!G35)) -> 405.70532 | AB46: =H46*('A1'!H35+$C46*('A1'!H33-'A1'!H35)) -> 428.5711 | AC46: =I46*('A1'!I35+$C46*('A1'!I33-'A1'!I35)) -> 445.32787 | AD46: =J46*('A1'!J35+$C46*('A1'!J33-'A1'!J35)) -> 462.00548 | AE46: =F46*('A1'!F43+$C46*('A1'!F41-'A1'!F43)) -> 637.07782 | AF46: =G46*('A1'!G43+$C46*('A1'!G41-'A1'!G43)) -> 706.5365 | AG46: =H46*('A1'!H43+$C46*('A1'!H41-'A1'!H43)) -> 701.49118 | AH46: =I46*('A1'!I43+$C46*('A1'!I41-'A1'!I43)) -> 678.09331 | AI46: =J46*('A1'!J43+$C46*('A1'!J41-'A1'!J43)) -> 685.85198 | AJ46: =(U46-Z46)*DCF!$H$40 -> 202.4729 | AK46: =(V46-AA46)*DCF!$H$40 -> 236.88257 | AL46: =(W46-AB46)*DCF!$H$40 -> 293.46732 | AM46: =(X46-AC46)*DCF!$H$40 -> 337.73016 | AN46: =(Y46-AD46)*DCF!$H$40 -> 383.71059 | AO46: =(F46-DCF!$H$7)*DCF!$H$41 -> 291.92623 | AP46: =(G46-F46)*DCF!$H$41 -> 248.56808 | AQ46: =(H46-G46)*DCF!$H$41 -> 236.62168 | AR46: =(I46-H46)*DCF!$H$41 -> 219.86379 | AS46: =(J46-I46)*DCF!$H$41 -> 216.56651 | AT46: =(U46-Z46)*(1-DCF!$H$40)+Z46-AE46-AO46 -> 67.431806 | AU46: =(V46-AA46)*(1-DCF!$H$40)+AA46-AF46-AP46 -> 192.57175 | AV46: =(W46-AB46)*(1-DCF!$H$40)+AB46-AG46-AQ46 -> 409.66579 | AW46: =(X46-AC46)*(1-DCF!$H$40)+AC46-AH46-AR46 -> 605.21978 | AX46: =(Y46-AD46)*(1-DCF!$H$40)+AD46-AI46-AS46 -> 761.45734 | AY46: =0.0925+$E46*(0.1125-0.0925) -> 0.10459898 | AZ46: =10+$E46*(14-10) -> 12.419796 | BA46: =SUMPRODUCT(AT46:AX46,(1+$AY46)^(-{1,2,3,4,5})) -> 1392.4097 | BB46: =Y46*$AZ46 -> 25430.606 | BC46: =BB46*(1+$AY46)^(-5) -> 15464.416 | BD46: =BA46+BC46 -> 16856.826 | BE46: =BD46-(DCF!$J$48-DCF!$J$51) -> 16294.686 | BF46: =BE46/DCF!$J$55 -> 657.58224
A47: 21 | B47: =RAND() -> 0.093618603 | C47: =IF(B47<0.5,SQRT(0.5*B47),1-SQRT(0.5*(1-B47))) -> 0.21635457 | D47: =RAND() -> 0.5607229 | E47: =IF(D47<0.5,SQRT(0.5*D47),1-SQRT(0.5*(1-D47))) -> 0.53134389 | F47: =DCF!$H$7*(1+('A1'!F14+$C47*('A1'!F12-'A1'!F14))) -> 6137.2137 | G47: =F47*(1+('A1'!G14+$C47*('A1'!G12-'A1'!G14))) -> 6704.6186 | H47: =G47*(1+('A1'!H14+$C47*('A1'!H12-'A1'!H14))) -> 7228.4243 | I47: =H47*(1+('A1'!I14+$C47*('A1'!I12-'A1'!I14))) -> 7730.5968 | J47: =I47*(1+('A1'!J14+$C47*('A1'!J12-'A1'!J14))) -> 8234.2051 | K47: ='A1'!F21+$C47*('A1'!F19-'A1'!F21) -> 0.3681005 | L47: ='A1'!G21+$C47*('A1'!G19-'A1'!G21) -> 0.36877341 | M47: ='A1'!H21+$C47*('A1'!H19-'A1'!H21) -> 0.36160986 | N47: ='A1'!I21+$C47*('A1'!I19-'A1'!I21) -> 0.35660986 | O47: ='A1'!J21+$C47*('A1'!J19-'A1'!J21) -> 0.35160986 | P47: ='A1'!F28+$C47*('A1'!F26-'A1'!F28) -> 0.45459114 | Q47: ='A1'!G28+$C47*('A1'!G26-'A1'!G28) -> 0.45526404 | R47: ='A1'!H28+$C47*('A1'!H26-'A1'!H28) -> 0.45201873 | S47: ='A1'!I28+$C47*('A1'!I26-'A1'!I28) -> 0.45093695 | T47: ='A1'!J28+$C47*('A1'!J26-'A1'!J28) -> 0.44985518 | U47: =F47*(1-K47-P47) -> 1088.1793 | V47: =G47*(1-L47-Q47) -> 1179.7618 | W47: =H47*(1-M47-R47) -> 1347.1717 | X47: =I47*(1-N47-S47) -> 1487.778 | Y47: =J47*(1-O47-T47) -> 1634.7776 | Z47: =F47*('A1'!F35+$C47*('A1'!F33-'A1'!F35)) -> 361.59375 | AA47: =G47*('A1'!G35+$C47*('A1'!G33-'A1'!G35)) -> 401.18061 | AB47: =H47*('A1'!H35+$C47*('A1'!H33-'A1'!H35)) -> 416.50253 | AC47: =I47*('A1'!I35+$C47*('A1'!I33-'A1'!I35)) -> 428.30401 | AD47: =J47*('A1'!J35+$C47*('A1'!J33-'A1'!J35)) -> 439.73739 | AE47: =F47*('A1'!F43+$C47*('A1'!F41-'A1'!F43)) -> 648.53722 | AF47: =G47*('A1'!G43+$C47*('A1'!G41-'A1'!G43)) -> 720.26102 | AG47: =H47*('A1'!H43+$C47*('A1'!H41-'A1'!H43)) -> 704.24796 | AH47: =I47*('A1'!I43+$C47*('A1'!I41-'A1'!I43)) -> 675.86744 | AI47: =J47*('A1'!J43+$C47*('A1'!J41-'A1'!J43)) -> 678.72568 | AJ47: =(U47-Z47)*DCF!$H$40 -> 175.83371 | AK47: =(V47-AA47)*DCF!$H$40 -> 188.41665 | AL47: =(W47-AB47)*DCF!$H$40 -> 225.22193 | AM47: =(X47-AC47)*DCF!$H$40 -> 256.3927 | AN47: =(Y47-AD47)*DCF!$H$40 -> 289.19972 | AO47: =(F47-DCF!$H$7)*DCF!$H$41 -> 256.037 | AP47: =(G47-F47)*DCF!$H$41 -> 188.28618 | AQ47: =(H47-G47)*DCF!$H$41 -> 173.81831 | AR47: =(I47-H47)*DCF!$H$41 -> 166.6396 | AS47: =(J47-I47)*DCF!$H$41 -> 167.11608 | AT47: =(U47-Z47)*(1-DCF!$H$40)+Z47-AE47-AO47 -> 7.7713978 | AU47: =(V47-AA47)*(1-DCF!$H$40)+AA47-AF47-AP47 -> 82.797935 | AV47: =(W47-AB47)*(1-DCF!$H$40)+AB47-AG47-AQ47 -> 243.88346 | AW47: =(X47-AC47)*(1-DCF!$H$40)+AC47-AH47-AR47 -> 388.87823 | AX47: =(Y47-AD47)*(1-DCF!$H$40)+AD47-AI47-AS47 -> 499.73609 | AY47: =0.0925+$E47*(0.1125-0.0925) -> 0.10312688 | AZ47: =10+$E47*(14-10) -> 12.125376 | BA47: =SUMPRODUCT(AT47:AX47,(1+$AY47)^(-{1,2,3,4,5})) -> 825.29925 | BB47: =Y47*$AZ47 -> 19822.292 | BC47: =BB47*(1+$AY47)^(-5) -> 12134.63 | BD47: =BA47+BC47 -> 12959.929 | BE47: =BD47-(DCF!$J$48-DCF!$J$51) -> 12397.789 | BF47: =BE47/DCF!$J$55 -> 500.32055
A48: 22 | B48: =RAND() -> 0.24398042 | C48: =IF(B48<0.5,SQRT(0.5*B48),1-SQRT(0.5*(1-B48))) -> 0.34927097 | D48: =RAND() -> 0.51613413 | E48: =IF(D48<0.5,SQRT(0.5*D48),1-SQRT(0.5*(1-D48))) -> 0.50813321 | F48: =DCF!$H$7*(1+('A1'!F14+$C48*('A1'!F12-'A1'!F14))) -> 6215.6636 | G48: =F48*(1+('A1'!G14+$C48*('A1'!G12-'A1'!G14))) -> 6914.2461 | H48: =G48*(1+('A1'!H14+$C48*('A1'!H12-'A1'!H14))) -> 7573.9013 | I48: =H48*(1+('A1'!I14+$C48*('A1'!I12-'A1'!I14))) -> 8190.6773 | J48: =I48*(1+('A1'!J14+$C48*('A1'!J12-'A1'!J14))) -> 8800.4648 | K48: ='A1'!F21+$C48*('A1'!F19-'A1'!F21) -> 0.3607901 | L48: ='A1'!G21+$C48*('A1'!G19-'A1'!G21) -> 0.35880468 | M48: ='A1'!H21+$C48*('A1'!H19-'A1'!H21) -> 0.35031197 | N48: ='A1'!I21+$C48*('A1'!I19-'A1'!I21) -> 0.34531197 | O48: ='A1'!J21+$C48*('A1'!J19-'A1'!J21) -> 0.34031197 | P48: ='A1'!F28+$C48*('A1'!F26-'A1'!F28) -> 0.45126823 | Q48: ='A1'!G28+$C48*('A1'!G26-'A1'!G28) -> 0.44928281 | R48: ='A1'!H28+$C48*('A1'!H26-'A1'!H28) -> 0.44404374 | S48: ='A1'!I28+$C48*('A1'!I26-'A1'!I28) -> 0.44229739 | T48: ='A1'!J28+$C48*('A1'!J26-'A1'!J28) -> 0.44055103 | U48: =F48*(1-K48-P48) -> 1168.1823 | V48: =G48*(1-L48-Q48) -> 1326.9304 | W48: =H48*(1-M48-R48) -> 1557.5296 | X48: =I48*(1-N48-S48) -> 1739.6232 | Y48: =J48*(1-O48-T48) -> 1928.5074 | Z48: =F48*('A1'!F35+$C48*('A1'!F33-'A1'!F35)) -> 362.08506 | AA48: =G48*('A1'!G35+$C48*('A1'!G33-'A1'!G35)) -> 404.5338 | AB48: =H48*('A1'!H35+$C48*('A1'!H33-'A1'!H35)) -> 425.3353 | AC48: =I48*('A1'!I35+$C48*('A1'!I33-'A1'!I35)) -> 440.73009 | AD48: =J48*('A1'!J35+$C48*('A1'!J33-'A1'!J35)) -> 455.94107 | AE48: =F48*('A1'!F43+$C48*('A1'!F41-'A1'!F43)) -> 640.30398 | AF48: =G48*('A1'!G43+$C48*('A1'!G41-'A1'!G43)) -> 710.61521 | AG48: =H48*('A1'!H43+$C48*('A1'!H41-'A1'!H43)) -> 702.6726 | AH48: =I48*('A1'!I43+$C48*('A1'!I41-'A1'!I43)) -> 677.98754 | AI48: =J48*('A1'!J43+$C48*('A1'!J41-'A1'!J43)) -> 684.46069 | AJ48: =(U48-Z48)*DCF!$H$40 -> 195.07552 | AK48: =(V48-AA48)*DCF!$H$40 -> 223.21997 | AL48: =(W48-AB48)*DCF!$H$40 -> 273.99101 | AM48: =(X48-AC48)*DCF!$H$40 -> 314.33214 | AN48: =(Y48-AD48)*DCF!$H$40 -> 356.36106 | AO48: =(F48-DCF!$H$7)*DCF!$H$41 -> 282.06963 | AP48: =(G48-F48)*DCF!$H$41 -> 231.81578 | AQ48: =(H48-G48)*DCF!$H$41 -> 218.89827 | AR48: =(I48-H48)*DCF!$H$41 -> 204.66934 | AS48: =(J48-I48)*DCF!$H$41 -> 202.35029 | AT48: =(U48-Z48)*(1-DCF!$H$40)+Z48-AE48-AO48 -> 50.733115 | AU48: =(V48-AA48)*(1-DCF!$H$40)+AA48-AF48-AP48 -> 161.27941 | AV48: =(W48-AB48)*(1-DCF!$H$40)+AB48-AG48-AQ48 -> 361.96768 | AW48: =(X48-AC48)*(1-DCF!$H$40)+AC48-AH48-AR48 -> 542.63421 | AX48: =(Y48-AD48)*(1-DCF!$H$40)+AD48-AI48-AS48 -> 685.33541 | AY48: =0.0925+$E48*(0.1125-0.0925) -> 0.10266266 | AZ48: =10+$E48*(14-10) -> 12.032533 | BA48: =SUMPRODUCT(AT48:AX48,(1+$AY48)^(-{1,2,3,4,5})) -> 1236.1276 | BB48: =Y48*$AZ48 -> 23204.829 | BC48: =BB48*(1+$AY48)^(-5) -> 14235.248 | BD48: =BA48+BC48 -> 15471.375 | BE48: =BD48-(DCF!$J$48-DCF!$J$51) -> 14909.235 | BF48: =BE48/DCF!$J$55 -> 601.67153
A49: 23 | B49: =RAND() -> 0.38596125 | C49: =IF(B49<0.5,SQRT(0.5*B49),1-SQRT(0.5*(1-B49))) -> 0.4392956 | D49: =RAND() -> 0.31579521 | E49: =IF(D49<0.5,SQRT(0.5*D49),1-SQRT(0.5*(1-D49))) -> 0.39736332 | F49: =DCF!$H$7*(1+('A1'!F14+$C49*('A1'!F12-'A1'!F14))) -> 6268.798 | G49: =F49*(1+('A1'!G14+$C49*('A1'!G12-'A1'!G14))) -> 7058.0042 | H49: =G49*(1+('A1'!H14+$C49*('A1'!H12-'A1'!H14))) -> 7813.976 | I49: =H49*(1+('A1'!I14+$C49*('A1'!I12-'A1'!I14))) -> 8513.6128 | J49: =I49*(1+('A1'!J14+$C49*('A1'!J12-'A1'!J14))) -> 9201.093 | K49: ='A1'!F21+$C49*('A1'!F19-'A1'!F21) -> 0.35583874 | L49: ='A1'!G21+$C49*('A1'!G19-'A1'!G21) -> 0.35205283 | M49: ='A1'!H21+$C49*('A1'!H19-'A1'!H21) -> 0.34265987 | N49: ='A1'!I21+$C49*('A1'!I19-'A1'!I21) -> 0.33765987 | O49: ='A1'!J21+$C49*('A1'!J19-'A1'!J21) -> 0.33265987 | P49: ='A1'!F28+$C49*('A1'!F26-'A1'!F28) -> 0.44901761 | Q49: ='A1'!G28+$C49*('A1'!G26-'A1'!G28) -> 0.4452317 | R49: ='A1'!H28+$C49*('A1'!H26-'A1'!H28) -> 0.43864226 | S49: ='A1'!I28+$C49*('A1'!I26-'A1'!I28) -> 0.43644579 | T49: ='A1'!J28+$C49*('A1'!J26-'A1'!J28) -> 0.43424931 | U49: =F49*(1-K49-P49) -> 1223.3161 | V49: =G49*(1-L49-Q49) -> 1430.7667 | W49: =H49*(1-M49-R49) -> 1708.8998 | X49: =I49*(1-N49-S49) -> 1923.177 | Y49: =J49*(1-O49-T49) -> 2144.6903 | Z49: =F49*('A1'!F35+$C49*('A1'!F33-'A1'!F35)) -> 362.3586 | AA49: =G49*('A1'!G35+$C49*('A1'!G33-'A1'!G35)) -> 406.59076 | AB49: =H49*('A1'!H35+$C49*('A1'!H33-'A1'!H35)) -> 431.07946 | AC49: =I49*('A1'!I35+$C49*('A1'!I33-'A1'!I35)) -> 448.90963 | AD49: =J49*('A1'!J35+$C49*('A1'!J33-'A1'!J35)) -> 466.75721 | AE49: =F49*('A1'!F43+$C49*('A1'!F41-'A1'!F43)) -> 634.49067 | AF49: =G49*('A1'!G43+$C49*('A1'!G41-'A1'!G43)) -> 703.15123 | AG49: =H49*('A1'!H43+$C49*('A1'!H41-'A1'!H43)) -> 700.32489 | AH49: =I49*('A1'!I43+$C49*('A1'!I41-'A1'!I43)) -> 677.89348 | AI49: =J49*('A1'!J43+$C49*('A1'!J41-'A1'!J43)) -> 686.62838 | AJ49: =(U49-Z49)*DCF!$H$40 -> 208.35172 | AK49: =(V49-AA49)*DCF!$H$40 -> 247.85057 | AL49: =(W49-AB49)*DCF!$H$40 -> 309.23253 | AM49: =(X49-AC49)*DCF!$H$40 -> 356.77269 | AN49: =(Y49-AD49)*DCF!$H$40 -> 406.05981 | AO49: =(F49-DCF!$H$7)*DCF!$H$41 -> 299.70161 | AP49: =(G49-F49)*DCF!$H$41 -> 261.88813 | AQ49: =(H49-G49)*DCF!$H$41 -> 250.85969 | AR49: =(I49-H49)*DCF!$H$41 -> 232.16568 | AS49: =(J49-I49)*DCF!$H$41 -> 228.13162 | AT49: =(U49-Z49)*(1-DCF!$H$40)+Z49-AE49-AO49 -> 80.772117 | AU49: =(V49-AA49)*(1-DCF!$H$40)+AA49-AF49-AP49 -> 217.87674 | AV49: =(W49-AB49)*(1-DCF!$H$40)+AB49-AG49-AQ49 -> 448.48272 | AW49: =(X49-AC49)*(1-DCF!$H$40)+AC49-AH49-AR49 -> 656.34511 | AX49: =(Y49-AD49)*(1-DCF!$H$40)+AD49-AI49-AS49 -> 823.87049 | AY49: =0.0925+$E49*(0.1125-0.0925) -> 0.10044727 | AZ49: =10+$E49*(14-10) -> 11.589453 | BA49: =SUMPRODUCT(AT49:AX49,(1+$AY49)^(-{1,2,3,4,5})) -> 1547.9416 | BB49: =Y49*$AZ49 -> 24855.788 | BC49: =BB49*(1+$AY49)^(-5) -> 15402.15 | BD49: =BA49+BC49 -> 16950.092 | BE49: =BD49-(DCF!$J$48-DCF!$J$51) -> 16387.952 | BF49: =BE49/DCF!$J$55 -> 661.34606
A50: 24 | B50: =RAND() -> 0.5921758 | C50: =IF(B50<0.5,SQRT(0.5*B50),1-SQRT(0.5*(1-B50))) -> 0.54843373 | D50: =RAND() -> 0.9694099 | E50: =IF(D50<0.5,SQRT(0.5*D50),1-SQRT(0.5*(1-D50))) -> 0.87632684 | F50: =DCF!$H$7*(1+('A1'!F14+$C50*('A1'!F12-'A1'!F14))) -> 6333.2136 | G50: =F50*(1+('A1'!G14+$C50*('A1'!G12-'A1'!G14))) -> 7234.2086 | H50: =G50*(1+('A1'!H14+$C50*('A1'!H12-'A1'!H14))) -> 8111.6919 | I50: =H50*(1+('A1'!I14+$C50*('A1'!I12-'A1'!I14))) -> 8917.6618 | J50: =I50*(1+('A1'!J14+$C50*('A1'!J12-'A1'!J14))) -> 9705.8972 | K50: ='A1'!F21+$C50*('A1'!F19-'A1'!F21) -> 0.34983614 | L50: ='A1'!G21+$C50*('A1'!G19-'A1'!G21) -> 0.34386747 | M50: ='A1'!H21+$C50*('A1'!H19-'A1'!H21) -> 0.33338313 | N50: ='A1'!I21+$C50*('A1'!I19-'A1'!I21) -> 0.32838313 | O50: ='A1'!J21+$C50*('A1'!J19-'A1'!J21) -> 0.32338313 | P50: ='A1'!F28+$C50*('A1'!F26-'A1'!F28) -> 0.44628916 | Q50: ='A1'!G28+$C50*('A1'!G26-'A1'!G28) -> 0.44032048 | R50: ='A1'!H28+$C50*('A1'!H26-'A1'!H28) -> 0.43209398 | S50: ='A1'!I28+$C50*('A1'!I26-'A1'!I28) -> 0.42935181 | T50: ='A1'!J28+$C50*('A1'!J26-'A1'!J28) -> 0.42660964 | U50: =F50*(1-K50-P50) -> 1291.182 | V50: =G50*(1-L50-Q50) -> 1561.2294 | W50: =H50*(1-M50-R50) -> 1902.3774 | X50: =I50*(1-N50-S50) -> 2160.4379 | Y50: =J50*(1-O50-T50) -> 2426.5444 | Z50: =F50*('A1'!F35+$C50*('A1'!F33-'A1'!F35)) -> 362.62607 | AA50: =G50*('A1'!G35+$C50*('A1'!G33-'A1'!G35)) -> 408.84609 | AB50: =H50*('A1'!H35+$C50*('A1'!H33-'A1'!H35)) -> 437.76554 | AC50: =I50*('A1'!I35+$C50*('A1'!I33-'A1'!I35)) -> 458.53543 | AD50: =J50*('A1'!J35+$C50*('A1'!J33-'A1'!J35)) -> 479.65374 | AE50: =F50*('A1'!F43+$C50*('A1'!F41-'A1'!F43)) -> 627.18653 | AF50: =G50*('A1'!G43+$C50*('A1'!G41-'A1'!G43)) -> 693.07205 | AG50: =H50*('A1'!H43+$C50*('A1'!H41-'A1'!H43)) -> 696.02226 | AH50: =I50*('A1'!I43+$C50*('A1'!I41-'A1'!I43)) -> 676.00174 | AI50: =J50*('A1'!J43+$C50*('A1'!J41-'A1'!J43)) -> 687.2243 | AJ50: =(U50-Z50)*DCF!$H$40 -> 224.71054 | AK50: =(V50-AA50)*DCF!$H$40 -> 278.87675 | AL50: =(W50-AB50)*DCF!$H$40 -> 354.43608 | AM50: =(X50-AC50)*DCF!$H$40 -> 411.86039 | AN50: =(Y50-AD50)*DCF!$H$40 -> 471.14755 | AO50: =(F50-DCF!$H$7)*DCF!$H$41 -> 321.07709 | AP50: =(G50-F50)*DCF!$H$41 -> 298.98384 | AQ50: =(H50-G50)*DCF!$H$41 -> 291.18179 | AR50: =(I50-H50)*DCF!$H$41 -> 267.45095 | AS50: =(J50-I50)*DCF!$H$41 -> 261.56596 | AT50: =(U50-Z50)*(1-DCF!$H$40)+Z50-AE50-AO50 -> 118.20784 | AU50: =(V50-AA50)*(1-DCF!$H$40)+AA50-AF50-AP50 -> 290.29673 | AV50: =(W50-AB50)*(1-DCF!$H$40)+AB50-AG50-AQ50 -> 560.73731 | AW50: =(X50-AC50)*(1-DCF!$H$40)+AC50-AH50-AR50 -> 805.12478 | AX50: =(Y50-AD50)*(1-DCF!$H$40)+AD50-AI50-AS50 -> 1006.6066 | AY50: =0.0925+$E50*(0.1125-0.0925) -> 0.11002654 | AZ50: =10+$E50*(14-10) -> 13.505307 | BA50: =SUMPRODUCT(AT50:AX50,(1+$AY50)^(-{1,2,3,4,5})) -> 1879.6785 | BB50: =Y50*$AZ50 -> 32771.229 | BC50: =BB50*(1+$AY50)^(-5) -> 19445.805 | BD50: =BA50+BC50 -> 21325.483 | BE50: =BD50-(DCF!$J$48-DCF!$J$51) -> 20763.343 | BF50: =BE50/DCF!$J$55 -> 837.91772
A51: 25 | B51: =RAND() -> 0.53844195 | C51: =IF(B51<0.5,SQRT(0.5*B51),1-SQRT(0.5*(1-B51))) -> 0.51960534 | D51: =RAND() -> 0.21228673 | E51: =IF(D51<0.5,SQRT(0.5*D51),1-SQRT(0.5*(1-D51))) -> 0.32579651 | F51: =DCF!$H$7*(1+('A1'!F14+$C51*('A1'!F12-'A1'!F14))) -> 6316.1985 | G51: =F51*(1+('A1'!G14+$C51*('A1'!G12-'A1'!G14))) -> 7187.46 | H51: =G51*(1+('A1'!H14+$C51*('A1'!H12-'A1'!H14))) -> 8032.3365 | I51: =H51*(1+('A1'!I14+$C51*('A1'!I12-'A1'!I14))) -> 8809.5814 | J51: =I51*(1+('A1'!J14+$C51*('A1'!J12-'A1'!J14))) -> 9570.4858 | K51: ='A1'!F21+$C51*('A1'!F19-'A1'!F21) -> 0.35142171 | L51: ='A1'!G21+$C51*('A1'!G19-'A1'!G21) -> 0.3460296 | M51: ='A1'!H21+$C51*('A1'!H19-'A1'!H21) -> 0.33583355 | N51: ='A1'!I21+$C51*('A1'!I19-'A1'!I21) -> 0.33083355 | O51: ='A1'!J21+$C51*('A1'!J19-'A1'!J21) -> 0.32583355 | P51: ='A1'!F28+$C51*('A1'!F26-'A1'!F28) -> 0.44700987 | Q51: ='A1'!G28+$C51*('A1'!G26-'A1'!G28) -> 0.44161776 | R51: ='A1'!H28+$C51*('A1'!H26-'A1'!H28) -> 0.43382368 | S51: ='A1'!I28+$C51*('A1'!I26-'A1'!I28) -> 0.43122565 | T51: ='A1'!J28+$C51*('A1'!J26-'A1'!J28) -> 0.42862763 | U51: =F51*(1-K51-P51) -> 1273.1462 | V51: =G51*(1-L51-Q51) -> 1526.2761 | W51: =H51*(1-M51-R51) -> 1850.1907 | X51: =I51*(1-N51-S51) -> 2096.1589 | Y51: =J51*(1-O51-T51) -> 2349.9259 | Z51: =F51*('A1'!F35+$C51*('A1'!F33-'A1'!F35)) -> 362.56226 | AA51: =G51*('A1'!G35+$C51*('A1'!G33-'A1'!G35)) -> 408.27609 | AB51: =H51*('A1'!H35+$C51*('A1'!H33-'A1'!H35)) -> 436.03009 | AC51: =I51*('A1'!I35+$C51*('A1'!I33-'A1'!I35)) -> 456.02565 | AD51: =J51*('A1'!J35+$C51*('A1'!J33-'A1'!J35)) -> 476.2727 | AE51: =F51*('A1'!F43+$C51*('A1'!F41-'A1'!F43)) -> 629.14322 | AF51: =G51*('A1'!G43+$C51*('A1'!G41-'A1'!G43)) -> 695.8454 | AG51: =H51*('A1'!H43+$C51*('A1'!H41-'A1'!H43)) -> 697.31776 | AH51: =I51*('A1'!I43+$C51*('A1'!I41-'A1'!I43)) -> 676.69754 | AI51: =J51*('A1'!J43+$C51*('A1'!J41-'A1'!J43)) -> 687.29308 | AJ51: =(U51-Z51)*DCF!$H$40 -> 220.36131 | AK51: =(V51-AA51)*DCF!$H$40 -> 270.556 | AL51: =(W51-AB51)*DCF!$H$40 -> 342.22686 | AM51: =(X51-AC51)*DCF!$H$40 -> 396.91223 | AN51: =(Y51-AD51)*DCF!$H$40 -> 453.42407 | AO51: =(F51-DCF!$H$7)*DCF!$H$41 -> 315.43085 | AP51: =(G51-F51)*DCF!$H$41 -> 289.11714 | AQ51: =(H51-G51)*DCF!$H$41 -> 280.36163 | AR51: =(I51-H51)*DCF!$H$41 -> 257.91891 | AS51: =(J51-I51)*DCF!$H$41 -> 252.49655 | AT51: =(U51-Z51)*(1-DCF!$H$40)+Z51-AE51-AO51 -> 108.21081 | AU51: =(V51-AA51)*(1-DCF!$H$40)+AA51-AF51-AP51 -> 270.75756 | AV51: =(W51-AB51)*(1-DCF!$H$40)+AB51-AG51-AQ51 -> 530.28443 | AW51: =(X51-AC51)*(1-DCF!$H$40)+AC51-AH51-AR51 -> 764.63017 | AX51: =(Y51-AD51)*(1-DCF!$H$40)+AD51-AI51-AS51 -> 956.71217 | AY51: =0.0925+$E51*(0.1125-0.0925) -> 0.09901593 | AZ51: =10+$E51*(14-10) -> 11.303186 | BA51: =SUMPRODUCT(AT51:AX51,(1+$AY51)^(-{1,2,3,4,5})) -> 1842.9438 | BB51: =Y51*$AZ51 -> 26561.649 | BC51: =BB51*(1+$AY51)^(-5) -> 16566.665 | BD51: =BA51+BC51 -> 18409.609 | BE51: =BD51-(DCF!$J$48-DCF!$J$51) -> 17847.469 | BF51: =BE51/DCF!$J$55 -> 720.2458
A52: 26 | B52: =RAND() -> 0.00061497113 | C52: =IF(B52<0.5,SQRT(0.5*B52),1-SQRT(0.5*(1-B52))) -> 0.017535266 | D52: =RAND() -> 0.54866388 | E52: =IF(D52<0.5,SQRT(0.5*D52),1-SQRT(0.5*(1-D52))) -> 0.52495467 | F52: =DCF!$H$7*(1+('A1'!F14+$C52*('A1'!F12-'A1'!F14))) -> 6019.8665 | G52: =F52*(1+('A1'!G14+$C52*('A1'!G12-'A1'!G14))) -> 6396.8925 | H52: =G52*(1+('A1'!H14+$C52*('A1'!H12-'A1'!H14))) -> 6731.3193 | I52: =H52*(1+('A1'!I14+$C52*('A1'!I12-'A1'!I14))) -> 7078.5085 | J52: =I52*(1+('A1'!J14+$C52*('A1'!J12-'A1'!J14))) -> 7441.1226 | K52: ='A1'!F21+$C52*('A1'!F19-'A1'!F21) -> 0.37903556 | L52: ='A1'!G21+$C52*('A1'!G19-'A1'!G21) -> 0.38368486 | M52: ='A1'!H21+$C52*('A1'!H19-'A1'!H21) -> 0.3785095 | N52: ='A1'!I21+$C52*('A1'!I19-'A1'!I21) -> 0.3735095 | O52: ='A1'!J21+$C52*('A1'!J19-'A1'!J21) -> 0.3685095 | P52: ='A1'!F28+$C52*('A1'!F26-'A1'!F28) -> 0.45956162 | Q52: ='A1'!G28+$C52*('A1'!G26-'A1'!G28) -> 0.46421091 | R52: ='A1'!H28+$C52*('A1'!H26-'A1'!H28) -> 0.46394788 | S52: ='A1'!I28+$C52*('A1'!I26-'A1'!I28) -> 0.46386021 | T52: ='A1'!J28+$C52*('A1'!J26-'A1'!J28) -> 0.46377253 | U52: =F52*(1-K52-P52) -> 971.62343 | V52: =G52*(1-L52-Q52) -> 972.99441 | W52: =H52*(1-M52-R52) -> 1060.4696 | X52: =I52*(1-N52-S52) -> 1151.1799 | Y52: =J52*(1-O52-T52) -> 1248.0099 | Z52: =F52*('A1'!F35+$C52*('A1'!F33-'A1'!F35)) -> 360.66419 | AA52: =G52*('A1'!G35+$C52*('A1'!G33-'A1'!G35)) -> 395.48562 | AB52: =H52*('A1'!H35+$C52*('A1'!H33-'A1'!H35)) -> 402.58077 | AC52: =I52*('A1'!I35+$C52*('A1'!I33-'A1'!I35)) -> 409.06401 | AD52: =J52*('A1'!J35+$C52*('A1'!J33-'A1'!J35)) -> 415.13708 | AE52: =F52*('A1'!F43+$C52*('A1'!F41-'A1'!F43)) -> 660.07411 | AF52: =G52*('A1'!G43+$C52*('A1'!G41-'A1'!G43)) -> 731.71664 | AG52: =H52*('A1'!H43+$C52*('A1'!H41-'A1'!H43)) -> 702.65729 | AH52: =I52*('A1'!I43+$C52*('A1'!I41-'A1'!I43)) -> 668.11398 | AI52: =J52*('A1'!J43+$C52*('A1'!J41-'A1'!J43)) -> 665.13416 | AJ52: =(U52-Z52)*DCF!$H$40 -> 147.85214 | AK52: =(V52-AA52)*DCF!$H$40 -> 139.75713 | AL52: =(W52-AB52)*DCF!$H$40 -> 159.20911 | AM52: =(X52-AC52)*DCF!$H$40 -> 179.59204 | AN52: =(Y52-AD52)*DCF!$H$40 -> 201.55523 | AO52: =(F52-DCF!$H$7)*DCF!$H$41 -> 217.09681 | AP52: =(G52-F52)*DCF!$H$41 -> 125.11132 | AQ52: =(H52-G52)*DCF!$H$41 -> 110.97534 | AR52: =(I52-H52)*DCF!$H$41 -> 115.21035 | AS52: =(J52-I52)*DCF!$H$41 -> 120.32891 | AT52: =(U52-Z52)*(1-DCF!$H$40)+Z52-AE52-AO52 -> -53.399625 | AU52: =(V52-AA52)*(1-DCF!$H$40)+AA52-AF52-AP52 -> -23.590674 | AV52: =(W52-AB52)*(1-DCF!$H$40)+AB52-AG52-AQ52 -> 87.627901 | AW52: =(X52-AC52)*(1-DCF!$H$40)+AC52-AH52-AR52 -> 188.26352 | AX52: =(Y52-AD52)*(1-DCF!$H$40)+AD52-AI52-AS52 -> 260.99164 | AY52: =0.0925+$E52*(0.1125-0.0925) -> 0.10299909 | AZ52: =10+$E52*(14-10) -> 12.099819 | BA52: =SUMPRODUCT(AT52:AX52,(1+$AY52)^(-{1,2,3,4,5})) -> 284.55464 | BB52: =Y52*$AZ52 -> 15100.694 | BC52: =BB52*(1+$AY52)^(-5) -> 9249.5612 | BD52: =BA52+BC52 -> 9534.1159 | BE52: =BD52-(DCF!$J$48-DCF!$J$51) -> 8971.9759 | BF52: =BE52/DCF!$J$55 -> 362.06971
A53: 27 | B53: =RAND() -> 0.25798967 | C53: =IF(B53<0.5,SQRT(0.5*B53),1-SQRT(0.5*(1-B53))) -> 0.35915851 | D53: =RAND() -> 0.63444886 | E53: =IF(D53<0.5,SQRT(0.5*D53),1-SQRT(0.5*(1-D53))) -> 0.5724774 | F53: =DCF!$H$7*(1+('A1'!F14+$C53*('A1'!F12-'A1'!F14))) -> 6221.4995 | G53: =F53*(1+('A1'!G14+$C53*('A1'!G12-'A1'!G14))) -> 6929.9651 | H53: =G53*(1+('A1'!H14+$C53*('A1'!H12-'A1'!H14))) -> 7600.0276 | I53: =H53*(1+('A1'!I14+$C53*('A1'!I12-'A1'!I14))) -> 8225.6943 | J53: =I53*(1+('A1'!J14+$C53*('A1'!J12-'A1'!J14))) -> 8843.782 | K53: ='A1'!F21+$C53*('A1'!F19-'A1'!F21) -> 0.36024628 | L53: ='A1'!G21+$C53*('A1'!G19-'A1'!G21) -> 0.35806311 | M53: ='A1'!H21+$C53*('A1'!H19-'A1'!H21) -> 0.34947153 | N53: ='A1'!I21+$C53*('A1'!I19-'A1'!I21) -> 0.34447153 | O53: ='A1'!J21+$C53*('A1'!J19-'A1'!J21) -> 0.33947153 | P53: ='A1'!F28+$C53*('A1'!F26-'A1'!F28) -> 0.45102104 | Q53: ='A1'!G28+$C53*('A1'!G26-'A1'!G28) -> 0.44883787 | R53: ='A1'!H28+$C53*('A1'!H26-'A1'!H28) -> 0.44345049 | S53: ='A1'!I28+$C53*('A1'!I26-'A1'!I28) -> 0.4416547 | T53: ='A1'!J28+$C53*('A1'!J26-'A1'!J28) -> 0.4398589 | U53: =F53*(1-K53-P53) -> 1174.2003 | V53: =G53*(1-L53-Q53) -> 1338.1695 | W53: =H53*(1-M53-R53) -> 1573.7984 | X53: =I53*(1-N53-S53) -> 1759.2603 | Y53: =J53*(1-O53-T53) -> 1951.5536 | Z53: =F53*('A1'!F35+$C53*('A1'!F33-'A1'!F35)) -> 362.11745 | AA53: =G53*('A1'!G35+$C53*('A1'!G33-'A1'!G35)) -> 404.76828 | AB53: =H53*('A1'!H35+$C53*('A1'!H33-'A1'!H35)) -> 425.9759 | AC53: =I53*('A1'!I35+$C53*('A1'!I33-'A1'!I35)) -> 441.63833 | AD53: =J53*('A1'!J35+$C53*('A1'!J33-'A1'!J35)) -> 457.13596 | AE53: =F53*('A1'!F43+$C53*('A1'!F41-'A1'!F43)) -> 639.67485 | AF53: =G53*('A1'!G43+$C53*('A1'!G41-'A1'!G43)) -> 709.83253 | AG53: =H53*('A1'!H43+$C53*('A1'!H41-'A1'!H43)) -> 702.46639 | AH53: =I53*('A1'!I43+$C53*('A1'!I41-'A1'!I43)) -> 678.03948 | AI53: =J53*('A1'!J43+$C53*('A1'!J41-'A1'!J43)) -> 684.7692 | AJ53: =(U53-Z53)*DCF!$H$40 -> 196.52404 | AK53: =(V53-AA53)*DCF!$H$40 -> 225.88309 | AL53: =(W53-AB53)*DCF!$H$40 -> 277.77305 | AM53: =(X53-AC53)*DCF!$H$40 -> 318.86452 | AN53: =(Y53-AD53)*DCF!$H$40 -> 361.64906 | AO53: =(F53-DCF!$H$7)*DCF!$H$41 -> 284.00618 | AP53: =(G53-F53)*DCF!$H$41 -> 235.09539 | AQ53: =(H53-G53)*DCF!$H$41 -> 222.3518 | AR53: =(I53-H53)*DCF!$H$41 -> 207.61961 | AS53: =(J53-I53)*DCF!$H$41 -> 205.10461 | AT53: =(U53-Z53)*(1-DCF!$H$40)+Z53-AE53-AO53 -> 53.995197 | AU53: =(V53-AA53)*(1-DCF!$H$40)+AA53-AF53-AP53 -> 167.35847 | AV53: =(W53-AB53)*(1-DCF!$H$40)+AB53-AG53-AQ53 -> 371.20716 | AW53: =(X53-AC53)*(1-DCF!$H$40)+AC53-AH53-AR53 -> 554.73671 | AX53: =(Y53-AD53)*(1-DCF!$H$40)+AD53-AI53-AS53 -> 700.0307 | AY53: =0.0925+$E53*(0.1125-0.0925) -> 0.10394955 | AZ53: =10+$E53*(14-10) -> 12.28991 | BA53: =SUMPRODUCT(AT53:AX53,(1+$AY53)^(-{1,2,3,4,5})) -> 1262.5901 | BB53: =Y53*$AZ53 -> 23984.417 | BC53: =BB53*(1+$AY53)^(-5) -> 14627.935 | BD53: =BA53+BC53 -> 15890.526 | BE53: =BD53-(DCF!$J$48-DCF!$J$51) -> 15328.386 | BF53: =BE53/DCF!$J$55 -> 618.5866
A54: 28 | B54: =RAND() -> 0.65094458 | C54: =IF(B54<0.5,SQRT(0.5*B54),1-SQRT(0.5*(1-B54))) -> 0.58223486 | D54: =RAND() -> 0.85985128 | E54: =IF(D54<0.5,SQRT(0.5*D54),1-SQRT(0.5*(1-D54))) -> 0.73528438 | F54: =DCF!$H$7*(1+('A1'!F14+$C54*('A1'!F12-'A1'!F14))) -> 6353.1637 | G54: =F54*(1+('A1'!G14+$C54*('A1'!G12-'A1'!G14))) -> 7289.2085 | H54: =G54*(1+('A1'!H14+$C54*('A1'!H12-'A1'!H14))) -> 8205.393 | I54: =H54*(1+('A1'!I14+$C54*('A1'!I12-'A1'!I14))) -> 9045.6346 | J54: =I54*(1+('A1'!J14+$C54*('A1'!J12-'A1'!J14))) -> 9866.5842 | K54: ='A1'!F21+$C54*('A1'!F19-'A1'!F21) -> 0.34797708 | L54: ='A1'!G21+$C54*('A1'!G19-'A1'!G21) -> 0.34133239 | M54: ='A1'!H21+$C54*('A1'!H19-'A1'!H21) -> 0.33051004 | N54: ='A1'!I21+$C54*('A1'!I19-'A1'!I21) -> 0.32551004 | O54: ='A1'!J21+$C54*('A1'!J19-'A1'!J21) -> 0.32051004 | P54: ='A1'!F28+$C54*('A1'!F26-'A1'!F28) -> 0.44544413 | Q54: ='A1'!G28+$C54*('A1'!G26-'A1'!G28) -> 0.43879943 | R54: ='A1'!H28+$C54*('A1'!H26-'A1'!H28) -> 0.43006591 | S54: ='A1'!I28+$C54*('A1'!I26-'A1'!I28) -> 0.42715473 | T54: ='A1'!J28+$C54*('A1'!J26-'A1'!J28) -> 0.42424356 | U54: =F54*(1-K54-P54) -> 1312.4289 | V54: =G54*(1-L54-Q54) -> 1602.665 | W54: =H54*(1-M54-R54) -> 1964.5685 | X54: =I54*(1-N54-S54) -> 2237.3041 | Y54: =J54*(1-O54-T54) -> 2518.4101 | Z54: =F54*('A1'!F35+$C54*('A1'!F33-'A1'!F35)) -> 362.69465 | AA54: =G54*('A1'!G35+$C54*('A1'!G33-'A1'!G35)) -> 409.49062 | AB54: =H54*('A1'!H35+$C54*('A1'!H33-'A1'!H35)) -> 439.77146 | AC54: =I54*('A1'!I35+$C54*('A1'!I33-'A1'!I35)) -> 461.4466 | AD54: =J54*('A1'!J35+$C54*('A1'!J33-'A1'!J35)) -> 483.59268 | AE54: =F54*('A1'!F43+$C54*('A1'!F41-'A1'!F43)) -> 624.86734 | AF54: =G54*('A1'!G43+$C54*('A1'!G41-'A1'!G43)) -> 689.71788 | AG54: =H54*('A1'!H43+$C54*('A1'!H41-'A1'!H43)) -> 694.35496 | AH54: =I54*('A1'!I43+$C54*('A1'!I41-'A1'!I43)) -> 675.00135 | AI54: =J54*('A1'!J43+$C54*('A1'!J41-'A1'!J43)) -> 686.92915 | AJ54: =(U54-Z54)*DCF!$H$40 -> 229.83568 | AK54: =(V54-AA54)*DCF!$H$40 -> 288.74821 | AL54: =(W54-AB54)*DCF!$H$40 -> 369.00088 | AM54: =(X54-AC54)*DCF!$H$40 -> 429.75752 | AN54: =(Y54-AD54)*DCF!$H$40 -> 492.42582 | AO54: =(F54-DCF!$H$7)*DCF!$H$41 -> 327.69729 | AP54: =(G54-F54)*DCF!$H$41 -> 310.61468 | AQ54: =(H54-G54)*DCF!$H$41 -> 304.02428 | AR54: =(I54-H54)*DCF!$H$41 -> 278.82358 | AS54: =(J54-I54)*DCF!$H$41 -> 272.42178 | AT54: =(U54-Z54)*(1-DCF!$H$40)+Z54-AE54-AO54 -> 130.02856 | AU54: =(V54-AA54)*(1-DCF!$H$40)+AA54-AF54-AP54 -> 313.58426 | AV54: =(W54-AB54)*(1-DCF!$H$40)+AB54-AG54-AQ54 -> 597.18835 | AW54: =(X54-AC54)*(1-DCF!$H$40)+AC54-AH54-AR54 -> 853.72166 | AX54: =(Y54-AD54)*(1-DCF!$H$40)+AD54-AI54-AS54 -> 1066.6334 | AY54: =0.0925+$E54*(0.1125-0.0925) -> 0.10720569 | AZ54: =10+$E54*(14-10) -> 12.941138 | BA54: =SUMPRODUCT(AT54:AX54,(1+$AY54)^(-{1,2,3,4,5})) -> 2022.3048 | BB54: =Y54*$AZ54 -> 32591.092 | BC54: =BB54*(1+$AY54)^(-5) -> 19586.524 | BD54: =BA54+BC54 -> 21608.829 | BE54: =BD54-(DCF!$J$48-DCF!$J$51) -> 21046.689 | BF54: =BE54/DCF!$J$55 -> 849.35231
A55: 29 | B55: =RAND() -> 0.91112366 | C55: =IF(B55<0.5,SQRT(0.5*B55),1-SQRT(0.5*(1-B55))) -> 0.78919637 | D55: =RAND() -> 0.48645299 | E55: =IF(D55<0.5,SQRT(0.5*D55),1-SQRT(0.5*(1-D55))) -> 0.49317998 | F55: =DCF!$H$7*(1+('A1'!F14+$C55*('A1'!F12-'A1'!F14))) -> 6475.3166 | G55: =F55*(1+('A1'!G14+$C55*('A1'!G12-'A1'!G14))) -> 7630.38 | H55: =G55*(1+('A1'!H14+$C55*('A1'!H12-'A1'!H14))) -> 8794.7419 | I55: =H55*(1+('A1'!I14+$C55*('A1'!I12-'A1'!I14))) -> 9859.1491 | J55: =I55*(1+('A1'!J14+$C55*('A1'!J12-'A1'!J14))) -> 10896.763 | K55: ='A1'!F21+$C55*('A1'!F19-'A1'!F21) -> 0.3365942 | L55: ='A1'!G21+$C55*('A1'!G19-'A1'!G21) -> 0.32581027 | M55: ='A1'!H21+$C55*('A1'!H19-'A1'!H21) -> 0.31291831 | N55: ='A1'!I21+$C55*('A1'!I19-'A1'!I21) -> 0.30791831 | O55: ='A1'!J21+$C55*('A1'!J19-'A1'!J21) -> 0.30291831 | P55: ='A1'!F28+$C55*('A1'!F26-'A1'!F28) -> 0.44027009 | Q55: ='A1'!G28+$C55*('A1'!G26-'A1'!G28) -> 0.42948616 | R55: ='A1'!H28+$C55*('A1'!H26-'A1'!H28) -> 0.41764822 | S55: ='A1'!I28+$C55*('A1'!I26-'A1'!I28) -> 0.41370224 | T55: ='A1'!J28+$C55*('A1'!J26-'A1'!J28) -> 0.40975625 | U55: =F55*(1-K55-P55) -> 1444.8744 | V55: =G55*(1-L55-Q55) -> 1867.1812 | W55: =H55*(1-M55-R55) -> 2369.5979 | X55: =I55*(1-N55-S55) -> 2744.5845 | Y55: =J55*(1-O55-T55) -> 3130.9171 | Z55: =F55*('A1'!F35+$C55*('A1'!F33-'A1'!F35)) -> 362.96751 | AA55: =G55*('A1'!G35+$C55*('A1'!G33-'A1'!G35)) -> 412.86488 | AB55: =H55*('A1'!H35+$C55*('A1'!H33-'A1'!H35)) -> 451.33595 | AC55: =I55*('A1'!I35+$C55*('A1'!I33-'A1'!I35)) -> 478.46099 | AD55: =J55*('A1'!J35+$C55*('A1'!J33-'A1'!J35)) -> 507.02249 | AE55: =F55*('A1'!F43+$C55*('A1'!F41-'A1'!F43)) -> 610.0789 | AF55: =G55*('A1'!G43+$C55*('A1'!G41-'A1'!G43)) -> 666.72832 | AG55: =H55*('A1'!H43+$C55*('A1'!H41-'A1'!H43)) -> 680.52066 | AH55: =I55*('A1'!I43+$C55*('A1'!I41-'A1'!I43)) -> 664.291 | AI55: =J55*('A1'!J43+$C55*('A1'!J41-'A1'!J43)) -> 679.71966 | AJ55: =(U55-Z55)*DCF!$H$40 -> 261.82146 | AK55: =(V55-AA55)*DCF!$H$40 -> 351.94455 | AL55: =(W55-AB55)*DCF!$H$40 -> 464.21938 | AM55: =(X55-AC55)*DCF!$H$40 -> 548.4019 | AN55: =(Y55-AD55)*DCF!$H$40 -> 634.98251 | AO55: =(F55-DCF!$H$7)*DCF!$H$41 -> 368.23219 | AP55: =(G55-F55)*DCF!$H$41 -> 383.29324 | AQ55: =(H55-G55)*DCF!$H$41 -> 386.37881 | AR55: =(I55-H55)*DCF!$H$41 -> 353.2101 | AS55: =(J55-I55)*DCF!$H$41 -> 344.31905 | AT55: =(U55-Z55)*(1-DCF!$H$40)+Z55-AE55-AO55 -> 204.74182 | AU55: =(V55-AA55)*(1-DCF!$H$40)+AA55-AF55-AP55 -> 465.21508 | AV55: =(W55-AB55)*(1-DCF!$H$40)+AB55-AG55-AQ55 -> 838.47901 | AW55: =(X55-AC55)*(1-DCF!$H$40)+AC55-AH55-AR55 -> 1178.6815 | AX55: =(Y55-AD55)*(1-DCF!$H$40)+AD55-AI55-AS55 -> 1471.8959 | AY55: =0.0925+$E55*(0.1125-0.0925) -> 0.1023636 | AZ55: =10+$E55*(14-10) -> 11.97272 | BA55: =SUMPRODUCT(AT55:AX55,(1+$AY55)^(-{1,2,3,4,5})) -> 2896.825 | BB55: =Y55*$AZ55 -> 37485.594 | BC55: =BB55*(1+$AY55)^(-5) -> 23027.144 | BD55: =BA55+BC55 -> 25923.969 | BE55: =BD55-(DCF!$J$48-DCF!$J$51) -> 25361.829 | BF55: =BE55/DCF!$J$55 -> 1023.4925
A56: 30 | B56: =RAND() -> 0.64779674 | C56: =IF(B56<0.5,SQRT(0.5*B56),1-SQRT(0.5*(1-B56))) -> 0.58035535 | D56: =RAND() -> 0.96757681 | E56: =IF(D56<0.5,SQRT(0.5*D56),1-SQRT(0.5*(1-D56))) -> 0.87267524 | F56: =DCF!$H$7*(1+('A1'!F14+$C56*('A1'!F12-'A1'!F14))) -> 6352.0544 | G56: =F56*(1+('A1'!G14+$C56*('A1'!G12-'A1'!G14))) -> 7286.1449 | H56: =G56*(1+('A1'!H14+$C56*('A1'!H12-'A1'!H14))) -> 8200.1641 | I56: =H56*(1+('A1'!I14+$C56*('A1'!I12-'A1'!I14))) -> 9038.4831 | J56: =I56*(1+('A1'!J14+$C56*('A1'!J12-'A1'!J14))) -> 9857.5945 | K56: ='A1'!F21+$C56*('A1'!F19-'A1'!F21) -> 0.34808046 | L56: ='A1'!G21+$C56*('A1'!G19-'A1'!G21) -> 0.34147335 | M56: ='A1'!H21+$C56*('A1'!H19-'A1'!H21) -> 0.33066979 | N56: ='A1'!I21+$C56*('A1'!I19-'A1'!I21) -> 0.32566979 | O56: ='A1'!J21+$C56*('A1'!J19-'A1'!J21) -> 0.32066979 | P56: ='A1'!F28+$C56*('A1'!F26-'A1'!F28) -> 0.44549112 | Q56: ='A1'!G28+$C56*('A1'!G26-'A1'!G28) -> 0.43888401 | R56: ='A1'!H28+$C56*('A1'!H26-'A1'!H28) -> 0.43017868 | S56: ='A1'!I28+$C56*('A1'!I26-'A1'!I28) -> 0.4272769 | T56: ='A1'!J28+$C56*('A1'!J26-'A1'!J28) -> 0.42437513 | U56: =F56*(1-K56-P56) -> 1311.2446 | V56: =G56*(1-L56-Q56) -> 1600.3481 | W56: =H56*(1-M56-R56) -> 1961.0818 | X56: =I56*(1-N56-S56) -> 2232.9871 | Y56: =J56*(1-O56-T56) -> 2513.2438 | Z56: =F56*('A1'!F35+$C56*('A1'!F33-'A1'!F35)) -> 362.69102 | AA56: =G56*('A1'!G35+$C56*('A1'!G33-'A1'!G35)) -> 409.45545 | AB56: =H56*('A1'!H35+$C56*('A1'!H33-'A1'!H35)) -> 439.66075 | AC56: =I56*('A1'!I35+$C56*('A1'!I33-'A1'!I35)) -> 461.28564 | AD56: =J56*('A1'!J35+$C56*('A1'!J33-'A1'!J35)) -> 483.3744 | AE56: =F56*('A1'!F43+$C56*('A1'!F41-'A1'!F43)) -> 624.99701 | AF56: =G56*('A1'!G43+$C56*('A1'!G41-'A1'!G43)) -> 689.90731 | AG56: =H56*('A1'!H43+$C56*('A1'!H41-'A1'!H43)) -> 694.45191 | AH56: =I56*('A1'!I43+$C56*('A1'!I41-'A1'!I43)) -> 675.06228 | AI56: =J56*('A1'!J43+$C56*('A1'!J41-'A1'!J43)) -> 686.95174 | AJ56: =(U56-Z56)*DCF!$H$40 -> 229.54997 | AK56: =(V56-AA56)*DCF!$H$40 -> 288.19603 | AL56: =(W56-AB56)*DCF!$H$40 -> 368.18389 | AM56: =(X56-AC56)*DCF!$H$40 -> 428.75176 | AN56: =(Y56-AD56)*DCF!$H$40 -> 491.2284 | AO56: =(F56-DCF!$H$7)*DCF!$H$41 -> 327.32917 | AP56: =(G56-F56)*DCF!$H$41 -> 309.96618 | AQ56: =(H56-G56)*DCF!$H$41 -> 303.30574 | AR56: =(I56-H56)*DCF!$H$41 -> 278.1856 | AS56: =(J56-I56)*DCF!$H$41 -> 271.81179 | AT56: =(U56-Z56)*(1-DCF!$H$40)+Z56-AE56-AO56 -> 129.36845 | AU56: =(V56-AA56)*(1-DCF!$H$40)+AA56-AF56-AP56 -> 312.27861 | AV56: =(W56-AB56)*(1-DCF!$H$40)+AB56-AG56-AQ56 -> 595.14023 | AW56: =(X56-AC56)*(1-DCF!$H$40)+AC56-AH56-AR56 -> 850.98748 | AX56: =(Y56-AD56)*(1-DCF!$H$40)+AD56-AI56-AS56 -> 1063.2519 | AY56: =0.0925+$E56*(0.1125-0.0925) -> 0.1099535 | AZ56: =10+$E56*(14-10) -> 13.490701 | BA56: =SUMPRODUCT(AT56:AX56,(1+$AY56)^(-{1,2,3,4,5})) -> 1997.0288 | BB56: =Y56*$AZ56 -> 33905.421 | BC56: =BB56*(1+$AY56)^(-5) -> 20125.432 | BD56: =BA56+BC56 -> 22122.46 | BE56: =BD56-(DCF!$J$48-DCF!$J$51) -> 21560.32 | BF56: =BE56/DCF!$J$55 -> 870.08024
A57: 31 | B57: =RAND() -> 0.70175872 | C57: =IF(B57<0.5,SQRT(0.5*B57),1-SQRT(0.5*(1-B57))) -> 0.61383858 | D57: =RAND() -> 0.67981334 | E57: =IF(D57<0.5,SQRT(0.5*D57),1-SQRT(0.5*(1-D57))) -> 0.59988335 | F57: =DCF!$H$7*(1+('A1'!F14+$C57*('A1'!F12-'A1'!F14))) -> 6371.8169 | G57: =F57*(1+('A1'!G14+$C57*('A1'!G12-'A1'!G14))) -> 7340.8159 | H57: =G57*(1+('A1'!H14+$C57*('A1'!H12-'A1'!H14))) -> 8293.6466 | I57: =H57*(1+('A1'!I14+$C57*('A1'!I12-'A1'!I14))) -> 9166.5153 | J57: =I57*(1+('A1'!J14+$C57*('A1'!J12-'A1'!J14))) -> 10018.714 | K57: ='A1'!F21+$C57*('A1'!F19-'A1'!F21) -> 0.34623888 | L57: ='A1'!G21+$C57*('A1'!G19-'A1'!G21) -> 0.33896211 | M57: ='A1'!H21+$C57*('A1'!H19-'A1'!H21) -> 0.32782372 | N57: ='A1'!I21+$C57*('A1'!I19-'A1'!I21) -> 0.32282372 | O57: ='A1'!J21+$C57*('A1'!J19-'A1'!J21) -> 0.31782372 | P57: ='A1'!F28+$C57*('A1'!F26-'A1'!F28) -> 0.44465404 | Q57: ='A1'!G28+$C57*('A1'!G26-'A1'!G28) -> 0.43737726 | R57: ='A1'!H28+$C57*('A1'!H26-'A1'!H28) -> 0.42816969 | S57: ='A1'!I28+$C57*('A1'!I26-'A1'!I28) -> 0.42510049 | T57: ='A1'!J28+$C57*('A1'!J26-'A1'!J28) -> 0.4220313 | U57: =F57*(1-K57-P57) -> 1332.3921 | V57: =G57*(1-L57-Q57) -> 1641.8515 | W57: =H57*(1-M57-R57) -> 2023.7045 | X57: =I57*(1-N57-S57) -> 2310.6566 | Y57: =J57*(1-O57-T57) -> 2606.3183 | Z57: =F57*('A1'!F35+$C57*('A1'!F33-'A1'!F35)) -> 362.75268 | AA57: =G57*('A1'!G35+$C57*('A1'!G33-'A1'!G35)) -> 410.06983 | AB57: =H57*('A1'!H35+$C57*('A1'!H33-'A1'!H35)) -> 441.61823 | AC57: =I57*('A1'!I35+$C57*('A1'!I33-'A1'!I35)) -> 464.13676 | AD57: =J57*('A1'!J35+$C57*('A1'!J33-'A1'!J35)) -> 487.24952 | AE57: =F57*('A1'!F43+$C57*('A1'!F41-'A1'!F43)) -> 622.67451 | AF57: =G57*('A1'!G43+$C57*('A1'!G41-'A1'!G43)) -> 686.48117 | AG57: =H57*('A1'!H43+$C57*('A1'!H41-'A1'!H43)) -> 692.64928 | AH57: =I57*('A1'!I43+$C57*('A1'!I41-'A1'!I43)) -> 673.88233 | AI57: =J57*('A1'!J43+$C57*('A1'!J41-'A1'!J43)) -> 686.43872 | AJ57: =(U57-Z57)*DCF!$H$40 -> 234.65273 | AK57: =(V57-AA57)*DCF!$H$40 -> 298.09117 | AL57: =(W57-AB57)*DCF!$H$40 -> 382.86487 | AM57: =(X57-AC57)*DCF!$H$40 -> 446.85779 | AN57: =(Y57-AD57)*DCF!$H$40 -> 512.81463 | AO57: =(F57-DCF!$H$7)*DCF!$H$41 -> 333.88711 | AP57: =(G57-F57)*DCF!$H$41 -> 321.55013 | AQ57: =(H57-G57)*DCF!$H$41 -> 316.18485 | AR57: =(I57-H57)*DCF!$H$41 -> 289.65049 | AS57: =(J57-I57)*DCF!$H$41 -> 282.7915 | AT57: =(U57-Z57)*(1-DCF!$H$40)+Z57-AE57-AO57 -> 141.17771 | AU57: =(V57-AA57)*(1-DCF!$H$40)+AA57-AF57-AP57 -> 335.72905 | AV57: =(W57-AB57)*(1-DCF!$H$40)+AB57-AG57-AQ57 -> 632.00546 | AW57: =(X57-AC57)*(1-DCF!$H$40)+AC57-AH57-AR57 -> 900.26595 | AX57: =(Y57-AD57)*(1-DCF!$H$40)+AD57-AI57-AS57 -> 1124.2734 | AY57: =0.0925+$E57*(0.1125-0.0925) -> 0.10449767 | AZ57: =10+$E57*(14-10) -> 12.399533 | BA57: =SUMPRODUCT(AT57:AX57,(1+$AY57)^(-{1,2,3,4,5})) -> 2161.0117 | BB57: =Y57*$AZ57 -> 32317.13 | BC57: =BB57*(1+$AY57)^(-5) -> 19661.144 | BD57: =BA57+BC57 -> 21822.155 | BE57: =BD57-(DCF!$J$48-DCF!$J$51) -> 21260.015 | BF57: =BE57/DCF!$J$55 -> 857.96123
A58: 32 | B58: =RAND() -> 0.12691263 | C58: =IF(B58<0.5,SQRT(0.5*B58),1-SQRT(0.5*(1-B58))) -> 0.25190537 | D58: =RAND() -> 0.22207816 | E58: =IF(D58<0.5,SQRT(0.5*D58),1-SQRT(0.5*(1-D58))) -> 0.33322527 | F58: =DCF!$H$7*(1+('A1'!F14+$C58*('A1'!F12-'A1'!F14))) -> 6158.1965 | G58: =F58*(1+('A1'!G14+$C58*('A1'!G12-'A1'!G14))) -> 6760.3807 | H58: =G58*(1+('A1'!H14+$C58*('A1'!H12-'A1'!H14))) -> 7319.7866 | I58: =H58*(1+('A1'!I14+$C58*('A1'!I12-'A1'!I14))) -> 7851.7264 | J58: =I58*(1+('A1'!J14+$C58*('A1'!J12-'A1'!J14))) -> 8382.7652 | K58: ='A1'!F21+$C58*('A1'!F19-'A1'!F21) -> 0.3661452 | L58: ='A1'!G21+$C58*('A1'!G19-'A1'!G21) -> 0.3661071 | M58: ='A1'!H21+$C58*('A1'!H19-'A1'!H21) -> 0.35858804 | N58: ='A1'!I21+$C58*('A1'!I19-'A1'!I21) -> 0.35358804 | O58: ='A1'!J21+$C58*('A1'!J19-'A1'!J21) -> 0.34858804 | P58: ='A1'!F28+$C58*('A1'!F26-'A1'!F28) -> 0.45370237 | Q58: ='A1'!G28+$C58*('A1'!G26-'A1'!G28) -> 0.45366426 | R58: ='A1'!H28+$C58*('A1'!H26-'A1'!H28) -> 0.44988568 | S58: ='A1'!I28+$C58*('A1'!I26-'A1'!I28) -> 0.44862615 | T58: ='A1'!J28+$C58*('A1'!J26-'A1'!J28) -> 0.44736662 | U58: =F58*(1-K58-P58) -> 1109.4141 | V58: =G58*(1-L58-Q58) -> 1218.4143 | W58: =H58*(1-M58-R58) -> 1401.9315 | X58: =I58*(1-N58-S58) -> 1552.96 | Y58: =J58*(1-O58-T58) -> 1710.4641 | Z58: =F58*('A1'!F35+$C58*('A1'!F33-'A1'!F35)) -> 361.73538 | AA58: =G58*('A1'!G35+$C58*('A1'!G33-'A1'!G35)) -> 402.11384 | AB58: =H58*('A1'!H35+$C58*('A1'!H33-'A1'!H35)) -> 418.90437 | AC58: =I58*('A1'!I35+$C58*('A1'!I33-'A1'!I35)) -> 431.66543 | AD58: =J58*('A1'!J35+$C58*('A1'!J33-'A1'!J35)) -> 444.09489 | AE58: =F58*('A1'!F43+$C58*('A1'!F41-'A1'!F43)) -> 646.37596 | AF58: =G58*('A1'!G43+$C58*('A1'!G41-'A1'!G43)) -> 717.83961 | AG58: =H58*('A1'!H43+$C58*('A1'!H41-'A1'!H43)) -> 704.04132 | AH58: =I58*('A1'!I43+$C58*('A1'!I41-'A1'!I43)) -> 676.68779 | AI58: =J58*('A1'!J43+$C58*('A1'!J41-'A1'!J43)) -> 680.54064 | AJ58: =(U58-Z58)*DCF!$H$40 -> 180.93824 | AK58: =(V58-AA58)*DCF!$H$40 -> 197.5447 | AL58: =(W58-AB58)*DCF!$H$40 -> 237.89257 | AM58: =(X58-AC58)*DCF!$H$40 -> 271.35329 | AN58: =(Y58-AD58)*DCF!$H$40 -> 306.46135 | AO58: =(F58-DCF!$H$7)*DCF!$H$41 -> 262.99988 | AP58: =(G58-F58)*DCF!$H$41 -> 199.82724 | AQ58: =(H58-G58)*DCF!$H$41 -> 185.63181 | AR58: =(I58-H58)*DCF!$H$41 -> 176.5175 | AS58: =(J58-I58)*DCF!$H$41 -> 176.21852 | AT58: =(U58-Z58)*(1-DCF!$H$40)+Z58-AE58-AO58 -> 19.09998 | AU58: =(V58-AA58)*(1-DCF!$H$40)+AA58-AF58-AP58 -> 103.2027 | AV58: =(W58-AB58)*(1-DCF!$H$40)+AB58-AG58-AQ58 -> 274.3658 | AW58: =(X58-AC58)*(1-DCF!$H$40)+AC58-AH58-AR58 -> 428.40145 | AX58: =(Y58-AD58)*(1-DCF!$H$40)+AD58-AI58-AS58 -> 547.2436 | AY58: =0.0925+$E58*(0.1125-0.0925) -> 0.099164505 | AZ58: =10+$E58*(14-10) -> 11.332901 | BA58: =SUMPRODUCT(AT58:AX58,(1+$AY58)^(-{1,2,3,4,5})) -> 943.98675 | BB58: =Y58*$AZ58 -> 19384.52 | BC58: =BB58*(1+$AY58)^(-5) -> 12082.077 | BD58: =BA58+BC58 -> 13026.063 | BE58: =BD58-(DCF!$J$48-DCF!$J$51) -> 12463.923 | BF58: =BE58/DCF!$J$55 -> 502.98944
A59: 33 | B59: =RAND() -> 0.91248693 | C59: =IF(B59<0.5,SQRT(0.5*B59),1-SQRT(0.5*(1-B59))) -> 0.79081937 | D59: =RAND() -> 0.46809327 | E59: =IF(D59<0.5,SQRT(0.5*D59),1-SQRT(0.5*(1-D59))) -> 0.48378366 | F59: =DCF!$H$7*(1+('A1'!F14+$C59*('A1'!F12-'A1'!F14))) -> 6476.2745 | G59: =F59*(1+('A1'!G14+$C59*('A1'!G12-'A1'!G14))) -> 7633.0855 | H59: =G59*(1+('A1'!H14+$C59*('A1'!H12-'A1'!H14))) -> 8799.4707 | I59: =H59*(1+('A1'!I14+$C59*('A1'!I12-'A1'!I14))) -> 9865.7355 | J59: =I59*(1+('A1'!J14+$C59*('A1'!J12-'A1'!J14))) -> 10905.163 | K59: ='A1'!F21+$C59*('A1'!F19-'A1'!F21) -> 0.33650493 | L59: ='A1'!G21+$C59*('A1'!G19-'A1'!G21) -> 0.32568855 | M59: ='A1'!H21+$C59*('A1'!H19-'A1'!H21) -> 0.31278035 | N59: ='A1'!I21+$C59*('A1'!I19-'A1'!I21) -> 0.30778035 | O59: ='A1'!J21+$C59*('A1'!J19-'A1'!J21) -> 0.30278035 | P59: ='A1'!F28+$C59*('A1'!F26-'A1'!F28) -> 0.44022952 | Q59: ='A1'!G28+$C59*('A1'!G26-'A1'!G28) -> 0.42941313 | R59: ='A1'!H28+$C59*('A1'!H26-'A1'!H28) -> 0.41755084 | S59: ='A1'!I28+$C59*('A1'!I26-'A1'!I28) -> 0.41359674 | T59: ='A1'!J28+$C59*('A1'!J26-'A1'!J28) -> 0.40964264 | U59: =F59*(1-K59-P59) -> 1445.929 | V59: =G59*(1-L59-Q59) -> 1869.3299 | W59: =H59*(1-M59-R59) -> 2372.9428 | X59: =I59*(1-N59-S59) -> 2748.8199 | Y59: =J59*(1-O59-T59) -> 3136.0742 | Z59: =F59*('A1'!F35+$C59*('A1'!F33-'A1'!F35)) -> 362.96865 | AA59: =G59*('A1'!G35+$C59*('A1'!G33-'A1'!G35)) -> 412.88738 | AB59: =H59*('A1'!H35+$C59*('A1'!H33-'A1'!H35)) -> 451.42153 | AC59: =I59*('A1'!I35+$C59*('A1'!I33-'A1'!I35)) -> 478.58848 | AD59: =J59*('A1'!J35+$C59*('A1'!J33-'A1'!J35)) -> 507.20097 | AE59: =F59*('A1'!F43+$C59*('A1'!F41-'A1'!F43)) -> 609.95893 | AF59: =G59*('A1'!G43+$C59*('A1'!G41-'A1'!G43)) -> 666.53112 | AG59: =H59*('A1'!H43+$C59*('A1'!H41-'A1'!H43)) -> 680.38671 | AH59: =I59*('A1'!I43+$C59*('A1'!I41-'A1'!I43)) -> 664.17436 | AI59: =J59*('A1'!J43+$C59*('A1'!J41-'A1'!J43)) -> 679.6242 | AJ59: =(U59-Z59)*DCF!$H$40 -> 262.0764 | AK59: =(V59-AA59)*DCF!$H$40 -> 352.45908 | AL59: =(W59-AB59)*DCF!$H$40 -> 465.00814 | AM59: =(X59-AC59)*DCF!$H$40 -> 549.396 | AN59: =(Y59-AD59)*DCF!$H$40 -> 636.18732 | AO59: =(F59-DCF!$H$7)*DCF!$H$41 -> 368.55007 | AP59: =(G59-F59)*DCF!$H$41 -> 383.87314 | AQ59: =(H59-G59)*DCF!$H$41 -> 387.05023 | AR59: =(I59-H59)*DCF!$H$41 -> 353.82654 | AS59: =(J59-I59)*DCF!$H$41 -> 344.92102 | AT59: =(U59-Z59)*(1-DCF!$H$40)+Z59-AE59-AO59 -> 205.34359 | AU59: =(V59-AA59)*(1-DCF!$H$40)+AA59-AF59-AP59 -> 466.46652 | AV59: =(W59-AB59)*(1-DCF!$H$40)+AB59-AG59-AQ59 -> 840.49771 | AW59: =(X59-AC59)*(1-DCF!$H$40)+AC59-AH59-AR59 -> 1181.423 | AX59: =(Y59-AD59)*(1-DCF!$H$40)+AD59-AI59-AS59 -> 1475.3417 | AY59: =0.0925+$E59*(0.1125-0.0925) -> 0.10217567 | AZ59: =10+$E59*(14-10) -> 11.935135 | BA59: =SUMPRODUCT(AT59:AX59,(1+$AY59)^(-{1,2,3,4,5})) -> 2905.6831 | BB59: =Y59*$AZ59 -> 37429.468 | BC59: =BB59*(1+$AY59)^(-5) -> 23012.274 | BD59: =BA59+BC59 -> 25917.958 | BE59: =BD59-(DCF!$J$48-DCF!$J$51) -> 25355.818 | BF59: =BE59/DCF!$J$55 -> 1023.2499
A60: 34 | B60: =RAND() -> 0.2504074 | C60: =IF(B60<0.5,SQRT(0.5*B60),1-SQRT(0.5*(1-B60))) -> 0.35384135 | D60: =RAND() -> 0.55827313 | E60: =IF(D60<0.5,SQRT(0.5*D60),1-SQRT(0.5*(1-D60))) -> 0.5300389 | F60: =DCF!$H$7*(1+('A1'!F14+$C60*('A1'!F12-'A1'!F14))) -> 6218.3612 | G60: =F60*(1+('A1'!G14+$C60*('A1'!G12-'A1'!G14))) -> 6921.5099 | H60: =G60*(1+('A1'!H14+$C60*('A1'!H12-'A1'!H14))) -> 7585.9705 | I60: =H60*(1+('A1'!I14+$C60*('A1'!I12-'A1'!I14))) -> 8206.8497 | J60: =I60*(1+('A1'!J14+$C60*('A1'!J12-'A1'!J14))) -> 8820.4668 | K60: ='A1'!F21+$C60*('A1'!F19-'A1'!F21) -> 0.36053873 | L60: ='A1'!G21+$C60*('A1'!G19-'A1'!G21) -> 0.3584619 | M60: ='A1'!H21+$C60*('A1'!H19-'A1'!H21) -> 0.34992349 | N60: ='A1'!I21+$C60*('A1'!I19-'A1'!I21) -> 0.34492349 | O60: ='A1'!J21+$C60*('A1'!J19-'A1'!J21) -> 0.33992349 | P60: ='A1'!F28+$C60*('A1'!F26-'A1'!F28) -> 0.45115397 | Q60: ='A1'!G28+$C60*('A1'!G26-'A1'!G28) -> 0.44907714 | R60: ='A1'!H28+$C60*('A1'!H26-'A1'!H28) -> 0.44376952 | S60: ='A1'!I28+$C60*('A1'!I26-'A1'!I28) -> 0.44200031 | T60: ='A1'!J28+$C60*('A1'!J26-'A1'!J28) -> 0.44023111 | U60: =F60*(1-K60-P60) -> 1170.9629 | V60: =G60*(1-L60-Q60) -> 1332.1204 | W60: =H60*(1-M60-R60) -> 1565.0388 | X60: =I60*(1-N60-S60) -> 1748.6844 | Y60: =J60*(1-O60-T60) -> 1939.1391 | Z60: =F60*('A1'!F35+$C60*('A1'!F33-'A1'!F35)) -> 362.1001 | AA60: =G60*('A1'!G35+$C60*('A1'!G33-'A1'!G35)) -> 404.64245 | AB60: =H60*('A1'!H35+$C60*('A1'!H33-'A1'!H35)) -> 425.6317 | AC60: =I60*('A1'!I35+$C60*('A1'!I33-'A1'!I35)) -> 441.15021 | AD60: =J60*('A1'!J35+$C60*('A1'!J33-'A1'!J35)) -> 456.49359 | AE60: =F60*('A1'!F43+$C60*('A1'!F41-'A1'!F43)) -> 640.01346 | AF60: =G60*('A1'!G43+$C60*('A1'!G41-'A1'!G43)) -> 710.25456 | AG60: =H60*('A1'!H43+$C60*('A1'!H41-'A1'!H43)) -> 702.57885 | AH60: =I60*('A1'!I43+$C60*('A1'!I41-'A1'!I43)) -> 678.01342 | AI60: =J60*('A1'!J43+$C60*('A1'!J41-'A1'!J43)) -> 684.6054 | AJ60: =(U60-Z60)*DCF!$H$40 -> 195.74479 | AK60: =(V60-AA60)*DCF!$H$40 -> 224.44968 | AL60: =(W60-AB60)*DCF!$H$40 -> 275.73651 | AM60: =(X60-AC60)*DCF!$H$40 -> 316.42327 | AN60: =(Y60-AD60)*DCF!$H$40 -> 358.80022 | AO60: =(F60-DCF!$H$7)*DCF!$H$41 -> 282.96478 | AP60: =(G60-F60)*DCF!$H$41 -> 233.33102 | AQ60: =(H60-G60)*DCF!$H$41 -> 220.49288 | AR60: =(I60-H60)*DCF!$H$41 -> 206.03095 | AS60: =(J60-I60)*DCF!$H$41 -> 203.62109 | AT60: =(U60-Z60)*(1-DCF!$H$40)+Z60-AE60-AO60 -> 52.239829 | AU60: =(V60-AA60)*(1-DCF!$H$40)+AA60-AF60-AP60 -> 164.08519 | AV60: =(W60-AB60)*(1-DCF!$H$40)+AB60-AG60-AQ60 -> 366.23053 | AW60: =(X60-AC60)*(1-DCF!$H$40)+AC60-AH60-AR60 -> 548.21673 | AX60: =(Y60-AD60)*(1-DCF!$H$40)+AD60-AI60-AS60 -> 692.11241 | AY60: =0.0925+$E60*(0.1125-0.0925) -> 0.10310078 | AZ60: =10+$E60*(14-10) -> 12.120156 | BA60: =SUMPRODUCT(AT60:AX60,(1+$AY60)^(-{1,2,3,4,5})) -> 1249.0323 | BB60: =Y60*$AZ60 -> 23502.668 | BC60: =BB60*(1+$AY60)^(-5) -> 14389.351 | BD60: =BA60+BC60 -> 15638.383 | BE60: =BD60-(DCF!$J$48-DCF!$J$51) -> 15076.243 | BF60: =BE60/DCF!$J$55 -> 608.41125
A61: 35 | B61: =RAND() -> 0.71756463 | C61: =IF(B61<0.5,SQRT(0.5*B61),1-SQRT(0.5*(1-B61))) -> 0.62421058 | D61: =RAND() -> 0.82316635 | E61: =IF(D61<0.5,SQRT(0.5*D61),1-SQRT(0.5*(1-D61))) -> 0.70265033 | F61: =DCF!$H$7*(1+('A1'!F14+$C61*('A1'!F12-'A1'!F14))) -> 6377.9386 | G61: =F61*(1+('A1'!G14+$C61*('A1'!G12-'A1'!G14))) -> 7357.7915 | H61: =G61*(1+('A1'!H14+$C61*('A1'!H12-'A1'!H14))) -> 8322.7465 | I61: =H61*(1+('A1'!I14+$C61*('A1'!I12-'A1'!I14))) -> 9206.447 | J61: =I61*(1+('A1'!J14+$C61*('A1'!J12-'A1'!J14))) -> 10069.043 | K61: ='A1'!F21+$C61*('A1'!F19-'A1'!F21) -> 0.34566842 | L61: ='A1'!G21+$C61*('A1'!G19-'A1'!G21) -> 0.33818421 | M61: ='A1'!H21+$C61*('A1'!H19-'A1'!H21) -> 0.3269421 | N61: ='A1'!I21+$C61*('A1'!I19-'A1'!I21) -> 0.3219421 | O61: ='A1'!J21+$C61*('A1'!J19-'A1'!J21) -> 0.3169421 | P61: ='A1'!F28+$C61*('A1'!F26-'A1'!F28) -> 0.44439474 | Q61: ='A1'!G28+$C61*('A1'!G26-'A1'!G28) -> 0.43691052 | R61: ='A1'!H28+$C61*('A1'!H26-'A1'!H28) -> 0.42754737 | S61: ='A1'!I28+$C61*('A1'!I26-'A1'!I28) -> 0.42442631 | T61: ='A1'!J28+$C61*('A1'!J26-'A1'!J28) -> 0.42130526 | U61: =F61*(1-K61-P61) -> 1338.9643 | V61: =G61*(1-L61-Q61) -> 1654.8061 | W61: =H61*(1-M61-R61) -> 2043.3219 | X61: =I61*(1-N61-S61) -> 2335.0458 | Y61: =J61*(1-O61-T61) -> 2635.5985 | Z61: =F61*('A1'!F35+$C61*('A1'!F33-'A1'!F35)) -> 362.77043 | AA61: =G61*('A1'!G35+$C61*('A1'!G33-'A1'!G35)) -> 410.25496 | AB61: =H61*('A1'!H35+$C61*('A1'!H33-'A1'!H35)) -> 442.21818 | AC61: =I61*('A1'!I35+$C61*('A1'!I33-'A1'!I35)) -> 465.01279 | AD61: =J61*('A1'!J35+$C61*('A1'!J33-'A1'!J35)) -> 488.44395 | AE61: =F61*('A1'!F43+$C61*('A1'!F41-'A1'!F43)) -> 621.94971 | AF61: =G61*('A1'!G43+$C61*('A1'!G41-'A1'!G43)) -> 685.39762 | AG61: =H61*('A1'!H43+$C61*('A1'!H41-'A1'!H43)) -> 692.05826 | AH61: =I61*('A1'!I43+$C61*('A1'!I41-'A1'!I43)) -> 673.47581 | AI61: =J61*('A1'!J43+$C61*('A1'!J41-'A1'!J43)) -> 686.23174 | AJ61: =(U61-Z61)*DCF!$H$40 -> 236.23892 | AK61: =(V61-AA61)*DCF!$H$40 -> 301.18137 | AL61: =(W61-AB61)*DCF!$H$40 -> 387.46711 | AM61: =(X61-AC61)*DCF!$H$40 -> 452.54798 | AN61: =(Y61-AD61)*DCF!$H$40 -> 519.6114 | AO61: =(F61-DCF!$H$7)*DCF!$H$41 -> 335.91854 | AP61: =(G61-F61)*DCF!$H$41 -> 325.15181 | AQ61: =(H61-G61)*DCF!$H$41 -> 320.20817 | AR61: =(I61-H61)*DCF!$H$41 -> 293.24487 | AS61: =(J61-I61)*DCF!$H$41 -> 286.2415 | AT61: =(U61-Z61)*(1-DCF!$H$40)+Z61-AE61-AO61 -> 144.85715 | AU61: =(V61-AA61)*(1-DCF!$H$40)+AA61-AF61-AP61 -> 343.07527 | AV61: =(W61-AB61)*(1-DCF!$H$40)+AB61-AG61-AQ61 -> 643.58841 | AW61: =(X61-AC61)*(1-DCF!$H$40)+AC61-AH61-AR61 -> 915.7771 | AX61: =(Y61-AD61)*(1-DCF!$H$40)+AD61-AI61-AS61 -> 1143.5139 | AY61: =0.0925+$E61*(0.1125-0.0925) -> 0.10655301 | AZ61: =10+$E61*(14-10) -> 12.810601 | BA61: =SUMPRODUCT(AT61:AX61,(1+$AY61)^(-{1,2,3,4,5})) -> 2186.1495 | BB61: =Y61*$AZ61 -> 33763.602 | BC61: =BB61*(1+$AY61)^(-5) -> 20351.089 | BD61: =BA61+BC61 -> 22537.239 | BE61: =BD61-(DCF!$J$48-DCF!$J$51) -> 21975.099 | BF61: =BE61/DCF!$J$55 -> 886.81887
A62: 36 | B62: =RAND() -> 0.83678691 | C62: =IF(B62<0.5,SQRT(0.5*B62),1-SQRT(0.5*(1-B62))) -> 0.71433141 | D62: =RAND() -> 0.40686947 | E62: =IF(D62<0.5,SQRT(0.5*D62),1-SQRT(0.5*(1-D62))) -> 0.4510374 | F62: =DCF!$H$7*(1+('A1'!F14+$C62*('A1'!F12-'A1'!F14))) -> 6431.1298 | G62: =F62*(1+('A1'!G14+$C62*('A1'!G12-'A1'!G14))) -> 7506.0913 | H62: =G62*(1+('A1'!H14+$C62*('A1'!H12-'A1'!H14))) -> 8578.4346 | I62: =H62*(1+('A1'!I14+$C62*('A1'!I12-'A1'!I14))) -> 9558.8624 | J62: =I62*(1+('A1'!J14+$C62*('A1'!J12-'A1'!J14))) -> 10514.779 | K62: ='A1'!F21+$C62*('A1'!F19-'A1'!F21) -> 0.34071177 | L62: ='A1'!G21+$C62*('A1'!G19-'A1'!G21) -> 0.33142514 | M62: ='A1'!H21+$C62*('A1'!H19-'A1'!H21) -> 0.31928183 | N62: ='A1'!I21+$C62*('A1'!I19-'A1'!I21) -> 0.31428183 | O62: ='A1'!J21+$C62*('A1'!J19-'A1'!J21) -> 0.30928183 | P62: ='A1'!F28+$C62*('A1'!F26-'A1'!F28) -> 0.44214171 | Q62: ='A1'!G28+$C62*('A1'!G26-'A1'!G28) -> 0.43285509 | R62: ='A1'!H28+$C62*('A1'!H26-'A1'!H28) -> 0.42214012 | S62: ='A1'!I28+$C62*('A1'!I26-'A1'!I28) -> 0.41856846 | T62: ='A1'!J28+$C62*('A1'!J26-'A1'!J28) -> 0.4149968 | U62: =F62*(1-K62-P62) -> 1396.4974 | V62: =G62*(1-L62-Q62) -> 1769.3341 | W62: =H62*(1-M62-R62) -> 2218.1949 | X62: =I62*(1-N62-S62) -> 2553.6473 | Y62: =J62*(1-O62-T62) -> 2899.1493 | Z62: =F62*('A1'!F35+$C62*('A1'!F33-'A1'!F35)) -> 362.898 | AA62: =G62*('A1'!G35+$C62*('A1'!G33-'A1'!G35)) -> 411.75929 | AB62: =H62*('A1'!H35+$C62*('A1'!H33-'A1'!H35)) -> 447.29978 | AC62: =I62*('A1'!I35+$C62*('A1'!I33-'A1'!I35)) -> 472.47567 | AD62: =J62*('A1'!J35+$C62*('A1'!J33-'A1'!J35)) -> 498.69519 | AE62: =F62*('A1'!F43+$C62*('A1'!F41-'A1'!F43)) -> 615.54511 | AF62: =G62*('A1'!G43+$C62*('A1'!G41-'A1'!G43)) -> 675.53621 | AG62: =H62*('A1'!H43+$C62*('A1'!H41-'A1'!H43)) -> 686.26105 | AH62: =I62*('A1'!I43+$C62*('A1'!I41-'A1'!I43)) -> 669.10508 | AI62: =J62*('A1'!J43+$C62*('A1'!J41-'A1'!J43)) -> 683.44383 | AJ62: =(U62-Z62)*DCF!$H$40 -> 250.13106 | AK62: =(V62-AA62)*DCF!$H$40 -> 328.5331 | AL62: =(W62-AB62)*DCF!$H$40 -> 428.55663 | AM62: =(X62-AC62)*DCF!$H$40 -> 503.64354 | AN62: =(Y62-AD62)*DCF!$H$40 -> 580.9099 | AO62: =(F62-DCF!$H$7)*DCF!$H$41 -> 353.56935 | AP62: =(G62-F62)*DCF!$H$41 -> 356.71242 | AQ62: =(H62-G62)*DCF!$H$41 -> 355.84362 | AR62: =(I62-H62)*DCF!$H$41 -> 325.34261 | AS62: =(J62-I62)*DCF!$H$41 -> 317.20895 | AT62: =(U62-Z62)*(1-DCF!$H$40)+Z62-AE62-AO62 -> 177.25188 | AU62: =(V62-AA62)*(1-DCF!$H$40)+AA62-AF62-AP62 -> 408.55237 | AV62: =(W62-AB62)*(1-DCF!$H$40)+AB62-AG62-AQ62 -> 747.53363 | AW62: =(X62-AC62)*(1-DCF!$H$40)+AC62-AH62-AR62 -> 1055.5561 | AX62: =(Y62-AD62)*(1-DCF!$H$40)+AD62-AI62-AS62 -> 1317.5866 | AY62: =0.0925+$E62*(0.1125-0.0925) -> 0.10152075 | AZ62: =10+$E62*(14-10) -> 11.80415 | BA62: =SUMPRODUCT(AT62:AX62,(1+$AY62)^(-{1,2,3,4,5})) -> 2586.4123 | BB62: =Y62*$AZ62 -> 34221.992 | BC62: =BB62*(1+$AY62)^(-5) -> 21102.887 | BD62: =BA62+BC62 -> 23689.3 | BE62: =BD62-(DCF!$J$48-DCF!$J$51) -> 23127.16 | BF62: =BE62/DCF!$J$55 -> 933.31101
A63: 37 | B63: =RAND() -> 0.83635315 | C63: =IF(B63<0.5,SQRT(0.5*B63),1-SQRT(0.5*(1-B63))) -> 0.71395206 | D63: =RAND() -> 0.6887732 | E63: =IF(D63<0.5,SQRT(0.5*D63),1-SQRT(0.5*(1-D63))) -> 0.60552135 | F63: =DCF!$H$7*(1+('A1'!F14+$C63*('A1'!F12-'A1'!F14))) -> 6430.9059 | G63: =F63*(1+('A1'!G14+$C63*('A1'!G12-'A1'!G14))) -> 7505.464 | H63: =G63*(1+('A1'!H14+$C63*('A1'!H12-'A1'!H14))) -> 8577.3476 | I63: =H63*(1+('A1'!I14+$C63*('A1'!I12-'A1'!I14))) -> 9557.3583 | J63: =I63*(1+('A1'!J14+$C63*('A1'!J12-'A1'!J14))) -> 10512.871 | K63: ='A1'!F21+$C63*('A1'!F19-'A1'!F21) -> 0.34073264 | L63: ='A1'!G21+$C63*('A1'!G19-'A1'!G21) -> 0.3314536 | M63: ='A1'!H21+$C63*('A1'!H19-'A1'!H21) -> 0.31931408 | N63: ='A1'!I21+$C63*('A1'!I19-'A1'!I21) -> 0.31431408 | O63: ='A1'!J21+$C63*('A1'!J19-'A1'!J21) -> 0.30931408 | P63: ='A1'!F28+$C63*('A1'!F26-'A1'!F28) -> 0.4421512 | Q63: ='A1'!G28+$C63*('A1'!G26-'A1'!G28) -> 0.43287216 | R63: ='A1'!H28+$C63*('A1'!H26-'A1'!H28) -> 0.42216288 | S63: ='A1'!I28+$C63*('A1'!I26-'A1'!I28) -> 0.41859312 | T63: ='A1'!J28+$C63*('A1'!J26-'A1'!J28) -> 0.41502336 | U63: =F63*(1-K63-P63) -> 1396.2536 | V63: =G63*(1-L63-Q63) -> 1768.8446 | W63: =H63*(1-M63-R63) -> 2217.442 | X63: =I63*(1-N63-S63) -> 2552.7017 | Y63: =J63*(1-O63-T63) -> 2898.005 | Z63: =F63*('A1'!F35+$C63*('A1'!F33-'A1'!F35)) -> 362.89756 | AA63: =G63*('A1'!G35+$C63*('A1'!G33-'A1'!G35)) -> 411.75335 | AB63: =H63*('A1'!H35+$C63*('A1'!H33-'A1'!H35)) -> 447.27889 | AC63: =I63*('A1'!I35+$C63*('A1'!I33-'A1'!I35)) -> 472.44483 | AD63: =J63*('A1'!J35+$C63*('A1'!J33-'A1'!J35)) -> 498.65254 | AE63: =F63*('A1'!F43+$C63*('A1'!F41-'A1'!F43)) -> 615.57248 | AF63: =G63*('A1'!G43+$C63*('A1'!G41-'A1'!G43)) -> 675.57941 | AG63: =H63*('A1'!H43+$C63*('A1'!H41-'A1'!H43)) -> 686.28797 | AH63: =I63*('A1'!I43+$C63*('A1'!I41-'A1'!I43)) -> 669.12669 | AI63: =J63*('A1'!J43+$C63*('A1'!J41-'A1'!J43)) -> 683.45938 | AJ63: =(U63-Z63)*DCF!$H$40 -> 250.07217 | AK63: =(V63-AA63)*DCF!$H$40 -> 328.41608 | AL63: =(W63-AB63)*DCF!$H$40 -> 428.37948 | AM63: =(X63-AC63)*DCF!$H$40 -> 503.42216 | AN63: =(Y63-AD63)*DCF!$H$40 -> 580.6433 | AO63: =(F63-DCF!$H$7)*DCF!$H$41 -> 353.49505 | AP63: =(G63-F63)*DCF!$H$41 -> 356.57857 | AQ63: =(H63-G63)*DCF!$H$41 -> 355.69106 | AR63: =(I63-H63)*DCF!$H$41 -> 325.20421 | AS63: =(J63-I63)*DCF!$H$41 -> 317.07482 | AT63: =(U63-Z63)*(1-DCF!$H$40)+Z63-AE63-AO63 -> 177.11392 | AU63: =(V63-AA63)*(1-DCF!$H$40)+AA63-AF63-AP63 -> 408.27052 | AV63: =(W63-AB63)*(1-DCF!$H$40)+AB63-AG63-AQ63 -> 747.08353 | AW63: =(X63-AC63)*(1-DCF!$H$40)+AC63-AH63-AR63 -> 1054.9486 | AX63: =(Y63-AD63)*(1-DCF!$H$40)+AD63-AI63-AS63 -> 1316.8275 | AY63: =0.0925+$E63*(0.1125-0.0925) -> 0.10461043 | AZ63: =10+$E63*(14-10) -> 12.422085 | BA63: =SUMPRODUCT(AT63:AX63,(1+$AY63)^(-{1,2,3,4,5})) -> 2558.5538 | BB63: =Y63*$AZ63 -> 35999.266 | BC63: =BB63*(1+$AY63)^(-5) -> 21890.11 | BD63: =BA63+BC63 -> 24448.664 | BE63: =BD63-(DCF!$J$48-DCF!$J$51) -> 23886.524 | BF63: =BE63/DCF!$J$55 -> 963.95565
A64: 38 | B64: =RAND() -> 0.61885525 | C64: =IF(B64<0.5,SQRT(0.5*B64),1-SQRT(0.5*(1-B64))) -> 0.56345404 | D64: =RAND() -> 0.71728008 | E64: =IF(D64<0.5,SQRT(0.5*D64),1-SQRT(0.5*(1-D64))) -> 0.62402133 | F64: =DCF!$H$7*(1+('A1'!F14+$C64*('A1'!F12-'A1'!F14))) -> 6342.0789 | G64: =F64*(1+('A1'!G14+$C64*('A1'!G12-'A1'!G14))) -> 7258.6241 | H64: =G64*(1+('A1'!H14+$C64*('A1'!H12-'A1'!H14))) -> 8153.2424 | I64: =H64*(1+('A1'!I14+$C64*('A1'!I12-'A1'!I14))) -> 8974.3625 | J64: =I64*(1+('A1'!J14+$C64*('A1'!J12-'A1'!J14))) -> 9777.0455 | K64: ='A1'!F21+$C64*('A1'!F19-'A1'!F21) -> 0.34901003 | L64: ='A1'!G21+$C64*('A1'!G19-'A1'!G21) -> 0.34274095 | M64: ='A1'!H21+$C64*('A1'!H19-'A1'!H21) -> 0.33210641 | N64: ='A1'!I21+$C64*('A1'!I19-'A1'!I21) -> 0.32710641 | O64: ='A1'!J21+$C64*('A1'!J19-'A1'!J21) -> 0.32210641 | P64: ='A1'!F28+$C64*('A1'!F26-'A1'!F28) -> 0.44591365 | Q64: ='A1'!G28+$C64*('A1'!G26-'A1'!G28) -> 0.43964457 | R64: ='A1'!H28+$C64*('A1'!H26-'A1'!H28) -> 0.43119276 | S64: ='A1'!I28+$C64*('A1'!I26-'A1'!I28) -> 0.42837549 | T64: ='A1'!J28+$C64*('A1'!J26-'A1'!J28) -> 0.42555822 | U64: =F64*(1-K64-P64) -> 1300.6102 | V64: =G64*(1-L64-Q64) -> 1579.5817 | W64: =H64*(1-M64-R64) -> 1929.8793 | X64: =I64*(1-N64-S64) -> 2194.3941 | Y64: =J64*(1-O64-T64) -> 2467.0945 | Z64: =F64*('A1'!F35+$C64*('A1'!F33-'A1'!F35)) -> 362.65738 | AA64: =G64*('A1'!G35+$C64*('A1'!G33-'A1'!G35)) -> 409.13568 | AB64: =H64*('A1'!H35+$C64*('A1'!H33-'A1'!H35)) -> 438.6608 | AC64: =I64*('A1'!I35+$C64*('A1'!I33-'A1'!I35)) -> 459.83334 | AD64: =J64*('A1'!J35+$C64*('A1'!J33-'A1'!J35)) -> 481.40756 | AE64: =F64*('A1'!F43+$C64*('A1'!F41-'A1'!F43)) -> 626.15928 | AF64: =G64*('A1'!G43+$C64*('A1'!G41-'A1'!G43)) -> 691.59523 | AG64: =H64*('A1'!H43+$C64*('A1'!H41-'A1'!H43)) -> 695.30125 | AH64: =I64*('A1'!I43+$C64*('A1'!I41-'A1'!I43)) -> 675.58201 | AI64: =J64*('A1'!J43+$C64*('A1'!J41-'A1'!J43)) -> 687.12204 | AJ64: =(U64-Z64)*DCF!$H$40 -> 226.98459 | AK64: =(V64-AA64)*DCF!$H$40 -> 283.24795 | AL64: =(W64-AB64)*DCF!$H$40 -> 360.87488 | AM64: =(X64-AC64)*DCF!$H$40 -> 419.76371 | AN64: =(Y64-AD64)*DCF!$H$40 -> 480.53623 | AO64: =(F64-DCF!$H$7)*DCF!$H$41 -> 324.01893 | AP64: =(G64-F64)*DCF!$H$41 -> 304.14398 | AQ64: =(H64-G64)*DCF!$H$41 -> 296.86782 | AR64: =(I64-H64)*DCF!$H$41 -> 272.47835 | AS64: =(J64-I64)*DCF!$H$41 -> 266.36023 | AT64: =(U64-Z64)*(1-DCF!$H$40)+Z64-AE64-AO64 -> 123.44742 | AU64: =(V64-AA64)*(1-DCF!$H$40)+AA64-AF64-AP64 -> 300.59458 | AV64: =(W64-AB64)*(1-DCF!$H$40)+AB64-AG64-AQ64 -> 576.83535 | AW64: =(X64-AC64)*(1-DCF!$H$40)+AC64-AH64-AR64 -> 826.57006 | AX64: =(Y64-AD64)*(1-DCF!$H$40)+AD64-AI64-AS64 -> 1033.076 | AY64: =0.0925+$E64*(0.1125-0.0925) -> 0.10498043 | AZ64: =10+$E64*(14-10) -> 12.496085 | BA64: =SUMPRODUCT(AT64:AX64,(1+$AY64)^(-{1,2,3,4,5})) -> 1967.0424 | BB64: =Y64*$AZ64 -> 30829.023 | BC64: =BB64*(1+$AY64)^(-5) -> 18714.871 | BD64: =BA64+BC64 -> 20681.913 | BE64: =BD64-(DCF!$J$48-DCF!$J$51) -> 20119.773 | BF64: =BE64/DCF!$J$55 -> 811.94605
A65: 39 | B65: =RAND() -> 0.28908456 | C65: =IF(B65<0.5,SQRT(0.5*B65),1-SQRT(0.5*(1-B65))) -> 0.38018716 | D65: =RAND() -> 0.69665975 | E65: =IF(D65<0.5,SQRT(0.5*D65),1-SQRT(0.5*(1-D65))) -> 0.61055151 | F65: =DCF!$H$7*(1+('A1'!F14+$C65*('A1'!F12-'A1'!F14))) -> 6233.911 | G65: =F65*(1+('A1'!G14+$C65*('A1'!G12-'A1'!G14))) -> 6963.4536 | H65: =G65*(1+('A1'!H14+$C65*('A1'!H12-'A1'!H14))) -> 7655.7903 | I65: =H65*(1+('A1'!I14+$C65*('A1'!I12-'A1'!I14))) -> 8300.5368 | J65: =I65*(1+('A1'!J14+$C65*('A1'!J12-'A1'!J14))) -> 8936.4667 | K65: ='A1'!F21+$C65*('A1'!F19-'A1'!F21) -> 0.35908971 | L65: ='A1'!G21+$C65*('A1'!G19-'A1'!G21) -> 0.35648596 | M65: ='A1'!H21+$C65*('A1'!H19-'A1'!H21) -> 0.34768409 | N65: ='A1'!I21+$C65*('A1'!I19-'A1'!I21) -> 0.34268409 | O65: ='A1'!J21+$C65*('A1'!J19-'A1'!J21) -> 0.33768409 | P65: ='A1'!F28+$C65*('A1'!F26-'A1'!F28) -> 0.45049532 | Q65: ='A1'!G28+$C65*('A1'!G26-'A1'!G28) -> 0.44789158 | R65: ='A1'!H28+$C65*('A1'!H26-'A1'!H28) -> 0.44218877 | S65: ='A1'!I28+$C65*('A1'!I26-'A1'!I28) -> 0.44028783 | T65: ='A1'!J28+$C65*('A1'!J26-'A1'!J28) -> 0.4383869 | U65: =F65*(1-K65-P65) -> 1187.03 | V65: =G65*(1-L65-Q65) -> 1362.2079 | W65: =H65*(1-M65-R65) -> 1608.6893 | X65: =I65*(1-N65-S65) -> 1801.4495 | Y65: =J65*(1-O65-T65) -> 2001.1341 | Z65: =F65*('A1'!F35+$C65*('A1'!F33-'A1'!F35)) -> 362.1844 | AA65: =G65*('A1'!G35+$C65*('A1'!G33-'A1'!G35)) -> 405.25997 | AB65: =H65*('A1'!H35+$C65*('A1'!H33-'A1'!H35)) -> 427.33046 | AC65: =I65*('A1'!I35+$C65*('A1'!I33-'A1'!I35)) -> 443.56205 | AD65: =J65*('A1'!J35+$C65*('A1'!J33-'A1'!J35)) -> 459.67178 | AE65: =F65*('A1'!F43+$C65*('A1'!F41-'A1'!F43)) -> 638.32915 | AF65: =G65*('A1'!G43+$C65*('A1'!G41-'A1'!G43)) -> 708.13762 | AG65: =H65*('A1'!H43+$C65*('A1'!H41-'A1'!H43)) -> 701.98582 | AH65: =I65*('A1'!I43+$C65*('A1'!I41-'A1'!I43)) -> 678.09949 | AI65: =J65*('A1'!J43+$C65*('A1'!J41-'A1'!J43)) -> 685.36846 | AJ65: =(U65-Z65)*DCF!$H$40 -> 199.61264 | AK65: =(V65-AA65)*DCF!$H$40 -> 231.58141 | AL65: =(W65-AB65)*DCF!$H$40 -> 285.88884 | AM65: =(X65-AC65)*DCF!$H$40 -> 328.60877 | AN65: =(Y65-AD65)*DCF!$H$40 -> 373.03389 | AO65: =(F65-DCF!$H$7)*DCF!$H$41 -> 288.12479 | AP65: =(G65-F65)*DCF!$H$41 -> 242.08952 | AQ65: =(H65-G65)*DCF!$H$41 -> 229.74321 | AR65: =(I65-H65)*DCF!$H$41 -> 213.951 | AS65: =(J65-I65)*DCF!$H$41 -> 211.02531 | AT65: =(U65-Z65)*(1-DCF!$H$40)+Z65-AE65-AO65 -> 60.963416 | AU65: =(V65-AA65)*(1-DCF!$H$40)+AA65-AF65-AP65 -> 180.39938 | AV65: =(W65-AB65)*(1-DCF!$H$40)+AB65-AG65-AQ65 -> 391.07144 | AW65: =(X65-AC65)*(1-DCF!$H$40)+AC65-AH65-AR65 -> 580.79027 | AX65: =(Y65-AD65)*(1-DCF!$H$40)+AD65-AI65-AS65 -> 731.70648 | AY65: =0.0925+$E65*(0.1125-0.0925) -> 0.10471103 | AZ65: =10+$E65*(14-10) -> 12.442206 | BA65: =SUMPRODUCT(AT65:AX65,(1+$AY65)^(-{1,2,3,4,5})) -> 1327.7723 | BB65: =Y65*$AZ65 -> 24898.523 | BC65: =BB65*(1+$AY65)^(-5) -> 15133.178 | BD65: =BA65+BC65 -> 16460.95 | BE65: =BD65-(DCF!$J$48-DCF!$J$51) -> 15898.81 | BF65: =BE65/DCF!$J$55 -> 641.60645
A66: 40 | B66: =RAND() -> 0.99919384 | C66: =IF(B66<0.5,SQRT(0.5*B66),1-SQRT(0.5*(1-B66))) -> 0.97992309 | D66: =RAND() -> 0.89862219 | E66: =IF(D66<0.5,SQRT(0.5*D66),1-SQRT(0.5*(1-D66))) -> 0.77485804 | F66: =DCF!$H$7*(1+('A1'!F14+$C66*('A1'!F12-'A1'!F14))) -> 6587.8874 | G66: =F66*(1+('A1'!G14+$C66*('A1'!G12-'A1'!G14))) -> 7951.5041 | H66: =G66*(1+('A1'!H14+$C66*('A1'!H12-'A1'!H14))) -> 9362.0214 | I66: =H66*(1+('A1'!I14+$C66*('A1'!I12-'A1'!I14))) -> 10655.788 | J66: =I66*(1+('A1'!J14+$C66*('A1'!J12-'A1'!J14))) -> 11919.507 | K66: ='A1'!F21+$C66*('A1'!F19-'A1'!F21) -> 0.32610423 | L66: ='A1'!G21+$C66*('A1'!G19-'A1'!G21) -> 0.31150577 | M66: ='A1'!H21+$C66*('A1'!H19-'A1'!H21) -> 0.29670654 | N66: ='A1'!I21+$C66*('A1'!I19-'A1'!I21) -> 0.29170654 | O66: ='A1'!J21+$C66*('A1'!J19-'A1'!J21) -> 0.28670654 | P66: ='A1'!F28+$C66*('A1'!F26-'A1'!F28) -> 0.43550192 | Q66: ='A1'!G28+$C66*('A1'!G26-'A1'!G28) -> 0.42090346 | R66: ='A1'!H28+$C66*('A1'!H26-'A1'!H28) -> 0.40620461 | S66: ='A1'!I28+$C66*('A1'!I26-'A1'!I28) -> 0.401305 | T66: ='A1'!J28+$C66*('A1'!J26-'A1'!J28) -> 0.39640538 | U66: =F66*(1-K66-P66) -> 1570.5118 | V66: =G66*(1-L66-Q66) -> 2127.7491 | W66: =H66*(1-M66-R66) -> 2781.3522 | X66: =I66*(1-N66-S66) -> 3271.204 | Y66: =J66*(1-O66-T66) -> 3777.1497 | Z66: =F66*('A1'!F35+$C66*('A1'!F33-'A1'!F35)) -> 362.99513 | AA66: =G66*('A1'!G35+$C66*('A1'!G33-'A1'!G35)) -> 415.07463 | AB66: =H66*('A1'!H35+$C66*('A1'!H33-'A1'!H35)) -> 460.80661 | AC66: =I66*('A1'!I35+$C66*('A1'!I33-'A1'!I35)) -> 492.73347 | AD66: =J66*('A1'!J35+$C66*('A1'!J33-'A1'!J35)) -> 527.32999 | AE66: =F66*('A1'!F43+$C66*('A1'!F41-'A1'!F43)) -> 595.55515 | AF66: =G66*('A1'!G43+$C66*('A1'!G41-'A1'!G43)) -> 641.70778 | AG66: =H66*('A1'!H43+$C66*('A1'!H41-'A1'!H43)) -> 661.92011 | AH66: =I66*('A1'!I43+$C66*('A1'!I41-'A1'!I43)) -> 646.83501 | AI66: =J66*('A1'!J43+$C66*('A1'!J41-'A1'!J43)) -> 663.94863 | AJ66: =(U66-Z66)*DCF!$H$40 -> 292.21904 | AK66: =(V66-AA66)*DCF!$H$40 -> 414.46723 | AL66: =(W66-AB66)*DCF!$H$40 -> 561.57202 | AM66: =(X66-AC66)*DCF!$H$40 -> 672.38987 | AN66: =(Y66-AD66)*DCF!$H$40 -> 786.45637 | AO66: =(F66-DCF!$H$7)*DCF!$H$41 -> 405.58739 | AP66: =(G66-F66)*DCF!$H$41 -> 452.49901 | AQ66: =(H66-G66)*DCF!$H$41 -> 468.0624 | AR66: =(I66-H66)*DCF!$H$41 -> 429.32013 | AS66: =(J66-I66)*DCF!$H$41 -> 419.34925 | AT66: =(U66-Z66)*(1-DCF!$H$40)+Z66-AE66-AO66 -> 277.15024 | AU66: =(V66-AA66)*(1-DCF!$H$40)+AA66-AF66-AP66 -> 619.07509 | AV66: =(W66-AB66)*(1-DCF!$H$40)+AB66-AG66-AQ66 -> 1089.7976 | AW66: =(X66-AC66)*(1-DCF!$H$40)+AC66-AH66-AR66 -> 1522.659 | AX66: =(Y66-AD66)*(1-DCF!$H$40)+AD66-AI66-AS66 -> 1907.3955 | AY66: =0.0925+$E66*(0.1125-0.0925) -> 0.10799716 | AZ66: =10+$E66*(14-10) -> 13.099432 | BA66: =SUMPRODUCT(AT66:AX66,(1+$AY66)^(-{1,2,3,4,5})) -> 3708.098 | BB66: =Y66*$AZ66 -> 49478.516 | BC66: =BB66*(1+$AY66)^(-5) -> 29629.439 | BD66: =BA66+BC66 -> 33337.537 | BE66: =BD66-(DCF!$J$48-DCF!$J$51) -> 32775.397 | BF66: =BE66/DCF!$J$55 -> 1322.6717
A67: 41 | B67: =RAND() -> 0.96145789 | C67: =IF(B67<0.5,SQRT(0.5*B67),1-SQRT(0.5*(1-B67))) -> 0.86117977 | D67: =RAND() -> 0.85421818 | E67: =IF(D67<0.5,SQRT(0.5*D67),1-SQRT(0.5*(1-D67))) -> 0.73001683 | F67: =DCF!$H$7*(1+('A1'!F14+$C67*('A1'!F12-'A1'!F14))) -> 6517.8027 | G67: =F67*(1+('A1'!G14+$C67*('A1'!G12-'A1'!G14))) -> 7750.8208 | H67: =G67*(1+('A1'!H14+$C67*('A1'!H12-'A1'!H14))) -> 9006.0923 | I67: =H67*(1+('A1'!I14+$C67*('A1'!I12-'A1'!I14))) -> 10154.425 | J67: =I67*(1+('A1'!J14+$C67*('A1'!J12-'A1'!J14))) -> 11274.281 | K67: ='A1'!F21+$C67*('A1'!F19-'A1'!F21) -> 0.33263511 | L67: ='A1'!G21+$C67*('A1'!G19-'A1'!G21) -> 0.32041152 | M67: ='A1'!H21+$C67*('A1'!H19-'A1'!H21) -> 0.30679972 | N67: ='A1'!I21+$C67*('A1'!I19-'A1'!I21) -> 0.30179972 | O67: ='A1'!J21+$C67*('A1'!J19-'A1'!J21) -> 0.29679972 | P67: ='A1'!F28+$C67*('A1'!F26-'A1'!F28) -> 0.43847051 | Q67: ='A1'!G28+$C67*('A1'!G26-'A1'!G28) -> 0.42624691 | R67: ='A1'!H28+$C67*('A1'!H26-'A1'!H28) -> 0.41332921 | S67: ='A1'!I28+$C67*('A1'!I26-'A1'!I28) -> 0.40902331 | T67: ='A1'!J28+$C67*('A1'!J26-'A1'!J28) -> 0.40471742 | U67: =F67*(1-K67-P67) -> 1491.8884 | V67: =G67*(1-L67-Q67) -> 1963.6051 | W67: =H67*(1-M67-R67) -> 2520.5447 | X67: =I67*(1-N67-S67) -> 2936.4257 | Y67: =J67*(1-O67-T67) -> 3365.1797 | Z67: =F67*('A1'!F35+$C67*('A1'!F33-'A1'!F35)) -> 363.00316 | AA67: =G67*('A1'!G35+$C67*('A1'!G33-'A1'!G35)) -> 413.80239 | AB67: =H67*('A1'!H35+$C67*('A1'!H33-'A1'!H35)) -> 455.05103 | AC67: =I67*('A1'!I35+$C67*('A1'!I33-'A1'!I35)) -> 484.01921 | AD67: =J67*('A1'!J35+$C67*('A1'!J33-'A1'!J35)) -> 514.84954 | AE67: =F67*('A1'!F43+$C67*('A1'!F41-'A1'!F43)) -> 604.6983 | AF67: =G67*('A1'!G43+$C67*('A1'!G41-'A1'!G43)) -> 657.72464 | AG67: =H67*('A1'!H43+$C67*('A1'!H41-'A1'!H43)) -> 674.18444 | AH67: =I67*('A1'!I43+$C67*('A1'!I41-'A1'!I43)) -> 658.60287 | AI67: =J67*('A1'!J43+$C67*('A1'!J41-'A1'!J43)) -> 674.86389 | AJ67: =(U67-Z67)*DCF!$H$40 -> 273.19023 | AK67: =(V67-AA67)*DCF!$H$40 -> 375.05226 | AL67: =(W67-AB67)*DCF!$H$40 -> 499.84946 | AM67: =(X67-AC67)*DCF!$H$40 -> 593.48238 | AN67: =(Y67-AD67)*DCF!$H$40 -> 689.77989 | AO67: =(F67-DCF!$H$7)*DCF!$H$41 -> 382.33066 | AP67: =(G67-F67)*DCF!$H$41 -> 409.16152 | AQ67: =(H67-G67)*DCF!$H$41 -> 416.54604 | AR67: =(I67-H67)*DCF!$H$41 -> 381.05964 | AS67: =(J67-I67)*DCF!$H$41 -> 371.61016 | AT67: =(U67-Z67)*(1-DCF!$H$40)+Z67-AE67-AO67 -> 231.66922 | AU67: =(V67-AA67)*(1-DCF!$H$40)+AA67-AF67-AP67 -> 521.6667 | AV67: =(W67-AB67)*(1-DCF!$H$40)+AB67-AG67-AQ67 -> 929.96473 | AW67: =(X67-AC67)*(1-DCF!$H$40)+AC67-AH67-AR67 -> 1303.2808 | AX67: =(Y67-AD67)*(1-DCF!$H$40)+AD67-AI67-AS67 -> 1628.9257 | AY67: =0.0925+$E67*(0.1125-0.0925) -> 0.10710034 | AZ67: =10+$E67*(14-10) -> 12.920067 | BA67: =SUMPRODUCT(AT67:AX67,(1+$AY67)^(-{1,2,3,4,5})) -> 3167.1693 | BB67: =Y67*$AZ67 -> 43478.348 | BC67: =BB67*(1+$AY67)^(-5) -> 26141.958 | BD67: =BA67+BC67 -> 29309.128 | BE67: =BD67-(DCF!$J$48-DCF!$J$51) -> 28746.988 | BF67: =BE67/DCF!$J$55 -> 1160.1027
A68: 42 | B68: =RAND() -> 0.76860298 | C68: =IF(B68<0.5,SQRT(0.5*B68),1-SQRT(0.5*(1-B68))) -> 0.65985517 | D68: =RAND() -> 0.041337255 | E68: =IF(D68<0.5,SQRT(0.5*D68),1-SQRT(0.5*(1-D68))) -> 0.14376588 | F68: =DCF!$H$7*(1+('A1'!F14+$C68*('A1'!F12-'A1'!F14))) -> 6398.9768 | G68: =F68*(1+('A1'!G14+$C68*('A1'!G12-'A1'!G14))) -> 7416.2751 | H68: =G68*(1+('A1'!H14+$C68*('A1'!H12-'A1'!H14))) -> 8423.2656 | I68: =H68*(1+('A1'!I14+$C68*('A1'!I12-'A1'!I14))) -> 9344.661 | J68: =I68*(1+('A1'!J14+$C68*('A1'!J12-'A1'!J14))) -> 10243.523 | K68: ='A1'!F21+$C68*('A1'!F19-'A1'!F21) -> 0.34370797 | L68: ='A1'!G21+$C68*('A1'!G19-'A1'!G21) -> 0.33551086 | M68: ='A1'!H21+$C68*('A1'!H19-'A1'!H21) -> 0.32391231 | N68: ='A1'!I21+$C68*('A1'!I19-'A1'!I21) -> 0.31891231 | O68: ='A1'!J21+$C68*('A1'!J19-'A1'!J21) -> 0.31391231 | P68: ='A1'!F28+$C68*('A1'!F26-'A1'!F28) -> 0.44350362 | Q68: ='A1'!G28+$C68*('A1'!G26-'A1'!G28) -> 0.43530652 | R68: ='A1'!H28+$C68*('A1'!H26-'A1'!H28) -> 0.42540869 | S68: ='A1'!I28+$C68*('A1'!I26-'A1'!I28) -> 0.42210941 | T68: ='A1'!J28+$C68*('A1'!J26-'A1'!J28) -> 0.41881014 | U68: =F68*(1-K68-P68) -> 1361.6281 | V68: =G68*(1-L68-Q68) -> 1699.6814 | W68: =H68*(1-M68-R68) -> 2111.5358 | X68: =I68*(1-N68-S68) -> 2420.0642 | Y68: =J68*(1-O68-T68) -> 2737.8637 | Z68: =F68*('A1'!F35+$C68*('A1'!F33-'A1'!F35)) -> 362.82662 | AA68: =G68*('A1'!G35+$C68*('A1'!G33-'A1'!G35)) -> 410.87238 | AB68: =H68*('A1'!H35+$C68*('A1'!H33-'A1'!H35)) -> 444.25645 | AC68: =I68*('A1'!I35+$C68*('A1'!I33-'A1'!I35)) -> 467.99687 | AD68: =J68*('A1'!J35+$C68*('A1'!J33-'A1'!J35)) -> 492.52637 | AE68: =F68*('A1'!F43+$C68*('A1'!F41-'A1'!F43)) -> 619.43949 | AF68: =G68*('A1'!G43+$C68*('A1'!G41-'A1'!G43)) -> 681.59327 | AG68: =H68*('A1'!H43+$C68*('A1'!H41-'A1'!H43)) -> 689.90815 | AH68: =I68*('A1'!I43+$C68*('A1'!I41-'A1'!I43)) -> 671.9285 | AI68: =J68*('A1'!J43+$C68*('A1'!J41-'A1'!J43)) -> 685.34359 | AJ68: =(U68-Z68)*DCF!$H$40 -> 241.70996 | AK68: =(V68-AA68)*DCF!$H$40 -> 311.89177 | AL68: =(W68-AB68)*DCF!$H$40 -> 403.4816 | AM68: =(X68-AC68)*DCF!$H$40 -> 472.40029 | AN68: =(Y68-AD68)*DCF!$H$40 -> 543.37162 | AO68: =(F68-DCF!$H$7)*DCF!$H$41 -> 342.89979 | AP68: =(G68-F68)*DCF!$H$41 -> 337.57761 | AQ68: =(H68-G68)*DCF!$H$41 -> 334.15711 | AR68: =(I68-H68)*DCF!$H$41 -> 305.75347 | AS68: =(J68-I68)*DCF!$H$41 -> 298.27591 | AT68: =(U68-Z68)*(1-DCF!$H$40)+Z68-AE68-AO68 -> 157.57888 | AU68: =(V68-AA68)*(1-DCF!$H$40)+AA68-AF68-AP68 -> 368.61869 | AV68: =(W68-AB68)*(1-DCF!$H$40)+AB68-AG68-AQ68 -> 683.98893 | AW68: =(X68-AC68)*(1-DCF!$H$40)+AC68-AH68-AR68 -> 969.98194 | AX68: =(Y68-AD68)*(1-DCF!$H$40)+AD68-AI68-AS68 -> 1210.8725 | AY68: =0.0925+$E68*(0.1125-0.0925) -> 0.095375318 | AZ68: =10+$E68*(14-10) -> 10.575064 | BA68: =SUMPRODUCT(AT68:AX68,(1+$AY68)^(-{1,2,3,4,5})) -> 2413.1404 | BB68: =Y68*$AZ68 -> 28953.082 | BC68: =BB68*(1+$AY68)^(-5) -> 18360.312 | BD68: =BA68+BC68 -> 20773.452 | BE68: =BD68-(DCF!$J$48-DCF!$J$51) -> 20211.312 | BF68: =BE68/DCF!$J$55 -> 815.64016
A69: 43 | B69: =RAND() -> 0.26661619 | C69: =IF(B69<0.5,SQRT(0.5*B69),1-SQRT(0.5*(1-B69))) -> 0.36511381 | D69: =RAND() -> 0.28901482 | E69: =IF(D69<0.5,SQRT(0.5*D69),1-SQRT(0.5*(1-D69))) -> 0.3801413 | F69: =DCF!$H$7*(1+('A1'!F14+$C69*('A1'!F12-'A1'!F14))) -> 6225.0144 | G69: =F69*(1+('A1'!G14+$C69*('A1'!G12-'A1'!G14))) -> 6939.4411 | H69: =G69*(1+('A1'!H14+$C69*('A1'!H12-'A1'!H14))) -> 7615.7923 | I69: =H69*(1+('A1'!I14+$C69*('A1'!I12-'A1'!I14))) -> 8246.8387 | J69: =I69*(1+('A1'!J14+$C69*('A1'!J12-'A1'!J14))) -> 8869.9531 | K69: ='A1'!F21+$C69*('A1'!F19-'A1'!F21) -> 0.35991874 | L69: ='A1'!G21+$C69*('A1'!G19-'A1'!G21) -> 0.35761646 | M69: ='A1'!H21+$C69*('A1'!H19-'A1'!H21) -> 0.34896533 | N69: ='A1'!I21+$C69*('A1'!I19-'A1'!I21) -> 0.34396533 | O69: ='A1'!J21+$C69*('A1'!J19-'A1'!J21) -> 0.33896533 | P69: ='A1'!F28+$C69*('A1'!F26-'A1'!F28) -> 0.45087215 | Q69: ='A1'!G28+$C69*('A1'!G26-'A1'!G28) -> 0.44856988 | R69: ='A1'!H28+$C69*('A1'!H26-'A1'!H28) -> 0.44309317 | S69: ='A1'!I28+$C69*('A1'!I26-'A1'!I28) -> 0.4412676 | T69: ='A1'!J28+$C69*('A1'!J26-'A1'!J28) -> 0.43944203 | U69: =F69*(1-K69-P69) -> 1177.8294 | V69: =G69*(1-L69-Q69) -> 1344.9585 | W69: =H69*(1-M69-R69) -> 1583.6393 | X69: =I69*(1-N69-S69) -> 1771.1494 | Y69: =J69*(1-O69-T69) -> 1965.5163 | Z69: =F69*('A1'!F35+$C69*('A1'!F33-'A1'!F35)) -> 362.13667 | AA69: =G69*('A1'!G35+$C69*('A1'!G33-'A1'!G35)) -> 404.90849 | AB69: =H69*('A1'!H35+$C69*('A1'!H33-'A1'!H35)) -> 426.3606 | AC69: =I69*('A1'!I35+$C69*('A1'!I33-'A1'!I35)) -> 442.18423 | AD69: =J69*('A1'!J35+$C69*('A1'!J33-'A1'!J35)) -> 457.85486 | AE69: =F69*('A1'!F43+$C69*('A1'!F41-'A1'!F43)) -> 639.29481 | AF69: =G69*('A1'!G43+$C69*('A1'!G41-'A1'!G43)) -> 709.35672 | AG69: =H69*('A1'!H43+$C69*('A1'!H41-'A1'!H43)) -> 702.33611 | AH69: =I69*('A1'!I43+$C69*('A1'!I41-'A1'!I43)) -> 678.06346 | AI69: =J69*('A1'!J43+$C69*('A1'!J41-'A1'!J43)) -> 684.94679 | AJ69: =(U69-Z69)*DCF!$H$40 -> 197.39764 | AK69: =(V69-AA69)*DCF!$H$40 -> 227.49209 | AL69: =(W69-AB69)*DCF!$H$40 -> 280.06144 | AM69: =(X69-AC69)*DCF!$H$40 -> 321.60957 | AN69: =(Y69-AD69)*DCF!$H$40 -> 364.85407 | AO69: =(F69-DCF!$H$7)*DCF!$H$41 -> 285.17257 | AP69: =(G69-F69)*DCF!$H$41 -> 237.07349 | AQ69: =(H69-G69)*DCF!$H$41 -> 224.43862 | AR69: =(I69-H69)*DCF!$H$41 -> 209.40479 | AS69: =(J69-I69)*DCF!$H$41 -> 206.77265 | AT69: =(U69-Z69)*(1-DCF!$H$40)+Z69-AE69-AO69 -> 55.964384 | AU69: =(V69-AA69)*(1-DCF!$H$40)+AA69-AF69-AP69 -> 171.03615 | AV69: =(W69-AB69)*(1-DCF!$H$40)+AB69-AG69-AQ69 -> 376.80312 | AW69: =(X69-AC69)*(1-DCF!$H$40)+AC69-AH69-AR69 -> 562.07157 | AX69: =(Y69-AD69)*(1-DCF!$H$40)+AD69-AI69-AS69 -> 708.94281 | AY69: =0.0925+$E69*(0.1125-0.0925) -> 0.10010283 | AZ69: =10+$E69*(14-10) -> 11.520565 | BA69: =SUMPRODUCT(AT69:AX69,(1+$AY69)^(-{1,2,3,4,5})) -> 1298.9671 | BB69: =Y69*$AZ69 -> 22643.859 | BC69: =BB69*(1+$AY69)^(-5) -> 14053.485 | BD69: =BA69+BC69 -> 15352.452 | BE69: =BD69-(DCF!$J$48-DCF!$J$51) -> 14790.312 | BF69: =BE69/DCF!$J$55 -> 596.87232
A70: 44 | B70: =RAND() -> 0.71600082 | C70: =IF(B70<0.5,SQRT(0.5*B70),1-SQRT(0.5*(1-B70))) -> 0.62317167 | D70: =RAND() -> 0.017487691 | E70: =IF(D70<0.5,SQRT(0.5*D70),1-SQRT(0.5*(1-D70))) -> 0.093508532 | F70: =DCF!$H$7*(1+('A1'!F14+$C70*('A1'!F12-'A1'!F14))) -> 6377.3254 | G70: =F70*(1+('A1'!G14+$C70*('A1'!G12-'A1'!G14))) -> 7356.0902 | H70: =G70*(1+('A1'!H14+$C70*('A1'!H12-'A1'!H14))) -> 8319.8287 | I70: =H70*(1+('A1'!I14+$C70*('A1'!I12-'A1'!I14))) -> 9202.4414 | J70: =I70*(1+('A1'!J14+$C70*('A1'!J12-'A1'!J14))) -> 10063.993 | K70: ='A1'!F21+$C70*('A1'!F19-'A1'!F21) -> 0.34572556 | L70: ='A1'!G21+$C70*('A1'!G19-'A1'!G21) -> 0.33826212 | M70: ='A1'!H21+$C70*('A1'!H19-'A1'!H21) -> 0.32703041 | N70: ='A1'!I21+$C70*('A1'!I19-'A1'!I21) -> 0.32203041 | O70: ='A1'!J21+$C70*('A1'!J19-'A1'!J21) -> 0.31703041 | P70: ='A1'!F28+$C70*('A1'!F26-'A1'!F28) -> 0.44442071 | Q70: ='A1'!G28+$C70*('A1'!G26-'A1'!G28) -> 0.43695727 | R70: ='A1'!H28+$C70*('A1'!H26-'A1'!H28) -> 0.4276097 | S70: ='A1'!I28+$C70*('A1'!I26-'A1'!I28) -> 0.42449384 | T70: ='A1'!J28+$C70*('A1'!J26-'A1'!J28) -> 0.42137798 | U70: =F70*(1-K70-P70) -> 1338.3056 | V70: =G70*(1-L70-Q70) -> 1653.5064 | W70: =H70*(1-M70-R70) -> 2041.3523 | X70: =I70*(1-N70-S70) -> 2332.5958 | Y70: =J70*(1-O70-T70) -> 2632.656 | Z70: =F70*('A1'!F35+$C70*('A1'!F33-'A1'!F35)) -> 362.76868 | AA70: =G70*('A1'!G35+$C70*('A1'!G33-'A1'!G35)) -> 410.23652 | AB70: =H70*('A1'!H35+$C70*('A1'!H33-'A1'!H35)) -> 442.15822 | AC70: =I70*('A1'!I35+$C70*('A1'!I33-'A1'!I35)) -> 464.92519 | AD70: =J70*('A1'!J35+$C70*('A1'!J33-'A1'!J35)) -> 488.32444 | AE70: =F70*('A1'!F43+$C70*('A1'!F41-'A1'!F43)) -> 622.02243 | AF70: =G70*('A1'!G43+$C70*('A1'!G41-'A1'!G43)) -> 685.50663 | AG70: =H70*('A1'!H43+$C70*('A1'!H41-'A1'!H43)) -> 692.11816 | AH70: =I70*('A1'!I43+$C70*('A1'!I41-'A1'!I43)) -> 673.51741 | AI70: =J70*('A1'!J43+$C70*('A1'!J41-'A1'!J43)) -> 686.2535 | AJ70: =(U70-Z70)*DCF!$H$40 -> 236.07992 | AK70: =(V70-AA70)*DCF!$H$40 -> 300.87131 | AL70: =(W70-AB70)*DCF!$H$40 -> 387.00496 | AM70: =(X70-AC70)*DCF!$H$40 -> 451.97628 | AN70: =(Y70-AD70)*DCF!$H$40 -> 518.92824 | AO70: =(F70-DCF!$H$7)*DCF!$H$41 -> 335.71506 | AP70: =(G70-F70)*DCF!$H$41 -> 324.79076 | AQ70: =(H70-G70)*DCF!$H$41 -> 319.80445 | AR70: =(I70-H70)*DCF!$H$41 -> 292.88392 | AS70: =(J70-I70)*DCF!$H$41 -> 285.89488 | AT70: =(U70-Z70)*(1-DCF!$H$40)+Z70-AE70-AO70 -> 144.48815 | AU70: =(V70-AA70)*(1-DCF!$H$40)+AA70-AF70-AP70 -> 342.33768 | AV70: =(W70-AB70)*(1-DCF!$H$40)+AB70-AG70-AQ70 -> 642.4247 | AW70: =(X70-AC70)*(1-DCF!$H$40)+AC70-AH70-AR70 -> 914.21815 | AX70: =(Y70-AD70)*(1-DCF!$H$40)+AD70-AI70-AS70 -> 1141.5794 | AY70: =0.0925+$E70*(0.1125-0.0925) -> 0.094370171 | AZ70: =10+$E70*(14-10) -> 10.374034 | BA70: =SUMPRODUCT(AT70:AX70,(1+$AY70)^(-{1,2,3,4,5})) -> 2272.645 | BB70: =Y70*$AZ70 -> 27311.263 | BC70: =BB70*(1+$AY70)^(-5) -> 17398.85 | BD70: =BA70+BC70 -> 19671.495 | BE70: =BD70-(DCF!$J$48-DCF!$J$51) -> 19109.355 | BF70: =BE70/DCF!$J$55 -> 771.17001
A71: 45 | B71: =RAND() -> 0.8532662 | C71: =IF(B71<0.5,SQRT(0.5*B71),1-SQRT(0.5*(1-B71))) -> 0.72913675 | D71: =RAND() -> 0.51473312 | E71: =IF(D71<0.5,SQRT(0.5*D71),1-SQRT(0.5*(1-D71))) -> 0.50742164 | F71: =DCF!$H$7*(1+('A1'!F14+$C71*('A1'!F12-'A1'!F14))) -> 6439.8682 | G71: =F71*(1+('A1'!G14+$C71*('A1'!G12-'A1'!G14))) -> 7530.592 | H71: =G71*(1+('A1'!H14+$C71*('A1'!H12-'A1'!H14))) -> 8620.9296 | I71: =H71*(1+('A1'!I14+$C71*('A1'!I12-'A1'!I14))) -> 9617.7014 | J71: =I71*(1+('A1'!J14+$C71*('A1'!J12-'A1'!J14))) -> 10589.47 | K71: ='A1'!F21+$C71*('A1'!F19-'A1'!F21) -> 0.33989748 | L71: ='A1'!G21+$C71*('A1'!G19-'A1'!G21) -> 0.33031474 | M71: ='A1'!H21+$C71*('A1'!H19-'A1'!H21) -> 0.31802338 | N71: ='A1'!I21+$C71*('A1'!I19-'A1'!I21) -> 0.31302338 | O71: ='A1'!J21+$C71*('A1'!J19-'A1'!J21) -> 0.30802338 | P71: ='A1'!F28+$C71*('A1'!F26-'A1'!F28) -> 0.44177158 | Q71: ='A1'!G28+$C71*('A1'!G26-'A1'!G28) -> 0.43218885 | R71: ='A1'!H28+$C71*('A1'!H26-'A1'!H28) -> 0.4212518 | S71: ='A1'!I28+$C71*('A1'!I26-'A1'!I28) -> 0.41760611 | T71: ='A1'!J28+$C71*('A1'!J26-'A1'!J28) -> 0.41396043 | U71: =F71*(1-K71-P71) -> 1406.0225 | V71: =G71*(1-L71-Q71) -> 1788.4886 | W71: =H71*(1-M71-R71) -> 2247.6904 | X71: =I71*(1-N71-S71) -> 2590.7251 | Y71: =J71*(1-O71-T71) -> 2944.0441 | Z71: =F71*('A1'!F35+$C71*('A1'!F33-'A1'!F35)) -> 362.91437 | AA71: =G71*('A1'!G35+$C71*('A1'!G33-'A1'!G35)) -> 411.98839 | AB71: =H71*('A1'!H35+$C71*('A1'!H33-'A1'!H35)) -> 448.11157 | AC71: =I71*('A1'!I35+$C71*('A1'!I33-'A1'!I35)) -> 473.67525 | AD71: =J71*('A1'!J35+$C71*('A1'!J33-'A1'!J35)) -> 500.35625 | AE71: =F71*('A1'!F43+$C71*('A1'!F41-'A1'!F43)) -> 614.47461 | AF71: =G71*('A1'!G43+$C71*('A1'!G41-'A1'!G43)) -> 673.83898 | AG71: =H71*('A1'!H43+$C71*('A1'!H41-'A1'!H43)) -> 685.19333 | AH71: =I71*('A1'!I43+$C71*('A1'!I41-'A1'!I43)) -> 668.23995 | AI71: =J71*('A1'!J43+$C71*('A1'!J41-'A1'!J43)) -> 682.81128 | AJ71: =(U71-Z71)*DCF!$H$40 -> 252.43216 | AK71: =(V71-AA71)*DCF!$H$40 -> 333.11304 | AL71: =(W71-AB71)*DCF!$H$40 -> 435.49807 | AM71: =(X71-AC71)*DCF!$H$40 -> 512.32608 | AN71: =(Y71-AD71)*DCF!$H$40 -> 591.37246 | AO71: =(F71-DCF!$H$7)*DCF!$H$41 -> 356.46908 | AP71: =(G71-F71)*DCF!$H$41 -> 361.94293 | AQ71: =(H71-G71)*DCF!$H$41 -> 361.81481 | AR71: =(I71-H71)*DCF!$H$41 -> 330.76615 | AS71: =(J71-I71)*DCF!$H$41 -> 322.46911 | AT71: =(U71-Z71)*(1-DCF!$H$40)+Z71-AE71-AO71 -> 182.64662 | AU71: =(V71-AA71)*(1-DCF!$H$40)+AA71-AF71-AP71 -> 419.5936 | AV71: =(W71-AB71)*(1-DCF!$H$40)+AB71-AG71-AQ71 -> 765.18418 | AW71: =(X71-AC71)*(1-DCF!$H$40)+AC71-AH71-AR71 -> 1079.393 | AX71: =(Y71-AD71)*(1-DCF!$H$40)+AD71-AI71-AS71 -> 1347.3913 | AY71: =0.0925+$E71*(0.1125-0.0925) -> 0.10264843 | AZ71: =10+$E71*(14-10) -> 12.029687 | BA71: =SUMPRODUCT(AT71:AX71,(1+$AY71)^(-{1,2,3,4,5})) -> 2638.3201 | BB71: =Y71*$AZ71 -> 35415.928 | BC71: =BB71*(1+$AY71)^(-5) -> 21727.677 | BD71: =BA71+BC71 -> 24365.997 | BE71: =BD71-(DCF!$J$48-DCF!$J$51) -> 23803.857 | BF71: =BE71/DCF!$J$55 -> 960.61958
A72: 46 | B72: =RAND() -> 0.52066334 | C72: =IF(B72<0.5,SQRT(0.5*B72),1-SQRT(0.5*(1-B72))) -> 0.51044068 | D72: =RAND() -> 0.97373578 | E72: =IF(D72<0.5,SQRT(0.5*D72),1-SQRT(0.5*(1-D72))) -> 0.88540459 | F72: =DCF!$H$7*(1+('A1'!F14+$C72*('A1'!F12-'A1'!F14))) -> 6310.7893 | G72: =F72*(1+('A1'!G14+$C72*('A1'!G12-'A1'!G14))) -> 7172.6292 | H72: =G72*(1+('A1'!H14+$C72*('A1'!H12-'A1'!H14))) -> 8007.2169 | I72: =H72*(1+('A1'!I14+$C72*('A1'!I12-'A1'!I14))) -> 8775.4265 | J72: =I72*(1+('A1'!J14+$C72*('A1'!J12-'A1'!J14))) -> 9527.7513 | K72: ='A1'!F21+$C72*('A1'!F19-'A1'!F21) -> 0.35192576 | L72: ='A1'!G21+$C72*('A1'!G19-'A1'!G21) -> 0.34671695 | M72: ='A1'!H21+$C72*('A1'!H19-'A1'!H21) -> 0.33661254 | N72: ='A1'!I21+$C72*('A1'!I19-'A1'!I21) -> 0.33161254 | O72: ='A1'!J21+$C72*('A1'!J19-'A1'!J21) -> 0.32661254 | P72: ='A1'!F28+$C72*('A1'!F26-'A1'!F28) -> 0.44723898 | Q72: ='A1'!G28+$C72*('A1'!G26-'A1'!G28) -> 0.44203017 | R72: ='A1'!H28+$C72*('A1'!H26-'A1'!H28) -> 0.43437356 | S72: ='A1'!I28+$C72*('A1'!I26-'A1'!I28) -> 0.43182136 | T72: ='A1'!J28+$C72*('A1'!J26-'A1'!J28) -> 0.42926915 | U72: =F72*(1-K72-P72) -> 1267.429 | V72: =G72*(1-L72-Q72) -> 1515.2386 | W72: =H72*(1-M72-R72) -> 1833.7639 | X72: =I72*(1-N72-S72) -> 2075.9684 | Y72: =J72*(1-O72-T72) -> 2325.8985 | Z72: =F72*('A1'!F35+$C72*('A1'!F33-'A1'!F35)) -> 362.54094 | AA72: =G72*('A1'!G35+$C72*('A1'!G33-'A1'!G35)) -> 408.09099 | AB72: =H72*('A1'!H35+$C72*('A1'!H33-'A1'!H35)) -> 435.47371 | AC72: =I72*('A1'!I35+$C72*('A1'!I33-'A1'!I35)) -> 455.22272 | AD72: =J72*('A1'!J35+$C72*('A1'!J33-'A1'!J35)) -> 475.19385 | AE72: =F72*('A1'!F43+$C72*('A1'!F41-'A1'!F43)) -> 629.76115 | AF72: =G72*('A1'!G43+$C72*('A1'!G41-'A1'!G43)) -> 696.7103 | AG72: =H72*('A1'!H43+$C72*('A1'!H41-'A1'!H43)) -> 697.70545 | AH72: =I72*('A1'!I43+$C72*('A1'!I41-'A1'!I43)) -> 676.88881 | AI72: =J72*('A1'!J43+$C72*('A1'!J41-'A1'!J43)) -> 687.2803 | AJ72: =(U72-Z72)*DCF!$H$40 -> 218.9829 | AK72: =(V72-AA72)*DCF!$H$40 -> 267.92972 | AL72: =(W72-AB72)*DCF!$H$40 -> 338.38624 | AM72: =(X72-AC72)*DCF!$H$40 -> 392.22046 | AN72: =(Y72-AD72)*DCF!$H$40 -> 447.87052 | AO72: =(F72-DCF!$H$7)*DCF!$H$41 -> 313.63588 | AP72: =(G72-F72)*DCF!$H$41 -> 285.9907 | AQ72: =(H72-G72)*DCF!$H$41 -> 276.9474 | AR72: =(I72-H72)*DCF!$H$41 -> 254.9207 | AS72: =(J72-I72)*DCF!$H$41 -> 249.64949 | AT72: =(U72-Z72)*(1-DCF!$H$40)+Z72-AE72-AO72 -> 105.04904 | AU72: =(V72-AA72)*(1-DCF!$H$40)+AA72-AF72-AP72 -> 264.60786 | AV72: =(W72-AB72)*(1-DCF!$H$40)+AB72-AG72-AQ72 -> 520.72486 | AW72: =(X72-AC72)*(1-DCF!$H$40)+AC72-AH72-AR72 -> 751.93848 | AX72: =(Y72-AD72)*(1-DCF!$H$40)+AD72-AI72-AS72 -> 941.09818 | AY72: =0.0925+$E72*(0.1125-0.0925) -> 0.11020809 | AZ72: =10+$E72*(14-10) -> 13.541618 | BA72: =SUMPRODUCT(AT72:AX72,(1+$AY72)^(-{1,2,3,4,5})) -> 1742.7643 | BB72: =Y72*$AZ72 -> 31496.43 | BC72: =BB72*(1+$AY72)^(-5) -> 18674.087 | BD72: =BA72+BC72 -> 20416.852 | BE72: =BD72-(DCF!$J$48-DCF!$J$51) -> 19854.712 | BF72: =BE72/DCF!$J$55 -> 801.24933
A73: 47 | B73: =RAND() -> 0.13913651 | C73: =IF(B73<0.5,SQRT(0.5*B73),1-SQRT(0.5*(1-B73))) -> 0.26375795 | D73: =RAND() -> 0.59459949 | E73: =IF(D73<0.5,SQRT(0.5*D73),1-SQRT(0.5*(1-D73))) -> 0.54977755 | F73: =DCF!$H$7*(1+('A1'!F14+$C73*('A1'!F12-'A1'!F14))) -> 6165.1921 | G73: =F73*(1+('A1'!G14+$C73*('A1'!G12-'A1'!G14))) -> 6779.0214 | H73: =G73*(1+('A1'!H14+$C73*('A1'!H12-'A1'!H14))) -> 7350.4152 | I73: =H73*(1+('A1'!I14+$C73*('A1'!I12-'A1'!I14))) -> 7892.4217 | J73: =I73*(1+('A1'!J14+$C73*('A1'!J12-'A1'!J14))) -> 8432.761 | K73: ='A1'!F21+$C73*('A1'!F19-'A1'!F21) -> 0.36549331 | L73: ='A1'!G21+$C73*('A1'!G19-'A1'!G21) -> 0.36521815 | M73: ='A1'!H21+$C73*('A1'!H19-'A1'!H21) -> 0.35758057 | N73: ='A1'!I21+$C73*('A1'!I19-'A1'!I21) -> 0.35258057 | O73: ='A1'!J21+$C73*('A1'!J19-'A1'!J21) -> 0.34758057 | P73: ='A1'!F28+$C73*('A1'!F26-'A1'!F28) -> 0.45340605 | Q73: ='A1'!G28+$C73*('A1'!G26-'A1'!G28) -> 0.45313089 | R73: ='A1'!H28+$C73*('A1'!H26-'A1'!H28) -> 0.44917452 | S73: ='A1'!I28+$C73*('A1'!I26-'A1'!I28) -> 0.44785573 | T73: ='A1'!J28+$C73*('A1'!J26-'A1'!J28) -> 0.44653694 | U73: =F73*(1-K73-P73) -> 1116.5202 | V73: =G73*(1-L73-Q73) -> 1231.4157 | W73: =H73*(1-M73-R73) -> 1420.4303 | X73: =I73*(1-N73-S73) -> 1575.0408 | Y73: =J73*(1-O73-T73) -> 1736.1578 | Z73: =F73*('A1'!F35+$C73*('A1'!F33-'A1'!F35)) -> 361.78094 | AA73: =G73*('A1'!G35+$C73*('A1'!G33-'A1'!G35)) -> 402.41912 | AB73: =H73*('A1'!H35+$C73*('A1'!H33-'A1'!H35)) -> 419.69888 | AC73: =I73*('A1'!I35+$C73*('A1'!I33-'A1'!I35)) -> 432.78019 | AD73: =J73*('A1'!J35+$C73*('A1'!J33-'A1'!J35)) -> 445.54412 | AE73: =F73*('A1'!F43+$C73*('A1'!F41-'A1'!F43)) -> 645.64876 | AF73: =G73*('A1'!G43+$C73*('A1'!G41-'A1'!G43)) -> 717.00674 | AG73: =H73*('A1'!H43+$C73*('A1'!H41-'A1'!H43)) -> 703.93803 | AH73: =I73*('A1'!I43+$C73*('A1'!I41-'A1'!I43)) -> 676.92095 | AI73: =J73*('A1'!J43+$C73*('A1'!J41-'A1'!J43)) -> 681.10122 | AJ73: =(U73-Z73)*DCF!$H$40 -> 182.64691 | AK73: =(V73-AA73)*DCF!$H$40 -> 200.61717 | AL73: =(W73-AB73)*DCF!$H$40 -> 242.177 | AM73: =(X73-AC73)*DCF!$H$40 -> 276.42707 | AN73: =(Y73-AD73)*DCF!$H$40 -> 312.3285 | AO73: =(F73-DCF!$H$7)*DCF!$H$41 -> 265.32129 | AP73: =(G73-F73)*DCF!$H$41 -> 203.69151 | AQ73: =(H73-G73)*DCF!$H$41 -> 189.60982 | AR73: =(I73-H73)*DCF!$H$41 -> 179.85802 | AS73: =(J73-I73)*DCF!$H$41 -> 179.30479 | AT73: =(U73-Z73)*(1-DCF!$H$40)+Z73-AE73-AO73 -> 22.903251 | AU73: =(V73-AA73)*(1-DCF!$H$40)+AA73-AF73-AP73 -> 110.10028 | AV73: =(W73-AB73)*(1-DCF!$H$40)+AB73-AG73-AQ73 -> 284.70542 | AW73: =(X73-AC73)*(1-DCF!$H$40)+AC73-AH73-AR73 -> 441.83477 | AX73: =(Y73-AD73)*(1-DCF!$H$40)+AD73-AI73-AS73 -> 563.42326 | AY73: =0.0925+$E73*(0.1125-0.0925) -> 0.10349555 | AZ73: =10+$E73*(14-10) -> 12.19911 | BA73: =SUMPRODUCT(AT73:AX73,(1+$AY73)^(-{1,2,3,4,5})) -> 965.35764 | BB73: =Y73*$AZ73 -> 21179.58 | BC73: =BB73*(1+$AY73)^(-5) -> 12943.878 | BD73: =BA73+BC73 -> 13909.236 | BE73: =BD73-(DCF!$J$48-DCF!$J$51) -> 13347.096 | BF73: =BE73/DCF!$J$55 -> 538.6304
A74: 48 | B74: =RAND() -> 0.53303622 | C74: =IF(B74<0.5,SQRT(0.5*B74),1-SQRT(0.5*(1-B74))) -> 0.51680036 | D74: =RAND() -> 0.31233296 | E74: =IF(D74<0.5,SQRT(0.5*D74),1-SQRT(0.5*(1-D74))) -> 0.39517905 | F74: =DCF!$H$7*(1+('A1'!F14+$C74*('A1'!F12-'A1'!F14))) -> 6314.5429 | G74: =F74*(1+('A1'!G14+$C74*('A1'!G12-'A1'!G14))) -> 7182.9192 | H74: =G74*(1+('A1'!H14+$C74*('A1'!H12-'A1'!H14))) -> 8024.6427 | I74: =H74*(1+('A1'!I14+$C74*('A1'!I12-'A1'!I14))) -> 8799.1173 | J74: =I74*(1+('A1'!J14+$C74*('A1'!J12-'A1'!J14))) -> 9557.3903 | K74: ='A1'!F21+$C74*('A1'!F19-'A1'!F21) -> 0.35157598 | L74: ='A1'!G21+$C74*('A1'!G19-'A1'!G21) -> 0.34623997 | M74: ='A1'!H21+$C74*('A1'!H19-'A1'!H21) -> 0.33607197 | N74: ='A1'!I21+$C74*('A1'!I19-'A1'!I21) -> 0.33107197 | O74: ='A1'!J21+$C74*('A1'!J19-'A1'!J21) -> 0.32607197 | P74: ='A1'!F28+$C74*('A1'!F26-'A1'!F28) -> 0.44707999 | Q74: ='A1'!G28+$C74*('A1'!G26-'A1'!G28) -> 0.44174398 | R74: ='A1'!H28+$C74*('A1'!H26-'A1'!H28) -> 0.43399198 | S74: ='A1'!I28+$C74*('A1'!I26-'A1'!I28) -> 0.43140798 | T74: ='A1'!J28+$C74*('A1'!J26-'A1'!J28) -> 0.42882397 | U74: =F74*(1-K74-P74) -> 1271.3955 | V74: =G74*(1-L74-Q74) -> 1522.8941 | W74: =H74*(1-M74-R74) -> 1845.1547 | X74: =I74*(1-N74-S74) -> 2089.9668 | Y74: =J74*(1-O74-T74) -> 2342.5551 | Z74: =F74*('A1'!F35+$C74*('A1'!F33-'A1'!F35)) -> 362.55578 | AA74: =G74*('A1'!G35+$C74*('A1'!G33-'A1'!G35)) -> 408.21964 | AB74: =H74*('A1'!H35+$C74*('A1'!H33-'A1'!H35)) -> 435.86004 | AC74: =I74*('A1'!I35+$C74*('A1'!I33-'A1'!I35)) -> 455.78016 | AD74: =J74*('A1'!J35+$C74*('A1'!J33-'A1'!J35)) -> 475.9427 | AE74: =F74*('A1'!F43+$C74*('A1'!F41-'A1'!F43)) -> 629.33256 | AF74: =G74*('A1'!G43+$C74*('A1'!G41-'A1'!G43)) -> 696.11097 | AG74: =H74*('A1'!H43+$C74*('A1'!H41-'A1'!H43)) -> 697.43765 | AH74: =I74*('A1'!I43+$C74*('A1'!I41-'A1'!I43)) -> 676.7576 | AI74: =J74*('A1'!J43+$C74*('A1'!J41-'A1'!J43)) -> 687.29093 | AJ74: =(U74-Z74)*DCF!$H$40 -> 219.93921 | AK74: =(V74-AA74)*DCF!$H$40 -> 269.75122 | AL74: =(W74-AB74)*DCF!$H$40 -> 341.0493 | AM74: =(X74-AC74)*DCF!$H$40 -> 395.47317 | AN74: =(Y74-AD74)*DCF!$H$40 -> 451.72021 | AO74: =(F74-DCF!$H$7)*DCF!$H$41 -> 314.88147 | AP74: =(G74-F74)*DCF!$H$41 -> 288.15972 | AQ74: =(H74-G74)*DCF!$H$41 -> 279.31535 | AR74: =(I74-H74)*DCF!$H$41 -> 256.99963 | AS74: =(J74-I74)*DCF!$H$41 -> 251.62332 | AT74: =(U74-Z74)*(1-DCF!$H$40)+Z74-AE74-AO74 -> 107.24227 | AU74: =(V74-AA74)*(1-DCF!$H$40)+AA74-AF74-AP74 -> 268.87219 | AV74: =(W74-AB74)*(1-DCF!$H$40)+AB74-AG74-AQ74 -> 527.35238 | AW74: =(X74-AC74)*(1-DCF!$H$40)+AC74-AH74-AR74 -> 760.73642 | AX74: =(Y74-AD74)*(1-DCF!$H$40)+AD74-AI74-AS74 -> 951.92067 | AY74: =0.0925+$E74*(0.1125-0.0925) -> 0.10040358 | AZ74: =10+$E74*(14-10) -> 11.580716 | BA74: =SUMPRODUCT(AT74:AX74,(1+$AY74)^(-{1,2,3,4,5})) -> 1824.0907 | BB74: =Y74*$AZ74 -> 27128.466 | BC74: =BB74*(1+$AY74)^(-5) -> 16813.776 | BD74: =BA74+BC74 -> 18637.867 | BE74: =BD74-(DCF!$J$48-DCF!$J$51) -> 18075.727 | BF74: =BE74/DCF!$J$55 -> 729.45728
A75: 49 | B75: =RAND() -> 0.33495729 | C75: =IF(B75<0.5,SQRT(0.5*B75),1-SQRT(0.5*(1-B75))) -> 0.40924155 | D75: =RAND() -> 0.65801756 | E75: =IF(D75<0.5,SQRT(0.5*D75),1-SQRT(0.5*(1-D75))) -> 0.58648915 | F75: =DCF!$H$7*(1+('A1'!F14+$C75*('A1'!F12-'A1'!F14))) -> 6251.0595 | G75: =F75*(1+('A1'!G14+$C75*('A1'!G12-'A1'!G14))) -> 7009.8521 | H75: =G75*(1+('A1'!H14+$C75*('A1'!H12-'A1'!H14))) -> 7733.2786 | I75: =H75*(1+('A1'!I14+$C75*('A1'!I12-'A1'!I14))) -> 8404.7727 | J75: =I75*(1+('A1'!J14+$C75*('A1'!J12-'A1'!J14))) -> 9065.7821 | K75: ='A1'!F21+$C75*('A1'!F19-'A1'!F21) -> 0.35749171 | L75: ='A1'!G21+$C75*('A1'!G19-'A1'!G21) -> 0.35430688 | M75: ='A1'!H21+$C75*('A1'!H19-'A1'!H21) -> 0.34521447 | N75: ='A1'!I21+$C75*('A1'!I19-'A1'!I21) -> 0.34021447 | O75: ='A1'!J21+$C75*('A1'!J19-'A1'!J21) -> 0.33521447 | P75: ='A1'!F28+$C75*('A1'!F26-'A1'!F28) -> 0.44976896 | Q75: ='A1'!G28+$C75*('A1'!G26-'A1'!G28) -> 0.44658413 | R75: ='A1'!H28+$C75*('A1'!H26-'A1'!H28) -> 0.44044551 | S75: ='A1'!I28+$C75*('A1'!I26-'A1'!I28) -> 0.4383993 | T75: ='A1'!J28+$C75*('A1'!J26-'A1'!J28) -> 0.43635309 | U75: =F75*(1-K75-P75) -> 1204.825 | V75: =G75*(1-L75-Q75) -> 1395.7245 | W75: =H75*(1-M75-R75) -> 1657.5511 | X75: =I75*(1-N75-S75) -> 1860.701 | Y75: =J75*(1-O75-T75) -> 2070.9187 | Z75: =F75*('A1'!F35+$C75*('A1'!F33-'A1'!F35)) -> 362.2726 | AA75: =G75*('A1'!G35+$C75*('A1'!G33-'A1'!G35)) -> 405.9236 | AB75: =H75*('A1'!H35+$C75*('A1'!H33-'A1'!H35)) -> 429.18415 | AC75: =I75*('A1'!I35+$C75*('A1'!I33-'A1'!I35)) -> 446.20183 | AD75: =J75*('A1'!J35+$C75*('A1'!J33-'A1'!J35)) -> 463.16266 | AE75: =F75*('A1'!F43+$C75*('A1'!F41-'A1'!F43)) -> 636.45268 | AF75: =G75*('A1'!G43+$C75*('A1'!G41-'A1'!G43)) -> 705.72769 | AG75: =H75*('A1'!H43+$C75*('A1'!H41-'A1'!H43)) -> 701.22699 | AH75: =I75*('A1'!I43+$C75*('A1'!I41-'A1'!I43)) -> 678.06803 | AI75: =J75*('A1'!J43+$C75*('A1'!J41-'A1'!J43)) -> 686.06707 | AJ75: =(U75-Z75)*DCF!$H$40 -> 203.89768 | AK75: =(V75-AA75)*DCF!$H$40 -> 239.53183 | AL75: =(W75-AB75)*DCF!$H$40 -> 297.26481 | AM75: =(X75-AC75)*DCF!$H$40 -> 342.30879 | AN75: =(Y75-AD75)*DCF!$H$40 -> 389.07697 | AO75: =(F75-DCF!$H$7)*DCF!$H$41 -> 293.8153 | AP75: =(G75-F75)*DCF!$H$41 -> 251.79575 | AQ75: =(H75-G75)*DCF!$H$41 -> 240.05998 | AR75: =(I75-H75)*DCF!$H$41 -> 222.82683 | AS75: =(J75-I75)*DCF!$H$41 -> 219.34763 | AT75: =(U75-Z75)*(1-DCF!$H$40)+Z75-AE75-AO75 -> 70.659324 | AU75: =(V75-AA75)*(1-DCF!$H$40)+AA75-AF75-AP75 -> 198.66927 | AV75: =(W75-AB75)*(1-DCF!$H$40)+AB75-AG75-AQ75 -> 418.99935 | AW75: =(X75-AC75)*(1-DCF!$H$40)+AC75-AH75-AR75 -> 617.49731 | AX75: =(Y75-AD75)*(1-DCF!$H$40)+AD75-AI75-AS75 -> 776.42705 | AY75: =0.0925+$E75*(0.1125-0.0925) -> 0.10422978 | AZ75: =10+$E75*(14-10) -> 12.345957 | BA75: =SUMPRODUCT(AT75:AX75,(1+$AY75)^(-{1,2,3,4,5})) -> 1426.3913 | BB75: =Y75*$AZ75 -> 25567.473 | BC75: =BB75*(1+$AY75)^(-5) -> 15573.654 | BD75: =BA75+BC75 -> 17000.045 | BE75: =BD75-(DCF!$J$48-DCF!$J$51) -> 16437.905 | BF75: =BE75/DCF!$J$55 -> 663.36196
