Workbook

Sheet Relative Valuation
A1: Peer Company | B1: Capitaline Code | C1: Company Name | D1: Net Sales | E1: Operating Profit | F1: Depreciation | G1: Extraordinary Items | H1: Earnings Per Share(Adj)-Unit Curr | I1: Book Value(Adj)-Unit Curr | J1: Minority Interest | K1: Total Debt | L1: Cash and Bank | M1: Latest No of Equity Shares | N1: 52 Week High - Unit Curr. (BSE) | O1: 52 Week Low - Unit Curr. (BSE) | P1: Market Capitalisation (BSE) | Q1: Latest Market Price - Unit Curr. (BSE) | R1: BSE Sensex | S1: Enterprise Value | T1: Adjusted EBIT | U1: Adjusted EBITDA | V1: Sector Specific parameter (If any) | X1: EV/Sales | Y1: EV/EBIT | Z1: EV/EBITDA | AA1: P/E | AB1: P/B | AC1: EV/Sector specific Ratio
A2: 1 | B2: N/A | C2: Granules India | D2: 4481.61 | E2: 988.91 | F2: 225.5 | G2: 20.45 | H2: 20.68 | I2: 153.19 | J2: 0 | K2: 1454.75 | L2: 596.38 | M2: 247796921 | N2: 910 | O2: 438.3 | P2: =M2*Q2/10000000 -> 22180.302 | Q2: 895.1 | R2: 0.8321 | S2: =P2+(K2-L2)+J2 -> 23038.672 | T2: =E2-G2 -> 968.46 | U2: =T2+F2 -> 1193.96 | X2: =S2/D2 -> 5.1407134 | Y2: =S2/T2 -> 23.788977 | Z2: =S2/U2 -> 19.296017 | AA2: =Q2/H2 -> 43.283366 | AB2: =Q2/I2 -> 5.8430707
A3: 2 | B3: N/A | C3: Strides Pharma | D3: 4565.34 | E3: 4116.14 | F3: 192.26 | G3: 69.88 | H3: 389.9 | I3: 276.88 | J3: 34.63 | K3: 1879.63 | L3: 136.78 | M3: 92172714 | N3: 1231 | O3: 768.65 | P3: =M3*Q3/10000000 -> 9872.6194 | Q3: 1071.1 | R3: 0.5601 | S3: =P3+(K3-L3)+J3 -> 11650.099 | T3: =E3-G3 -> 4046.26 | U3: =T3+F3 -> 4238.52 | X3: =S3/D3 -> 2.551858 | Y3: =S3/T3 -> 2.8792266 | Z3: =S3/U3 -> 2.7486244 | AA3: =Q3/H3 -> 2.7471146 | AB3: =Q3/I3 -> 3.8684629
A4: 3 | B4: N/A | C4: FDC | D4: 2108.12 | E4: 415.46 | F4: 53.73 | G4: 7.73 | H4: 16.39 | I4: 140.11 | J4: 0 | K4: 21.17 | L4: 52.77 | M4: 162810084 | N4: 527.8 | O4: 312.95 | P4: =M4*Q4/10000000 -> 6864.8872 | Q4: 421.65 | R4: 0.4593 | S4: =P4+(K4-L4)+J4 -> 6833.2872 | T4: =E4-G4 -> 407.73 | U4: =T4+F4 -> 461.46 | X4: =S4/D4 -> 3.2414128 | Y4: =S4/T4 -> 16.759344 | Z4: =S4/U4 -> 14.807973 | AA4: =Q4/H4 -> 25.726052 | AB4: =Q4/I4 -> 3.0094212
A5: 4 | B5: N/A | C5: Orchid Pharma | D5: 921.93 | E5: 145.04 | F5: 34.55 | G5: -0.32 | H5: 19.65 | I5: 236.35 | J5: 0 | K5: 174.61 | L5: 179.63 | M5: 50719105 | N5: 1133 | O5: 480 | P5: =M5*Q5/10000000 -> 5340.4682 | Q5: 1052.95 | R5: 1.2321 | S5: =P5+(K5-L5)+J5 -> 5335.4482 | T5: =E5-G5 -> 145.36 | U5: =T5+F5 -> 179.91 | X5: =S5/D5 -> 5.7872595 | Y5: =S5/T5 -> 36.705064 | Z5: =S5/U5 -> 29.656207 | AA5: =Q5/H5 -> 53.585242 | AB5: =Q5/I5 -> 4.4550455
A6: 5 | B6: N/A | C6: RPG Life Sciences | D6: 707.52 | E6: 177.45 | F6: 21.48 | G6: 5.5 | H6: 69.64 | I6: 366.05 | J6: 0 | K6: 20 | L6: 191.56 | M6: 16539015 | N6: 3082 | O6: 1733 | P6: =M6*Q6/10000000 -> 4532.0209 | Q6: 2740.2 | R6: 0.8112 | S6: =P6+(K6-L6)+J6 -> 4360.4609 | T6: =E6-G6 -> 171.95 | U6: =T6+F6 -> 193.43 | X6: =S6/D6 -> 6.1630214 | Y6: =S6/T6 -> 25.358889 | Z6: =S6/U6 -> 22.542837 | AA6: =Q6/H6 -> 39.348076 | AB6: =Q6/I6 -> 7.4858626
A7: 6 | B7: N/A | C7: Indoco Remedies | D7: 1664.92 | E7: 105.7 | F7: 113.84 | G7: 1.15 | H7: -7.99 | I7: 110.79 | J7: -3.62 | K7: 993.57 | L7: 17.07 | M7: 92303605 | N7: 332.2 | O7: 162.19 | P7: =M7*Q7/10000000 -> 2294.0215 | Q7: 248.53 | R7: 0.8164 | S7: =P7+(K7-L7)+J7 -> 3266.9015 | T7: =E7-G7 -> 104.55 | U7: =T7+F7 -> 218.39 | X7: =S7/D7 -> 1.9621973 | Y7: =S7/T7 -> 31.247264 | Z7: =S7/U7 -> 14.959025 | AA7: =Q7/H7 -> -31.105131 | AB7: =Q7/I7 -> 2.243253
W9: Average | X9: =AVERAGE(X2:X7) -> 4.1410771 | Y9: =AVERAGE(Y2:Y7) -> 22.789794 | Z9: =AVERAGE(Z2:Z7) -> 17.335114 | AA9: =AVERAGE(AA2:AA7) -> 22.26412 | AB9: =AVERAGE(AB2:AB7) -> 4.484186
J10: ` | W10: Median | X10: =MEDIAN(X2:X7) -> 4.1910631 | Y10: =MEDIAN(Y2:Y7) -> 24.573933 | Z10: =MEDIAN(Z2:Z7) -> 17.127521 | AA10: =MEDIAN(AA2:AA7) -> 32.537064 | AB10: =MEDIAN(AB2:AB7) -> 4.1617542
W11: 25th percentile | X11: =QUARTILE(X2:X7,1) -> 2.7242467 | Y11: =QUARTILE(Y2:Y7,1) -> 18.516752 | Z11: =QUARTILE(Z2:Z7,1) -> 14.845736 | AA11: =QUARTILE(AA2:AA7,1) -> 8.4918491 | AB11: =QUARTILE(AB2:AB7,1) -> 3.2241816
W12: 75th percentile | X12: =QUARTILE(X2:X7,3) -> 5.625623 | Y12: =QUARTILE(Y2:Y7,3) -> 29.77517 | Z12: =QUARTILE(Z2:Z7,3) -> 21.731132 | AA12: =QUARTILE(AA2:AA7,3) -> 42.299543 | AB12: =QUARTILE(AB2:AB7,3) -> 5.4960644
A13: Target company | B13: N/A | C13: Unichem Laboratories Ltd | D13: 2201.85 | E13: 449.09 | F13: 125.12 | G13: 170.95 | H13: 35.91 | I13: 386 | J13: 0 | K13: 500.15 | L13: 294.7 | M13: 70405750 | N13: 687.2 | O13: 280 | P13: =M13*Q13/10000000 -> 4093.0383 | Q13: 581.35 | R13: 1.1662 | S13: =P13+(K13-L13)+J13 -> 4298.4883 | T13: =E13-G13 -> 278.14 | U13: =T13+F13 -> 403.26
W14: Implied Enterprise value (M) | X14: =X10*$D$13 -> 9228.0923 | Y14: =Y10*$T$13 -> 6834.9936 | Z14: =Z10*$U$13 -> 6906.8441
W15: Implied Enterprise value (25th) | X15: =X11*$D$13 -> 5998.3826 | Y15: =Y11*$D$13 -> 40771.11 | Z15: =Z11*$D$13 -> 32688.084
W16: Implied Enterprise value (75th) | X16: =X12*$D$13 -> 12386.778 | Y16: =Y12*$D$13 -> 65560.459 | Z16: =Z12*$D$13 -> 47848.692
W18: Implied Eq value (M) | X18: =X14-($K$13-$L$13)-$J$13 -> 9022.6423 | Y18: =Y14-($K$13-$L$13)-$J$13 -> 6629.5436 | Z18: =Z14-($K$13-$L$13)-$J$13 -> 6701.3941
W19: Implied Eq value (25th) | X19: =X15-($K$13-$L$13)-$J$13 -> 5792.9326 | Y19: =Y15-($K$13-$L$13)-$J$13 -> 40565.66 | Z19: =Z15-($K$13-$L$13)-$J$13 -> 32482.634
W20: Implied Eq value (75th) | X20: =X16-($K$13-$L$13)-$J$13 -> 12181.328 | Y20: =Y16-($K$13-$L$13)-$J$13 -> 65355.009 | Z20: =Z16-($K$13-$L$13)-$J$13 -> 47643.242
W22: Per share value (M) | X22: =(X18/($M$13/10000000)) -> 1281.5207 | Y22: =(Y18/($M$13/10000000)) -> 941.61963 | Z22: =(Z18/($M$13/10000000)) -> 951.82483 | AA22: =AA10*$H$13 -> 1168.406 | AB22: =AB10*$I$13 -> 1606.4371
W23: Per share value (25th) | X23: =(X19/($M$13/10000000)) -> 822.79254 | Y23: =(Y19/($M$13/10000000)) -> 5761.6971 | Z23: =(Z19/($M$13/10000000)) -> 4613.6337 | AA23: =AA11*$H$13 -> 304.9423 | AB23: =AB11*$I$13 -> 1244.5341
W24: Per share value (75th) | X24: =(X20/($M$13/10000000)) -> 1730.161 | Y24: =(Y20/($M$13/10000000)) -> 9282.6238 | Z24: =(Z20/($M$13/10000000)) -> 6766.9533 | AA24: =AA12*$H$13 -> 1518.9766 | AB24: =AB12*$I$13 -> 2121.4809
W26: Current market price of Target | X26: =Q13 -> 581.35

Sheet WACC
A1: Data from Capitaline
A2: Date | B2: Unichem price | C2: Unichem Return | D2: Sensex | E2: Sensex return | G2: Adjusted Regression Beta | H2: 2 years | I2: 5 years | M2: Risk-free rate | O2: Source | R2: Source | S2: Capital | T2: Weight | U2: Cost | V2: Product
A3: 44287 | B3: 314.05 | D3: 50029.83 | G3: Levered Raw Beta | H3: 2 years | I3: 5 years | M3: 10 Yr G-Bonds | N3: 0.068 | O3: https://www.worldgovernmentbonds.com | R3: Equity (M Cap) | S3: 4093.0383 | T3: =S3/$S$7 -> 0.89111049 | U3: =N3+(K20*N12) -> 0.11094764 | V3: =T3*U3 -> 0.098866604
A4: 44295 | B4: 325 | C4: =B3/B4-1 -> -0.033692308 | D4: 49591.32 | E4: =D3/D4-1 -> 0.0088424749 | G4: Slope | H4: =SLOPE(C159:C263,E159:E263) -> 1.1572726 | I4: =SLOPE(C4:C263,E4:E263) -> 0.65283188 | R4: Debt | S4: 500.15 | T4: =S4/$S$7 -> 0.10888951 | U4: =S15 -> 0.063161052 | V4: =T4*U4 -> 0.0068775757
A5: 44302 | B5: 320.3 | C5: =B4/B5-1 -> 0.014673743 | D5: 48832.03 | E5: =D4/D5-1 -> 0.015549016 | G5: Weight | H5: 0.67 | I5: 0.67 | R5: Preference Share | S5: 0 | T5: =S5/$S$7 -> 0 | U5: 0 | V5: =T5*U5 -> 0
A6: 44309 | B6: 338.25 | C6: =B5/B6-1 -> -0.053067258 | D6: 47878.45 | E6: =D5/D6-1 -> 0.019916685 | G6: Adjusted regression Beta | H6: =(H4*H5)+(1*(1-H5)) -> 1.1053726 | I6: =(I4*I5)+(1*(1-I5)) -> 0.76739736 | R6: Non- controlling Interest | S6: 0 | T6: =S6/$S$7 -> 0 | U6: =U3 -> 0.11094764 | V6: =T6*U6 -> 0
A7: 44316 | B7: 320.5 | C7: =B6/B7-1 -> 0.055382215 | D7: 48782.36 | E7: =D6/D7-1 -> -0.018529444 | O7: Source | R7: Total | S7: 4593.1883
A8: 44323 | B8: 330.35 | C8: =B7/B8-1 -> -0.029816861 | D8: 49206.47 | E8: =D7/D8-1 -> -0.0086189885 | M8: BSE Sensex return for 10 years | N8: 0.1221 | O8: https://www.bseindices.com/Downloads/Factsheet/Factsheet_BSESENSEX_May2026.pdf | R8: WACC | V8: =SUM(V3:V6) -> 0.10574418
A9: 44330 | B9: 335.2 | C9: =B8/B9-1 -> -0.014468974 | D9: 48732.55 | E9: =D8/D9-1 -> 0.0097249169 | G9: Bottom up Beta (fundamental beta): Data from Capitaline
A10: 44337 | B10: 359.6 | C10: =B9/B10-1 -> -0.06785317 | D10: 50540.48 | E10: =D9/D10-1 -> -0.03577192 | G10: Company Name (Same business) | H10: Total Debt | I10: Market Cap | J10: Sensex beta | K10: Unlevered beta
A11: 44344 | B11: 360.95 | C11: =B10/B11-1 -> -0.0037401302 | D11: 51422.88 | E11: =D10/D11-1 -> -0.017159677 | G11: ='Relative Valuation'!C2 -> Granules India | H11: ='Relative Valuation'!K2 -> 1454.75 | I11: ='Relative Valuation'!P2 -> 22180.302 | J11: ='Relative Valuation'!R2 -> 0.8321 | K11: =J11/(1+((H11/I11)*(1-0.3))) -> 0.79557421 | O11: Source | R11: Source
A12: 44351 | B12: 325.35 | C12: =B11/B12-1 -> 0.10942062 | D12: 52100.05 | E12: =D11/D12-1 -> -0.012997492 | G12: ='Relative Valuation'!C3 -> Strides Pharma | H12: ='Relative Valuation'!K3 -> 1879.63 | I12: ='Relative Valuation'!P3 -> 9872.6194 | J12: ='Relative Valuation'!R3 -> 0.5601 | K12: =J12/(1+((H12/I12)*(1-0.3))) -> 0.49423275 | M12: Historical Risk Premiun | N12: =N8-N3 -> 0.0541 | R12: Historical Risk Premium = 10Y Sensex return - risk-free rate
A13: 44358 | B13: 329.9 | C13: =B12/B13-1 -> -0.013792058 | D13: 52474.76 | E13: =D12/D13-1 -> -0.0071407663 | G13: ='Relative Valuation'!C4 -> FDC | H13: ='Relative Valuation'!K4 -> 21.17 | I13: ='Relative Valuation'!P4 -> 6864.8872 | J13: ='Relative Valuation'!R4 -> 0.4593 | K13: =J13/(1+((H13/I13)*(1-0.3))) -> 0.45831066 | R13: The one-year LIBOR rate is currently 6.04143%
A14: 44365 | B14: 320.45 | C14: =B13/B14-1 -> 0.02948978 | D14: 52344.45 | E14: =D13/D14-1 -> 0.0024894712 | G14: ='Relative Valuation'!C5 -> Orchid Pharma | H14: ='Relative Valuation'!K5 -> 174.61 | I14: ='Relative Valuation'!P5 -> 5340.4682 | J14: ='Relative Valuation'!R5 -> 1.2321 | K14: =J14/(1+((H14/I14)*(1-0.3))) -> 1.2045319 | R14: Cost of debt = Finance cost / Total financial obligations | S14: =0.0604143+0.03 -> 0.0904143
A15: 44372 | B15: 322.35 | C15: =B14/B15-1 -> -0.0058942144 | D15: 52925.04 | E15: =D14/D15-1 -> -0.010970044 | G15: ='Relative Valuation'!C6 -> RPG Life Sciences | H15: ='Relative Valuation'!K6 -> 20 | I15: ='Relative Valuation'!P6 -> 4532.0209 | J15: ='Relative Valuation'!R6 -> 0.8112 | K15: =J15/(1+((H15/I15)*(1-0.3))) -> 0.80870182 | R15: Finance cost/Total Debt | S15: ='Reform Stat, Ratio, GROWTH'!AJ14/'Reform Stat, Ratio, GROWTH'!AJ67 -> 0.063161052
A16: 44379 | B16: 329 | C16: =B15/B16-1 -> -0.020212766 | D16: 52484.67 | E16: =D15/D16-1 -> 0.00839045 | G16: ='Relative Valuation'!C7 -> Indoco Remedies | H16: ='Relative Valuation'!K7 -> 993.57 | I16: ='Relative Valuation'!P7 -> 2294.0215 | J16: ='Relative Valuation'!R7 -> 0.8164 | K16: =J16/(1+((H16/I16)*(1-0.3))) -> 0.62646807
A17: 44386 | B17: 327.8 | C17: =B16/B17-1 -> 0.0036607688 | D17: 52386.19 | E17: =D16/D17-1 -> 0.0018798848 | G17: Av unlevered beta | K17: =AVERAGE(K11:K16) -> 0.73130324
A18: 44393 | B18: 336.15 | C18: =B17/B18-1 -> -0.024840101 | D18: 53140.06 | E18: =D17/D18-1 -> -0.014186473
A19: 44400 | B19: 334.65 | C19: =B18/B19-1 -> 0.0044822949 | D19: 52975.8 | E19: =D18/D19-1 -> 0.0031006611
A20: 44407 | B20: 332.85 | C20: =B19/B20-1 -> 0.0054078414 | D20: 52586.84 | E20: =D19/D20-1 -> 0.0073965273 | G20: Relevered beta of Unichem Laboratories Ltd | K20: =K17*(1+(H21/I21)*(1-0.3)) -> 0.79385651
A21: 44414 | B21: 299.75 | C21: =B20/B21-1 -> 0.11042535 | D21: 54277.72 | E21: =D20/D21-1 -> -0.031152377 | G21: Target company | H21: 500.15 | I21: 4093.0383
A22: 44421 | B22: 289.65 | C22: =B21/B22-1 -> 0.03486967 | D22: 55437.29 | E22: =D21/D22-1 -> -0.020916787 | G22: Regression beta (2-year adjusted) | H22: 1.1023214 | I22: Regression beta (5-year adjusted) | J22: 0.76220242
A23: 44428 | B23: 270.35 | C23: =B22/B23-1 -> 0.07138894 | D23: 55329.32 | E23: =D22/D23-1 -> 0.0019514066 | G23: WACC selection | H23: Bottom-up beta, as in professor reference model
A24: 44435 | B24: 284.2 | C24: =B23/B24-1 -> -0.048733286 | D24: 56124.72 | E24: =D23/D24-1 -> -0.014172008 | G24: Data note | H24: Capitaline weekly Unichem + Sensex data supplied; regression beta is shown, while bottom-up beta is retained as the selected WACC method to match the professor reference model. | K24: 1.16
A25: 44442 | B25: 285.5 | C25: =B24/B25-1 -> -0.0045534151 | D25: 58129.95 | E25: =D24/D25-1 -> -0.034495643
A26: 44448 | B26: 273.75 | C26: =B25/B26-1 -> 0.042922374 | D26: 58305.07 | E26: =D25/D26-1 -> -0.0030035124
A27: 44456 | B27: 274.05 | C27: =B26/B27-1 -> -0.0010946907 | D27: 59015.89 | E27: =D26/D27-1 -> -0.012044553
A28: 44463 | B28: 254.75 | C28: =B27/B28-1 -> 0.07576055 | D28: 60048.47 | E28: =D27/D28-1 -> -0.017195775
A29: 44470 | B29: 275.35 | C29: =B28/B29-1 -> -0.074813873 | D29: 58765.58 | E29: =D28/D29-1 -> 0.021830636
A30: 44477 | B30: 264.9 | C30: =B29/B30-1 -> 0.039448849 | D30: 60059.06 | E30: =D29/D30-1 -> -0.021536801
A31: 44483 | B31: 263.65 | C31: =B30/B31-1 -> 0.0047411341 | D31: 61305.95 | E31: =D30/D31-1 -> -0.020338809
A32: 44491 | B32: 245.9 | C32: =B31/B32-1 -> 0.072183815 | D32: 60821.62 | E32: =D31/D32-1 -> 0.0079631223
A33: 44498 | B33: 241.6 | C33: =B32/B33-1 -> 0.017798013 | D33: 59306.93 | E33: =D32/D33-1 -> 0.025539848
A34: 44504 | B34: 223.1 | C34: =B33/B34-1 -> 0.082922456 | D34: 60067.62 | E34: =D33/D34-1 -> -0.012663894
A35: 44512 | B35: 206.9 | C35: =B34/B35-1 -> 0.078298695 | D35: 60686.69 | E35: =D34/D35-1 -> -0.010201084
A36: 44518 | B36: 203.3 | C36: =B35/B36-1 -> 0.017707821 | D36: 59636.01 | E36: =D35/D36-1 -> 0.017618214
... A263: 46108 | B263: 283.8 | C263: =B262/B263-1 -> 0.10306554 | D263: 73583.22 | E263: =D262/D263-1 -> 0.012907019
A264: 44393 | B264: 184.05 | D264: 53140.06
A265: 44386 | B265: 182.1 | D265: 52386.19
A266: 44379 | B266: 182.35 | D266: 52484.67
A267: 44372 | B267: 182.7 | D267: 52925.04
A268: 44365 | B268: 185 | D268: 52344.45
A269: 44358 | B269: 191.55 | D269: 52474.76
A270: 44351 | B270: 193.55 | D270: 52100.05
A271: 44344 | B271: 191.95 | D271: 51422.88
A272: 44337 | B272: 187.1 | D272: 50540.48
A273: 44330 | B273: 181.45 | D273: 48732.55
A274: 44323 | B274: 183.35 | D274: 49206.47
A275: 44316 | B275: 177.9 | D275: 48782.36
... A290: 44211 | B290: 200.15 | D290: 49034.67

Sheet Raw BS
A1: Finance >>Balance Sheet IND (Consolidated)>>Unichem Laboratories Ltd (Curr. in ₹ crore)
A2: Year | B2: 201703 | C2: 201803 | D2: 201903 | E2: 202003 | F2: 202103 | G2: 202203 | H2: 202303 | I2: 202403 | J2: 202503 | K2: 202603
A3: Non-Current Assets:
A4: Fixed Assets | B4: 737.19 | C4: 812.6 | D4: 898.68 | E4: 1147.21 | F4: 1447.92 | G4: 1483.85 | H4: 1404.12 | I4: 1375.11 | J4: 1330.24 | K4: 1312.72 | M4: Note:
A5: Property, Plant and Equipment | B5: 484.03 | C5: 572.44 | D5: 804.5 | E5: 815.2 | F5: 832.81 | G5: 924.49 | H5: 1196.12 | I5: 1125.2 | J5: 1211.01 | K5: 1135.9 | M5: If 2026 data is not avialble on capitaline then check the financial statements available on the website of the company
A6: Capital Work in Progress | B6: 249.98 | C6: 238.15 | D6: 92.39 | E6: 330.47 | F6: 567.5 | G6: 493.81 | H6: 147.45 | I6: 122.71 | J6: 30.67 | K6: 100.14
A7: Right-of-Use Assets | B7: 0 | C7: 0 | D7: 0 | E7: 0 | F7: 0 | G7: 64 | H7: 58.99 | I7: 69.29 | J7: 68.31 | K7: 67.8
A8: Intangible Assets | B8: 3.19 | C8: 2.01 | D8: 1.79 | E8: 1.55 | F8: 1.55 | G8: 1.55 | H8: 1.55 | I8: 57.91 | J8: 20.25 | K8: 8.88
A9: Intangible Assets under Development | B9: 0 | C9: 0 | D9: 0 | E9: 0 | F9: 0 | G9: 0 | H9: 0 | I9: 0 | J9: 0 | K9: 0
A10: Fixed Assets Held For Sale | B10: 0 | C10: 0 | D10: 0 | E10: 0 | F10: 0 | G10: 0 | H10: 0 | I10: 0 | J10: 0 | K10: 0
A11: Lease Adjustment | B11: 0 | C11: 0 | D11: 0 | E11: 0 | F11: 0 | G11: 0 | H11: 0 | I11: 0 | J11: 0 | K11: 0
A12: Biological Assets other than Bearer Plants | B12: 0 | C12: 0 | D12: 0 | E12: 0 | F12: 0 | G12: 0 | H12: 0 | I12: 0 | J12: 0 | K12: 0
A13: Non-current Investments
A14: Investment Properties | B14: 3.79 | C14: 3.72 | D14: 3.66 | E14: 3.6 | F14: 3.53 | G14: 0 | H14: 0 | I14: 0 | J14: 0 | K14: 0
A15: Investments in Subsidiaries, Associates and Joint venture | B15: 5.62 | C15: 5.4 | D15: 5.46 | E15: 6.27 | F15: 5.93 | G15: 0 | H15: 0 | I15: 0 | J15: 0 | K15: 0
A16: Financial Assets :
A17: Investments of Life Insurance Business | B17: 0 | C17: 0 | D17: 0 | E17: 0 | F17: 0 | G17: 0 | H17: 0 | I17: 0 | J17: 0 | K17: 0
A18: Investments - Long-term | B18: 0.1 | C18: 0.09 | D18: 120.08 | E18: 124.51 | F18: 149.66 | G18: 0.28 | H18: 0.16 | I18: 0.02 | J18: 0.02 | K18: 0.02
A19: Loans - Long - Term | B19: 0.09 | C19: 0.07 | D19: 0.06 | E19: 0.08 | F19: 0.07 | G19: 0.12 | H19: 0.13 | I19: 0.13 | J19: 0.14 | K19: 0.11
A20: Others Financial Assets - Long-term | B20: 12.59 | C20: 9.41 | D20: 9.74 | E20: 10.03 | F20: 10.26 | G20: 8.13 | H20: 6.32 | I20: 5.91 | J20: 8.27 | K20: 8.59
A21: Non Current Tax Assets - Long - Term | B21: 0 | C21: 0 | D21: 0 | E21: 0 | F21: 0 | G21: 0 | H21: 0 | I21: 0 | J21: 0 | K21: 0
A22: Insurance Related Assets | B22: 0 | C22: 0 | D22: 0 | E22: 0 | F22: 0 | G22: 0 | H22: 0 | I22: 0 | J22: 0 | K22: 0
A23: Other Non-current Assets | B23: 12.9 | C23: 22.31 | D23: 55.96 | E23: 114.31 | F23: 117.07 | G23: 173.65 | H23: 180.34 | I23: 140.33 | J23: 167 | K23: 184.85
A24: Deferred Tax Assets (Net) | B24: 5.91 | C24: 3.61 | D24: 16.68 | E24: 2.94 | F24: 13.95 | G24: 4.36 | H24: 10.11 | I24: 6.78 | J24: 25.78 | K24: 30.56
A25: Total Reported Non-current Assets | B25: 778.19 | C25: 857.2 | D25: 1110.33 | E25: 1458.27 | F25: 1748.4 | G25: 1670.38 | H25: 1601.17 | I25: 1528.28 | J25: 1531.45 | K25: 1536.85
A26: Current Assets:
A27: Inventories | B27: 281.71 | C27: 272.86 | D27: 338.66 | E27: 396.54 | F27: 538.34 | G27: 600.22 | H27: 625.23 | I27: 736.26 | J27: 988.74 | K27: 974.97
A28: Biological Assets other than Bearer Plants | B28: 0 | C28: 0 | D28: 0 | E28: 0 | F28: 0 | G28: 0 | H28: 0 | I28: 0 | J28: 0 | K28: 0
A29: Financial Assets :
A30: Current Investments | B30: 8 | C30: 895.55 | D30: 800.75 | E30: 419.1 | F30: 236.43 | G30: 263.58 | H30: 1.54 | I30: 1.34 | J30: 0 | K30: 0
A31: Trade Receivables | B31: 315.32 | C31: 276.92 | D31: 436.05 | E31: 390.14 | F31: 250.27 | G31: 495.43 | H31: 588.62 | I31: 642.31 | J31: 778.81 | K31: 828.58
A32: Cash and Cash Equivalents | B32: 11.21 | C32: 666.07 | D32: 197.05 | E32: 231.52 | F32: 77.46 | G32: 109.2 | H32: 183.75 | I32: 154.75 | J32: 89.58 | K32: 289.48
A33: Bank Balances Other Than Cash and Cash Equivalents | B33: 4.93 | C33: 15.39 | D33: 3.94 | E33: 2.29 | F33: 4.99 | G33: 4.91 | H33: 1.61 | I33: 3.41 | J33: 28.05 | K33: 5.22
A34: Loans - Short-term | B34: 0.09 | C34: 0.05 | D34: 0.06 | E34: 0.04 | F34: 0.04 | G34: 0.05 | H34: 0.06 | I34: 0.04 | J34: 0.06 | K34: 0.06
A35: Others Financial Assets - Short-term | B35: 2.49 | C35: 29.25 | D35: 23.65 | E35: 15.33 | F35: 9.2 | G35: 0.55 | H35: 1.71 | I35: 0.23 | J35: 4.83 | K35: 4.42
A36: Current Tax Assets - Short-term | B36: 0 | C36: 0 | D36: 0 | E36: 0 | F36: 0 | G36: 0 | H36: 0 | I36: 0 | J36: 0 | K36: 0
A37: Insurance Related Assets | B37: 0 | C37: 0 | D37: 0 | E37: 0 | F37: 0 | G37: 0 | H37: 0 | I37: 0 | J37: 0 | K37: 0
A38: Other Current Assets | B38: 124.71 | C38: 180.37 | D38: 238.25 | E38: 231.5 | F38: 260.59 | G38: 170.98 | H38: 185.95 | I38: 204.98 | J38: 139.4 | K38: 94.61
A39: Assets Classified as Held for Sale | B39: 0 | C39: 0 | D39: 0 | E39: 0 | F39: 0 | G39: 3.47 | H39: 0 | I39: 0 | J39: 0 | K39: 3.25
A40: Total Current Assets | B40: 748.46 | C40: 2336.47 | D40: 2038.41 | E40: 1686.47 | F40: 1377.32 | G40: 1648.39 | H40: 1588.47 | I40: 1743.32 | J40: 2029.47 | K40: 2197.34
A42: Foreign Currency Monetary Item Translation Difference Account | B42: 0 | C42: 0 | D42: 0 | E42: 0 | F42: 0 | G42: 0 | H42: 0 | I42: 0 | J42: 0 | K42: 0
... A47: Total Assets | B47: 1526.65 | C47: 3193.67 | D47: 3149.61 | E47: 3144.74 | F47: 3125.71 | G47: 3318.77 | H47: 3193.05 | I47: 3274.95 | J47: 3569.4 | K47: 3737.44
A48: EQUITY AND LIABILITIES
A50: Share Capital | B50: 18.18 | C50: 14.07 | D50: 14.08 | E50: 14.08 | F50: 14.08 | G50: 14.08 | H50: 14.08 | I50: 14.08 | J50: 14.08 | K50: 14.08
A51: Number of Equity Shares - Bought Back during the Current period | B51: 0 | C51: 2.06 | D51: 0 | E51: 0 | F51: 0 | G51: 0 | H51: 0 | I51: 0 | J51: 0 | K51: 0
A52: Number of Total Bonus Shares Issued upto Current period | B52: 7.35 | C52: 7.35 | D52: 7.35 | E52: 0.73 | F52: 0.73 | G52: 0.73 | H52: 0.73 | I52: 0 | J52: 0.73 | K52: 0
A53: Number of Equity Shares - Paid Up | B53: 9.09 | C53: 7.03 | D53: 7.04 | E53: 7.04 | F53: 7.04 | G53: 7.04 | H53: 7.04 | I53: 7.04 | J53: 7.04 | K53: 7.040575
A54: Paid Up Capital | B54: 18.18 | C54: 14.07 | D54: 14.08 | E54: 14.08 | F54: 14.08 | G54: 14.08 | H54: 14.08 | I54: 14.08 | J54: 14.08 | K54: 14.08
A55: Treasury Shares | B55: 0 | C55: 0 | D55: 0 | E55: 0 | F55: 0 | G55: 0 | H55: 0 | I55: 0 | J55: 0 | K55: 0
A56: Number of Bonus Shares Issued During the Current Period. | B56: 0 | C56: 0 | D56: 0 | E56: 0 | F56: 0 | G56: 0 | H56: 0 | I56: 0 | J56: 0 | K56: 0
A57: Number of Shares Splitted During the Current Period. | B57: 0 | C57: 0 | D57: 0 | E57: 0 | F57: 0 | G57: 0 | H57: 0 | I57: 0 | J57: 0 | K57: 0
A58: Other Equity | B58: 1045.33 | C58: 2666.02 | D58: 2605.83 | E58: 2517.27 | F58: 2542.75 | G58: 2604.33 | H58: 2421.22 | I58: 2424.22 | J58: 2436.51 | K58: 2703.36
A59: Money Received Against Share Warrants | B59: 0 | C59: 0 | D59: 0 | E59: 0 | F59: 0 | G59: 0 | H59: 0 | I59: 0 | J59: 0 | K59: 0
A60: Employee Stock Options / Others | B60: 0 | C60: 0 | D60: 0 | E60: 0 | F60: 0 | G60: 0 | H60: 0 | I60: 0 | J60: 0 | K60: 0.81
A61: Share Application Money Pending Allotment | B61: 0.12 | C61: 0 | D61: 0 | E61: 0 | F61: 0 | G61: 0 | H61: 0 | I61: 0 | J61: 0 | K61: 0
... A65: Total Equity | B65: 1063.62 | C65: 2680.08 | D65: 2619.91 | E65: 2531.35 | F65: 2556.83 | G65: 2618.41 | H65: 2435.3 | I65: 2438.3 | J65: 2450.59 | K65: 2717.44
A66: Non-Current Liabilities:
A67: Long Term Borrowings | B67: 0.44 | C67: 0.33 | D67: 0 | E67: 0 | F67: 0 | G67: 89.01 | H67: 63.65 | I67: 38.22 | J67: 60.81 | K67: 39.12
A68: Lease Liabilities | B68: 0 | C68: 0 | D68: 0 | E68: 0 | F68: 0 | G68: 4.22 | H68: 5.16 | I68: 4.21 | J68: 4.61 | K68: 26
A69: Others Financial Liabilities - Long-term | B69: 20.15 | C69: 0 | D69: 0 | E69: 0 | F69: 0 | G69: 0 | H69: 0 | I69: 0 | J69: 0 | K69: 0
A70: Non Current Tax Liabilities - Long-term | B70: 0 | C70: 0 | D70: 0 | E70: 0 | F70: 0 | G70: 0 | H70: 0 | I70: 0 | J70: 0 | K70: 0
A71: Long-term Provisions | B71: 25.33 | C71: 10.76 | D71: 14.6 | E71: 23.51 | F71: 30.41 | G71: 39.96 | H71: 41.91 | I71: 35.8 | J71: 37.86 | K71: 28.64
A72: Deferred Tax Liabilities (Net) | B72: 24.5 | C72: 34.29 | D72: 7.5 | E72: 0 | F72: 13.7 | G72: 0 | H72: 0 | I72: 0 | J72: 0 | K72: 39.88
A73: Insurance Related Liabilities | B73: 0 | C73: 0 | D73: 0 | E73: 0 | F73: 0 | G73: 0 | H73: 0 | I73: 0 | J73: 0 | K73: 0
A74: Other Non-Current Liabilities | B74: 0 | C74: 4.69 | D74: 4.69 | E74: 4.69 | F74: 4.69 | G74: 4.69 | H74: 1.1 | I74: 0.87 | J74: 0.64 | K74: 0.42
A75: Total Reported Non-current Liabilities | B75: 70.4 | C75: 50.07 | D75: 26.79 | E75: 46.66 | F75: 63.12 | G75: 148.24 | H75: 118.14 | I75: 99.05 | J75: 124.5 | K75: 134.06
A76: Current Liabilities:
A77: Short Term Borrowings | B77: 97.62 | C77: 150.29 | D77: 199.67 | E77: 184.03 | F77: 100.63 | G77: 241.35 | H77: 233.74 | I77: 180.93 | J77: 369.16 | K77: 429.66
A78: Lease Liabilities | B78: 0 | C78: 0 | D78: 0 | E78: 0 | F78: 0 | G78: 4.22 | H78: 5.16 | I78: 4.21 | J78: 4.61 | K78: 5.37
A79: Trade Payables | B79: 210.73 | C79: 226.23 | D79: 221.41 | E79: 250.22 | F79: 210.08 | G79: 183.19 | H79: 290.69 | I79: 351.26 | J79: 386.94 | K79: 356.63
A80: Others Financial Liabilities - Short-term | B80: 52.75 | C80: 42.02 | D80: 33.71 | E80: 72.7 | F80: 116.19 | G80: 52.53 | H80: 45.62 | I80: 29.18 | J80: 66.29 | K80: 59.66
A81: Current Tax Liabilities - Short-term | B81: 1.68 | C81: 4.61 | D81: 2.14 | E81: 0.63 | F81: 3.26 | G81: 2.1 | H81: 0.49 | I81: 2.21 | J81: 4.34 | K81: 0
A82: Provisions | B82: 14.57 | C82: 19.35 | D82: 11.25 | E82: 9.81 | F82: 14.83 | G82: 16.09 | H82: 12.01 | I82: 135.85 | J82: 137.64 | K82: 4.7
A83: Insurance Related Liabilities | B83: 0 | C83: 0 | D83: 0 | E83: 0 | F83: 0 | G83: 0 | H83: 0 | I83: 0 | J83: 0 | K83: 0
A84: Other Current Liabilities | B84: 15.26 | C84: 21.01 | D84: 34.74 | E84: 45.31 | F84: 56.63 | G84: 52.65 | H84: 51.89 | I84: 33.96 | J84: 22.99 | K84: 29.92
A85: Liabilities Directly Associated with Assets Classified as Held for Sale | B85: 0 | C85: 0 | D85: 0 | E85: 0 | F85: 0 | G85: 0 | H85: 0 | I85: 0 | J85: 0 | K85: 0
A86: Total Current Liabilities | B86: 392.62 | C86: 463.51 | D86: 502.92 | E86: 566.73 | F86: 505.76 | G86: 552.13 | H86: 639.6 | I86: 737.6 | J86: 991.97 | K86: 885.94
A87: Foreign Currency Monetary Item Translation Difference Account | B87: 0 | C87: 0 | D87: 0 | E87: 0 | F87: 0 | G87: 0 | H87: 0 | I87: 0 | J87: 0 | K87: 0
A88: Hybrid Perpetual Securities | B88: 0 | C88: 0 | D88: 0 | E88: 0 | F88: 0 | G88: 0 | H88: 0 | I88: 0 | J88: 0 | K88: 0
... A93: Book Value (Unit Curr) | B93: 117.03 | C93: 381.03 | D93: 372.23 | E93: 359.54 | F93: 363.16 | G93: 371.9 | H93: 345.9 | I93: 346.32 | J93: 348.07 | K93: 385.97

Sheet Raw IS
A1: Finance >>Profit & Loss IND (Consolidated)>>Unichem Laboratories Ltd (Curr. in ₹ crore)
A2: Year | B2: 201703 | C2: 201803 | D2: 201903 | E2: 202003 | F2: 202103 | G2: 202203 | H2: 202303 | I2: 202403 | J2: 202503 | K2: 202603
A3: Revenue From Operations | B3: 698.67 | C3: 814.98 | D3: 1180.05 | E3: 1103.71 | F3: 1235.14 | G3: 1269.83 | H3: 1343.02 | I3: 1785.11 | J3: 2110.97 | K3: 2201.85
A4: Less: Excise Duty | B4: 0.95 | C4: 0.39 | D4: 0 | E4: 0 | F4: 0 | G4: 0 | H4: 0 | I4: 0 | J4: 0 | K4: 0
A5: Revenue From Operations(Net) | B5: 697.71 | C5: 814.59 | D5: 1180.05 | E5: 1103.71 | F5: 1235.14 | G5: 1269.83 | H5: 1343.02 | I5: 1785.11 | J5: 2110.97 | K5: 2201.85
A6: Other Income | B6: 5.5 | C6: 60.88 | D6: 98.41 | E6: 91.31 | F6: 50.19 | G6: 47.51 | H6: 38.52 | I6: 31.59 | J6: 35.32 | K6: 63.06
A7: Total Revenue | B7: 703.22 | C7: 875.47 | D7: 1278.46 | E7: 1195.03 | F7: 1285.32 | G7: 1317.34 | H7: 1381.54 | I7: 1816.7 | J7: 2146.29 | K7: 2264.91
A8: EXPENSES:
A9: Cost of Material Consumed | B9: 262.42 | C9: 387.57 | D9: 476.92 | E9: 421.88 | F9: 466.99 | G9: 456.01 | H9: 532.2 | I9: 762.83 | J9: 888.24 | K9: 768.83
A10: Internally Manufactured Intermediates or Components Consumed | B10: 0 | C10: 0 | D10: 0 | E10: 0 | F10: 0 | G10: 0 | H10: 0 | I10: 0 | J10: 0 | K10: 0
A11: Purchases of Stock-in-Trade | B11: 0 | C11: 0.16 | D11: 0.21 | E11: 1.04 | F11: 0.54 | G11: 1.35 | H11: 1.53 | I11: 80.83 | J11: 175.78 | K11: 231.51
A12: Changes in Inventories of Finished Goods, Work-in-Progress and Stock-in-Trade | B12: -3.25 | C12: -29.48 | D12: -32.48 | E12: -35.76 | F12: -88.14 | G12: -41.53 | H12: 17.2 | I12: -106.96 | J12: -200.35 | K12: -200.35
A13: Employee Benefits / Salaries & other Staff Cost | B13: 169.04 | C13: 200.64 | D13: 238.52 | E13: 273.28 | F13: 306.97 | G13: 330.49 | H13: 356.41 | I13: 403.2 | J13: 402.21 | K13: 396.63
A14: Finance Cost | B14: 3.36 | C14: 8.01 | D14: 7.52 | E14: 7.85 | F14: 5.12 | G14: 6.11 | H14: 17.31 | I14: 22.66 | J14: 21.03 | K14: 31.59
A15: Depreciation and Amortization | B15: 43.52 | C15: 50.51 | D15: 67.37 | E15: 81.67 | F15: 84.36 | G15: 91.17 | H15: 113.44 | I15: 123.16 | J15: 124.56 | K15: 125.12
A16: Other Expenses | B16: 310.9 | C16: 387.59 | D16: 580.37 | E16: 494.09 | F16: 457.67 | G16: 450.72 | H16: 481.24 | I16: 558.33 | J16: 580.23 | K16: 600.5
A17: Total Expenses | B17: 785.98 | C17: 1005 | D17: 1338.43 | E17: 1244.05 | F17: 1233.5 | G17: 1294.31 | H17: 1519.33 | I17: 1844.05 | J17: 1991.7 | K17: 2174.39
A18: Share of Profits / Loss of Associated Companies Before Tax | B18: 0.19 | C18: -0.22 | D18: 0.07 | E18: 0.81 | F18: -0.34 | G18: -1.06 | H18: 0 | I18: 0 | J18: 0 | K18: 0
A19: Minority Interest Before Net Profit | B19: 0 | C19: 0 | D19: 0 | E19: 0 | F19: 0 | G19: 0 | H19: 0 | I19: 0 | J19: 0 | K19: 0
A20: Profit Before Exceptional Items and Tax | B20: -82.58 | C20: -129.76 | D20: -59.91 | E20: -48.21 | F20: 51.48 | G20: 21.97 | H20: -137.8 | I20: -27.35 | J20: 154.59 | K20: 90.52
... A63: Unappropriated Profits Carried Forward | B63: 108.68 | C63: 2544.91 | D63: -23.8 | E63: -60.18 | F63: 34.32 | G63: 33.06 | H63: -202.23 | I63: -93.76 | J63: 137.52 | K63: 252.84
A64: Other Comprehensive Income :
A65: Other Comprehensive Income That Will Not Be Reclassified to Profit Or Loss | B65: -1.24 | C65: -1.8 | D65: -0.28 | E65: 3 | F65: 21.3 | G65: 55.37 | H65: 38.73 | I65: -0.28 | J65: 1.38 | K65: 7.6
A66: Other Comprehensive Income That Will Be Reclassified to Profit Or Loss : | B66: 0.9 | C66: -2.79 | D66: 2.15 | E66: 0.06 | F66: -4.91 | G66: -1.62 | H66: 7.2 | I66: -5.37 | J66: -8.35 | K66: 4.39
A67: Other Comprehensive Income no Specification : | B67: 0 | C67: 0 | D67: 0 | E67: 0 | F67: 0 | G67: 0 | H67: 0 | I67: 0 | J67: 0 | K67: 0
A68: Non-Controlling Interests | B68: 0 | C68: 0 | D68: 0 | E68: 0 | F68: 0 | G68: 0 | H68: 0 | I68: 0 | J68: 0 | K68: 0
A69: Total Comprehensive Income for the Year | B69: 108.34 | C69: 2540.32 | D69: -21.93 | E69: -57.13 | F69: 50.72 | G69: 86.81 | H69: -156.3 | I69: -99.41 | J69: 130.55 | K69: 264.83
A70: Net Profit attributable to:
A71: a) Owners of the Company | B71: 108.34 | C71: 2540.32 | D71: -21.93 | E71: -57.13 | F71: 50.72 | G71: 86.81 | H71: -156.3 | I71: -99.41 | J71: 130.55 | K71: 252.84
A72: b) Non Controlling Interest | B72: 0 | C72: 0 | D72: 0 | E72: 0 | F72: 0 | G72: 0 | H72: 0 | I72: 0 | J72: 0 | K72: 0
A73: Other Comprehensive Income attributable to:
A74: a) Owners of the Company | B74: 108.34 | C74: 2540.32 | D74: -21.93 | E74: -57.13 | F74: 50.72 | G74: 86.81 | H74: -156.3 | I74: -99.41 | J74: 130.55 | K74: 264.83
A75: b) Non Controlling Interest | B75: 0 | C75: 0 | D75: 0 | E75: 0 | F75: 0 | G75: 0 | H75: 0 | I75: 0 | J75: 0 | K75: 0
A76: Total Comprehensive Income attributable to:
A77: a) Owners of the Company | B77: 108.34 | C77: 2540.32 | D77: -21.93 | E77: -57.13 | F77: 50.72 | G77: 86.81 | H77: -156.3 | I77: -99.41 | J77: 130.55 | K77: 264.83
A78: b) Non Controlling Interest | B78: 0 | C78: 0 | D78: 0 | E78: 0 | F78: 0 | G78: 0 | H78: 0 | I78: 0 | J78: 0 | K78: 0
A79: Earning Per Share - Basic | B79: 11.96 | C79: 280.6 | D79: -3.38 | E79: -8.55 | F79: 4.88 | G79: 4.7 | H79: -28.72 | I79: -13.32 | J79: 19.53 | K79: 35.91
A80: Earning Per Share - Diluted | B80: 11.94 | C80: 280.41 | D80: -3.38 | E80: -8.55 | F80: 4.88 | G80: 4.68 | H80: -28.72 | I80: -13.32 | J80: 19.47 | K80: 35.85
A81: Dividend Per Share | K81: 0
A82: Interim 1 | B82: 0 | C82: 0 | D82: 0 | E82: 0 | F82: 0 | G82: 0 | H82: 0 | I82: 0 | J82: 0 | K82: 0
A83: Interim 2 | B83: 0 | C83: 0 | D83: 0 | E83: 0 | F83: 0 | G83: 0 | H83: 0 | I83: 0 | J83: 0 | K83: 0
A84: Interim 3 | B84: 0 | C84: 0 | D84: 0 | E84: 0 | F84: 0 | G84: 0 | H84: 0 | I84: 0 | J84: 0 | K84: 0
A85: Interim 4 | B85: 0 | C85: 0 | D85: 0 | E85: 0 | F85: 0 | G85: 0 | H85: 0 | I85: 0 | J85: 0 | K85: 0
A86: Special | B86: 0 | C86: 0 | D86: 0 | E86: 0 | F86: 0 | G86: 0 | H86: 0 | I86: 0 | J86: 0 | K86: 0
A87: Final | B87: 150 | C87: 250 | D87: 200 | E87: 200 | F87: 200 | G87: 200 | H87: 200 | I87: 0 | J87: 0 | K87: 0
A88: Total Dividend Per Share | B88: 3 | C88: 5 | D88: 4 | E88: 4 | F88: 4 | G88: 4 | H88: 4 | I88: 0 | J88: 0 | K88: 0
A89: Dividend Percentage | K89: 0
A90: Interim 1 | B90: 0 | C90: 0 | D90: 0 | E90: 0 | F90: 0 | G90: 0 | H90: 0 | I90: 0 | J90: 0 | K90: 0
A91: Interim 2 | B91: 0 | C91: 0 | D91: 0 | E91: 0 | F91: 0 | G91: 0 | H91: 0 | I91: 0 | J91: 0 | K91: 0
A92: Interim 3 | B92: 0 | C92: 0 | D92: 0 | E92: 0 | F92: 0 | G92: 0 | H92: 0 | I92: 0 | J92: 0 | K92: 0
A93: Interim 4 | B93: 0 | C93: 0 | D93: 0 | E93: 0 | F93: 0 | G93: 0 | H93: 0 | I93: 0 | J93: 0 | K93: 0
A94: Special | B94: 0 | C94: 0 | D94: 0 | E94: 0 | F94: 0 | G94: 0 | H94: 0 | I94: 0 | J94: 0 | K94: 0
A95: Final | B95: 150 | C95: 250 | D95: 200 | E95: 200 | F95: 200 | G95: 200 | H95: 200 | I95: 0 | J95: 0 | K95: 0
A96: Total Dividend Percentage | B96: 150 | C96: 250 | D96: 200 | E96: 200 | F96: 200 | G96: 200 | H96: 200 | I96: 0 | J96: 0 | K96: 0
A97: Total Dividend | B97: 32.81 | C97: 35.17 | D97: 28.15 | E97: 28.16 | F97: 28.16 | G97: 28.16 | H97: 0.28 | I97: 0 | J97: 0 | K97: 0
A98: Preference Dividend | B98: 0 | C98: 0 | D98: 0 | E98: 0 | F98: 0 | G98: 0 | H98: 0 | I98: 0 | J98: 0 | K98: 0
A99: Weighted Average Number of Shares in Issue - Basic | B99: 9.09 | C99: 9.07 | D99: 7.04 | E99: 7.04 | F99: 7.04 | G99: 7.04 | H99: 7.04 | I99: 7.04 | J99: 7.04 | K99: 7.040575
A100: Weighted Average Number of Shares in Issue - Diluted | B100: 9.1 | C100: 9.08 | D100: 7.04 | E100: 7.04 | F100: 7.04 | G100: 7.06 | H100: 7.04 | I100: 7.04 | J100: 7.06 | K100: 7.040575
A101: Interim Dividend Amount | B101: 0 | C101: 0 | D101: 0 | E101: 0 | F101: 0 | G101: 0 | H101: 0 | I101: 0 | J101: 0 | K101: 0
... A105: Other Dividend Amount | B105: 0 | C105: 0 | D105: 0 | E105: 0 | F105: 0 | G105: 0 | H105: 0 | I105: 0 | J105: 0 | K105: 0

Sheet Raw CFS
A1: Finance >>Cash Flow (Consolidated)>>Unichem Laboratories Ltd (Curr. in ₹ crore)
A2: Year | B2: 201703 | C2: 201803 | D2: 201903 | E2: 202003 | F2: 202103 | G2: 202203 | H2: 202303 | I2: 202403 | J2: 202503 | K2: 202603
A3: Cash Flow Summary
A4: Cash and Cash Equivalents at Beginning of the year | B4: 11.67 | C4: 11.21 | D4: 813.24 | E4: 309.91 | F4: 231.52 | G4: 77.46 | H4: 109.2 | I4: 183.75 | J4: 154.75 | K4: 89.58
A5: Net Cash from Operating Activities | B5: 68.19 | C5: -112.34 | D5: -327.77 | E5: 19.82 | F5: 32.98 | G5: -259.61 | H5: -85.09 | I5: 14 | J5: -7.02 | K5: 3.64
A6: Net Profit before Tax & Extraordinary Items | B6: 141.25 | C6: 3241.14 | D6: -57.44 | E6: -48.21 | F6: 51.48 | G6: 21.97 | H6: -176.36 | I6: -84.96 | J6: 154.59 | K6: 90.52
A7: Depreciation | B7: 45.18 | C7: 51.77 | D7: 67.43 | E7: 81.72 | F7: 84.42 | G7: 91.23 | H7: 113.44 | I7: 123.16 | J7: 124.56 | K7: 125.12
A8: Interest (Net) | B8: 0.88 | C8: -5.52 | D8: -37.46 | E8: -30.84 | F8: -17.82 | G8: -0.37 | H8: 16.8 | I8: 21.99 | J8: 18.18 | K8: 26.17
A9: Dividend Received | B9: 0 | C9: 18.4 | D9: 10.99 | E9: 1.58 | F9: 0 | G9: 10.01 | H9: 0.01 | I9: 0 | J9: 0 | K9: 0
A10: P/L on Sales of Assets | B10: 0 | C10: 5.03 | D10: 10.28 | E10: 1.86 | F10: 0.52 | G10: 0.23 | H10: -1.28 | I10: -4.86 | J10: -0.95 | K10: -274.29
A11: P/L on Sales of Invest | B11: 0 | C11: 0 | D11: 1.95 | E11: 0 | F11: 0 | G11: 0 | H11: 5.02 | I11: -64.78 | J11: -0.02 | K11: 0
A12: Prov. & W/O (Net) | B12: -0.38 | C12: 1.68 | D12: -3.31 | E12: -0.75 | F12: -0.15 | G12: 6.13 | H12: 4.22 | I12: 126.17 | J12: 0.12 | K12: -0.69
A13: P/L in Forex | B13: 7.82 | C13: -11.2 | D13: 4.04 | E13: -5.49 | F13: 7.61 | G13: -7.22 | H13: 2.66 | I13: -1 | J13: 4.01 | K13: -5.88
A14: Fin. Lease & Rental Chrgs | B14: 0.01 | C14: 0 | D14: 0 | E14: 0 | F14: 0 | G14: 0 | H14: 0 | I14: 0 | J14: 0 | K14: 0
A15: Others | B15: 63.01 | C15: -840.42 | D15: 0 | E15: 0 | F15: 0 | G15: 0 | H15: 0 | I15: 0 | J15: 0 | K15: 0
... A83: Cash and Cash Equivalents at End of the year | B83: 11.21 | C83: 666.07 | D83: 197.05 | E83: 231.52 | F83: 77.46 | G83: 109.2 | H83: 183.75 | I83: 154.75 | J83: 89.58 | K83: 289.48

Sheet Reform Stat, Ratio, GROWTH
B1: Finance >>Profit & Loss IND (Consolidated)>>Unichem Laboratories Ltd(Curr. in ) | N1: CONDENSED INCOME STATEMENT (₹ crore) | Z1: REFORMULATED INCOME STATEMENT (₹ crore) | AL1: RATIO ANALYSIS & VALUATION DASHBOARD >> UNICHEM LABORATORIES LTD (₹ crore, except per-share data) | AY1: HISTORICAL REINVESTMENT, GROWTH & WORKING CAPITAL ANALYSIS >> UNICHEM LABORATORIES LTD
B2: Year | C2: 201703 | D2: 201803 | E2: 201903 | F2: 202003 | G2: 202103 | H2: 202203 | I2: 202303 | J2: 202403 | K2: 202503 | L2: 202603 | N2: Year | O2: 201703 | P2: 201803 | Q2: 201903 | R2: 202003 | S2: 202103 | T2: 202203 | U2: 202303 | V2: 202403 | W2: 202503 | X2: 202603 | Z2: Year | AA2: 201703 | AB2: 201803 | AC2: 201903 | AD2: 202003 | AE2: 202103 | AF2: 202203 | AG2: 202303 | AH2: 202403 | AI2: 202503 | AJ2: 202603 | AL2: Year | AM2: =O2 -> 201703 | AN2: =P2 -> 201803 | AO2: =Q2 -> 201903 | AP2: =R2 -> 202003 | AQ2: =S2 -> 202103 | AR2: =T2 -> 202203 | AS2: =U2 -> 202303 | AT2: =V2 -> 202403 | ... AV2: =X2 -> 202603 | AW2: Trend Line | AY2: Particulars | AZ2: =C2 -> 201703 | BA2: =D2 -> 201803 | BB2: =E2 -> 201903 | BC2: =F2 -> 202003 | BD2: =G2 -> 202103 | BE2: =H2 -> 202203 | BF2: =I2 -> 202303 | BG2: =J2 -> 202403 | ... BI2: =L2 -> 202603 | BJ2: Historical Average | BK2: Remarks
B3: Revenue From Operations | C3: ='Raw IS'!B3 -> 698.67 | D3: ='Raw IS'!C3 -> 814.98 | E3: ='Raw IS'!D3 -> 1180.05 | F3: ='Raw IS'!E3 -> 1103.71 | G3: ='Raw IS'!F3 -> 1235.14 | H3: ='Raw IS'!G3 -> 1269.83 | I3: ='Raw IS'!H3 -> 1343.02 | J3: ='Raw IS'!I3 -> 1785.11 | ... L3: ='Raw IS'!K3 -> 2201.85 | N3: Revenue from Operations (Net) | O3: =C5 -> 697.71 | P3: =D5 -> 814.59 | Q3: =E5 -> 1180.05 | R3: =F5 -> 1103.71 | S3: =G5 -> 1235.14 | T3: =H5 -> 1269.83 | U3: =I5 -> 1343.02 | V3: =J5 -> 1785.11 | ... X3: =L5 -> 2201.85 | Z3: Operating Revenue | AA3: =O3 -> 697.71 | AB3: =P3 -> 814.59 | AC3: =Q3 -> 1180.05 | AD3: =R3 -> 1103.71 | AE3: =S3 -> 1235.14 | AF3: =T3 -> 1269.83 | AG3: =U3 -> 1343.02 | AH3: =V3 -> 1785.11 | ... AJ3: =X3 -> 2201.85 | AL3: Growth (%) | AY3: Capital Expenditure and Reinvestment
B4: Less: Excise Duty | C4: ='Raw IS'!B4 -> 0.95 | D4: ='Raw IS'!C4 -> 0.39 | E4: ='Raw IS'!D4 -> 0 | F4: ='Raw IS'!E4 -> 0 | G4: ='Raw IS'!F4 -> 0 | H4: ='Raw IS'!G4 -> 0 | I4: ='Raw IS'!H4 -> 0 | J4: ='Raw IS'!I4 -> 0 | ... L4: ='Raw IS'!K4 -> 0 | N4: Other Income | O4: =C6 -> 5.5 | P4: =D6 -> 60.88 | Q4: =E6 -> 98.41 | R4: =F6 -> 91.31 | S4: =G6 -> 50.19 | T4: =H6 -> 47.51 | U4: =I6 -> 38.52 | V4: =J6 -> 31.59 | ... X4: =L6 -> 63.06 | Z4: Cost of Goods Sold (COGS) | AA4: =O6 -> 259.17 | AB4: =P6 -> 358.25 | AC4: =Q6 -> 444.65 | AD4: =R6 -> 387.16 | AE4: =S6 -> 379.39 | AF4: =T6 -> 415.83 | AG4: =U6 -> 550.93 | AH4: =V6 -> 736.7 | ... AJ4: =X6 -> 799.99 | AL4: Sales Growth | AM4: ="" | AN4: =IFERROR(P3/O3-1,"") -> 0.16751946 | AO4: =IFERROR(Q3/P3-1,"") -> 0.44864288 | AP4: =IFERROR(R3/Q3-1,"") -> -0.064692174 | AQ4: =IFERROR(S3/R3-1,"") -> 0.11908019 | AR4: =IFERROR(T3/S3-1,"") -> 0.028085885 | AS4: =IFERROR(U3/T3-1,"") -> 0.057637637 | AT4: =IFERROR(V3/U3-1,"") -> 0.32917604 | AU4: =IFERROR(W3/V3-1,"") -> 0.18254337 | AV4: =IFERROR(X3/W3-1,"") -> 0.043051299 | AY4: Total Capital Expenditure | AZ4: =-C175 -> 149.83 | BA4: =-D175 -> 159.57 | BB4: =-E175 -> 194.31 | BC4: =-F175 -> 386.15 | BD4: =-G175 -> 287.81 | BE4: =-H175 -> 127 | BF4: =-I175 -> 44.32 | BG4: =-J175 -> 22.55 | ... BI4: =-L175 -> 123.04 | BJ4: =AVERAGE(AZ4:BI4) -> 163.194
B5: Revenue From Operations(Net) | C5: ='Raw IS'!B5 -> 697.71 | D5: ='Raw IS'!C5 -> 814.59 | E5: ='Raw IS'!D5 -> 1180.05 | F5: ='Raw IS'!E5 -> 1103.71 | G5: ='Raw IS'!F5 -> 1235.14 | H5: ='Raw IS'!G5 -> 1269.83 | I5: ='Raw IS'!H5 -> 1343.02 | J5: ='Raw IS'!I5 -> 1785.11 | ... L5: ='Raw IS'!K5 -> 2201.85 | N5: Total Income | O5: =SUM(O3:O4) -> 703.21 | P5: =SUM(P3:P4) -> 875.47 | Q5: =SUM(Q3:Q4) -> 1278.46 | R5: =SUM(R3:R4) -> 1195.02 | S5: =SUM(S3:S4) -> 1285.33 | T5: =SUM(T3:T4) -> 1317.34 | U5: =SUM(U3:U4) -> 1381.54 | V5: =SUM(V3:V4) -> 1816.7 | ... X5: =SUM(X3:X4) -> 2264.91 | Z5: Selling, General & Administrative Expenses (SG&A) | AA5: =SUM(O7:O8) -> 479.94 | AB5: =SUM(P7:P8) -> 588.23 | AC5: =SUM(Q7:Q8) -> 818.89 | AD5: =SUM(R7:R8) -> 767.37 | AE5: =SUM(S7:S8) -> 764.64 | AF5: =SUM(T7:T8) -> 781.21 | AG5: =SUM(U7:U8) -> 837.65 | AH5: =SUM(V7:V8) -> 961.53 | ... AJ5: =SUM(X7:X8) -> 997.13 | AL5: EBITDA Growth | AM5: ="" | AN5: =IFERROR(P9/O9-1,"") -> 0.97799443 | AO5: =IFERROR(Q9/P9-1,"") -> -1.2101113 | AP5: =IFERROR(R9/Q9-1,"") -> 1.713807 | AQ5: =IFERROR(S9/R9-1,"") -> 2.4897506 | AR5: =IFERROR(T9/S9-1,"") -> -0.14861996 | AS5: =IFERROR(U9/T9-1,"") -> -1.0585204 | AT5: =IFERROR(V9/U9-1,"") -> -17.828125 | AU5: =IFERROR(W9/V9-1,"") -> 1.533806 | AV5: =IFERROR(X9/W9-1,"") -> 0.55836498 | AY5: Depreciation Expenditure | AZ5: =O10 -> 43.52 | BA5: =P10 -> 50.51 | BB5: =Q10 -> 67.37 | BC5: =R10 -> 81.67 | BD5: =S10 -> 84.36 | BE5: =T10 -> 91.17 | BF5: =U10 -> 113.44 | BG5: =V10 -> 123.16 | ... BI5: =X10 -> 125.12 | BJ5: =AVERAGE(AZ5:BI5) -> 90.488
B6: Other Income | C6: ='Raw IS'!B6 -> 5.5 | D6: ='Raw IS'!C6 -> 60.88 | E6: ='Raw IS'!D6 -> 98.41 | F6: ='Raw IS'!E6 -> 91.31 | G6: ='Raw IS'!F6 -> 50.19 | H6: ='Raw IS'!G6 -> 47.51 | I6: ='Raw IS'!H6 -> 38.52 | J6: ='Raw IS'!I6 -> 31.59 | ... L6: ='Raw IS'!K6 -> 63.06 | N6: Cost of Goods Sold | O6: =SUM(C9:C12) -> 259.17 | P6: =SUM(D9:D12) -> 358.25 | Q6: =SUM(E9:E12) -> 444.65 | R6: =SUM(F9:F12) -> 387.16 | S6: =SUM(G9:G12) -> 379.39 | T6: =SUM(H9:H12) -> 415.83 | U6: =SUM(I9:I12) -> 550.93 | V6: =SUM(J9:J12) -> 736.7 | ... X6: =SUM(L9:L12) -> 799.99 | Z6: EBITDA from Operations | AA6: =AA3-AA4-AA5 -> -41.4 | AB6: =AB3-AB4-AB5 -> -131.89 | AC6: =AC3-AC4-AC5 -> -83.49 | AD6: =AD3-AD4-AD5 -> -50.82 | AE6: =AE3-AE4-AE5 -> 91.11 | AF6: =AF3-AF4-AF5 -> 72.79 | AG6: =AG3-AG4-AG5 -> -45.56 | AH6: =AH3-AH4-AH5 -> 86.88 | ... AJ6: =AJ3-AJ4-AJ5 -> 404.73 | AL6: EBIT Growth | AM6: ="" | AN6: =IFERROR(P11/O11-1,"") -> 0.53009318 | AO6: =IFERROR(Q11/P11-1,"") -> -0.56838381 | AP6: =IFERROR(R11/Q11-1,"") -> -0.21487131 | AQ6: =IFERROR(S11/R11-1,"") -> -2.3827101 | AR6: =IFERROR(T11/S11-1,"") -> -0.48840885 | AS6: =IFERROR(U11/T11-1,"") -> -5.1359423 | AT6: =IFERROR(V11/U11-1,"") -> -0.96107238 | AU6: =IFERROR(W11/V11-1,"") -> -38.445629 | AV6: =IFERROR(X11/W11-1,"") -> 0.95120146 | AY6: Net Capital Expenditure | AZ6: =AZ4-AZ5 -> 106.31 | BA6: =BA4-BA5 -> 109.06 | BB6: =BB4-BB5 -> 126.94 | BC6: =BC4-BC5 -> 304.48 | BD6: =BD4-BD5 -> 203.45 | BE6: =BE4-BE5 -> 35.83 | BF6: =BF4-BF5 -> -69.12 | BG6: =BG4-BG5 -> -100.61 | ... BI6: =BI4-BI5 -> -2.08 | BJ6: =AVERAGE(AZ6:BI6) -> 72.706
B7: Total Revenue | C7: ='Raw IS'!B7 -> 703.22 | D7: ='Raw IS'!C7 -> 875.47 | E7: ='Raw IS'!D7 -> 1278.46 | F7: ='Raw IS'!E7 -> 1195.03 | G7: ='Raw IS'!F7 -> 1285.32 | H7: ='Raw IS'!G7 -> 1317.34 | I7: ='Raw IS'!H7 -> 1381.54 | J7: ='Raw IS'!I7 -> 1816.7 | ... L7: ='Raw IS'!K7 -> 2264.91 | N7: Employee Benefits Expense | O7: =C13 -> 169.04 | P7: =D13 -> 200.64 | Q7: =E13 -> 238.52 | R7: =F13 -> 273.28 | S7: =G13 -> 306.97 | T7: =H13 -> 330.49 | U7: =I13 -> 356.41 | V7: =J13 -> 403.2 | ... X7: =L13 -> 396.63 | Z7: Depreciation & Amortization | AA7: =O10 -> 43.52 | AB7: =P10 -> 50.51 | AC7: =Q10 -> 67.37 | AD7: =R10 -> 81.67 | AE7: =S10 -> 84.36 | AF7: =T10 -> 91.17 | AG7: =U10 -> 113.44 | AH7: =V10 -> 123.16 | ... AJ7: =X10 -> 125.12 | AL7: Net Profit Growth | AM7: ="" | AN7: =IFERROR(P17/O17-1,"") -> 0.88139666 | AO7: =IFERROR(Q17/P17-1,"") -> -0.80802464 | AP7: =IFERROR(R17/Q17-1,"") -> 1.355773 | AQ7: =IFERROR(S17/R17-1,"") -> -1.5703605 | AR7: =IFERROR(T17/S17-1,"") -> -0.037285173 | AS7: =IFERROR(U17/T17-1,"") -> -7.1186082 | AT7: =IFERROR(V17/U17-1,"") -> -0.53634655 | AU7: =IFERROR(W17/V17-1,"") -> -2.4667235 | AV7: =IFERROR(X17/W17-1,"") -> 2.4424084
B8: EXPENSES: | C8: ='Raw IS'!B8 -> 0 | D8: ='Raw IS'!C8 -> 0 | E8: ='Raw IS'!D8 -> 0 | F8: ='Raw IS'!E8 -> 0 | G8: ='Raw IS'!F8 -> 0 | H8: ='Raw IS'!G8 -> 0 | I8: ='Raw IS'!H8 -> 0 | J8: ='Raw IS'!I8 -> 0 | ... L8: ='Raw IS'!K8 -> 0 | N8: Other Operating Expenses | O8: =C16 -> 310.9 | P8: =D16 -> 387.59 | Q8: =E16 -> 580.37 | R8: =F16 -> 494.09 | S8: =G16 -> 457.67 | T8: =H16 -> 450.72 | U8: =I16 -> 481.24 | V8: =J16 -> 558.33 | ... X8: =L16 -> 600.5 | Z8: Operating Profit (EBIT) | AA8: =AA6-AA7 -> -84.92 | AB8: =AB6-AB7 -> -182.4 | AC8: =AC6-AC7 -> -150.86 | AD8: =AD6-AD7 -> -132.49 | AE8: =AE6-AE7 -> 6.75 | AF8: =AF6-AF7 -> -18.38 | AG8: =AG6-AG7 -> -159 | AH8: =AH6-AH7 -> -36.28 | ... AJ8: =AJ6-AJ7 -> 279.61 | AY8: Current Assets
B9: Cost of Material Consumed | C9: ='Raw IS'!B9 -> 262.42 | D9: ='Raw IS'!C9 -> 387.57 | E9: ='Raw IS'!D9 -> 476.92 | F9: ='Raw IS'!E9 -> 421.88 | G9: ='Raw IS'!F9 -> 466.99 | H9: ='Raw IS'!G9 -> 456.01 | I9: ='Raw IS'!H9 -> 532.2 | J9: ='Raw IS'!I9 -> 762.83 | ... L9: ='Raw IS'!K9 -> 768.83 | N9: EBITDA | O9: =O5-SUM(O6:O8) -> -35.9 | P9: =P5-SUM(P6:P8) -> -71.01 | Q9: =Q5-SUM(Q6:Q8) -> 14.92 | R9: =R5-SUM(R6:R8) -> 40.49 | S9: =S5-SUM(S6:S8) -> 141.3 | T9: =T5-SUM(T6:T8) -> 120.3 | U9: =U5-SUM(U6:U8) -> -7.04 | V9: =V5-SUM(V6:V8) -> 118.47 | ... X9: =X5-SUM(X6:X8) -> 467.79 | Z9: Less: Tax Expense | AA9: =O16 -> -11.85 | AB9: =P16 -> 3.34 | AC9: =Q16 -> -34.35 | AD9: =R16 -> 11.97 | AE9: =S16 -> 17.15 | AF9: =T16 -> -11.09 | AG9: =U16 -> 25.86 | AH9: =V16 -> 8.8 | ... AJ9: =X16 -> 39.54 | AL9: Margins (%) | AY9: Inventories | AZ9: =C65 -> 281.71 | BA9: =D65 -> 272.86 | BB9: =E65 -> 338.66 | BC9: =F65 -> 396.54 | BD9: =G65 -> 538.34 | BE9: =H65 -> 600.22 | BF9: =I65 -> 625.23 | BG9: =J65 -> 736.26 | ... BI9: =L65 -> 974.97
B10: Internally Manufactured Intermediates or Components Consumed | C10: ='Raw IS'!B10 -> 0 | D10: ='Raw IS'!C10 -> 0 | E10: ='Raw IS'!D10 -> 0 | F10: ='Raw IS'!E10 -> 0 | G10: ='Raw IS'!F10 -> 0 | H10: ='Raw IS'!G10 -> 0 | I10: ='Raw IS'!H10 -> 0 | J10: ='Raw IS'!I10 -> 0 | ... L10: ='Raw IS'!K10 -> 0 | N10: Depreciation & Amortization | O10: =C15 -> 43.52 | P10: =D15 -> 50.51 | Q10: =E15 -> 67.37 | R10: =F15 -> 81.67 | S10: =G15 -> 84.36 | T10: =H15 -> 91.17 | U10: =I15 -> 113.44 | V10: =J15 -> 123.16 | ... X10: =L15 -> 125.12 | Z10: Net Operating Profit After Tax (NOPAT) | AA10: =AA8-AA9 -> -73.07 | AB10: =AB8-AB9 -> -185.74 | AC10: =AC8-AC9 -> -116.51 | AD10: =AD8-AD9 -> -144.46 | AE10: =AE8-AE9 -> -10.4 | AF10: =AF8-AF9 -> -7.29 | AG10: =AG8-AG9 -> -184.86 | AH10: =AH8-AH9 -> -45.08 | ... AJ10: =AJ8-AJ9 -> 240.07 | AL10: Gross Margin | AM10: =IFERROR((O3-O6)/O3,0) -> 0.62854194 | AN10: =IFERROR((P3-P6)/P3,0) -> 0.5602082 | AO10: =IFERROR((Q3-Q6)/Q3,0) -> 0.62319393 | AP10: =IFERROR((R3-R6)/R3,0) -> 0.64921945 | AQ10: =IFERROR((S3-S6)/S3,0) -> 0.69283644 | AR10: =IFERROR((T3-T6)/T3,0) -> 0.67253097 | AS10: =IFERROR((U3-U6)/U3,0) -> 0.58978273 | AT10: =IFERROR((V3-V6)/V3,0) -> 0.58730835 | ... AV10: =IFERROR((X3-X6)/X3,0) -> 0.63667371 | AY10: Trade Receivables | AZ10: =C69 -> 315.32 | BA10: =D69 -> 276.92 | BB10: =E69 -> 436.05 | BC10: =F69 -> 390.14 | BD10: =G69 -> 250.27 | BE10: =H69 -> 495.43 | BF10: =I69 -> 588.62 | BG10: =J69 -> 642.31 | ... BI10: =L69 -> 828.58
B11: Purchases of Stock-in-Trade | C11: ='Raw IS'!B11 -> 0 | D11: ='Raw IS'!C11 -> 0.16 | E11: ='Raw IS'!D11 -> 0.21 | F11: ='Raw IS'!E11 -> 1.04 | G11: ='Raw IS'!F11 -> 0.54 | H11: ='Raw IS'!G11 -> 1.35 | I11: ='Raw IS'!H11 -> 1.53 | J11: ='Raw IS'!I11 -> 80.83 | ... L11: ='Raw IS'!K11 -> 231.51 | N11: EBIT | O11: =O9-O10 -> -79.42 | P11: =P9-P10 -> -121.52 | Q11: =Q9-Q10 -> -52.45 | R11: =R9-R10 -> -41.18 | S11: =S9-S10 -> 56.94 | T11: =T9-T10 -> 29.13 | U11: =U9-U10 -> -120.48 | V11: =V9-V10 -> -4.69 | ... X11: =X9-X10 -> 342.67 | Z11: Other / Non-operating Income | AA11: =O4 -> 5.5 | AB11: =P4 -> 60.88 | AC11: =Q4 -> 98.41 | AD11: =R4 -> 91.31 | AE11: =S4 -> 50.19 | AF11: =T4 -> 47.51 | AG11: =U4 -> 38.52 | AH11: =V4 -> 31.59 | ... AJ11: =X4 -> 63.06 | AL11: EBITDA Margin | AM11: =IFERROR(AA6/AA3,0) -> -0.059336974 | AN11: =IFERROR(AB6/AB3,0) -> -0.16190967 | AO11: =IFERROR(AC6/AC3,0) -> -0.070751239 | AP11: =IFERROR(AD6/AD3,0) -> -0.046044704 | AQ11: =IFERROR(AE6/AE3,0) -> 0.073764917 | AR11: =IFERROR(AF6/AF3,0) -> 0.057322634 | AS11: =IFERROR(AG6/AG3,0) -> -0.033923545 | AT11: =IFERROR(AH6/AH3,0) -> 0.04866927 | ... AV11: =IFERROR(AJ6/AJ3,0) -> 0.18381361 | AY11: Short-Term Loans and Advances | AZ11: =C72 -> 0.09 | BA11: =D72 -> 0.05 | BB11: =E72 -> 0.06 | BC11: =F72 -> 0.04 | BD11: =G72 -> 0.04 | BE11: =H72 -> 0.05 | BF11: =I72 -> 0.06 | BG11: =J72 -> 0.04 | ... BI11: =L72 -> 0.06
B12: Changes in Inventories of Finished Goods, Work-in-Progress and Stock-in-Trade | C12: ='Raw IS'!B12 -> -3.25 | D12: ='Raw IS'!C12 -> -29.48 | E12: ='Raw IS'!D12 -> -32.48 | F12: ='Raw IS'!E12 -> -35.76 | G12: ='Raw IS'!F12 -> -88.14 | H12: ='Raw IS'!G12 -> -41.53 | I12: ='Raw IS'!H12 -> 17.2 | J12: ='Raw IS'!I12 -> -106.96 | ... L12: ='Raw IS'!K12 -> -200.35 | N12: Finance Cost | O12: =C14 -> 3.36 | P12: =D14 -> 8.01 | Q12: =E14 -> 7.52 | R12: =F14 -> 7.85 | S12: =G14 -> 5.12 | T12: =H14 -> 6.11 | U12: =I14 -> 17.31 | V12: =J14 -> 22.66 | ... X12: =L14 -> 31.59 | Z12: Share of Profit/(Loss) of Associates | AA12: =O13 -> 0.19 | AB12: =P13 -> -0.22 | AC12: =Q13 -> 0.07 | AD12: =R13 -> 0.81 | AE12: =S13 -> -0.34 | AF12: =T13 -> -1.06 | AG12: =U13 -> 0 | AH12: =V13 -> 0 | ... AJ12: =X13 -> 0 | AL12: EBIT Margin | AM12: =IFERROR(AA8/AA3,0) -> -0.12171246 | AN12: =IFERROR(AB8/AB3,0) -> -0.22391633 | AO12: =IFERROR(AC8/AC3,0) -> -0.12784204 | AP12: =IFERROR(AD8/AD3,0) -> -0.12004059 | AQ12: =IFERROR(AE8/AE3,0) -> 0.0054649675 | AR12: =IFERROR(AF8/AF3,0) -> -0.014474378 | AS12: =IFERROR(AG8/AG3,0) -> -0.1183899 | AT12: =IFERROR(AH8/AH3,0) -> -0.020323678 | ... AV12: =IFERROR(AJ8/AJ3,0) -> 0.12698867 | AY12: Other Current Assets | AZ12: =C76 -> 124.71 | BA12: =D76 -> 180.37 | BB12: =E76 -> 238.25 | BC12: =F76 -> 231.5 | BD12: =G76 -> 260.59 | BE12: =H76 -> 170.98 | BF12: =I76 -> 185.95 | BG12: =J76 -> 204.98 | ... BI12: =L76 -> 94.61
B13: Employee Benefits / Salaries & other Staff Cost | C13: ='Raw IS'!B13 -> 169.04 | D13: ='Raw IS'!C13 -> 200.64 | E13: ='Raw IS'!D13 -> 238.52 | F13: ='Raw IS'!E13 -> 273.28 | G13: ='Raw IS'!F13 -> 306.97 | H13: ='Raw IS'!G13 -> 330.49 | I13: ='Raw IS'!H13 -> 356.41 | J13: ='Raw IS'!I13 -> 403.2 | ... L13: ='Raw IS'!K13 -> 396.63 | N13: Share of Profit/(Loss) of Associates | O13: =C18 -> 0.19 | P13: =D18 -> -0.22 | Q13: =E18 -> 0.07 | R13: =F18 -> 0.81 | S13: =G18 -> -0.34 | T13: =H18 -> -1.06 | U13: =I18 -> 0 | V13: =J18 -> 0 | ... X13: =L18 -> 0 | Z13: Exceptional & Other Adjustments | AA13: =O14 -> 0 | AB13: =P14 -> 0 | AC13: =Q14 -> 0 | AD13: =R14 -> 0 | AE13: =S14 -> 0 | AF13: =T14 -> 0 | AG13: =U14 -> -38.57 | AH13: =V14 -> -57.61 | ... AJ13: =X14 -> 201.86 | AL13: EBT Margin | AM13: =IFERROR(O15/O3,0) -> -0.11837296 | AN13: =IFERROR(P15/P3,0) -> -0.15928258 | AO13: =IFERROR(Q15/Q3,0) -> -0.050760561 | AP13: =IFERROR(R15/R3,0) -> -0.043689013 | AQ13: =IFERROR(S15/S3,0) -> 0.041679486 | AR13: =IFERROR(T15/T3,0) -> 0.017293653 | AS13: =IFERROR(U15/U3,0) -> -0.13131599 | AT13: =IFERROR(V15/V3,0) -> -0.047593706 | ... AV13: =IFERROR(X15/X3,0) -> 0.23295865 | AY13: Total Current Operating Assets | AZ13: =SUM(AZ9:AZ12) -> 721.83 | BA13: =SUM(BA9:BA12) -> 730.2 | BB13: =SUM(BB9:BB12) -> 1013.02 | BC13: =SUM(BC9:BC12) -> 1018.22 | BD13: =SUM(BD9:BD12) -> 1049.24 | BE13: =SUM(BE9:BE12) -> 1266.68 | BF13: =SUM(BF9:BF12) -> 1399.86 | BG13: =SUM(BG9:BG12) -> 1583.59 | ... BI13: =SUM(BI9:BI12) -> 1898.22 | BJ13: =AVERAGE(AZ13:BI13) -> 1258.787
B14: Finance Cost | C14: ='Raw IS'!B14 -> 3.36 | D14: ='Raw IS'!C14 -> 8.01 | E14: ='Raw IS'!D14 -> 7.52 | F14: ='Raw IS'!E14 -> 7.85 | G14: ='Raw IS'!F14 -> 5.12 | H14: ='Raw IS'!G14 -> 6.11 | I14: ='Raw IS'!H14 -> 17.31 | J14: ='Raw IS'!I14 -> 22.66 | ... L14: ='Raw IS'!K14 -> 31.59 | N14: Exceptional & Other Adjustments | O14: =SUM(C21,C23:C25) -> 0 | P14: =SUM(D21,D23:D25) -> 0 | Q14: =SUM(E21,E23:E25) -> 0 | R14: =SUM(F21,F23:F25) -> 0 | S14: =SUM(G21,G23:G25) -> 0 | T14: =SUM(H21,H23:H25) -> 0 | U14: =SUM(I21,I23:I25) -> -38.57 | V14: =SUM(J21,J23:J25) -> -57.61 | ... X14: =SUM(L21,L23:L25) -> 201.86 | Z14: Less: Net Finance Cost | AA14: =O12 -> 3.36 | AB14: =P12 -> 8.01 | AC14: =Q12 -> 7.52 | AD14: =R12 -> 7.85 | AE14: =S12 -> 5.12 | AF14: =T12 -> 6.11 | AG14: =U12 -> 17.31 | AH14: =V12 -> 22.66 | ... AJ14: =X12 -> 31.59 | AL14: Net Profit Margin | AM14: =IFERROR(O17/O3,0) -> -0.10138883 | AN14: =IFERROR(P17/P3,0) -> -0.16338281 | AO14: =IFERROR(Q17/Q3,0) -> -0.021651625 | AP14: =IFERROR(R17/R3,0) -> -0.054534253 | AQ14: =IFERROR(S17/S3,0) -> 0.02779442 | AR14: =IFERROR(T17/T3,0) -> 0.026027106 | AS14: =IFERROR(U17/U3,0) -> -0.1505711 | AT14: =IFERROR(V17/V3,0) -> -0.052523374 | ... AV14: =IFERROR(X17/X3,0) -> 0.21500102
B15: Depreciation and Amortization | C15: ='Raw IS'!B15 -> 43.52 | D15: ='Raw IS'!C15 -> 50.51 | E15: ='Raw IS'!D15 -> 67.37 | F15: ='Raw IS'!E15 -> 81.67 | G15: ='Raw IS'!F15 -> 84.36 | H15: ='Raw IS'!G15 -> 91.17 | I15: ='Raw IS'!H15 -> 113.44 | J15: ='Raw IS'!I15 -> 123.16 | ... L15: ='Raw IS'!K15 -> 125.12 | N15: Profit Before Tax | O15: =O11-O12+O13+O14 -> -82.59 | P15: =P11-P12+P13+P14 -> -129.75 | Q15: =Q11-Q12+Q13+Q14 -> -59.9 | R15: =R11-R12+R13+R14 -> -48.22 | S15: =S11-S12+S13+S14 -> 51.48 | T15: =T11-T12+T13+T14 -> 21.96 | U15: =U11-U12+U13+U14 -> -176.36 | V15: =V11-V12+V13+V14 -> -84.96 | ... X15: =X11-X12+X13+X14 -> 512.94 | Z15: Net Profit | AA15: =AA10+SUM(AA11:AA13)-AA14 -> -70.74 | AB15: =AB10+SUM(AB11:AB13)-AB14 -> -133.09 | AC15: =AC10+SUM(AC11:AC13)-AC14 -> -25.55 | AD15: =AD10+SUM(AD11:AD13)-AD14 -> -60.19 | AE15: =AE10+SUM(AE11:AE13)-AE14 -> 34.33 | AF15: =AF10+SUM(AF11:AF13)-AF14 -> 33.05 | AG15: =AG10+SUM(AG11:AG13)-AG14 -> -202.22 | AH15: =AH10+SUM(AH11:AH13)-AH14 -> -93.76 | ... AJ15: =AJ10+SUM(AJ11:AJ13)-AJ14 -> 473.4 | AY15: Current Liabilities
B16: Other Expenses | C16: ='Raw IS'!B16 -> 310.9 | D16: ='Raw IS'!C16 -> 387.59 | E16: ='Raw IS'!D16 -> 580.37 | F16: ='Raw IS'!E16 -> 494.09 | G16: ='Raw IS'!F16 -> 457.67 | H16: ='Raw IS'!G16 -> 450.72 | I16: ='Raw IS'!H16 -> 481.24 | J16: ='Raw IS'!I16 -> 558.33 | ... L16: ='Raw IS'!K16 -> 600.5 | N16: Tax Expense | O16: =C27 -> -11.85 | P16: =D27 -> 3.34 | Q16: =E27 -> -34.35 | R16: =F27 -> 11.97 | S16: =G27 -> 17.15 | T16: =H27 -> -11.09 | U16: =I27 -> 25.86 | V16: =J27 -> 8.8 | ... X16: =L27 -> 39.54 | Z16: Net Profit Reconciliation Check | AA16: =AA15-O17 -> 0 | AB16: =AB15-P17 -> 0 | AC16: =AC15-Q17 -> -1.030287e-13 | AD16: =AD15-R17 -> 0 | AE16: =AE15-S17 -> -5.6843419e-14 | AF16: =AF15-T17 -> -1.1368684e-13 | AG16: =AG15-U17 -> 0 | AH16: =AH15-V17 -> 0 | ... AJ16: =AJ15-X17 -> 0 | AL16: Expense Ratios (%) | AY16: Trade Payables | AZ16: =C117 -> 210.73 | BA16: =D117 -> 226.23 | BB16: =E117 -> 221.41 | BC16: =F117 -> 250.22 | BD16: =G117 -> 210.08 | BE16: =H117 -> 183.19 | BF16: =I117 -> 290.69 | BG16: =J117 -> 351.26 | ... BI16: =L117 -> 356.63
B17: Total Expenses | C17: ='Raw IS'!B17 -> 785.98 | D17: ='Raw IS'!C17 -> 1005 | E17: ='Raw IS'!D17 -> 1338.43 | F17: ='Raw IS'!E17 -> 1244.05 | G17: ='Raw IS'!F17 -> 1233.5 | H17: ='Raw IS'!G17 -> 1294.31 | I17: ='Raw IS'!H17 -> 1519.33 | J17: ='Raw IS'!I17 -> 1844.05 | ... L17: ='Raw IS'!K17 -> 2174.39 | N17: Net Profit | O17: =O15-O16 -> -70.74 | P17: =P15-P16 -> -133.09 | Q17: =Q15-Q16 -> -25.55 | R17: =R15-R16 -> -60.19 | S17: =S15-S16 -> 34.33 | T17: =T15-T16 -> 33.05 | U17: =U15-U16 -> -202.22 | V17: =V15-V16 -> -93.76 | ... X17: =X15-X16 -> 473.4 | AL17: COGS / Sales | AM17: =IFERROR(O6/O3,0) -> 0.37145806 | AN17: =IFERROR(P6/P3,0) -> 0.4397918 | AO17: =IFERROR(Q6/Q3,0) -> 0.37680607 | AP17: =IFERROR(R6/R3,0) -> 0.35078055 | AQ17: =IFERROR(S6/S3,0) -> 0.30716356 | AR17: =IFERROR(T6/T3,0) -> 0.32746903 | AS17: =IFERROR(U6/U3,0) -> 0.41021727 | AT17: =IFERROR(V6/V3,0) -> 0.41269165 | ... AV17: =IFERROR(X6/X3,0) -> 0.36332629 | AY17: Other Current Liabilities | AZ17: =C122 -> 15.26 | BA17: =D122 -> 21.01 | BB17: =E122 -> 34.74 | BC17: =F122 -> 45.31 | BD17: =G122 -> 56.63 | BE17: =H122 -> 52.65 | BF17: =I122 -> 51.89 | BG17: =J122 -> 33.96 | ... BI17: =L122 -> 29.92
B18: Share of Profits / Loss of Associated Companies Before Tax | C18: ='Raw IS'!B18 -> 0.19 | D18: ='Raw IS'!C18 -> -0.22 | E18: ='Raw IS'!D18 -> 0.07 | F18: ='Raw IS'!E18 -> 0.81 | G18: ='Raw IS'!F18 -> -0.34 | H18: ='Raw IS'!G18 -> -1.06 | I18: ='Raw IS'!H18 -> 0 | J18: ='Raw IS'!I18 -> 0 | ... L18: ='Raw IS'!K18 -> 0 | N18: Net Profit Reconciliation Check | O18: =O17-C36 -> -0.02 | P18: =P17-D36 -> 0.01 | Q18: =Q17-E36 -> 0.01 | R18: =R17-F36 -> -0.01 | S18: =S17-G36 -> 0.01 | T18: =T17-H36 -> -0.01 | U18: =U17-I36 -> 0.01 | V18: =V17-J36 -> -1.8474111e-13 | ... X18: =X17-L36 -> 220.56 | AL18: Employee Expenses / Sales | AM18: =IFERROR(O7/O3,0) -> 0.24227831 | AN18: =IFERROR(P7/P3,0) -> 0.24630796 | AO18: =IFERROR(Q7/Q3,0) -> 0.20212703 | AP18: =IFERROR(R7/R3,0) -> 0.24760127 | AQ18: =IFERROR(S7/S3,0) -> 0.24853053 | AR18: =IFERROR(T7/T3,0) -> 0.26026318 | AS18: =IFERROR(U7/U3,0) -> 0.26537952 | AT18: =IFERROR(V7/V3,0) -> 0.22586843 | ... AV18: =IFERROR(X7/X3,0) -> 0.18013489 | AY18: Total Current Operating Liabilities | AZ18: =SUM(AZ16:AZ17) -> 225.99 | BA18: =SUM(BA16:BA17) -> 247.24 | BB18: =SUM(BB16:BB17) -> 256.15 | BC18: =SUM(BC16:BC17) -> 295.53 | BD18: =SUM(BD16:BD17) -> 266.71 | BE18: =SUM(BE16:BE17) -> 235.84 | BF18: =SUM(BF16:BF17) -> 342.58 | BG18: =SUM(BG16:BG17) -> 385.22 | ... BI18: =SUM(BI16:BI17) -> 386.55 | BJ18: =AVERAGE(AZ18:BI18) -> 305.174
B19: Minority Interest Before Net Profit | C19: ='Raw IS'!B19 -> 0 | D19: ='Raw IS'!C19 -> 0 | E19: ='Raw IS'!D19 -> 0 | F19: ='Raw IS'!E19 -> 0 | G19: ='Raw IS'!F19 -> 0 | H19: ='Raw IS'!G19 -> 0 | I19: ='Raw IS'!H19 -> 0 | J19: ='Raw IS'!I19 -> 0 | ... L19: ='Raw IS'!K19 -> 0 | AL19: Other Expenses / Sales | AM19: =IFERROR(O8/O3,0) -> 0.44560061 | AN19: =IFERROR(P8/P3,0) -> 0.47580992 | AO19: =IFERROR(Q8/Q3,0) -> 0.49181814 | AP19: =IFERROR(R8/R3,0) -> 0.44766288 | AQ19: =IFERROR(S8/S3,0) -> 0.37054099 | AR19: =IFERROR(T8/T3,0) -> 0.35494515 | AS19: =IFERROR(U8/U3,0) -> 0.35832676 | AT19: =IFERROR(V8/V3,0) -> 0.31277064 | ... AV19: =IFERROR(X8/X3,0) -> 0.27272521
B20: Profit Before Exceptional Items and Tax | C20: ='Raw IS'!B20 -> -82.58 | D20: ='Raw IS'!C20 -> -129.76 | E20: ='Raw IS'!D20 -> -59.91 | F20: ='Raw IS'!E20 -> -48.21 | G20: ='Raw IS'!F20 -> 51.48 | H20: ='Raw IS'!G20 -> 21.97 | I20: ='Raw IS'!H20 -> -137.8 | J20: ='Raw IS'!I20 -> -27.35 | ... L20: ='Raw IS'!K20 -> 90.52 | AL20: Depreciation / Sales | AM20: =IFERROR(O10/O3,0) -> 0.062375486 | AN20: =IFERROR(P10/P3,0) -> 0.062006654 | AO20: =IFERROR(Q10/Q3,0) -> 0.057090801 | AP20: =IFERROR(R10/R3,0) -> 0.073995887 | AQ20: =IFERROR(S10/S3,0) -> 0.06829995 | AR20: =IFERROR(T10/T3,0) -> 0.071797012 | AS20: =IFERROR(U10/U3,0) -> 0.084466352 | AT20: =IFERROR(V10/V3,0) -> 0.068992947 | ... AV20: =IFERROR(X10/X3,0) -> 0.056824943 | AY20: Net Working Capital | AZ20: =AZ13-AZ18 -> 495.84 | BA20: =BA13-BA18 -> 482.96 | BB20: =BB13-BB18 -> 756.87 | BC20: =BC13-BC18 -> 722.69 | BD20: =BD13-BD18 -> 782.53 | BE20: =BE13-BE18 -> 1030.84 | BF20: =BF13-BF18 -> 1057.28 | BG20: =BG13-BG18 -> 1198.37 | ... BI20: =BI13-BI18 -> 1511.67 | BJ20: =AVERAGE(AZ20:BI20) -> 953.613
B21: Exceptional Items Before Tax | C21: ='Raw IS'!B21 -> 0 | D21: ='Raw IS'!C21 -> 0 | E21: ='Raw IS'!D21 -> 0 | F21: ='Raw IS'!E21 -> 0 | G21: ='Raw IS'!F21 -> 0 | H21: ='Raw IS'!G21 -> 0 | I21: ='Raw IS'!H21 -> -38.57 | J21: ='Raw IS'!I21 -> -57.61 | ... L21: ='Raw IS'!K21 -> 201.86 | AL21: Finance Cost / Sales | AM21: =IFERROR(O12/O3,0) -> 0.0048157544 | AN21: =IFERROR(P12/P3,0) -> 0.0098331676 | AO21: =IFERROR(Q12/Q3,0) -> 0.0063726113 | AP21: =IFERROR(R12/R3,0) -> 0.0071123755 | AQ21: =IFERROR(S12/S3,0) -> 0.0041452791 | AR21: =IFERROR(T12/T3,0) -> 0.0048116677 | AS21: =IFERROR(U12/U3,0) -> 0.012888862 | AT21: =IFERROR(V12/V3,0) -> 0.012693896 | ... AV21: =IFERROR(X12/X3,0) -> 0.014347026 | AY21: Change in Working Capital | AZ21: ="" | BA21: =BA20-AZ20 -> -12.88 | BB21: =BB20-BA20 -> 273.91 | BC21: =BC20-BB20 -> -34.18 | BD21: =BD20-BC20 -> 59.84 | BE21: =BE20-BD20 -> 248.31 | BF21: =BF20-BE20 -> 26.44 | BG21: =BG20-BF20 -> 141.09 | BH21: =BH20-BG20 -> 298.71 | BI21: =BI20-BH20 -> 14.59 | BJ21: =AVERAGE(BA21:BI21) -> 112.87
B22: Profit Before Extraordinary Items and Tax | C22: ='Raw IS'!B22 -> -82.58 | D22: ='Raw IS'!C22 -> -129.76 | E22: ='Raw IS'!D22 -> -59.91 | F22: ='Raw IS'!E22 -> -48.21 | G22: ='Raw IS'!F22 -> 51.48 | H22: ='Raw IS'!G22 -> 21.97 | I22: ='Raw IS'!H22 -> -176.36 | J22: ='Raw IS'!I22 -> -84.96 | ... L22: ='Raw IS'!K22 -> 292.38 | AL22: Tax / Sales | AM22: =IFERROR(O16/O3,0) -> -0.016984134 | AN22: =IFERROR(P16/P3,0) -> 0.0041002222 | AO22: =IFERROR(Q16/Q3,0) -> -0.029108936 | AP22: =IFERROR(R16/R3,0) -> 0.01084524 | AQ22: =IFERROR(S16/S3,0) -> 0.013885066 | AR22: =IFERROR(T16/T3,0) -> -0.0087334525 | AS22: =IFERROR(U16/U3,0) -> 0.019255112 | AT22: =IFERROR(V16/V3,0) -> 0.0049296682 | ... AV22: =IFERROR(X16/X3,0) -> 0.017957627 | AY22: Total Reinvestment (Net Capex + Change in WC) | AZ22: ="" | BA22: =BA6+BA21 -> 96.18 | BB22: =BB6+BB21 -> 400.85 | BC22: =BC6+BC21 -> 270.3 | BD22: =BD6+BD21 -> 263.29 | BE22: =BE6+BE21 -> 284.14 | BF22: =BF6+BF21 -> -42.68 | BG22: =BG6+BG21 -> 40.48 | BH22: =BH6+BH21 -> 311.51 | BI22: =BI6+BI21 -> 12.51 | BJ22: =AVERAGE(BA22:BI22) -> 181.84222
B23: Prior Year Adjustments | C23: ='Raw IS'!B23 -> 0 | D23: ='Raw IS'!C23 -> 0 | E23: ='Raw IS'!D23 -> 0 | F23: ='Raw IS'!E23 -> 0 | G23: ='Raw IS'!F23 -> 0 | H23: ='Raw IS'!G23 -> 0 | I23: ='Raw IS'!H23 -> 0 | J23: ='Raw IS'!I23 -> 0 | ... L23: ='Raw IS'!K23 -> 0
B24: Other Adjustments Before Tax | C24: ='Raw IS'!B24 -> 0 | D24: ='Raw IS'!C24 -> 0 | E24: ='Raw IS'!D24 -> 0 | F24: ='Raw IS'!E24 -> 0 | G24: ='Raw IS'!F24 -> 0 | H24: ='Raw IS'!G24 -> 0 | I24: ='Raw IS'!H24 -> 0 | J24: ='Raw IS'!I24 -> 0 | ... L24: ='Raw IS'!K24 -> 0 | AL24: Return Ratios (%) | AY24: EBIT | AZ24: =O11 -> -79.42 | BA24: =P11 -> -121.52 | BB24: =Q11 -> -52.45 | BC24: =R11 -> -41.18 | BD24: =S11 -> 56.94 | BE24: =T11 -> 29.13 | BF24: =U11 -> -120.48 | BG24: =V11 -> -4.69 | ... BI24: =X11 -> 342.67 | BJ24: =AVERAGE(AZ24:BI24) -> 18.462
B25: Extraordinary Items Before Tax | C25: ='Raw IS'!B25 -> 0 | D25: ='Raw IS'!C25 -> 0 | E25: ='Raw IS'!D25 -> 0 | F25: ='Raw IS'!E25 -> 0 | G25: ='Raw IS'!F25 -> 0 | H25: ='Raw IS'!G25 -> 0 | I25: ='Raw IS'!H25 -> 0 | J25: ='Raw IS'!I25 -> 0 | ... L25: ='Raw IS'!K25 -> 0 | AL25: Return on Capital Employed (ROCE) | AM25: ="" | AN25: =IFERROR(AB8/AVERAGE((P51+P52+P53+P54+P55+P58+P59),(O51+O52+O53+O54+O55+O58+O59)),"") -> -0.091376356 | AO25: =IFERROR(AC8/AVERAGE((Q51+Q52+Q53+Q54+Q55+Q58+Q59),(P51+P52+P53+P54+P55+P58+P59)),"") -> -0.053399029 | AP25: =IFERROR(AD8/AVERAGE((R51+R52+R53+R54+R55+R58+R59),(Q51+Q52+Q53+Q54+Q55+Q58+Q59)),"") -> -0.047873878 | AQ25: =IFERROR(AE8/AVERAGE((S51+S52+S53+S54+S55+S58+S59),(R51+R52+R53+R54+R55+R58+R59)),"") -> 0.0025126376 | AR25: =IFERROR(AF8/AVERAGE((T51+T52+T53+T54+T55+T58+T59),(S51+S52+S53+S54+S55+S58+S59)),"") -> -0.0065471346 | AS25: =IFERROR(AG8/AVERAGE((U51+U52+U53+U54+U55+U58+U59),(T51+T52+T53+T54+T55+T58+T59)),"") -> -0.05578732 | AT25: =IFERROR(AH8/AVERAGE((V51+V52+V53+V54+V55+V58+V59),(U51+U52+U53+U54+U55+U58+U59)),"") -> -0.013414977 | AU25: =IFERROR(AI8/AVERAGE((W51+W52+W53+W54+W55+W58+W59),(V51+V52+V53+V54+V55+V58+V59)),"") -> 0.050507141 | AV25: =IFERROR(AJ8/AVERAGE((X51+X52+X53+X54+X55+X58+X59),(W51+W52+W53+W54+W55+W58+W59)),"") -> 0.091564782 | AY25: Reinvestment Rate | AZ25: ="" | BA25: =IFERROR(BA22/BA24,"") -> -0.79147465 | BB25: =IFERROR(BB22/BB24,"") -> -7.6425167 | BC25: =IFERROR(BC22/BC24,"") -> -6.563866 | BD25: =IFERROR(BD22/BD24,"") -> 4.6239902 | BE25: =IFERROR(BE22/BE24,"") -> 9.7542053 | BF25: =IFERROR(BF22/BF24,"") -> 0.35424967 | BG25: =IFERROR(BG22/BG24,"") -> -8.6311301 | BH25: =IFERROR(BH22/BH24,"") -> 1.7737729 | BI25: =IFERROR(BI22/BI24,"") -> 0.036507427 | BJ25: =AVERAGE(BA25:BI25) -> -0.78736243 | BK25: Average reinvestment rate
B26: Profit Before Tax | C26: ='Raw IS'!B26 -> -82.58 | D26: ='Raw IS'!C26 -> -129.76 | E26: ='Raw IS'!D26 -> -59.91 | F26: ='Raw IS'!E26 -> -48.21 | G26: ='Raw IS'!F26 -> 51.48 | H26: ='Raw IS'!G26 -> 21.97 | I26: ='Raw IS'!H26 -> -176.36 | J26: ='Raw IS'!I26 -> -84.96 | ... L26: ='Raw IS'!K26 -> 292.38 | AL26: Return on Assets (ROA) | AM26: ="" | AN26: =IFERROR(P17/AVERAGE(P49,O49),"") -> -0.056390125 | AO26: =IFERROR(Q17/AVERAGE(Q49,P49),"") -> -0.008056887 | AP26: =IFERROR(R17/AVERAGE(R49,Q49),"") -> -0.019278845 | AQ26: =IFERROR(S17/AVERAGE(S49,R49),"") -> 0.011118902 | AR26: =IFERROR(T17/AVERAGE(T49,S49),"") -> 0.010330659 | AS26: =IFERROR(U17/AVERAGE(U49,T49),"") -> -0.062141042 | AT26: =IFERROR(V17/AVERAGE(V49,U49),"") -> -0.029022293 | AU26: =IFERROR(W17/AVERAGE(W49,V49),"") -> 0.040254547 | AV26: =IFERROR(X17/AVERAGE(X49,W49),"") -> 0.12972777 | AY26: Total Capital Employed | AZ26: =SUM(O51:O53)+O54+O55+O58+O59-O47 -> 1145.43 | BA26: =SUM(P51:P53)+P54+P55+P58+P59-P47 -> 2149.25 | BB26: =SUM(Q51:Q53)+Q54+Q55+Q58+Q59-Q47 -> 2618.59 | BC26: =SUM(R51:R53)+R54+R55+R58+R59-R47 -> 2481.57 | BD26: =SUM(S51:S53)+S54+S55+S58+S59-S47 -> 2575.01 | BE26: =SUM(T51:T53)+T54+T55+T58+T59-T47 -> 2843.1 | BF26: =SUM(U51:U53)+U54+U55+U58+U59-U47 -> 2557.65 | BG26: =SUM(V51:V53)+V54+V55+V58+V59-V47 -> 2507.71 | ... BI26: =SUM(X51:X53)+X54+X55+X58+X59-X47 -> 2922.89 | BJ26: =AVERAGE(AZ26:BI26) -> 2457.335
B27: Tax Expenses | C27: ='Raw IS'!B27 -> -11.85 | D27: ='Raw IS'!C27 -> 3.34 | E27: ='Raw IS'!D27 -> -34.35 | F27: ='Raw IS'!E27 -> 11.97 | G27: ='Raw IS'!F27 -> 17.15 | H27: ='Raw IS'!G27 -> -11.09 | I27: ='Raw IS'!H27 -> 25.86 | J27: ='Raw IS'!I27 -> 8.8 | ... L27: ='Raw IS'!K27 -> 39.54 | AL27: Return on Equity (ROE) | AM27: ="" | AN27: =IFERROR(P17/AVERAGE(SUM(P51:P52),SUM(O51:O52)),"") -> -0.071102682 | AO27: =IFERROR(Q17/AVERAGE(SUM(Q51:Q52),SUM(P51:P52)),"") -> -0.0096415094 | AP27: =IFERROR(R17/AVERAGE(SUM(R51:R52),SUM(Q51:Q52)),"") -> -0.02336904 | AQ27: =IFERROR(S17/AVERAGE(SUM(S51:S52),SUM(R51:R52)),"") -> 0.013494019 | AR27: =IFERROR(T17/AVERAGE(SUM(T51:T52),SUM(S51:S52)),"") -> 0.012772355 | AS27: =IFERROR(U17/AVERAGE(SUM(U51:U52),SUM(T51:T52)),"") -> -0.080028336 | AT27: =IFERROR(V17/AVERAGE(SUM(V51:V52),SUM(U51:U52)),"") -> -0.038476691 | AU27: =IFERROR(W17/AVERAGE(SUM(W51:W52),SUM(V51:V52)),"") -> 0.056258169 | AV27: =IFERROR(X17/AVERAGE(SUM(X51:X52),SUM(W51:W52)),"") -> 0.18320327 | AY27: Return on Capital Employed | AZ27: =IFERROR(AZ24/AZ26,"") -> -0.069336406 | BA27: =IFERROR(BA24/BA26,"") -> -0.056540654 | BB27: =IFERROR(BB24/BB26,"") -> -0.020029863 | BC27: =IFERROR(BC24/BC26,"") -> -0.016594333 | BD27: =IFERROR(BD24/BD26,"") -> 0.022112535 | BE27: =IFERROR(BE24/BE26,"") -> 0.010245858 | BF27: =IFERROR(BF24/BF26,"") -> -0.047105742 | BG27: =IFERROR(BG24/BG26,"") -> -0.0018702322 | ... BI27: =IFERROR(BI24/BI26,"") -> 0.11723671 | BJ27: =AVERAGE(AZ27:BI27) -> 0.00014694209
B28: Current Tax | C28: ='Raw IS'!B28 -> -13.66 | D28: ='Raw IS'!C28 -> 1.15 | E28: ='Raw IS'!D28 -> 7.14 | F28: ='Raw IS'!E28 -> 5.47 | G28: ='Raw IS'!F28 -> 16.68 | H28: ='Raw IS'!G28 -> 10.51 | I28: ='Raw IS'!H28 -> 11.06 | J28: ='Raw IS'!I28 -> 7.94 | ... L28: ='Raw IS'!K28 -> 3.57 | AL28: Return on Invested Capital (ROIC) | AM28: ="" | AN28: =IFERROR(AB10/AVERAGE(AB77,AA77),"") -> -0.15657547 | AO28: =IFERROR(AC10/AVERAGE(AC77,AB77),"") -> -0.079468256 | AP28: =IFERROR(AD10/AVERAGE(AD77,AC77),"") -> -0.080501308 | AQ28: =IFERROR(AE10/AVERAGE(AE77,AD77),"") -> -0.005131849 | AR28: =IFERROR(AF10/AVERAGE(AF77,AE77),"") -> -0.0030750022 | AS28: =IFERROR(AG10/AVERAGE(AG77,AF77),"") -> -0.071811626 | AT28: =IFERROR(AH10/AVERAGE(AH77,AG77),"") -> -0.017741675 | AU28: =IFERROR(AI10/AVERAGE(AI77,AH77),"") -> 0.046418509 | AV28: =IFERROR(AJ10/AVERAGE(AJ77,AI77),"") -> 0.084095813
B29: Deferred Tax | C29: ='Raw IS'!B29 -> 1.81 | D29: ='Raw IS'!C29 -> 14.91 | E29: ='Raw IS'!D29 -> -40.24 | F29: ='Raw IS'!E29 -> 6.5 | G29: ='Raw IS'!F29 -> -0.15 | H29: ='Raw IS'!G29 -> -21.84 | I29: ='Raw IS'!H29 -> 15.35 | J29: ='Raw IS'!I29 -> 0.86 | ... L29: ='Raw IS'!K29 -> 35.53 | AY29: Expected Growth | AZ29: ="" | BA29: =IFERROR(BA25*BA27,"") -> 0.044750494 | BB29: =IFERROR(BB25*BB27,"") -> 0.15307857 | BC29: =IFERROR(BC25*BC27,"") -> 0.10892298 | BD29: =IFERROR(BD25*BD27,"") -> 0.10224815 | BE29: =IFERROR(BE25*BE27,"") -> 0.099940206 | BF29: =IFERROR(BF25*BF27,"") -> -0.016687193 | BG29: =IFERROR(BG25*BG27,"") -> 0.016142217 | BH29: =IFERROR(BH25*BH27,"") -> 0.11237126 | BI29: =IFERROR(BI25*BI27,"") -> 0.0042800105 | BJ29: =AVERAGE(BA29:BI29) -> 0.069449632 | BK29: Average expected growth
B30: Other Tax Adjustments | C30: ='Raw IS'!B30 -> 0 | D30: ='Raw IS'!C30 -> -12.72 | E30: ='Raw IS'!D30 -> -1.24 | F30: ='Raw IS'!E30 -> 0 | G30: ='Raw IS'!F30 -> 0.62 | H30: ='Raw IS'!G30 -> 0.24 | I30: ='Raw IS'!H30 -> -0.54 | J30: ='Raw IS'!I30 -> 0 | ... L30: ='Raw IS'!K30 -> 0.44 | AL30: DuPont Analysis
B31: Current Tax - MAT / MAT Credit Entitlement | C31: ='Raw IS'!B31 -> 0 | D31: ='Raw IS'!C31 -> 0 | E31: ='Raw IS'!D31 -> 0 | F31: ='Raw IS'!E31 -> 0 | G31: ='Raw IS'!F31 -> 0 | H31: ='Raw IS'!G31 -> 0 | I31: ='Raw IS'!H31 -> 0 | J31: ='Raw IS'!I31 -> 0 | ... L31: ='Raw IS'!K31 -> 0 | AL31: PAT Margin (%) | AM31: =IFERROR(O17/O3,0) -> -0.10138883 | AN31: =IFERROR(P17/P3,0) -> -0.16338281 | AO31: =IFERROR(Q17/Q3,0) -> -0.021651625 | AP31: =IFERROR(R17/R3,0) -> -0.054534253 | AQ31: =IFERROR(S17/S3,0) -> 0.02779442 | AR31: =IFERROR(T17/T3,0) -> 0.026027106 | AS31: =IFERROR(U17/U3,0) -> -0.1505711 | AT31: =IFERROR(V17/V3,0) -> -0.052523374 | ... AV31: =IFERROR(X17/X3,0) -> 0.21500102 | AY31: Working Capital as a Percentage of Sales
B32: Fringe Benefits Tax | C32: ='Raw IS'!B32 -> 0 | D32: ='Raw IS'!C32 -> 0 | E32: ='Raw IS'!D32 -> 0 | F32: ='Raw IS'!E32 -> 0 | G32: ='Raw IS'!F32 -> 0 | H32: ='Raw IS'!G32 -> 0 | I32: ='Raw IS'!H32 -> 0 | J32: ='Raw IS'!I32 -> 0 | ... L32: ='Raw IS'!K32 -> 0 | AL32: Asset Turnover (x) | AM32: ="" | AN32: =IFERROR(P3/AVERAGE(P49,O49),NA()) -> 0.34514112 | AO32: =IFERROR(Q3/AVERAGE(Q49,P49),NA()) -> 0.37211466 | AP32: =IFERROR(R3/AVERAGE(R49,Q49),NA()) -> 0.35351809 | AQ32: =IFERROR(S3/AVERAGE(S49,R49),NA()) -> 0.40004081 | AR32: =IFERROR(T3/AVERAGE(T49,S49),NA()) -> 0.39691924 | AS32: =IFERROR(U3/AVERAGE(U49,T49),NA()) -> 0.41270231 | AT32: =IFERROR(V3/AVERAGE(V49,U49),NA()) -> 0.55255957 | AU32: =IFERROR(W3/AVERAGE(W49,V49),NA()) -> 0.61791843 | AV32: =IFERROR(X3/AVERAGE(X49,W49),NA()) -> 0.60338213 | AY32: Sales | AZ32: =C3 -> 698.67 | BA32: =D3 -> 814.98 | BB32: =E3 -> 1180.05 | BC32: =F3 -> 1103.71 | BD32: =G3 -> 1235.14 | BE32: =H3 -> 1269.83 | BF32: =I3 -> 1343.02 | BG32: =J3 -> 1785.11 | ... BI32: =L3 -> 2201.85 | BJ32: =AVERAGE(AZ32:BI32) -> 1374.333
B33: Provision for Wealth Tax | C33: ='Raw IS'!B33 -> 0 | D33: ='Raw IS'!C33 -> 0 | E33: ='Raw IS'!D33 -> 0 | F33: ='Raw IS'!E33 -> 0 | G33: ='Raw IS'!F33 -> 0 | H33: ='Raw IS'!G33 -> 0 | I33: ='Raw IS'!H33 -> 0 | J33: ='Raw IS'!I33 -> 0 | ... L33: ='Raw IS'!K33 -> 0 | AL33: Financial Leverage (x) | AM33: ="" | AN33: =IFERROR(AVERAGE(P49,O49)/AVERAGE(SUM(P51:P52),SUM(O51:O52)),NA()) -> 1.2609066 | AO33: =IFERROR(AVERAGE(Q49,P49)/AVERAGE(SUM(Q51:Q52),SUM(P51:P52)),NA()) -> 1.1966792 | AP33: =IFERROR(AVERAGE(R49,Q49)/AVERAGE(SUM(R51:R52),SUM(Q51:Q52)),NA()) -> 1.2121597 | AQ33: =IFERROR(AVERAGE(S49,R49)/AVERAGE(SUM(S51:S52),SUM(R51:R52)),NA()) -> 1.2136108 | AR33: =IFERROR(AVERAGE(T49,S49)/AVERAGE(SUM(T51:T52),SUM(S51:S52)),NA()) -> 1.2363543 | AS33: =IFERROR(AVERAGE(U49,T49)/AVERAGE(SUM(U51:U52),SUM(T51:T52)),NA()) -> 1.2878499 | AT33: =IFERROR(AVERAGE(V49,U49)/AVERAGE(SUM(V51:V52),SUM(U51:U52)),NA()) -> 1.3257633 | AU33: =IFERROR(AVERAGE(W49,V49)/AVERAGE(SUM(W51:W52),SUM(V51:V52)),NA()) -> 1.3975606 | AV33: =IFERROR(AVERAGE(X49,W49)/AVERAGE(SUM(X51:X52),SUM(W51:W52)),NA()) -> 1.4122132 | AY33: Change in Sales | AZ33: ="" | BA33: =BA32-AZ32 -> 116.31 | BB33: =BB32-BA32 -> 365.07 | BC33: =BC32-BB32 -> -76.34 | BD33: =BD32-BC32 -> 131.43 | BE33: =BE32-BD32 -> 34.69 | BF33: =BF32-BE32 -> 73.19 | BG33: =BG32-BF32 -> 442.09 | BH33: =BH32-BG32 -> 325.86 | BI33: =BI32-BH32 -> 90.88 | BJ33: =AVERAGE(BA33:BI33) -> 167.02
B34: Adjust for Previous Year | C34: ='Raw IS'!B34 -> 0 | D34: ='Raw IS'!C34 -> -12.72 | E34: ='Raw IS'!D34 -> -1.24 | F34: ='Raw IS'!E34 -> 0 | G34: ='Raw IS'!F34 -> 0.62 | H34: ='Raw IS'!G34 -> 0.24 | I34: ='Raw IS'!H34 -> -0.54 | J34: ='Raw IS'!I34 -> 0 | ... L34: ='Raw IS'!K34 -> 0.44 | AL34: ROE (%) | AM34: ="" | AN34: =IFERROR(AN31*AN32*AN33,NA()) -> -0.071102682 | AO34: =IFERROR(AO31*AO32*AO33,NA()) -> -0.0096415094 | AP34: =IFERROR(AP31*AP32*AP33,NA()) -> -0.02336904 | AQ34: =IFERROR(AQ31*AQ32*AQ33,NA()) -> 0.013494019 | AR34: =IFERROR(AR31*AR32*AR33,NA()) -> 0.012772355 | AS34: =IFERROR(AS31*AS32*AS33,NA()) -> -0.080028336 | AT34: =IFERROR(AT31*AT32*AT33,NA()) -> -0.038476691 | AU34: =IFERROR(AU31*AU32*AU33,NA()) -> 0.056258169 | AV34: =IFERROR(AV31*AV32*AV33,NA()) -> 0.18320327 | AY34: Working Capital | AZ34: =AZ20 -> 495.84 | BA34: =BA20 -> 482.96 | BB34: =BB20 -> 756.87 | BC34: =BC20 -> 722.69 | BD34: =BD20 -> 782.53 | BE34: =BE20 -> 1030.84 | BF34: =BF20 -> 1057.28 | BG34: =BG20 -> 1198.37 | ... BI34: =BI20 -> 1511.67 | BJ34: =AVERAGE(AZ34:BI34) -> 953.613
B35: Others | C35: ='Raw IS'!B35 -> 0 | D35: ='Raw IS'!C35 -> 0 | E35: ='Raw IS'!D35 -> 0 | F35: ='Raw IS'!E35 -> 0 | G35: ='Raw IS'!F35 -> 0 | H35: ='Raw IS'!G35 -> 0 | I35: ='Raw IS'!H35 -> 0 | J35: ='Raw IS'!I35 -> 0 | ... L35: ='Raw IS'!K35 -> 0 | AY35: Change in Working Capital | AZ35: =AZ21 | BA35: =BA21 -> -12.88 | BB35: =BB21 -> 273.91 | BC35: =BC21 -> -34.18 | BD35: =BD21 -> 59.84 | BE35: =BE21 -> 248.31 | BF35: =BF21 -> 26.44 | BG35: =BG21 -> 141.09 | ... BI35: =BI21 -> 14.59 | BJ35: =AVERAGE(BA35:BI35) -> 112.87
B36: Profit After Tax | C36: ='Raw IS'!B36 -> -70.72 | D36: ='Raw IS'!C36 -> -133.1 | E36: ='Raw IS'!D36 -> -25.56 | F36: ='Raw IS'!E36 -> -60.18 | G36: ='Raw IS'!F36 -> 34.32 | H36: ='Raw IS'!G36 -> 33.06 | I36: ='Raw IS'!H36 -> -202.23 | J36: ='Raw IS'!I36 -> -93.76 | ... L36: ='Raw IS'!K36 -> 252.84 | AL36: Liquidity & Working Capital | AY36: Working Capital as % of Sales | AZ36: =IFERROR(AZ34/AZ32,"") -> 0.70969127 | BA36: =IFERROR(BA34/BA32,"") -> 0.5926035 | BB36: =IFERROR(BB34/BB32,"") -> 0.64138808 | BC36: =IFERROR(BC34/BC32,"") -> 0.65478251 | BD36: =IFERROR(BD34/BD32,"") -> 0.63355571 | BE36: =IFERROR(BE34/BE32,"") -> 0.8117937 | BF36: =IFERROR(BF34/BF32,"") -> 0.7872407 | BG36: =IFERROR(BG34/BG32,"") -> 0.67131437 | ... BI36: =IFERROR(BI34/BI32,"") -> 0.68654541 | BJ36: =AVERAGE(AZ36:BI36) -> 0.68981058
AL37: Receivable Days | AM37: ="" | AN37: =IFERROR(AVERAGE(P45,O45)/P3*365,"") -> 132.68491 | AO37: =IFERROR(AVERAGE(Q45,P45)/Q3*365,"") -> 110.26399 | AP37: =IFERROR(AVERAGE(R45,Q45)/R3*365,"") -> 136.61168 | AQ37: =IFERROR(AVERAGE(S45,R45)/S3*365,"") -> 94.624759 | AR37: =IFERROR(AVERAGE(T45,S45)/T3*365,"") -> 107.17202 | AS37: =IFERROR(AVERAGE(U45,T45)/U3*365,"") -> 147.30914 | AT37: =IFERROR(AVERAGE(V45,U45)/V3*365,"") -> 125.84363 | AU37: =IFERROR(AVERAGE(W45,V45)/W3*365,"") -> 122.8603 | AV37: =IFERROR(AVERAGE(X45,W45)/X3*365,"") -> 133.22827 | AY37: Change in Working Capital as % of Change in Sales | AZ37: ="" | BA37: =IFERROR(BA35/BA33,"") -> -0.11073854 | BB37: =IFERROR(BB35/BB33,"") -> 0.75029446 | BC37: =IFERROR(BC35/BC33,"") -> 0.44773382 | BD37: =IFERROR(BD35/BD33,"") -> 0.4552994 | BE37: =IFERROR(BE35/BE33,"") -> 7.1579706 | BF37: =IFERROR(BF35/BF33,"") -> 0.36125154 | BG37: =IFERROR(BG35/BG33,"") -> 0.31914316 | BH37: =IFERROR(BH35/BH33,"") -> 0.91668201 | BI37: =IFERROR(BI35/BI33,"") -> 0.16054137 | BJ37: =AVERAGE(BA37:BI37) -> 1.1620198 | BK37: Historical average
AL38: Inventory Days | AM38: ="" | AN38: =IFERROR(AVERAGE(P44,O44)/P6*365,"") -> 282.50949 | AO38: =IFERROR(AVERAGE(Q44,P44)/Q6*365,"") -> 250.98932 | AP38: =IFERROR(AVERAGE(R44,Q44)/R6*365,"") -> 346.55956 | AQ38: =IFERROR(AVERAGE(S44,R44)/S6*365,"") -> 449.71032 | AR38: =IFERROR(AVERAGE(T44,S44)/T6*365,"") -> 499.69266 | AS38: =IFERROR(AVERAGE(U44,T44)/U6*365,"") -> 405.94018 | AT38: =IFERROR(AVERAGE(V44,U44)/V6*365,"") -> 337.27694 | AU38: =IFERROR(AVERAGE(W44,V44)/W6*365,"") -> 364.50554 | AV38: =IFERROR(AVERAGE(X44,W44)/X6*365,"") -> 447.97694
B39: Finance >>Balance Sheet IND (Consolidated)>>Unichem Laboratories Ltd(Curr. in ) | N39: CONDENSED BALANCE SHEET (₹ crore) | Z39: REFORMULATED BALANCE SHEET (₹ crore) | AL39: Payable Days | AM39: ="" | AN39: =IFERROR(AVERAGE(P57,O57)/P6*365,"") -> 222.59651 | AO39: =IFERROR(AVERAGE(Q57,P57)/Q6*365,"") -> 183.7272 | AP39: =IFERROR(AVERAGE(R57,Q57)/R6*365,"") -> 222.31758 | AQ39: =IFERROR(AVERAGE(S57,R57)/S6*365,"") -> 221.42057 | AR39: =IFERROR(AVERAGE(T57,S57)/T6*365,"") -> 172.59884 | AS39: =IFERROR(AVERAGE(U57,T57)/U6*365,"") -> 156.97657 | AT39: =IFERROR(AVERAGE(V57,U57)/V6*365,"") -> 159.02793 | AU39: =IFERROR(AVERAGE(W57,V57)/W6*365,"") -> 155.98724 | AV39: =IFERROR(AVERAGE(X57,W57)/X6*365,"") -> 169.62903
B40: Year | C40: 201703 | D40: 201803 | E40: 201903 | F40: 202003 | G40: 202103 | H40: 202203 | I40: 202303 | J40: 202403 | K40: 202503 | L40: 202603 | N40: Year | O40: 201703 | P40: 201803 | Q40: 201903 | R40: 202003 | S40: 202103 | T40: 202203 | U40: 202303 | V40: 202403 | W40: 202503 | X40: 202603 | Z40: Year | AA40: 201703 | AB40: 201803 | AC40: 201903 | AD40: 202003 | AE40: 202103 | AF40: 202203 | AG40: 202303 | AH40: 202403 | AI40: 202503 | AJ40: 202603 | AL40: Operating Cycle | AM40: ="" | AN40: =IFERROR(AN37+AN38,"") -> 415.1944 | AO40: =IFERROR(AO37+AO38,"") -> 361.25331 | AP40: =IFERROR(AP37+AP38,"") -> 483.17124 | AQ40: =IFERROR(AQ37+AQ38,"") -> 544.33508 | AR40: =IFERROR(AR37+AR38,"") -> 606.86469 | AS40: =IFERROR(AS37+AS38,"") -> 553.24933 | AT40: =IFERROR(AT37+AT38,"") -> 463.12058 | AU40: =IFERROR(AU37+AU38,"") -> 487.36584 | AV40: =IFERROR(AV37+AV38,"") -> 581.20522
B41: Non-Current Assets: | C41: ='Raw BS'!B3 -> 0 | D41: ='Raw BS'!C3 -> 0 | E41: ='Raw BS'!D3 -> 0 | F41: ='Raw BS'!E3 -> 0 | G41: ='Raw BS'!F3 -> 0 | H41: ='Raw BS'!G3 -> 0 | I41: ='Raw BS'!H3 -> 0 | J41: ='Raw BS'!I3 -> 0 | ... L41: ='Raw BS'!K3 -> 0 | N41: Fixed Assets | O41: =SUM(C43:C50) -> 737.2 | P41: =SUM(D43:D50) -> 812.6 | Q41: =SUM(E43:E50) -> 898.68 | R41: =SUM(F43:F50) -> 1147.22 | S41: =SUM(G43:G50) -> 1401.86 | T41: =SUM(H43:H50) -> 1483.85 | U41: =SUM(I43:I50) -> 1404.11 | V41: =SUM(J43:J50) -> 1375.11 | ... X41: =SUM(L43:L50) -> 1312.72 | Z41: OPERATING ASSETS | AL41: Cash Conversion Cycle | AM41: ="" | AN41: =IFERROR(AN40-AN39,"") -> 192.59789 | AO41: =IFERROR(AO40-AO39,"") -> 177.52611 | AP41: =IFERROR(AP40-AP39,"") -> 260.85366 | AQ41: =IFERROR(AQ40-AQ39,"") -> 322.91451 | AR41: =IFERROR(AR40-AR39,"") -> 434.26585 | AS41: =IFERROR(AS40-AS39,"") -> 396.27276 | AT41: =IFERROR(AT40-AT39,"") -> 304.09265 | AU41: =IFERROR(AU40-AU39,"") -> 331.3786 | AV41: =IFERROR(AV40-AV39,"") -> 411.57619
B42: Fixed Assets | C42: ='Raw BS'!B4 -> 737.19 | D42: ='Raw BS'!C4 -> 812.6 | E42: ='Raw BS'!D4 -> 898.68 | F42: ='Raw BS'!E4 -> 1147.21 | G42: ='Raw BS'!F4 -> 1447.92 | H42: ='Raw BS'!G4 -> 1483.85 | I42: ='Raw BS'!H4 -> 1404.12 | J42: ='Raw BS'!I4 -> 1375.11 | ... L42: ='Raw BS'!K4 -> 1312.72 | N42: Long term investments | O42: =SUM(C52:C53,C55:C56) -> 9.51 | P42: =SUM(D52:D53,D55:D56) -> 9.21 | Q42: =SUM(E52:E53,E55:E56) -> 129.2 | R42: =SUM(F52:F53,F55:F56) -> 134.38 | S42: =SUM(G52:G53,G55:G56) -> 159.12 | T42: =SUM(H52:H53,H55:H56) -> 0.28 | U42: =SUM(I52:I53,I55:I56) -> 0.16 | V42: =SUM(J52:J53,J55:J56) -> 0.02 | ... X42: =SUM(L52:L53,L55:L56) -> 0.02 | Z42: Fixed Assets | AA42: =O41 -> 737.2 | AB42: =P41 -> 812.6 | AC42: =Q41 -> 898.68 | AD42: =R41 -> 1147.22 | AE42: =S41 -> 1401.86 | AF42: =T41 -> 1483.85 | AG42: =U41 -> 1404.11 | AH42: =V41 -> 1375.11 | ... AJ42: =X41 -> 1312.72 | AL42: Current Ratio | AM42: =IFERROR(SUM(O44:O48)/SUM(O57:O60),0) -> 1.9063702 | AN42: =IFERROR(SUM(P44:P48)/SUM(P57:P60),0) -> 5.0407974 | AO42: =IFERROR(SUM(Q44:Q48)/SUM(Q57:Q60),0) -> 4.0531496 | AP42: =IFERROR(SUM(R44:R48)/SUM(R57:R60),0) -> 2.9970855 | AQ42: =IFERROR(SUM(S44:S48)/SUM(S57:S60),0) -> 2.7457438 | AR42: =IFERROR(SUM(T44:T48)/SUM(T57:T60),0) -> 2.9855107 | AS42: =IFERROR(SUM(U44:U48)/SUM(U57:U60),0) -> 2.4835366 | AT42: =IFERROR(SUM(V44:V48)/SUM(V57:V60),0) -> 2.3635033 | ... AV42: =IFERROR(SUM(X44:X48)/SUM(X57:X60),0) -> 2.4839041
B43: Property, Plant and Equipment | C43: ='Raw BS'!B5 -> 484.03 | D43: ='Raw BS'!C5 -> 572.44 | E43: ='Raw BS'!D5 -> 804.5 | F43: ='Raw BS'!E5 -> 815.2 | G43: ='Raw BS'!F5 -> 832.81 | H43: ='Raw BS'!G5 -> 924.49 | I43: ='Raw BS'!H5 -> 1196.12 | J43: ='Raw BS'!I5 -> 1125.2 | ... L43: ='Raw BS'!K5 -> 1135.9 | N43: Other non-current assets | O43: =SUM(C57:C62) -> 31.49 | P43: =SUM(D57:D62) -> 35.4 | Q43: =SUM(E57:E62) -> 82.44 | R43: =SUM(F57:F62) -> 127.36 | S43: =SUM(G57:G62) -> 141.35 | T43: =SUM(H57:H62) -> 186.26 | U43: =SUM(I57:I62) -> 196.9 | V43: =SUM(J57:J62) -> 153.15 | ... X43: =SUM(L57:L62) -> 224.11 | Z43: Other Non-current Operating Assets | AA43: =O43 -> 31.49 | AB43: =P43 -> 35.4 | AC43: =Q43 -> 82.44 | AD43: =R43 -> 127.36 | AE43: =S43 -> 141.35 | AF43: =T43 -> 186.26 | AG43: =U43 -> 196.9 | AH43: =V43 -> 153.15 | ... AJ43: =X43 -> 224.11 | AL43: Quick Ratio | AM43: =IFERROR((SUM(O44:O48)-O44)/SUM(O57:O60),0) -> 1.1888388 | AN43: =IFERROR((SUM(P44:P48)-P44)/SUM(P57:P60),0) -> 4.4521154 | AO43: =IFERROR((SUM(Q44:Q48)-Q44)/SUM(Q57:Q60),0) -> 3.3797622 | AP43: =IFERROR((SUM(R44:R48)-R44)/SUM(R57:R60),0) -> 2.292376 | AQ43: =IFERROR((SUM(S44:S48)-S44)/SUM(S57:S60),0) -> 1.672541 | AR43: =IFERROR((SUM(T44:T48)-T44)/SUM(T57:T60),0) -> 1.8984116 | AS43: =IFERROR((SUM(U44:U48)-U44)/SUM(U57:U60),0) -> 1.5060038 | AT43: =IFERROR((SUM(V44:V48)-V44)/SUM(V57:V60),0) -> 1.36532 | ... AV43: =IFERROR((SUM(X44:X48)-X44)/SUM(X57:X60),0) -> 1.383412
B44: Capital Work in Progress | C44: ='Raw BS'!B6 -> 249.98 | D44: ='Raw BS'!C6 -> 238.15 | E44: ='Raw BS'!D6 -> 92.39 | F44: ='Raw BS'!E6 -> 330.47 | G44: ='Raw BS'!F6 -> 567.5 | H44: ='Raw BS'!G6 -> 493.81 | I44: ='Raw BS'!H6 -> 147.45 | J44: ='Raw BS'!I6 -> 122.71 | ... L44: ='Raw BS'!K6 -> 100.14 | N44: Inventories | O44: =C65 -> 281.71 | P44: =D65 -> 272.86 | Q44: =E65 -> 338.66 | R44: =F65 -> 396.54 | S44: =G65 -> 538.34 | T44: =H65 -> 600.22 | U44: =I65 -> 625.23 | V44: =J65 -> 736.26 | ... X44: =L65 -> 974.97 | Z44: Inventories | AA44: =O44 -> 281.71 | AB44: =P44 -> 272.86 | AC44: =Q44 -> 338.66 | AD44: =R44 -> 396.54 | AE44: =S44 -> 538.34 | AF44: =T44 -> 600.22 | AG44: =U44 -> 625.23 | AH44: =V44 -> 736.26 | ... AJ44: =X44 -> 974.97 | AL44: Cash Ratio | AM44: =IFERROR(SUM(O46:O47)/SUM(O57:O60),0) -> 0.061485953 | AN44: =IFERROR(SUM(P46:P47)/SUM(P57:P60),0) -> 3.4023214 | AO44: =IFERROR(SUM(Q46:Q47)/SUM(Q57:Q60),0) -> 1.9918476 | AP44: =IFERROR(SUM(R46:R47)/SUM(R57:R60),0) -> 1.1603163 | AQ44: =IFERROR(SUM(S46:S47)/SUM(S57:S60),0) -> 0.63570033 | AR44: =IFERROR(SUM(T46:T47)/SUM(T57:T60),0) -> 0.68405991 | AS44: =IFERROR(SUM(U46:U47)/SUM(U57:U60),0) -> 0.29221388 | AT44: =IFERROR(SUM(V46:V47)/SUM(V57:V60),0) -> 0.21624187 | ... AV44: =IFERROR(SUM(X46:X47)/SUM(X57:X60),0) -> 0.33264104
B45: Right-of-Use Assets | C45: ='Raw BS'!B7 -> 0 | D45: ='Raw BS'!C7 -> 0 | E45: ='Raw BS'!D7 -> 0 | F45: ='Raw BS'!E7 -> 0 | G45: ='Raw BS'!F7 -> 0 | H45: ='Raw BS'!G7 -> 64 | I45: ='Raw BS'!H7 -> 58.99 | J45: ='Raw BS'!I7 -> 69.29 | ... L45: ='Raw BS'!K7 -> 67.8 | N45: Trade Receivables | O45: =C69 -> 315.32 | P45: =D69 -> 276.92 | Q45: =E69 -> 436.05 | R45: =F69 -> 390.14 | S45: =G69 -> 250.27 | T45: =H69 -> 495.43 | U45: =I69 -> 588.62 | V45: =J69 -> 642.31 | ... X45: =L69 -> 828.58 | Z45: Trade Receivables | AA45: =O45 -> 315.32 | AB45: =P45 -> 276.92 | AC45: =Q45 -> 436.05 | AD45: =R45 -> 390.14 | AE45: =S45 -> 250.27 | AF45: =T45 -> 495.43 | AG45: =U45 -> 588.62 | AH45: =V45 -> 642.31 | ... AJ45: =X45 -> 828.58
B46: Intangible Assets | C46: ='Raw BS'!B8 -> 3.19 | D46: ='Raw BS'!C8 -> 2.01 | E46: ='Raw BS'!D8 -> 1.79 | F46: ='Raw BS'!E8 -> 1.55 | G46: ='Raw BS'!F8 -> 1.55 | H46: ='Raw BS'!G8 -> 1.55 | I46: ='Raw BS'!H8 -> 1.55 | J46: ='Raw BS'!I8 -> 57.91 | ... L46: ='Raw BS'!K8 -> 8.88 | N46: Short term investments | O46: =C68 -> 8 | P46: =D68 -> 895.55 | Q46: =E68 -> 800.75 | R46: =F68 -> 419.1 | S46: =G68 -> 236.43 | T46: =H68 -> 263.58 | U46: =I68 -> 1.54 | V46: =J68 -> 1.34 | ... X46: =L68 -> 0 | Z46: Other Current Operating Assets | AA46: =O48 -> 127.29 | AB46: =P48 -> 209.67 | AC46: =Q48 -> 261.96 | AD46: =R48 -> 246.87 | AE46: =S48 -> 269.83 | AF46: =T48 -> 175.05 | AG46: =U48 -> 187.72 | AH46: =V48 -> 205.25 | ... AJ46: =X48 -> 102.34 | AL46: Solvency Ratios
B47: Intangible Assets under Development | C47: ='Raw BS'!B9 -> 0 | D47: ='Raw BS'!C9 -> 0 | E47: ='Raw BS'!D9 -> 0 | F47: ='Raw BS'!E9 -> 0 | G47: ='Raw BS'!F9 -> 0 | H47: ='Raw BS'!G9 -> 0 | I47: ='Raw BS'!H9 -> 0 | J47: ='Raw BS'!I9 -> 0 | ... L47: ='Raw BS'!K9 -> 0 | N47: Cash and Cash Equivalents | O47: =SUM(C70:C71) -> 16.14 | P47: =SUM(D70:D71) -> 681.46 | Q47: =SUM(E70:E71) -> 200.99 | R47: =SUM(F70:F71) -> 233.81 | S47: =SUM(G70:G71) -> 82.45 | T47: =SUM(H70:H71) -> 114.11 | U47: =SUM(I70:I71) -> 185.36 | V47: =SUM(J70:J71) -> 158.16 | ... X47: =SUM(L70:L71) -> 294.7 | Z47: Total Operating Assets | AA47: =SUM(AA42:AA46) -> 1493.01 | AB47: =SUM(AB42:AB46) -> 1607.45 | AC47: =SUM(AC42:AC46) -> 2017.79 | AD47: =SUM(AD42:AD46) -> 2308.13 | AE47: =SUM(AE42:AE46) -> 2601.65 | AF47: =SUM(AF42:AF46) -> 2940.81 | AG47: =SUM(AG42:AG46) -> 3002.58 | AH47: =SUM(AH42:AH46) -> 3112.08 | ... AJ47: =SUM(AJ42:AJ46) -> 3442.72 | AL47: Debt / Equity | AM47: =IFERROR((O54+O55+O58+O59)/SUM(O51:O52),0) -> 0.092204117 | AN47: =IFERROR((P54+P55+P58+P59)/SUM(P51:P52),0) -> 0.056199605 | AO47: =IFERROR((Q54+Q55+Q58+Q59)/SUM(Q51:Q52),0) -> 0.076212542 | AP47: =IFERROR((R54+R55+R58+R59)/SUM(R51:R52),0) -> 0.072700338 | AQ47: =IFERROR((S54+S55+S58+S59)/SUM(S51:S52),0) -> 0.039357329 | AR47: =IFERROR((T54+T55+T58+T59)/SUM(T51:T52),0) -> 0.1293915 | AS47: =IFERROR((U54+U55+U58+U59)/SUM(U51:U52),0) -> 0.12635404 | AT47: =IFERROR((V54+V55+V58+V59)/SUM(V51:V52),0) -> 0.093331419 | ... AV47: =IFERROR((X54+X55+X58+X59)/SUM(X51:X52),0) -> 0.1840519
B48: Fixed Assets Held For Sale | C48: ='Raw BS'!B10 -> 0 | D48: ='Raw BS'!C10 -> 0 | E48: ='Raw BS'!D10 -> 0 | F48: ='Raw BS'!E10 -> 0 | G48: ='Raw BS'!F10 -> 0 | H48: ='Raw BS'!G10 -> 0 | I48: ='Raw BS'!H10 -> 0 | J48: ='Raw BS'!I10 -> 0 | ... L48: ='Raw BS'!K10 -> 0 | N48: Other current assets | O48: =SUM(C66,C72:C77) -> 127.29 | P48: =SUM(D66,D72:D77) -> 209.67 | Q48: =SUM(E66,E72:E77) -> 261.96 | R48: =SUM(F66,F72:F77) -> 246.87 | S48: =SUM(G66,G72:G77) -> 269.83 | T48: =SUM(H66,H72:H77) -> 175.05 | U48: =SUM(I66,I72:I77) -> 187.72 | V48: =SUM(J66,J72:J77) -> 205.25 | ... X48: =SUM(L66,L72:L77) -> 102.34 | AL48: Debt / Capital | AM48: =IFERROR((O54+O55+O58+O59)/((O54+O55+O58+O59)+SUM(O51:O52)),0) -> 0.084420224 | AN48: =IFERROR((P54+P55+P58+P59)/((P54+P55+P58+P59)+SUM(P51:P52)),0) -> 0.053209266 | AO48: =IFERROR((Q54+Q55+Q58+Q59)/((Q54+Q55+Q58+Q59)+SUM(Q51:Q52)),0) -> 0.070815512 | AP48: =IFERROR((R54+R55+R58+R59)/((R54+R55+R58+R59)+SUM(R51:R52)),0) -> 0.067773203 | AQ48: =IFERROR((S54+S55+S58+S59)/((S54+S55+S58+S59)+SUM(S51:S52)),0) -> 0.037866986 | AR48: =IFERROR((T54+T55+T58+T59)/((T54+T55+T58+T59)+SUM(T51:T52)),0) -> 0.11456745 | AS48: =IFERROR((U54+U55+U58+U59)/((U54+U55+U58+U59)+SUM(U51:U52)),0) -> 0.11217969 | AT48: =IFERROR((V54+V55+V58+V59)/((V54+V55+V58+V59)+SUM(V51:V52)),0) -> 0.085364253 | ... AV48: =IFERROR((X54+X55+X58+X59)/((X54+X55+X58+X59)+SUM(X51:X52)),0) -> 0.15544243
B49: Lease Adjustment | C49: ='Raw BS'!B11 -> 0 | D49: ='Raw BS'!C11 -> 0 | E49: ='Raw BS'!D11 -> 0 | F49: ='Raw BS'!E11 -> 0 | G49: ='Raw BS'!F11 -> 0 | H49: ='Raw BS'!G11 -> 0 | I49: ='Raw BS'!H11 -> 0 | J49: ='Raw BS'!I11 -> 0 | ... L49: ='Raw BS'!K11 -> 0 | N49: Total assets | O49: =SUM(O41:O48) -> 1526.66 | P49: =SUM(P41:P48) -> 3193.67 | Q49: =SUM(Q41:Q48) -> 3148.73 | R49: =SUM(R41:R48) -> 3095.42 | S49: =SUM(S41:S48) -> 3079.65 | T49: =SUM(T41:T48) -> 3318.78 | U49: =SUM(U41:U48) -> 3189.64 | V49: =SUM(V41:V48) -> 3271.6 | ... X49: =SUM(X41:X48) -> 3737.44 | Z49: FINANCIAL ASSETS | AL49: Debt / EBITDA | AM49: =IFERROR((O54+O55+O58+O59)/O9,0) -> -2.7314763 | AN49: =IFERROR((P54+P55+P58+P59)/P9,0) -> -2.1211097 | AO49: =IFERROR((Q54+Q55+Q58+Q59)/Q9,0) -> 13.382708 | AP49: =IFERROR((R54+R55+R58+R59)/R9,0) -> 4.5450729 | AQ49: =IFERROR((S54+S55+S58+S59)/S9,0) -> 0.71217268 | AR49: =IFERROR((T54+T55+T58+T59)/T9,0) -> 2.8162926 | AS49: =IFERROR((U54+U55+U58+U59)/U9,0) -> -43.708807 | AT49: =IFERROR((V54+V55+V58+V59)/V9,0) -> 1.9209082 | ... AV49: =IFERROR((X54+X55+X58+X59)/X9,0) -> 1.0691763
B50: Biological Assets other than Bearer Plants | C50: ='Raw BS'!B12 -> 0 | D50: ='Raw BS'!C12 -> 0 | E50: ='Raw BS'!D12 -> 0 | F50: ='Raw BS'!E12 -> 0 | G50: ='Raw BS'!F12 -> 0 | H50: ='Raw BS'!G12 -> 0 | I50: ='Raw BS'!H12 -> 0 | J50: ='Raw BS'!I12 -> 0 | ... L50: ='Raw BS'!K12 -> 0 | Z50: Long-term Investments | AA50: =O42 -> 9.51 | AB50: =P42 -> 9.21 | AC50: =Q42 -> 129.2 | AD50: =R42 -> 134.38 | AE50: =S42 -> 159.12 | AF50: =T42 -> 0.28 | AG50: =U42 -> 0.16 | AH50: =V42 -> 0.02 | ... AJ50: =X42 -> 0.02 | AL50: Net Debt / EBITDA | AM50: =IFERROR(((O54+O55+O58+O59)-O46-O47)/O9,0) -> -2.0590529 | AN50: =IFERROR(((P54+P55+P58+P59)-P46-P47)/P9,0) -> 20.087171 | AO50: =IFERROR(((Q54+Q55+Q58+Q59)-Q46-Q47)/Q9,0) -> -53.758043 | AP50: =IFERROR(((R54+R55+R58+R59)-R46-R47)/R9,0) -> -11.580143 | AQ50: =IFERROR(((S54+S55+S58+S59)-S46-S47)/S9,0) -> -1.544586 | AR50: =IFERROR(((T54+T55+T58+T59)-T46-T47)/T9,0) -> -0.32327515 | AS50: =IFERROR(((U54+U55+U58+U59)-U46-U47)/U9,0) -> -17.160511 | AT50: =IFERROR(((V54+V55+V58+V59)-V46-V47)/V9,0) -> 0.57457584 | ... AV50: =IFERROR(((X54+X55+X58+X59)-X46-X47)/X9,0) -> 0.4391928
B51: Non-current Investments | C51: ='Raw BS'!B13 -> 0 | D51: ='Raw BS'!C13 -> 0 | E51: ='Raw BS'!D13 -> 0 | F51: ='Raw BS'!E13 -> 0 | G51: ='Raw BS'!F13 -> 0 | H51: ='Raw BS'!G13 -> 0 | I51: ='Raw BS'!H13 -> 0 | J51: ='Raw BS'!I13 -> 0 | ... L51: ='Raw BS'!K13 -> 0 | N51: Common Share Capital | O51: =C88 -> 18.18 | P51: =D88 -> 14.07 | Q51: =E88 -> 14.08 | R51: =F88 -> 14.08 | S51: =G88 -> 14.08 | T51: =H88 -> 14.08 | U51: =I88 -> 14.08 | V51: =J88 -> 14.08 | ... X51: =L88 -> 14.08 | Z51: Short-term Investments | AA51: =O46 -> 8 | AB51: =P46 -> 895.55 | AC51: =Q46 -> 800.75 | AD51: =R46 -> 419.1 | AE51: =S46 -> 236.43 | AF51: =T46 -> 263.58 | AG51: =U46 -> 1.54 | AH51: =V46 -> 1.34 | ... AJ51: =X46 -> 0 | AL51: Interest Coverage | AM51: =IFERROR(O11/O12,0) -> -23.636905 | AN51: =IFERROR(P11/P12,0) -> -15.171036 | AO51: =IFERROR(Q11/Q12,0) -> -6.974734 | AP51: =IFERROR(R11/R12,0) -> -5.2458599 | AQ51: =IFERROR(S11/S12,0) -> 11.121094 | AR51: =IFERROR(T11/T12,0) -> 4.7675941 | AS51: =IFERROR(U11/U12,0) -> -6.9601386 | AT51: =IFERROR(V11/V12,0) -> -0.20697264 | ... AV51: =IFERROR(X11/X12,0) -> 10.84742
B52: Investment Properties | C52: ='Raw BS'!B14 -> 3.79 | D52: ='Raw BS'!C14 -> 3.72 | E52: ='Raw BS'!D14 -> 3.66 | F52: ='Raw BS'!E14 -> 3.6 | G52: ='Raw BS'!F14 -> 3.53 | H52: ='Raw BS'!G14 -> 0 | I52: ='Raw BS'!H14 -> 0 | J52: ='Raw BS'!I14 -> 0 | ... L52: ='Raw BS'!K14 -> 0 | N52: Other Equity | O52: =C96 -> 1045.33 | P52: =D96 -> 2666.02 | Q52: =E96 -> 2605.83 | R52: =F96 -> 2517.27 | S52: =G96 -> 2542.75 | T52: =H96 -> 2604.33 | U52: =I96 -> 2421.22 | V52: =J96 -> 2424.22 | ... X52: =L96 -> 2703.36 | Z52: Cash & Cash Equivalents | AA52: =O47 -> 16.14 | AB52: =P47 -> 681.46 | AC52: =Q47 -> 200.99 | AD52: =R47 -> 233.81 | AE52: =S47 -> 82.45 | AF52: =T47 -> 114.11 | AG52: =U47 -> 185.36 | AH52: =V47 -> 158.16 | ... AJ52: =X47 -> 294.7
B53: Investments in Subsidiaries, Associates and Joint venture | C53: ='Raw BS'!B15 -> 5.62 | D53: ='Raw BS'!C15 -> 5.4 | E53: ='Raw BS'!D15 -> 5.46 | F53: ='Raw BS'!E15 -> 6.27 | G53: ='Raw BS'!F15 -> 5.93 | H53: ='Raw BS'!G15 -> 0 | I53: ='Raw BS'!H15 -> 0 | J53: ='Raw BS'!I15 -> 0 | ... L53: ='Raw BS'!K15 -> 0 | N53: Minority Interest | O53: =C102 -> 0 | P53: =D102 -> 0 | Q53: =E102 -> 0 | R53: =F102 -> 0 | S53: =G102 -> 0 | T53: =H102 -> 0 | U53: =I102 -> 0 | V53: =J102 -> 0 | ... X53: =L102 -> 0 | Z53: Total Financial Assets | AA53: =SUM(AA50:AA52) -> 33.65 | AB53: =SUM(AB50:AB52) -> 1586.22 | AC53: =SUM(AC50:AC52) -> 1130.94 | AD53: =SUM(AD50:AD52) -> 787.29 | AE53: =SUM(AE50:AE52) -> 478 | AF53: =SUM(AF50:AF52) -> 377.97 | AG53: =SUM(AG50:AG52) -> 187.06 | AH53: =SUM(AH50:AH52) -> 159.52 | ... AJ53: =SUM(AJ50:AJ52) -> 294.72 | AL53: Turnover & Efficiency Ratios
B54: Financial Assets : | C54: ='Raw BS'!B16 -> 0 | D54: ='Raw BS'!C16 -> 0 | E54: ='Raw BS'!D16 -> 0 | F54: ='Raw BS'!E16 -> 0 | G54: ='Raw BS'!F16 -> 0 | H54: ='Raw BS'!G16 -> 0 | I54: ='Raw BS'!H16 -> 0 | J54: ='Raw BS'!I16 -> 0 | ... L54: ='Raw BS'!K16 -> 0 | N54: Long Term Borrowings | O54: =C105 -> 0.44 | P54: =D105 -> 0.33 | Q54: =E105 -> 0 | R54: =F105 -> 0 | S54: =G105 -> 0 | T54: =H105 -> 89.01 | U54: =I105 -> 63.65 | V54: =J105 -> 38.22 | ... X54: =L105 -> 39.12 | Z54: Total Assets | AA54: =AA47+AA53 -> 1526.66 | AB54: =AB47+AB53 -> 3193.67 | AC54: =AC47+AC53 -> 3148.73 | AD54: =AD47+AD53 -> 3095.42 | AE54: =AE47+AE53 -> 3079.65 | AF54: =AF47+AF53 -> 3318.78 | AG54: =AG47+AG53 -> 3189.64 | AH54: =AH47+AH53 -> 3271.6 | ... AJ54: =AJ47+AJ53 -> 3737.44 | AL54: Working Capital Turnover | AM54: ="" | AN54: =IFERROR(P3/AVERAGE(SUM(P44:P48)-SUM(P57:P60),SUM(O44:O48)-SUM(O57:O60)),"") -> 0.73096734 | AO54: =IFERROR(Q3/AVERAGE(SUM(Q44:Q48)-SUM(Q57:Q60),SUM(P44:P48)-SUM(P57:P60)),"") -> 0.69242821 | AP54: =IFERROR(R3/AVERAGE(SUM(R44:R48)-SUM(R57:R60),SUM(Q44:Q48)-SUM(Q57:Q60)),"") -> 0.83009119 | AQ54: =IFERROR(S3/AVERAGE(SUM(S44:S48)-SUM(S57:S60),SUM(R44:R48)-SUM(R57:R60)),"") -> 1.2354736 | AR54: =IFERROR(T3/AVERAGE(SUM(T44:T48)-SUM(T57:T60),SUM(S44:S48)-SUM(S57:S60)),"") -> 1.2878862 | AS54: =IFERROR(U3/AVERAGE(SUM(U44:U48)-SUM(U57:U60),SUM(T44:T48)-SUM(T57:T60)),"") -> 1.3133835 | AT54: =IFERROR(V3/AVERAGE(SUM(V44:V48)-SUM(V57:V60),SUM(U44:U48)-SUM(U57:U60)),"") -> 1.8265826 | AU54: =IFERROR(W3/AVERAGE(SUM(W44:W48)-SUM(W57:W60),SUM(V44:V48)-SUM(V57:V60)),"") -> 2.0663169 | AV54: =IFERROR(X3/AVERAGE(SUM(X44:X48)-SUM(X57:X60),SUM(W44:W48)-SUM(W57:W60)),"") -> 1.872202
B55: Investments of Life Insurance Business | C55: ='Raw BS'!B17 -> 0 | D55: ='Raw BS'!C17 -> 0 | E55: ='Raw BS'!D17 -> 0 | F55: ='Raw BS'!E17 -> 0 | G55: ='Raw BS'!F17 -> 0 | H55: ='Raw BS'!G17 -> 0 | I55: ='Raw BS'!H17 -> 0 | J55: ='Raw BS'!I17 -> 0 | ... L55: ='Raw BS'!K17 -> 0 | N55: Lease Liabilities | O55: =C106 -> 0 | P55: =D106 -> 0 | Q55: =E106 -> 0 | R55: =F106 -> 0 | S55: =G106 -> 0 | T55: =H106 -> 4.22 | U55: =I106 -> 5.16 | V55: =J106 -> 4.21 | ... X55: =L106 -> 26 | AL55: Fixed Asset Turnover | AM55: ="" | AN55: =IFERROR(P3/AVERAGE(P41,O41),"") -> 1.0512195 | AO55: =IFERROR(Q3/AVERAGE(Q41,P41),"") -> 1.3791431 | AP55: =IFERROR(R3/AVERAGE(R41,Q41),"") -> 1.0789481 | AQ55: =IFERROR(S3/AVERAGE(S41,R41),"") -> 0.96908689 | AR55: =IFERROR(T3/AVERAGE(T41,S41),"") -> 0.88008151 | AS55: =IFERROR(U3/AVERAGE(U41,T41),"") -> 0.93008213 | AT55: =IFERROR(V3/AVERAGE(V41,U41),"") -> 1.2846122 | AU55: =IFERROR(W3/AVERAGE(W41,V41),"") -> 1.5605892 | AV55: =IFERROR(X3/AVERAGE(X41,W41),"") -> 1.6662
B56: Investments - Long-term | C56: ='Raw BS'!B18 -> 0.1 | D56: ='Raw BS'!C18 -> 0.09 | E56: ='Raw BS'!D18 -> 120.08 | F56: ='Raw BS'!E18 -> 124.51 | G56: ='Raw BS'!F18 -> 149.66 | H56: ='Raw BS'!G18 -> 0.28 | I56: ='Raw BS'!H18 -> 0.16 | J56: ='Raw BS'!I18 -> 0.02 | ... L56: ='Raw BS'!K18 -> 0.02 | N56: Other non-current liabilities | O56: =SUM(C107:C112) -> 69.98 | P56: =SUM(D107:D112) -> 49.74 | Q56: =SUM(E107:E112) -> 26.79 | R56: =SUM(F107:F112) -> 28.2 | S56: =SUM(G107:G112) -> 48.8 | T56: =SUM(H107:H112) -> 44.65 | U56: =SUM(I107:I112) -> 43.01 | V56: =SUM(J107:J112) -> 36.67 | ... X56: =SUM(L107:L112) -> 68.94 | Z56: OPERATING LIABILITIES | AL56: Inventory Turnover | AM56: ="" | AN56: =IFERROR(P6/AVERAGE(P44,O44),"") -> 1.291992 | AO56: =IFERROR(Q6/AVERAGE(Q44,P44),"") -> 1.4542452 | AP56: =IFERROR(R6/AVERAGE(R44,Q44),"") -> 1.05321 | AQ56: =IFERROR(S6/AVERAGE(S44,R44),"") -> 0.81163358 | AR56: =IFERROR(T6/AVERAGE(T44,S44),"") -> 0.73044899 | AS56: =IFERROR(U6/AVERAGE(U44,T44),"") -> 0.89914725 | AT56: =IFERROR(V6/AVERAGE(V44,U44),"") -> 1.0821967 | AU56: =IFERROR(W6/AVERAGE(W44,V44),"") -> 1.0013565 | AV56: =IFERROR(X6/AVERAGE(X44,W44),"") -> 0.81477408
B57: Loans - Long - Term | C57: ='Raw BS'!B19 -> 0.09 | D57: ='Raw BS'!C19 -> 0.07 | E57: ='Raw BS'!D19 -> 0.06 | F57: ='Raw BS'!E19 -> 0.08 | G57: ='Raw BS'!F19 -> 0.07 | H57: ='Raw BS'!G19 -> 0.12 | I57: ='Raw BS'!H19 -> 0.13 | J57: ='Raw BS'!I19 -> 0.13 | ... L57: ='Raw BS'!K19 -> 0.11 | N57: Trade Payables | O57: =C117 -> 210.73 | P57: =D117 -> 226.23 | Q57: =E117 -> 221.41 | R57: =F117 -> 250.22 | S57: =G117 -> 210.08 | T57: =H117 -> 183.19 | U57: =I117 -> 290.69 | V57: =J117 -> 351.26 | ... X57: =L117 -> 356.63 | Z57: Other Non-current Operating Liabilities | AA57: =O56 -> 69.98 | AB57: =P56 -> 49.74 | AC57: =Q56 -> 26.79 | AD57: =R56 -> 28.2 | AE57: =S56 -> 48.8 | AF57: =T56 -> 44.65 | AG57: =U56 -> 43.01 | AH57: =V56 -> 36.67 | ... AJ57: =X56 -> 68.94 | AL57: Receivable Turnover | AM57: ="" | AN57: =IFERROR(P3/AVERAGE(P45,O45),"") -> 2.750878 | AO57: =IFERROR(Q3/AVERAGE(Q45,P45),"") -> 3.3102375 | AP57: =IFERROR(R3/AVERAGE(R45,Q45),"") -> 2.6718067 | AQ57: =IFERROR(S3/AVERAGE(S45,R45),"") -> 3.8573414 | AR57: =IFERROR(T3/AVERAGE(T45,S45),"") -> 3.4057396 | AS57: =IFERROR(U3/AVERAGE(U45,T45),"") -> 2.4777824 | AT57: =IFERROR(V3/AVERAGE(V45,U45),"") -> 2.9004249 | AU57: =IFERROR(W3/AVERAGE(W45,V45),"") -> 2.970854 | AV57: =IFERROR(X3/AVERAGE(X45,W45),"") -> 2.7396587
B58: Others Financial Assets - Long-term | C58: ='Raw BS'!B20 -> 12.59 | D58: ='Raw BS'!C20 -> 9.41 | E58: ='Raw BS'!D20 -> 9.74 | F58: ='Raw BS'!E20 -> 10.03 | G58: ='Raw BS'!F20 -> 10.26 | H58: ='Raw BS'!G20 -> 8.13 | I58: ='Raw BS'!H20 -> 6.32 | J58: ='Raw BS'!I20 -> 5.91 | ... L58: ='Raw BS'!K20 -> 8.59 | N58: Short Term Borrowings | O58: =C115 -> 97.62 | P58: =D115 -> 150.29 | Q58: =E115 -> 199.67 | R58: =F115 -> 184.03 | S58: =G115 -> 100.63 | T58: =H115 -> 241.35 | U58: =I115 -> 233.74 | V58: =J115 -> 180.93 | ... X58: =L115 -> 429.66 | Z58: Trade Payables | AA58: =O57 -> 210.73 | AB58: =P57 -> 226.23 | AC58: =Q57 -> 221.41 | AD58: =R57 -> 250.22 | AE58: =S57 -> 210.08 | AF58: =T57 -> 183.19 | AG58: =U57 -> 290.69 | AH58: =V57 -> 351.26 | ... AJ58: =X57 -> 356.63 | AL58: Payable Turnover | AM58: ="" | AN58: =IFERROR(P6/AVERAGE(P57,O57),"") -> 1.6397382 | AO58: =IFERROR(Q6/AVERAGE(Q57,P57),"") -> 1.9866411 | AP58: =IFERROR(R6/AVERAGE(R57,Q57),"") -> 1.6417955 | AQ58: =IFERROR(S6/AVERAGE(S57,R57),"") -> 1.6484467 | AR58: =IFERROR(T6/AVERAGE(T57,S57),"") -> 2.1147303 | AS58: =IFERROR(U6/AVERAGE(U57,T57),"") -> 2.3251878 | AT58: =IFERROR(V6/AVERAGE(V57,U57),"") -> 2.2951943 | AU58: =IFERROR(W6/AVERAGE(W57,V57),"") -> 2.339935 | AV58: =IFERROR(X6/AVERAGE(X57,W57),"") -> 2.1517544
B59: Non Current Tax Assets - Long - Term | C59: ='Raw BS'!B21 -> 0 | D59: ='Raw BS'!C21 -> 0 | E59: ='Raw BS'!D21 -> 0 | F59: ='Raw BS'!E21 -> 0 | G59: ='Raw BS'!F21 -> 0 | H59: ='Raw BS'!G21 -> 0 | I59: ='Raw BS'!H21 -> 0 | J59: ='Raw BS'!I21 -> 0 | ... L59: ='Raw BS'!K21 -> 0 | N59: Short term lease liabilities | O59: =C116 -> 0 | P59: =D116 -> 0 | Q59: =E116 -> 0 | R59: =F116 -> 0 | S59: =G116 -> 0 | T59: =H116 -> 4.22 | U59: =I116 -> 5.16 | V59: =J116 -> 4.21 | ... X59: =L116 -> 5.37 | Z59: Other Current Operating Liabilities | AA59: =O60 -> 84.26 | AB59: =P60 -> 86.99 | AC59: =Q60 -> 81.84 | AD59: =R60 -> 128.45 | AE59: =S60 -> 190.91 | AF59: =T60 -> 123.37 | AG59: =U60 -> 110.01 | AH59: =V60 -> 201.2 | ... AJ59: =X60 -> 94.28
B60: Insurance Related Assets | C60: ='Raw BS'!B22 -> 0 | D60: ='Raw BS'!C22 -> 0 | E60: ='Raw BS'!D22 -> 0 | F60: ='Raw BS'!E22 -> 0 | G60: ='Raw BS'!F22 -> 0 | H60: ='Raw BS'!G22 -> 0 | I60: ='Raw BS'!H22 -> 0 | J60: ='Raw BS'!I22 -> 0 | ... L60: ='Raw BS'!K22 -> 0 | N60: Other Current Liabilities | O60: =SUM(C118:C123) -> 84.26 | P60: =SUM(D118:D123) -> 86.99 | Q60: =SUM(E118:E123) -> 81.84 | R60: =SUM(F118:F123) -> 128.45 | S60: =SUM(G118:G123) -> 190.91 | T60: =SUM(H118:H123) -> 123.37 | U60: =SUM(I118:I123) -> 110.01 | V60: =SUM(J118:J123) -> 201.2 | ... X60: =SUM(L118:L123) -> 94.28 | Z60: Total Operating Liabilities | AA60: =SUM(AA57:AA59) -> 364.97 | AB60: =SUM(AB57:AB59) -> 362.96 | AC60: =SUM(AC57:AC59) -> 330.04 | AD60: =SUM(AD57:AD59) -> 406.87 | AE60: =SUM(AE57:AE59) -> 449.79 | AF60: =SUM(AF57:AF59) -> 351.21 | AG60: =SUM(AG57:AG59) -> 443.71 | AH60: =SUM(AH57:AH59) -> 589.13 | ... AJ60: =SUM(AJ57:AJ59) -> 519.85 | AL60: Model-Derived Cash Flow Analysis
B61: Other Non-current Assets | C61: ='Raw BS'!B23 -> 12.9 | D61: ='Raw BS'!C23 -> 22.31 | E61: ='Raw BS'!D23 -> 55.96 | F61: ='Raw BS'!E23 -> 114.31 | G61: ='Raw BS'!F23 -> 117.07 | H61: ='Raw BS'!G23 -> 173.65 | I61: ='Raw BS'!H23 -> 180.34 | J61: ='Raw BS'!I23 -> 140.33 | ... L61: ='Raw BS'!K23 -> 184.85 | N61: Total liabilities and equity | O61: =SUM(O51:O60) -> 1526.54 | P61: =SUM(P51:P60) -> 3193.67 | Q61: =SUM(Q51:Q60) -> 3149.62 | R61: =SUM(R51:R60) -> 3122.25 | S61: =SUM(S51:S60) -> 3107.25 | T61: =SUM(T51:T60) -> 3308.42 | U61: =SUM(U51:U60) -> 3186.72 | V61: =SUM(V51:V60) -> 3255 | ... X61: =SUM(X51:X60) -> 3737.44 | AL61: Operating Working Capital | AM61: =(O44+O45+O48-O57-O60) -> 429.33 | AN61: =(P44+P45+P48-P57-P60) -> 446.23 | AO61: =(Q44+Q45+Q48-Q57-Q60) -> 733.42 | AP61: =(R44+R45+R48-R57-R60) -> 654.88 | AQ61: =(S44+S45+S48-S57-S60) -> 657.45 | AR61: =(T44+T45+T48-T57-T60) -> 964.14 | AS61: =(U44+U45+U48-U57-U60) -> 1000.87 | AT61: =(V44+V45+V48-V57-V60) -> 1031.36 | ... AV61: =(X44+X45+X48-X57-X60) -> 1454.98
B62: Deferred Tax Assets (Net) | C62: ='Raw BS'!B24 -> 5.91 | D62: ='Raw BS'!C24 -> 3.61 | E62: ='Raw BS'!D24 -> 16.68 | F62: ='Raw BS'!E24 -> 2.94 | G62: ='Raw BS'!F24 -> 13.95 | H62: ='Raw BS'!G24 -> 4.36 | I62: ='Raw BS'!H24 -> 10.11 | J62: ='Raw BS'!I24 -> 6.78 | ... L62: ='Raw BS'!K24 -> 30.56 | N62: Balance Sheet Reconciliation Check | O62: =O49-O61 -> 0.12 | P62: =P49-P61 -> 0 | Q62: =Q49-Q61 -> -0.89 | R62: =R49-R61 -> -26.83 | S62: =S49-S61 -> -27.6 | T62: =T49-T61 -> 10.36 | U62: =U49-U61 -> 2.92 | V62: =V49-V61 -> 16.6 | ... X62: =X49-X61 -> 0 | Z62: FINANCIAL OBLIGATIONS | AL62: Change in Operating Working Capital | AM62: ="" | AN62: =(P44+P45+P48-P57-P60)-(O44+O45+O48-O57-O60) -> 16.9 | AO62: =(Q44+Q45+Q48-Q57-Q60)-(P44+P45+P48-P57-P60) -> 287.19 | AP62: =(R44+R45+R48-R57-R60)-(Q44+Q45+Q48-Q57-Q60) -> -78.54 | AQ62: =(S44+S45+S48-S57-S60)-(R44+R45+R48-R57-R60) -> 2.57 | AR62: =(T44+T45+T48-T57-T60)-(S44+S45+S48-S57-S60) -> 306.69 | AS62: =(U44+U45+U48-U57-U60)-(T44+T45+T48-T57-T60) -> 36.73 | AT62: =(V44+V45+V48-V57-V60)-(U44+U45+U48-U57-U60) -> 30.49 | AU62: =(W44+W45+W48-W57-W60)-(V44+V45+V48-V57-V60) -> 262.28 | AV62: =(X44+X45+X48-X57-X60)-(W44+W45+W48-W57-W60) -> 161.34
B63: Total Reported Non-current Assets | C63: ='Raw BS'!B25 -> 778.19 | D63: ='Raw BS'!C25 -> 857.2 | E63: ='Raw BS'!D25 -> 1110.33 | F63: ='Raw BS'!E25 -> 1458.27 | G63: ='Raw BS'!F25 -> 1748.4 | H63: ='Raw BS'!G25 -> 1670.38 | I63: ='Raw BS'!H25 -> 1601.17 | J63: ='Raw BS'!I25 -> 1528.28 | ... L63: ='Raw BS'!K25 -> 1536.85 | Z63: Long-term Borrowings | AA63: =O54 -> 0.44 | AB63: =P54 -> 0.33 | AC63: =Q54 -> 0 | AD63: =R54 -> 0 | AE63: =S54 -> 0 | AF63: =T54 -> 89.01 | AG63: =U54 -> 63.65 | AH63: =V54 -> 38.22 | ... AJ63: =X54 -> 39.12 | AL63: Capital Expenditure | AM63: ="" | AN63: =P41-O41+P10 -> 125.91 | AO63: =Q41-P41+Q10 -> 153.45 | AP63: =R41-Q41+R10 -> 330.21 | AQ63: =S41-R41+S10 -> 339 | AR63: =T41-S41+T10 -> 173.16 | AS63: =U41-T41+U10 -> 33.7 | AT63: =V41-U41+V10 -> 94.16 | AU63: =W41-V41+W10 -> 79.69 | AV63: =X41-W41+X10 -> 107.6
B64: Current Assets: | C64: ='Raw BS'!B26 -> 0 | D64: ='Raw BS'!C26 -> 0 | E64: ='Raw BS'!D26 -> 0 | F64: ='Raw BS'!E26 -> 0 | G64: ='Raw BS'!F26 -> 0 | H64: ='Raw BS'!G26 -> 0 | I64: ='Raw BS'!H26 -> 0 | J64: ='Raw BS'!I26 -> 0 | ... L64: ='Raw BS'!K26 -> 0 | Z64: Long-term Lease Liabilities | AA64: =O55 -> 0 | AB64: =P55 -> 0 | AC64: =Q55 -> 0 | AD64: =R55 -> 0 | AE64: =S55 -> 0 | AF64: =T55 -> 4.22 | AG64: =U55 -> 5.16 | AH64: =V55 -> 4.21 | ... AJ64: =X55 -> 26 | AL64: Cash Flow from Operations (CFO) | AM64: ="" | AN64: =P17+P10-AN62 -> -99.48 | AO64: =Q17+Q10-AO62 -> -245.37 | AP64: =R17+R10-AP62 -> 100.02 | AQ64: =S17+S10-AQ62 -> 116.12 | AR64: =T17+T10-AR62 -> -182.47 | AS64: =U17+U10-AS62 -> -125.51 | AT64: =V17+V10-AT62 -> -1.09 | AU64: =W17+W10-AU62 -> -0.2 | AV64: =X17+X10-AV62 -> 437.18
B65: Inventories | C65: ='Raw BS'!B27 -> 281.71 | D65: ='Raw BS'!C27 -> 272.86 | E65: ='Raw BS'!D27 -> 338.66 | F65: ='Raw BS'!E27 -> 396.54 | G65: ='Raw BS'!F27 -> 538.34 | H65: ='Raw BS'!G27 -> 600.22 | I65: ='Raw BS'!H27 -> 625.23 | J65: ='Raw BS'!I27 -> 736.26 | ... L65: ='Raw BS'!K27 -> 974.97 | Z65: Short-term Borrowings | AA65: =O58 -> 97.62 | AB65: =P58 -> 150.29 | AC65: =Q58 -> 199.67 | AD65: =R58 -> 184.03 | AE65: =S58 -> 100.63 | AF65: =T58 -> 241.35 | AG65: =U58 -> 233.74 | AH65: =V58 -> 180.93 | ... AJ65: =X58 -> 429.66 | AL65: Free Cash Flow to Firm (FCFF) | AM65: ="" | AN65: =AB10+P10-AN63-AN62 -> -278.04 | AO65: =AC10+Q10-AO63-AO62 -> -489.78 | AP65: =AD10+R10-AP63-AP62 -> -314.46 | AQ65: =AE10+S10-AQ63-AQ62 -> -267.61 | AR65: =AF10+T10-AR63-AR62 -> -395.97 | AS65: =AG10+U10-AS63-AS62 -> -141.85 | AT65: =AH10+V10-AT63-AT62 -> -46.57 | AU65: =AI10+W10-AU63-AU62 -> -94.18 | AV65: =AJ10+X10-AV63-AV62 -> 96.25
B66: Biological Assets other than Bearer Plants | C66: ='Raw BS'!B28 -> 0 | D66: ='Raw BS'!C28 -> 0 | E66: ='Raw BS'!D28 -> 0 | F66: ='Raw BS'!E28 -> 0 | G66: ='Raw BS'!F28 -> 0 | H66: ='Raw BS'!G28 -> 0 | I66: ='Raw BS'!H28 -> 0 | J66: ='Raw BS'!I28 -> 0 | ... L66: ='Raw BS'!K28 -> 0 | Z66: Short-term Lease Liabilities | AA66: =O59 -> 0 | AB66: =P59 -> 0 | AC66: =Q59 -> 0 | AD66: =R59 -> 0 | AE66: =S59 -> 0 | AF66: =T59 -> 4.22 | AG66: =U59 -> 5.16 | AH66: =V59 -> 4.21 | ... AJ66: =X59 -> 5.37 | AL66: Net Borrowing | AM66: ="" | AN66: =(P54+P55+P58+P59)-(O54+O55+O58+O59) -> 52.56 | AO66: =(Q54+Q55+Q58+Q59)-(P54+P55+P58+P59) -> 49.05 | AP66: =(R54+R55+R58+R59)-(Q54+Q55+Q58+Q59) -> -15.64 | AQ66: =(S54+S55+S58+S59)-(R54+R55+R58+R59) -> -83.4 | AR66: =(T54+T55+T58+T59)-(S54+S55+S58+S59) -> 238.17 | AS66: =(U54+U55+U58+U59)-(T54+T55+T58+T59) -> -31.09 | AT66: =(V54+V55+V58+V59)-(U54+U55+U58+U59) -> -80.14 | AU66: =(W54+W55+W58+W59)-(V54+V55+V58+V59) -> 211.62 | AV66: =(X54+X55+X58+X59)-(W54+W55+W58+W59) -> 60.96
B67: Financial Assets : | C67: ='Raw BS'!B29 -> 0 | D67: ='Raw BS'!C29 -> 0 | E67: ='Raw BS'!D29 -> 0 | F67: ='Raw BS'!E29 -> 0 | G67: ='Raw BS'!F29 -> 0 | H67: ='Raw BS'!G29 -> 0 | I67: ='Raw BS'!H29 -> 0 | J67: ='Raw BS'!I29 -> 0 | ... L67: ='Raw BS'!K29 -> 0 | Z67: Total Financial Obligations | AA67: =SUM(AA63:AA66) -> 98.06 | AB67: =SUM(AB63:AB66) -> 150.62 | AC67: =SUM(AC63:AC66) -> 199.67 | AD67: =SUM(AD63:AD66) -> 184.03 | AE67: =SUM(AE63:AE66) -> 100.63 | AF67: =SUM(AF63:AF66) -> 338.8 | AG67: =SUM(AG63:AG66) -> 307.71 | AH67: =SUM(AH63:AH66) -> 227.57 | ... AJ67: =SUM(AJ63:AJ66) -> 500.15 | AL67: Free Cash Flow to Equity (FCFE) | AM67: ="" | AN67: =AN64-AN63+AN66 -> -172.83 | AO67: =AO64-AO63+AO66 -> -349.77 | AP67: =AP64-AP63+AP66 -> -245.83 | AQ67: =AQ64-AQ63+AQ66 -> -306.28 | AR67: =AR64-AR63+AR66 -> -117.46 | AS67: =AS64-AS63+AS66 -> -190.3 | AT67: =AT64-AT63+AT66 -> -175.39 | AU67: =AU64-AU63+AU66 -> 131.73 | AV67: =AV64-AV63+AV66 -> 390.54
B68: Current Investments | C68: ='Raw BS'!B30 -> 8 | D68: ='Raw BS'!C30 -> 895.55 | E68: ='Raw BS'!D30 -> 800.75 | F68: ='Raw BS'!E30 -> 419.1 | G68: ='Raw BS'!F30 -> 236.43 | H68: ='Raw BS'!G30 -> 263.58 | I68: ='Raw BS'!H30 -> 1.54 | J68: ='Raw BS'!I30 -> 1.34 | ... L68: ='Raw BS'!K30 -> 0 | AL68: CFO / EBITDA | AM68: ="" | AN68: =IFERROR(AN64/P9,"") -> 1.4009294 | AO68: =IFERROR(AO64/Q9,"") -> -16.44571 | AP68: =IFERROR(AP64/R9,"") -> 2.4702396 | AQ68: =IFERROR(AQ64/S9,"") -> 0.82179759 | AR68: =IFERROR(AR64/T9,"") -> -1.5167914 | AS68: =IFERROR(AS64/U9,"") -> 17.828125 | AT68: =IFERROR(AT64/V9,"") -> -0.0092006415 | AU68: =IFERROR(AU64/W9,"") -> -0.00066626691 | AV68: =IFERROR(AV64/X9,"") -> 0.93456466
B69: Trade Receivables | C69: ='Raw BS'!B31 -> 315.32 | D69: ='Raw BS'!C31 -> 276.92 | E69: ='Raw BS'!D31 -> 436.05 | F69: ='Raw BS'!E31 -> 390.14 | G69: ='Raw BS'!F31 -> 250.27 | H69: ='Raw BS'!G31 -> 495.43 | I69: ='Raw BS'!H31 -> 588.62 | J69: ='Raw BS'!I31 -> 642.31 | ... L69: ='Raw BS'!K31 -> 828.58 | Z69: EQUITY | AL69: CFO / Net Profit | AM69: ="" | AN69: =IFERROR(AN64/P17,"") -> 0.74746412 | AO69: =IFERROR(AO64/Q17,"") -> 9.6035225 | AP69: =IFERROR(AP64/R17,"") -> -1.6617378 | AQ69: =IFERROR(AQ64/S17,"") -> 3.3824643 | AR69: =IFERROR(AR64/T17,"") -> -5.5210287 | AS69: =IFERROR(AS64/U17,"") -> 0.62066067 | AT69: =IFERROR(AT64/V17,"") -> 0.011625427 | AU69: =IFERROR(AU64/W17,"") -> -0.0014543339 | AV69: =IFERROR(AV64/X17,"") -> 0.92348965
B70: Cash and Cash Equivalents | C70: ='Raw BS'!B32 -> 11.21 | D70: ='Raw BS'!C32 -> 666.07 | E70: ='Raw BS'!D32 -> 197.05 | F70: ='Raw BS'!E32 -> 231.52 | G70: ='Raw BS'!F32 -> 77.46 | H70: ='Raw BS'!G32 -> 109.2 | I70: ='Raw BS'!H32 -> 183.75 | J70: ='Raw BS'!I32 -> 154.75 | ... L70: ='Raw BS'!K32 -> 289.48 | Z70: Common Share Capital | AA70: =O51 -> 18.18 | AB70: =P51 -> 14.07 | AC70: =Q51 -> 14.08 | AD70: =R51 -> 14.08 | AE70: =S51 -> 14.08 | AF70: =T51 -> 14.08 | AG70: =U51 -> 14.08 | AH70: =V51 -> 14.08 | ... AJ70: =X51 -> 14.08 | AL70: Capex / Sales | AM70: ="" | AN70: =IFERROR(AN63/P3,"") -> 0.15456856 | AO70: =IFERROR(AO63/Q3,"") -> 0.13003686 | AP70: =IFERROR(AP63/R3,"") -> 0.29918185 | AQ70: =IFERROR(AQ63/S3,"") -> 0.27446281 | AR70: =IFERROR(AR63/T3,"") -> 0.13636471 | AS70: =IFERROR(AS63/U3,"") -> 0.025092702 | AT70: =IFERROR(AT63/V3,"") -> 0.05274745 | AU70: =IFERROR(AU63/W3,"") -> 0.037750418 | AV70: =IFERROR(AV63/X3,"") -> 0.048867997
B71: Bank Balances Other Than Cash and Cash Equivalents | C71: ='Raw BS'!B33 -> 4.93 | D71: ='Raw BS'!C33 -> 15.39 | E71: ='Raw BS'!D33 -> 3.94 | F71: ='Raw BS'!E33 -> 2.29 | G71: ='Raw BS'!F33 -> 4.99 | H71: ='Raw BS'!G33 -> 4.91 | I71: ='Raw BS'!H33 -> 1.61 | J71: ='Raw BS'!I33 -> 3.41 | ... L71: ='Raw BS'!K33 -> 5.22 | Z71: Other Equity | AA71: =O52 -> 1045.33 | AB71: =P52 -> 2666.02 | AC71: =Q52 -> 2605.83 | AD71: =R52 -> 2517.27 | AE71: =S52 -> 2542.75 | AF71: =T52 -> 2604.33 | AG71: =U52 -> 2421.22 | AH71: =V52 -> 2424.22 | ... AJ71: =X52 -> 2703.36 | AL71: FCFF Margin | AM71: ="" | AN71: =IFERROR(AN65/P3,"") -> -0.34132508 | AO71: =IFERROR(AO65/Q3,"") -> -0.41505021 | AP71: =IFERROR(AP65/R3,"") -> -0.2849118 | AQ71: =IFERROR(AQ65/S3,"") -> -0.2166637 | AR71: =IFERROR(AR65/T3,"") -> -0.31182914 | AS71: =IFERROR(AS65/U3,"") -> -0.10562017 | AT71: =IFERROR(AT65/V3,"") -> -0.026088028 | AU71: =IFERROR(AU65/W3,"") -> -0.044614561 | AV71: =IFERROR(AV65/X3,"") -> 0.043713241
B72: Loans - Short-term | C72: ='Raw BS'!B34 -> 0.09 | D72: ='Raw BS'!C34 -> 0.05 | E72: ='Raw BS'!D34 -> 0.06 | F72: ='Raw BS'!E34 -> 0.04 | G72: ='Raw BS'!F34 -> 0.04 | H72: ='Raw BS'!G34 -> 0.05 | I72: ='Raw BS'!H34 -> 0.06 | J72: ='Raw BS'!I34 -> 0.04 | ... L72: ='Raw BS'!K34 -> 0.06 | Z72: Minority Interest | AA72: =O53 -> 0 | AB72: =P53 -> 0 | AC72: =Q53 -> 0 | AD72: =R53 -> 0 | AE72: =S53 -> 0 | AF72: =T53 -> 0 | AG72: =U53 -> 0 | AH72: =V53 -> 0 | ... AJ72: =X53 -> 0
B73: Others Financial Assets - Short-term | C73: ='Raw BS'!B35 -> 2.49 | D73: ='Raw BS'!C35 -> 29.25 | E73: ='Raw BS'!D35 -> 23.65 | F73: ='Raw BS'!E35 -> 15.33 | G73: ='Raw BS'!F35 -> 9.2 | H73: ='Raw BS'!G35 -> 0.55 | I73: ='Raw BS'!H35 -> 1.71 | J73: ='Raw BS'!I35 -> 0.23 | ... L73: ='Raw BS'!K35 -> 4.42 | Z73: Total Equity | AA73: =SUM(AA70:AA72) -> 1063.51 | AB73: =SUM(AB70:AB72) -> 2680.09 | AC73: =SUM(AC70:AC72) -> 2619.91 | AD73: =SUM(AD70:AD72) -> 2531.35 | AE73: =SUM(AE70:AE72) -> 2556.83 | AF73: =SUM(AF70:AF72) -> 2618.41 | AG73: =SUM(AG70:AG72) -> 2435.3 | AH73: =SUM(AH70:AH72) -> 2438.3 | ... AJ73: =SUM(AJ70:AJ72) -> 2717.44 | AL73: Per Share Analysis
B74: Current Tax Assets - Short-term | C74: ='Raw BS'!B36 -> 0 | D74: ='Raw BS'!C36 -> 0 | E74: ='Raw BS'!D36 -> 0 | F74: ='Raw BS'!E36 -> 0 | G74: ='Raw BS'!F36 -> 0 | H74: ='Raw BS'!G36 -> 0 | I74: ='Raw BS'!H36 -> 0 | J74: ='Raw BS'!I36 -> 0 | ... L74: ='Raw BS'!K36 -> 0 | Z74: Total Liabilities and Equity | AA74: =SUM(AA60,AA67,AA73) -> 1526.54 | AB74: =SUM(AB60,AB67,AB73) -> 3193.67 | AC74: =SUM(AC60,AC67,AC73) -> 3149.62 | AD74: =SUM(AD60,AD67,AD73) -> 3122.25 | AE74: =SUM(AE60,AE67,AE73) -> 3107.25 | AF74: =SUM(AF60,AF67,AF73) -> 3308.42 | AG74: =SUM(AG60,AG67,AG73) -> 3186.72 | AH74: =SUM(AH60,AH67,AH73) -> 3255 | ... AJ74: =SUM(AJ60,AJ67,AJ73) -> 3737.44 | AL74: Shares Outstanding Proxy (crore; FV ₹1) | AM74: =O51 -> 18.18 | AN74: =P51 -> 14.07 | AO74: =Q51 -> 14.08 | AP74: =R51 -> 14.08 | AQ74: =S51 -> 14.08 | AR74: =T51 -> 14.08 | AS74: =U51 -> 14.08 | AT74: =V51 -> 14.08 | ... AV74: =X51 -> 14.08
B75: Insurance Related Assets | C75: ='Raw BS'!B37 -> 0 | D75: ='Raw BS'!C37 -> 0 | E75: ='Raw BS'!D37 -> 0 | F75: ='Raw BS'!E37 -> 0 | G75: ='Raw BS'!F37 -> 0 | H75: ='Raw BS'!G37 -> 0 | I75: ='Raw BS'!H37 -> 0 | J75: ='Raw BS'!I37 -> 0 | ... L75: ='Raw BS'!K37 -> 0 | Z75: Balance Sheet Reconciliation Check | AA75: =AA54-AA74 -> 0.12 | AB75: =AB54-AB74 -> 0 | AC75: =AC54-AC74 -> -0.89 | AD75: =AD54-AD74 -> -26.83 | AE75: =AE54-AE74 -> -27.6 | AF75: =AF54-AF74 -> 10.36 | AG75: =AG54-AG74 -> 2.92 | AH75: =AH54-AH74 -> 16.6 | ... AJ75: =AJ54-AJ74 -> 0 | AL75: Earnings Per Share (₹) | AM75: =IFERROR(O17/O51,0) -> -3.8910891 | AN75: =IFERROR(P17/P51,0) -> -9.4591329 | AO75: =IFERROR(Q17/Q51,0) -> -1.8146307 | AP75: =IFERROR(R17/R51,0) -> -4.274858 | AQ75: =IFERROR(S17/S51,0) -> 2.4382102 | AR75: =IFERROR(T17/T51,0) -> 2.3473011 | AS75: =IFERROR(U17/U51,0) -> -14.362216 | AT75: =IFERROR(V17/V51,0) -> -6.6590909 | ... AV75: =IFERROR(X17/X51,0) -> 33.622159
B76: Other Current Assets | C76: ='Raw BS'!B38 -> 124.71 | D76: ='Raw BS'!C38 -> 180.37 | E76: ='Raw BS'!D38 -> 238.25 | F76: ='Raw BS'!E38 -> 231.5 | G76: ='Raw BS'!F38 -> 260.59 | H76: ='Raw BS'!G38 -> 170.98 | I76: ='Raw BS'!H38 -> 185.95 | J76: ='Raw BS'!I38 -> 204.98 | ... L76: ='Raw BS'!K38 -> 94.61 | AL76: Book Value Per Share (₹) | AM76: =IFERROR(SUM(O51:O52)/O51,0) -> 58.4989 | AN76: =IFERROR(SUM(P51:P52)/P51,0) -> 190.48259 | AO76: =IFERROR(SUM(Q51:Q52)/Q51,0) -> 186.07315 | AP76: =IFERROR(SUM(R51:R52)/R51,0) -> 179.78338 | AQ76: =IFERROR(SUM(S51:S52)/S51,0) -> 181.59304 | AR76: =IFERROR(SUM(T51:T52)/T51,0) -> 185.96662 | AS76: =IFERROR(SUM(U51:U52)/U51,0) -> 172.96165 | AT76: =IFERROR(SUM(V51:V52)/V51,0) -> 173.17472 | ... AV76: =IFERROR(SUM(X51:X52)/X51,0) -> 193
B77: Assets Classified as Held for Sale | C77: ='Raw BS'!B39 -> 0 | D77: ='Raw BS'!C39 -> 0 | E77: ='Raw BS'!D39 -> 0 | F77: ='Raw BS'!E39 -> 0 | G77: ='Raw BS'!F39 -> 0 | H77: ='Raw BS'!G39 -> 3.47 | I77: ='Raw BS'!H39 -> 0 | J77: ='Raw BS'!I39 -> 0 | ... L77: ='Raw BS'!K39 -> 3.25 | Z77: Net Operating Assets | AA77: =AA47-AA60 -> 1128.04 | AB77: =AB47-AB60 -> 1244.49 | AC77: =AC47-AC60 -> 1687.75 | AD77: =AD47-AD60 -> 1901.26 | AE77: =AE47-AE60 -> 2151.86 | AF77: =AF47-AF60 -> 2589.6 | AG77: =AG47-AG60 -> 2558.87 | AH77: =AH47-AH60 -> 2522.95 | ... AJ77: =AJ47-AJ60 -> 2922.87 | AL77: CFO Per Share (₹) | AM77: NA | AN77: =IFERROR(AN64/P51,NA()) -> -7.0703625 | AO77: =IFERROR(AO64/Q51,NA()) -> -17.426847 | AP77: =IFERROR(AP64/R51,NA()) -> 7.1036932 | AQ77: =IFERROR(AQ64/S51,NA()) -> 8.2471591 | AR77: =IFERROR(AR64/T51,NA()) -> -12.959517 | AS77: =IFERROR(AS64/U51,NA()) -> -8.9140625 | AT77: =IFERROR(AT64/V51,NA()) -> -0.077414773 | AU77: =IFERROR(AU64/W51,NA()) -> -0.014204545 | AV77: =IFERROR(AV64/X51,NA()) -> 31.049716
B78: Total Current Assets | C78: ='Raw BS'!B40 -> 748.46 | D78: ='Raw BS'!C40 -> 2336.47 | E78: ='Raw BS'!D40 -> 2038.41 | F78: ='Raw BS'!E40 -> 1686.47 | G78: ='Raw BS'!F40 -> 1377.32 | H78: ='Raw BS'!G40 -> 1648.39 | I78: ='Raw BS'!H40 -> 1588.47 | J78: ='Raw BS'!I40 -> 1743.32 | ... L78: ='Raw BS'!K40 -> 2197.34 | Z78: Net Financial Assets/(Obligations) | AA78: =AA53-AA67 -> -64.41 | AB78: =AB53-AB67 -> 1435.6 | AC78: =AC53-AC67 -> 931.27 | AD78: =AD53-AD67 -> 603.26 | AE78: =AE53-AE67 -> 377.37 | AF78: =AF53-AF67 -> 39.17 | AG78: =AG53-AG67 -> -120.65 | AH78: =AH53-AH67 -> -68.05 | ... AJ78: =AJ53-AJ67 -> -205.43 | AL78: FCFF Per Share (₹) | AM78: NA | AN78: =IFERROR(AN65/P51,NA()) -> -19.761194 | AO78: =IFERROR(AO65/Q51,NA()) -> -34.785511 | AP78: =IFERROR(AP65/R51,NA()) -> -22.333807 | AQ78: =IFERROR(AQ65/S51,NA()) -> -19.006392 | AR78: =IFERROR(AR65/T51,NA()) -> -28.122869 | AS78: =IFERROR(AS65/U51,NA()) -> -10.074574 | AT78: =IFERROR(AT65/V51,NA()) -> -3.3075284 | AU78: =IFERROR(AU65/W51,NA()) -> -6.6889205 | AV78: =IFERROR(AV65/X51,NA()) -> 6.8359375
C79: ='Raw BS'!B41 -> 0 | D79: ='Raw BS'!C41 -> 0 | E79: ='Raw BS'!D41 -> 0 | F79: ='Raw BS'!E41 -> 0 | G79: ='Raw BS'!F41 -> 0 | H79: ='Raw BS'!G41 -> 0 | I79: ='Raw BS'!H41 -> 0 | J79: ='Raw BS'!I41 -> 0 | ... L79: ='Raw BS'!K41 -> 0 | Z79: Common Equity + Minority Interest Check | AA79: =AA77+AA78-AA73 -> 0.12 | AB79: =AB77+AB78-AB73 -> 0 | AC79: =AC77+AC78-AC73 -> -0.89 | AD79: =AD77+AD78-AD73 -> -26.83 | AE79: =AE77+AE78-AE73 -> -27.6 | AF79: =AF77+AF78-AF73 -> 10.36 | AG79: =AG77+AG78-AG73 -> 2.92 | AH79: =AH77+AH78-AH73 -> 16.6 | ... AJ79: =AJ77+AJ78-AJ73 -> 0 | AL79: FCFE Per Share (₹) | AM79: NA | AN79: =IFERROR(AN67/P51,NA()) -> -12.283582 | AO79: =IFERROR(AO67/Q51,NA()) -> -24.841619 | AP79: =IFERROR(AP67/R51,NA()) -> -17.459517 | AQ79: =IFERROR(AQ67/S51,NA()) -> -21.752841 | AR79: =IFERROR(AR67/T51,NA()) -> -8.3423295 | AS79: =IFERROR(AS67/U51,NA()) -> -13.515625 | AT79: =IFERROR(AT67/V51,NA()) -> -12.456676 | AU79: =IFERROR(AU67/W51,NA()) -> 9.3558239 | AV79: =IFERROR(AV67/X51,NA()) -> 27.737216
B80: Foreign Currency Monetary Item Translation Difference Account | C80: ='Raw BS'!B42 -> 0 | D80: ='Raw BS'!C42 -> 0 | E80: ='Raw BS'!D42 -> 0 | F80: ='Raw BS'!E42 -> 0 | G80: ='Raw BS'!F42 -> 0 | H80: ='Raw BS'!G42 -> 0 | I80: ='Raw BS'!H42 -> 0 | J80: ='Raw BS'!I42 -> 0 | ... L80: ='Raw BS'!K42 -> 0
B81: Regulatory Deferral Account - Debit Balance | C81: ='Raw BS'!B43 -> 0 | D81: ='Raw BS'!C43 -> 0 | E81: ='Raw BS'!D43 -> 0 | F81: ='Raw BS'!E43 -> 0 | G81: ='Raw BS'!F43 -> 0 | H81: ='Raw BS'!G43 -> 0 | I81: ='Raw BS'!H43 -> 0 | J81: ='Raw BS'!I43 -> 0 | ... L81: ='Raw BS'!K43 -> 0 | AL81: Valuation Inputs & Multiples
B82: Non-Current Assets Classified as Held for Sale | C82: ='Raw BS'!B44 -> 0 | D82: ='Raw BS'!C44 -> 0 | E82: ='Raw BS'!D44 -> 0.87 | F82: ='Raw BS'!E44 -> 0 | G82: ='Raw BS'!F44 -> 0 | H82: ='Raw BS'!G44 -> 0 | I82: ='Raw BS'!H44 -> 3.41 | J82: ='Raw BS'!I44 -> 3.35 | ... L82: ='Raw BS'!K44 -> 3.25 | AL82: Market Price Per Share (₹) | AM82: 224.35 | AN82: 222.85 | AO82: 218.7 | AP82: 131.6 | AQ82: 183.6 | AR82: 151.1 | AS82: 177.95 | AT82: 304.55 | AU82: 360.45 | AV82: 287.9
B83: Other Assets Excluding Non-Current and Current Assets | C83: ='Raw BS'!B45 -> 0 | D83: ='Raw BS'!C45 -> 0 | E83: ='Raw BS'!D45 -> 0.87 | F83: ='Raw BS'!E45 -> 0 | G83: ='Raw BS'!F45 -> 0 | H83: ='Raw BS'!G45 -> 0 | I83: ='Raw BS'!H45 -> 3.41 | J83: ='Raw BS'!I45 -> 3.35 | ... L83: ='Raw BS'!K45 -> 3.25 | AL83: Market Capitalization | AM83: =IF(AM82="","",IFERROR(AM82*AM74,"")) -> 4078.683 | AN83: =IF(AN82="","",IFERROR(AN82*AN74,"")) -> 3135.4995 | AO83: =IF(AO82="","",IFERROR(AO82*AO74,"")) -> 3079.296 | AP83: =IF(AP82="","",IFERROR(AP82*AP74,"")) -> 1852.928 | AQ83: =IF(AQ82="","",IFERROR(AQ82*AQ74,"")) -> 2585.088 | AR83: =IF(AR82="","",IFERROR(AR82*AR74,"")) -> 2127.488 | AS83: =IF(AS82="","",IFERROR(AS82*AS74,"")) -> 2505.536 | AT83: =IF(AT82="","",IFERROR(AT82*AT74,"")) -> 4288.064 | ... AV83: =IF(AV82="","",IFERROR(AV82*AV74,"")) -> 4053.632
B84: Total Non-Current and Other Assets | C84: ='Raw BS'!B46 -> 778.19 | D84: ='Raw BS'!C46 -> 857.2 | E84: ='Raw BS'!D46 -> 1111.2 | F84: ='Raw BS'!E46 -> 1458.27 | G84: ='Raw BS'!F46 -> 1748.4 | H84: ='Raw BS'!G46 -> 1670.38 | I84: ='Raw BS'!H46 -> 1604.58 | J84: ='Raw BS'!I46 -> 1531.63 | ... L84: ='Raw BS'!K46 -> 1540.1 | AL84: Enterprise Value | AM84: =IF(AM82="","",IFERROR((AM82*AM74+(O54+O55+O58+O59)-O46-O47),"")) -> 4152.603 | AN84: =IF(AN82="","",IFERROR((AN82*AN74+(P54+P55+P58+P59)-P46-P47),"")) -> 1709.1095 | AO84: =IF(AO82="","",IFERROR((AO82*AO74+(Q54+Q55+Q58+Q59)-Q46-Q47),"")) -> 2277.226 | AP84: =IF(AP82="","",IFERROR((AP82*AP74+(R54+R55+R58+R59)-R46-R47),"")) -> 1384.048 | AQ84: =IF(AQ82="","",IFERROR((AQ82*AQ74+(S54+S55+S58+S59)-S46-S47),"")) -> 2366.838 | AR84: =IF(AR82="","",IFERROR((AR82*AR74+(T54+T55+T58+T59)-T46-T47),"")) -> 2088.598 | AS84: =IF(AS82="","",IFERROR((AS82*AS74+(U54+U55+U58+U59)-U46-U47),"")) -> 2626.346 | AT84: =IF(AT82="","",IFERROR((AT82*AT74+(V54+V55+V58+V59)-V46-V47),"")) -> 4356.134 | ... AV84: =IF(AV82="","",IFERROR((AV82*AV74+(X54+X55+X58+X59)-X46-X47),"")) -> 4259.082
B85: Total Assets | C85: ='Raw BS'!B47 -> 1526.65 | D85: ='Raw BS'!C47 -> 3193.67 | E85: ='Raw BS'!D47 -> 3149.61 | F85: ='Raw BS'!E47 -> 3144.74 | G85: ='Raw BS'!F47 -> 3125.71 | H85: ='Raw BS'!G47 -> 3318.77 | I85: ='Raw BS'!H47 -> 3193.05 | J85: ='Raw BS'!I47 -> 3274.95 | ... L85: ='Raw BS'!K47 -> 3737.44 | AL85: Price / Earnings | AM85: =IF(AM82="","",IFERROR(AM82/AM75,"")) -> -57.657379 | AN85: =IF(AN82="","",IFERROR(AN82/AN75,"")) -> -23.559242 | AO85: =IF(AO82="","",IFERROR(AO82/AO75,"")) -> -120.52039 | AP85: =IF(AP82="","",IFERROR(AP82/AP75,"")) -> -30.784649 | AQ85: =IF(AQ82="","",IFERROR(AQ82/AQ75,"")) -> 75.301136 | AR85: =IF(AR82="","",IFERROR(AR82/AR75,"")) -> 64.3718 | AS85: =IF(AS82="","",IFERROR(AS82/AS75,"")) -> -12.390149 | AT85: =IF(AT82="","",IFERROR(AT82/AT75,"")) -> -45.734471 | ... AV85: =IF(AV82="","",IFERROR(AV82/AV75,"")) -> 8.5628052
B86: EQUITY AND LIABILITIES | C86: ='Raw BS'!B48 -> 0 | D86: ='Raw BS'!C48 -> 0 | E86: ='Raw BS'!D48 -> 0 | F86: ='Raw BS'!E48 -> 0 | G86: ='Raw BS'!F48 -> 0 | H86: ='Raw BS'!G48 -> 0 | I86: ='Raw BS'!H48 -> 0 | J86: ='Raw BS'!I48 -> 0 | ... L86: ='Raw BS'!K48 -> 0 | AL86: Price / Book Value | AM86: =IF(AM82="","",IFERROR(AM82/AM76,"")) -> 3.8351149 | AN86: =IF(AN82="","",IFERROR(AN82/AN76,"")) -> 1.1699232 | AO86: =IF(AO82="","",IFERROR(AO82/AO76,"")) -> 1.1753442 | AP86: =IF(AP82="","",IFERROR(AP82/AP76,"")) -> 0.73199202 | AQ86: =IF(AQ82="","",IFERROR(AQ82/AQ76,"")) -> 1.011052 | AR86: =IF(AR82="","",IFERROR(AR82/AR76,"")) -> 0.81251141 | AS86: =IF(AS82="","",IFERROR(AS82/AS76,"")) -> 1.0288408 | AT86: =IF(AT82="","",IFERROR(AT82/AT76,"")) -> 1.7586286 | ... AV86: =IF(AV82="","",IFERROR(AV82/AV76,"")) -> 1.4917098
C87: ='Raw BS'!B49 -> 0 | D87: ='Raw BS'!C49 -> 0 | E87: ='Raw BS'!D49 -> 0 | F87: ='Raw BS'!E49 -> 0 | G87: ='Raw BS'!F49 -> 0 | H87: ='Raw BS'!G49 -> 0 | I87: ='Raw BS'!H49 -> 0 | J87: ='Raw BS'!I49 -> 0 | ... L87: ='Raw BS'!K49 -> 0 | AL87: EV / Sales | AM87: =IF(AM82="","",IFERROR((AM82*AM74+(O54+O55+O58+O59)-O46-O47)/O3,"")) -> 5.9517608 | AN87: =IF(AN82="","",IFERROR((AN82*AN74+(P54+P55+P58+P59)-P46-P47)/P3,"")) -> 2.0981224 | AO87: =IF(AO82="","",IFERROR((AO82*AO74+(Q54+Q55+Q58+Q59)-Q46-Q47)/Q3,"")) -> 1.9297708 | AP87: =IF(AP82="","",IFERROR((AP82*AP74+(R54+R55+R58+R59)-R46-R47)/R3,"")) -> 1.2539961 | AQ87: =IF(AQ82="","",IFERROR((AQ82*AQ74+(S54+S55+S58+S59)-S46-S47)/S3,"")) -> 1.9162508 | AR87: =IF(AR82="","",IFERROR((AR82*AR74+(T54+T55+T58+T59)-T46-T47)/T3,"")) -> 1.6447855 | AS87: =IF(AS82="","",IFERROR((AS82*AS74+(U54+U55+U58+U59)-U46-U47)/U3,"")) -> 1.9555524 | AT87: =IF(AT82="","",IFERROR((AT82*AT74+(V54+V55+V58+V59)-V46-V47)/V3,"")) -> 2.4402608 | ... AV87: =IF(AV82="","",IFERROR((AV82*AV74+(X54+X55+X58+X59)-X46-X47)/X3,"")) -> 1.9343198
B88: Share Capital | C88: ='Raw BS'!B50 -> 18.18 | D88: ='Raw BS'!C50 -> 14.07 | E88: ='Raw BS'!D50 -> 14.08 | F88: ='Raw BS'!E50 -> 14.08 | G88: ='Raw BS'!F50 -> 14.08 | H88: ='Raw BS'!G50 -> 14.08 | I88: ='Raw BS'!H50 -> 14.08 | J88: ='Raw BS'!I50 -> 14.08 | ... L88: ='Raw BS'!K50 -> 14.08 | AL88: EV / EBITDA | AM88: =IF(AM82="","",IFERROR((AM82*AM74+(O54+O55+O58+O59)-O46-O47)/O9,"")) -> -115.67139 | AN88: =IF(AN82="","",IFERROR((AN82*AN74+(P54+P55+P58+P59)-P46-P47)/P9,"")) -> -24.068575 | AO88: =IF(AO82="","",IFERROR((AO82*AO74+(Q54+Q55+Q58+Q59)-Q46-Q47)/Q9,"")) -> 152.62909 | AP88: =IF(AP82="","",IFERROR((AP82*AP74+(R54+R55+R58+R59)-R46-R47)/R9,"")) -> 34.182465 | AQ88: =IF(AQ82="","",IFERROR((AQ82*AQ74+(S54+S55+S58+S59)-S46-S47)/S9,"")) -> 16.750446 | AR88: =IF(AR82="","",IFERROR((AR82*AR74+(T54+T55+T58+T59)-T46-T47)/T9,"")) -> 17.361579 | AS88: =IF(AS82="","",IFERROR((AS82*AS74+(U54+U55+U58+U59)-U46-U47)/U9,"")) -> -373.06051 | AT88: =IF(AT82="","",IFERROR((AT82*AT74+(V54+V55+V58+V59)-V46-V47)/V9,"")) -> 36.769933 | ... AV88: =IF(AV82="","",IFERROR((AV82*AV74+(X54+X55+X58+X59)-X46-X47)/X9,"")) -> 9.104688
B89: Number of Equity Shares - Bought Back during the Current period | C89: ='Raw BS'!B51 -> 0 | D89: ='Raw BS'!C51 -> 2.06 | E89: ='Raw BS'!D51 -> 0 | F89: ='Raw BS'!E51 -> 0 | G89: ='Raw BS'!F51 -> 0 | H89: ='Raw BS'!G51 -> 0 | I89: ='Raw BS'!H51 -> 0 | J89: ='Raw BS'!I51 -> 0 | ... L89: ='Raw BS'!K51 -> 0 | AL89: EV / EBIT | AM89: =IF(AM82="","",IFERROR((AM82*AM74+(O54+O55+O58+O59)-O46-O47)/O11,"")) -> -52.286615 | AN89: =IF(AN82="","",IFERROR((AN82*AN74+(P54+P55+P58+P59)-P46-P47)/P11,"")) -> -14.06443 | AO89: =IF(AO82="","",IFERROR((AO82*AO74+(Q54+Q55+Q58+Q59)-Q46-Q47)/Q11,"")) -> -43.417083 | AP89: =IF(AP82="","",IFERROR((AP82*AP74+(R54+R55+R58+R59)-R46-R47)/R11,"")) -> -33.609713 | AQ89: =IF(AQ82="","",IFERROR((AQ82*AQ74+(S54+S55+S58+S59)-S46-S47)/S11,"")) -> 41.567229 | AR89: =IF(AR82="","",IFERROR((AR82*AR74+(T54+T55+T58+T59)-T46-T47)/T11,"")) -> 71.69921 | AS89: =IF(AS82="","",IFERROR((AS82*AS74+(U54+U55+U58+U59)-U46-U47)/U11,"")) -> -21.799021 | AT89: =IF(AT82="","",IFERROR((AT82*AT74+(V54+V55+V58+V59)-V46-V47)/V11,"")) -> -928.81322 | ... AV89: =IF(AV82="","",IFERROR((AV82*AV74+(X54+X55+X58+X59)-X46-X47)/X11,"")) -> 12.429107
B90: Number of Total Bonus Shares Issued upto Current period | C90: ='Raw BS'!B52 -> 7.35 | D90: ='Raw BS'!C52 -> 7.35 | E90: ='Raw BS'!D52 -> 7.35 | F90: ='Raw BS'!E52 -> 0.73 | G90: ='Raw BS'!F52 -> 0.73 | H90: ='Raw BS'!G52 -> 0.73 | I90: ='Raw BS'!H52 -> 0.73 | J90: ='Raw BS'!I52 -> 0 | ... L90: ='Raw BS'!K52 -> 0 | AL90: EV / FCFF | AM90: =IF(AM82="","",IFERROR((AM82*AM74+(O54+O55+O58+O59)-O46-O47)/AM65,"")) | AN90: =IF(AN82="","",IFERROR((AN82*AN74+(P54+P55+P58+P59)-P46-P47)/AN65,"")) -> -6.1469914 | AO90: =IF(AO82="","",IFERROR((AO82*AO74+(Q54+Q55+Q58+Q59)-Q46-Q47)/AO65,"")) -> -4.6494875 | AP90: =IF(AP82="","",IFERROR((AP82*AP74+(R54+R55+R58+R59)-R46-R47)/AP65,"")) -> -4.4013483 | AQ90: =IF(AQ82="","",IFERROR((AQ82*AQ74+(S54+S55+S58+S59)-S46-S47)/AQ65,"")) -> -8.8443556 | AR90: =IF(AR82="","",IFERROR((AR82*AR74+(T54+T55+T58+T59)-T46-T47)/AR65,"")) -> -5.274637 | AS90: =IF(AS82="","",IFERROR((AS82*AS74+(U54+U55+U58+U59)-U46-U47)/AS65,"")) -> -18.514952 | AT90: =IF(AT82="","",IFERROR((AT82*AT74+(V54+V55+V58+V59)-V46-V47)/AT65,"")) -> -93.539489 | ... AV90: =IF(AV82="","",IFERROR((AV82*AV74+(X54+X55+X58+X59)-X46-X47)/AV65,"")) -> 44.250203
B91: Number of Equity Shares - Paid Up | C91: ='Raw BS'!B53 -> 9.09 | D91: ='Raw BS'!C53 -> 7.03 | E91: ='Raw BS'!D53 -> 7.04 | F91: ='Raw BS'!E53 -> 7.04 | G91: ='Raw BS'!F53 -> 7.04 | H91: ='Raw BS'!G53 -> 7.04 | I91: ='Raw BS'!H53 -> 7.04 | J91: ='Raw BS'!I53 -> 7.04 | ... L91: ='Raw BS'!K53 -> 7.040575
B92: Paid Up Capital | C92: ='Raw BS'!B54 -> 18.18 | D92: ='Raw BS'!C54 -> 14.07 | E92: ='Raw BS'!D54 -> 14.08 | F92: ='Raw BS'!E54 -> 14.08 | G92: ='Raw BS'!F54 -> 14.08 | H92: ='Raw BS'!G54 -> 14.08 | I92: ='Raw BS'!H54 -> 14.08 | J92: ='Raw BS'!I54 -> 14.08 | ... L92: ='Raw BS'!K54 -> 14.08 | AL92: Latest Year Financial Dashboard
B93: Treasury Shares | C93: ='Raw BS'!B55 -> 0 | D93: ='Raw BS'!C55 -> 0 | E93: ='Raw BS'!D55 -> 0 | F93: ='Raw BS'!E55 -> 0 | G93: ='Raw BS'!F55 -> 0 | H93: ='Raw BS'!G55 -> 0 | I93: ='Raw BS'!H55 -> 0 | J93: ='Raw BS'!I55 -> 0 | ... L93: ='Raw BS'!K55 -> 0 | AL93: Latest Year | AM93: =AV2 -> 202603
B94: Number of Bonus Shares Issued During the Current Period. | C94: ='Raw BS'!B56 -> 0 | D94: ='Raw BS'!C56 -> 0 | E94: ='Raw BS'!D56 -> 0 | F94: ='Raw BS'!E56 -> 0 | G94: ='Raw BS'!F56 -> 0 | H94: ='Raw BS'!G56 -> 0 | I94: ='Raw BS'!H56 -> 0 | J94: ='Raw BS'!I56 -> 0 | ... L94: ='Raw BS'!K56 -> 0 | AL94: Sales Growth | AM94: =AV4 -> 0.043051299
B95: Number of Shares Splitted During the Current Period. | C95: ='Raw BS'!B57 -> 0 | D95: ='Raw BS'!C57 -> 0 | E95: ='Raw BS'!D57 -> 0 | F95: ='Raw BS'!E57 -> 0 | G95: ='Raw BS'!F57 -> 0 | H95: ='Raw BS'!G57 -> 0 | I95: ='Raw BS'!H57 -> 0 | J95: ='Raw BS'!I57 -> 0 | ... L95: ='Raw BS'!K57 -> 0 | AL95: EBITDA Margin | AM95: =AV11 -> 0.18381361
B96: Other Equity | C96: ='Raw BS'!B58 -> 1045.33 | D96: ='Raw BS'!C58 -> 2666.02 | E96: ='Raw BS'!D58 -> 2605.83 | F96: ='Raw BS'!E58 -> 2517.27 | G96: ='Raw BS'!F58 -> 2542.75 | H96: ='Raw BS'!G58 -> 2604.33 | I96: ='Raw BS'!H58 -> 2421.22 | J96: ='Raw BS'!I58 -> 2424.22 | ... L96: ='Raw BS'!K58 -> 2703.36 | AL96: ROE | AM96: =AV27 -> 0.18320327
B97: Money Received Against Share Warrants | C97: ='Raw BS'!B59 -> 0 | D97: ='Raw BS'!C59 -> 0 | E97: ='Raw BS'!D59 -> 0 | F97: ='Raw BS'!E59 -> 0 | G97: ='Raw BS'!F59 -> 0 | H97: ='Raw BS'!G59 -> 0 | I97: ='Raw BS'!H59 -> 0 | J97: ='Raw BS'!I59 -> 0 | ... L97: ='Raw BS'!K59 -> 0 | AL97: ROIC | AM97: =AV28 -> 0.084095813
B98: Employee Stock Options / Others | C98: ='Raw BS'!B60 -> 0 | D98: ='Raw BS'!C60 -> 0 | E98: ='Raw BS'!D60 -> 0 | F98: ='Raw BS'!E60 -> 0 | G98: ='Raw BS'!F60 -> 0 | H98: ='Raw BS'!G60 -> 0 | I98: ='Raw BS'!H60 -> 0 | J98: ='Raw BS'!I60 -> 0 | ... L98: ='Raw BS'!K60 -> 0.81 | AL98: Cash Conversion Cycle | AM98: =AV41 -> 411.57619
B99: Share Application Money Pending Allotment | C99: ='Raw BS'!B61 -> 0.12 | D99: ='Raw BS'!C61 -> 0 | E99: ='Raw BS'!D61 -> 0 | F99: ='Raw BS'!E61 -> 0 | G99: ='Raw BS'!F61 -> 0 | H99: ='Raw BS'!G61 -> 0 | I99: ='Raw BS'!H61 -> 0 | J99: ='Raw BS'!I61 -> 0 | ... L99: ='Raw BS'!K61 -> 0 | AL99: CFO | AM99: =AV64 -> 437.18
B100: Total Stockholders’ Equity | C100: ='Raw BS'!B62 -> 1063.62 | D100: ='Raw BS'!C62 -> 2680.08 | E100: ='Raw BS'!D62 -> 2619.91 | F100: ='Raw BS'!E62 -> 2531.35 | G100: ='Raw BS'!F62 -> 2556.83 | H100: ='Raw BS'!G62 -> 2618.41 | I100: ='Raw BS'!H62 -> 2435.3 | J100: ='Raw BS'!I62 -> 2438.3 | ... L100: ='Raw BS'!K62 -> 2717.44 | AL100: FCFF | AM100: =AV65 -> 96.25
...

Sheet Projected FCF
B1: Scenario | C1: 1
C3: Historical | F3: Projected
C4: 2024 | D4: 2025 | E4: 2026 | F4: 2027 | G4: 2028 | H4: 2029 | I4: 2030 | J4: 2031
B5: Sales | C5: ='Reform Stat, Ratio, GROWTH'!AH3 -> 1785.11 | D5: ='Reform Stat, Ratio, GROWTH'!AI3 -> 2110.97 | E5: ='Reform Stat, Ratio, GROWTH'!AJ3 -> 2201.85 | F5: =E5*(1+F24) -> 2422.035 | G5: =F5*(1+G24) -> 2640.0182 | H5: =G5*(1+H24) -> 2851.2196 | I5: =H5*(1+I24) -> 3050.805 | J5: =I5*(1+J24) -> 3233.8533
B6: COGS | C6: ='Reform Stat, Ratio, GROWTH'!AH4 -> 736.7 | D6: ='Reform Stat, Ratio, GROWTH'!AI4 -> 863.67 | E6: ='Reform Stat, Ratio, GROWTH'!AJ4 -> 799.99 | F6: =F5*F25 -> 956.82665 | G6: =G5*G25 -> 1042.9411 | H6: =H5*H25 -> 1126.3763 | I6: =I5*I25 -> 1205.2227 | J6: =J5*J25 -> 1277.536
B7: Gross Profit | C7: =C5-C6 -> 1048.41 | D7: =D5-D6 -> 1247.3 | E7: =E5-E6 -> 1401.86 | F7: =F5-F6 -> 1465.2083 | G7: =G5-G6 -> 1597.0771 | H7: =H5-H6 -> 1724.8433 | I7: =I5-I6 -> 1845.5823 | J7: =J5-J6 -> 1956.3172
B9: SG&A | C9: ='Reform Stat, Ratio, GROWTH'!AH5 -> 961.53 | D9: ='Reform Stat, Ratio, GROWTH'!AI5 -> 982.44 | E9: ='Reform Stat, Ratio, GROWTH'!AJ5 -> 997.13 | F9: =F26*F5 -> 1176.2182 | G9: =G26*G5 -> 1282.0778 | H9: =H26*H5 -> 1353.4972 | I9: =I26*I5 -> 1470.4601 | J9: =J26*J5 -> 1554.7625
B10: EBITDA | C10: =C7-C9 -> 86.88 | D10: =D7-D9 -> 264.86 | E10: =E7-E9 -> 404.73 | F10: =F7-F9 -> 288.99017 | G10: =G7-G9 -> 314.99928 | H10: =H7-H9 -> 371.34604 | I10: =I7-I9 -> 375.1222 | J10: =J7-J9 -> 401.55473
B11: EBITDA Margin % | C11: =C10/C5 -> 0.04866927 | D11: =D10/D5 -> 0.12546839 | E11: =E10/E5 -> 0.18381361 | F11: =F10/F5 -> 0.11931709 | G11: =G10/G5 -> 0.11931709 | H11: =H10/H5 -> 0.13024112 | I11: =I10/I5 -> 0.12295843 | J11: =J10/J5 -> 0.12417222
B13: Depreciation & Amortization | C13: ='Reform Stat, Ratio, GROWTH'!AH7 -> 123.16 | D13: ='Reform Stat, Ratio, GROWTH'!AI7 -> 124.56 | E13: ='Reform Stat, Ratio, GROWTH'!AJ7 -> 125.12 | F13: =F19*F30 -> 333.18806 | G13: =G19*G30 -> 298.18337 | H13: =H19*H30 -> 322.03804 | I13: =I19*I30 -> 344.5807 | J13: =J19*J30 -> 365.25554
B14: EBIT | C14: =C10-C13 -> -36.28 | D14: =D10-D13 -> 140.3 | E14: =E10-E13 -> 279.61 | F14: =F10-F13 -> -44.197892 | G14: =G10-G13 -> 16.815913 | H14: =H10-H13 -> 49.308007 | I14: =I10-I13 -> 30.541502 | J14: =J10-J13 -> 36.299184
B15: Taxes (30.0%) | C15: =30%*C14 -> -10.884 | D15: =30%*D14 -> 42.09 | E15: =30%*E14 -> 83.883 | F15: =F14*0.3 -> -13.259368 | G15: =G14*0.3 -> 5.0447739 | H15: =H14*0.3 -> 14.792402 | I15: =I14*0.3 -> 9.1624506 | J15: =J14*0.3 -> 10.889755
B16: Tax-effected EBIT | C16: =C14-C15 -> -25.396 | D16: =D14-D15 -> 98.21 | E16: =E14-E15 -> 195.727 | F16: =F14-F15 -> -30.938525 | G16: =G14-G15 -> 11.771139 | H16: =H14-H15 -> 34.515605 | I16: =I14-I15 -> 21.379051 | J16: =J14-J15 -> 25.409429
B18: Depreciation and Amortization | C18: =C13 -> 123.16 | D18: =D13 -> 124.56 | E18: =E13 -> 125.12 | F18: =F13 -> 333.18806 | G18: =G13 -> 298.18337 | H18: =H13 -> 322.03804 | I18: =I13 -> 344.5807 | J18: =J13 -> 365.25554
B19: Capital Expenditures | C19: ='Reform Stat, Ratio, GROWTH'!BG4 -> 22.55 | D19: ='Reform Stat, Ratio, GROWTH'!BH4 -> 137.36 | E19: ='Reform Stat, Ratio, GROWTH'!BI4 -> 123.04 | F19: =F29*F5 -> 135.344 | G19: =G29*G5 -> 121.12478 | H19: =H29*H5 -> 130.81476 | I19: =I29*I5 -> 139.97179 | J19: =J29*J5 -> 148.3701
B20: Change in working capital | C20: ='Reform Stat, Ratio, GROWTH'!BG21 -> 141.09 | D20: ='Reform Stat, Ratio, GROWTH'!BH21 -> 298.71 | E20: ='Reform Stat, Ratio, GROWTH'!BI21 -> 14.59 | F20: =(F5-E5)*F31 -> 255.85932 | G20: =(G5-F5)*G31 -> 253.30073 | H20: =(H5-G5)*H31 -> 245.42026 | I20: =(I5-H5)*I31 -> 231.92215 | J20: =(J5-I5)*J31 -> 212.70574
B21: Free Cash Flow | C21: =C16+C18-C19-C20 -> -65.876 | D21: =D16+D18-D19-D20 -> -213.3 | E21: =E16+E18-E19-E20 -> 183.217 | F21: =F16+F18-F19-F20 -> -88.953787 | G21: =G16+G18-G19-G20 -> -64.470999 | H21: =H16+H18-H19-H20 -> -19.681379 | I21: =I16+I18-I19-I20 -> -5.9341884 | J21: =J16+J18-J19-J20 -> 29.589129
B23: Operating Assumptions
B24: Sales Growth | C24: NA | D24: =(D5-C5)/C5 -> 0.18254337 | E24: =(E5-D5)/D5 -> 0.043051299 | F24: =CHOOSE($C$1,F36,F37,F38) -> 0.1 | G24: =CHOOSE($C$1,G36,G37,G38) -> 0.09 | H24: =CHOOSE($C$1,H36,H37,H38) -> 0.08 | I24: =CHOOSE($C$1,I36,I37,I38) -> 0.07 | J24: =CHOOSE($C$1,J36,J37,J38) -> 0.06
B25: COGS (% of sales) | C25: =C6/C5 -> 0.41269165 | D25: =D6/D5 -> 0.40913419 | E25: =E6/E5 -> 0.36332629 | F25: =AVERAGE(C25:E25) -> 0.39505071 | G25: =F25 -> 0.39505071 | H25: =G25 -> 0.39505071 | I25: =H25 -> 0.39505071 | J25: =I25 -> 0.39505071
B26: SG&A (% of sales) | C26: =C9/C5 -> 0.53863908 | D26: =D9/D5 -> 0.46539742 | E26: =E9/E5 -> 0.45286009 | F26: =AVERAGE(C26:E26) -> 0.4856322 | G26: =F26 -> 0.4856322 | H26: =AVERAGE(E26:G26) -> 0.47470816 | I26: =AVERAGE(F26:H26) -> 0.48199085 | J26: =AVERAGE(G26:I26) -> 0.48077707
B28: Primary Expenditure Assumptions
B29: CapEx (% of sales) | C29: =C19/C5 -> 0.012632275 | D29: =D19/D5 -> 0.065069613 | E29: =E19/E5 -> 0.055880282 | F29: =E29 -> 0.055880282 | G29: =F29-1% -> 0.045880282 | H29: =G29 -> 0.045880282 | I29: =H29 -> 0.045880282 | J29: =I29 -> 0.045880282
B30: Depreciation & Amortization (% of CapEx) | C30: =C13/C19 -> 5.4616408 | D30: =D13/D19 -> 0.90681421 | E30: =E13/E19 -> 1.0169051 | F30: =AVERAGE(C30:E30) -> 2.4617867 | G30: =F30 -> 2.4617867 | H30: =G30 -> 2.4617867 | I30: =H30 -> 2.4617867 | J30: =I30 -> 2.4617867
B31: Change in Working Capital (% of ∆ sales) | C31: =IFERROR(C20/(C5-'Reform Stat, Ratio, GROWTH'!AG3),"") -> 0.31914316 | D31: =D20/(D5-C5) -> 0.91668201 | E31: =E20/(E5-D5) -> 0.16054137 | F31: ='Reform Stat, Ratio, GROWTH'!BJ37 -> 1.1620198 | G31: =F31 -> 1.1620198 | H31: =G31 -> 1.1620198 | I31: =H31 -> 1.1620198 | J31: =I31 -> 1.1620198
B33: Rupees values are in crore. FY2026 is actual from Unichem Annual Report; FY2027 onward is projected. | L33: Data / assumption note | M33: FY2026 actual from Unichem annual report; FY2027 10% guidance; FY2028–FY2031 taper assumptions 9%, 8%, 7%, 6%.
M34: CapEx and working-capital assumptions are model-derived; no unsupported historical numbers are inserted.
B35: Scenario building (Sales growth)
B36: Base-1 | F36: 0.1 | G36: 0.09 | H36: 0.08 | I36: 0.07 | J36: 0.06 | L36: FY2027 10% guidance; FY2028-31 taper assumptions.
B37: Worst-2 | F37: =F36-2% -> 0.08 | G37: =G36-2% -> 0.07 | H37: =H36-2% -> 0.06 | I37: =I36-2% -> 0.05 | J37: =J36-2% -> 0.04 | L37: Worst case = base - 2%
B38: Best-3 | F38: =F36+2% -> 0.12 | G38: =G36+2% -> 0.11 | H38: =H36+2% -> 0.1 | I38: =I36+2% -> 0.09 | J38: =J36+2% -> 0.08 | L38: Best case = base + 2%

Sheet Perpetual growth Vs EVEBITDA
A1: Perpetuity Growth Method | I1: EBITDA Multiple Method
A2: WACC | B2: =WACC!V8 -> 0.10574418 | I2: WACC | J2: =WACC!V8 -> 0.10574418
A3: Terminal Growth Rate | B3: ='Reform Stat, Ratio, GROWTH'!BJ29 -> 0.069449632 | I3: Existing EBITDA Multple | J3: ='Relative Valuation'!S13/'Relative Valuation'!U13 -> 10.659347
A4: Perpetuity Multiple | B4: =(1+B3)/(B2-B3) -> 29.465849 | I4: Exit EBITDA | J4: ='Projected FCF'!J10 -> 401.55473
A7: Years into the future | B7: 1 | C7: 2 | D7: 3 | E7: 4 | F7: 5 | I7: Years into the future | J7: 1 | K7: 2 | L7: 3 | M7: 4 | N7: 5
A8: FCF | B8: ='Projected FCF'!F21 -> -88.953787 | C8: ='Projected FCF'!G21 -> -64.470999 | D8: ='Projected FCF'!H21 -> -19.681379 | E8: ='Projected FCF'!I21 -> -5.9341884 | F8: ='Projected FCF'!J21 -> 29.589129 | I8: FCF | J8: ='Projected FCF'!F21 -> -88.953787 | K8: ='Projected FCF'!G21 -> -64.470999 | L8: ='Projected FCF'!H21 -> -19.681379 | M8: ='Projected FCF'!I21 -> -5.9341884 | N8: ='Projected FCF'!J21 -> 29.589129
A9: NPV | B9: =B8/(1+$B$2)^B7 -> -80.446986 | C9: =C8/(1+$B$2)^C7 -> -52.729672 | D9: =D8/(1+$B$2)^D7 -> -14.557659 | E9: =E8/(1+$B$2)^E7 -> -3.9695629 | F9: =F8/(1+$B$2)^F7 -> 17.900241 | I9: NPV | J9: =J8/(1+$J$2)^J7 -> -80.446986 | K9: =K8/(1+$J$2)^K7 -> -52.729672 | L9: =L8/(1+$J$2)^L7 -> -14.557659 | M9: =M8/(1+$J$2)^M7 -> -3.9695629 | N9: =N8/(1+$J$2)^N7 -> 17.900241
A10: NPV of 5-years FCF | B10: =SUM(B9:F9) -> -133.80364 | I10: NPV of 5-years FCF | J10: =SUM(J9:N9) -> -133.80364
A11: Terminal Value of FCF | B11: =F8*B4 -> 871.86881 | I11: Terminal Value Using EBITDA | J11: =J4*J3 -> 4280.3112
A12: PV of TV (Discounted 5 Years) | B12: =B11/(1+B2)^5 -> 527.44579 | I12: PV of TV (Discounted 5 Years) | J12: =J11/(1+J2)^5 -> 2589.4172
A14: Enterprise Value | B14: =B10+B12 -> 393.64215 | I14: Enterprise Value | J14: =J12+J10 -> 2455.6136
A17: PV of TV as % of EV | B17: =B12/B14 -> 1.3399119 | I17: PV of TV as % of EV | J17: =J12/J14 -> 1.0544889
A18: Terminal Year FCF | B18: ='Projected FCF'!J21 -> 29.589129 | I18: Terminal Year EBITDA | J18: =J4 -> 401.55473
A19: WACC | B19: =B2 -> 0.10574418 | I19: WACC | J19: =J2 -> 0.10574418
A20: Terminal Growth Rate | B20: =B3 -> 0.069449632 | I20: EBIDTA Multiple | J20: =J3 -> 10.659347
A21: Terminal Year EBITDA | B21: ='Projected FCF'!J10 -> 401.55473 | I21: Terminal Year FCF | J21: ='Projected FCF'!J21 -> 29.589129
A22: Implied EBITDA Terminal Multiple | B22: =(B18*(1+B20))/(B21*(B19-B20)) -> 2.1712328 | I22: Implied Growth Rate | J22: =((J18*J20*J19)-J21)/((J18*J20)+J21) -> 0.098152819
A25: Add: Total Financial assets | B25: ='Reform Stat, Ratio, GROWTH'!AJ53 -> 294.72 | I25: Add: Total Financial assets | J25: ='Reform Stat, Ratio, GROWTH'!AJ53 -> 294.72
A26: Less: Total Financial Obligations | B26: ='Reform Stat, Ratio, GROWTH'!AJ67 -> 500.15 | I26: Less: Total Financial Obligations | J26: ='Reform Stat, Ratio, GROWTH'!AJ67 -> 500.15
A27: Less: Non-controlling interest | B27: ='Reform Stat, Ratio, GROWTH'!AJ72 -> 0 | I27: Less: Non-controlling interest | J27: ='Reform Stat, Ratio, GROWTH'!AJ72 -> 0
A28: Value of Equity | B28: =B14+B25-B26-B27 -> 188.21215 | I28: Value of Equity | J28: =J14+J25-J26-J27 -> 2250.1836
A29: No. of Shares (in Cr) | B29: ='Relative Valuation'!M13/10000000 -> 7.040575 | I29: No. of Shares (in Cr) | J29: ='Relative Valuation'!M13/10000000 -> 7.040575
A30: Value per Share | B30: =B28/B29 -> 26.732497 | I30: Value per Share | J30: =J28/J29 -> 319.60225
A33: Sensitivity Analysis | I33: Sensitivity Analysis
C34: WACC | K34: WACC
B35: =B30 -> 26.732497 | C35: 0.1 | D35: 0.11 | E35: 0.12 | F35: 0.13 | G35: 0.14 | J35: =J30 -> 319.60225 | K35: 0.1 | L35: 0.11 | M35: 0.12 | N35: 0.13 | O35: 0.14
A36: Growth | B36: 0.06 | C36: =((SUMPRODUCT($B$8:$F$8,1/(1+C$35)^$B$7:$F$7)+($F$8*(1+$B36)/(C$35-$B36))/(1+C$35)^5)+$B$25-$B$26-$B$27)/$B$29 -> 20.854178 | D36: =((SUMPRODUCT($B$8:$F$8,1/(1+D$35)^$B$7:$F$7)+($F$8*(1+$B36)/(D$35-$B36))/(1+D$35)^5)+$B$25-$B$26-$B$27)/$B$29 -> 4.7767375 | E36: =((SUMPRODUCT($B$8:$F$8,1/(1+E$35)^$B$7:$F$7)+($F$8*(1+$B36)/(E$35-$B36))/(1+E$35)^5)+$B$25-$B$26-$B$27)/$B$29 -> -5.7696847 | F36: =((SUMPRODUCT($B$8:$F$8,1/(1+F$35)^$B$7:$F$7)+($F$8*(1+$B36)/(F$35-$B36))/(1+F$35)^5)+$B$25-$B$26-$B$27)/$B$29 -> -13.162161 | G36: =((SUMPRODUCT($B$8:$F$8,1/(1+G$35)^$B$7:$F$7)+($F$8*(1+$B36)/(G$35-$B36))/(1+G$35)^5)+$B$25-$B$26-$B$27)/$B$29 -> -18.58891 | I36: EV/EBITDA | J36: 12 | K36: =((SUMPRODUCT($J$8:$N$8,1/(1+K$35)^$J$7:$N$7)+($J$4*$J36)/(1+K$35)^5)+$J$25-$J$26-$J$27)/$J$29 -> 376.66814 | L36: =((SUMPRODUCT($J$8:$N$8,1/(1+L$35)^$J$7:$N$7)+($J$4*$J36)/(1+L$35)^5)+$J$25-$J$26-$J$27)/$J$29 -> 358.06783 | M36: =((SUMPRODUCT($J$8:$N$8,1/(1+M$35)^$J$7:$N$7)+($J$4*$J36)/(1+M$35)^5)+$J$25-$J$26-$J$27)/$J$29 -> 340.45456 | N36: =((SUMPRODUCT($J$8:$N$8,1/(1+N$35)^$J$7:$N$7)+($J$4*$J36)/(1+N$35)^5)+$J$25-$J$26-$J$27)/$J$29 -> 323.76808 | O36: =((SUMPRODUCT($J$8:$N$8,1/(1+O$35)^$J$7:$N$7)+($J$4*$J36)/(1+O$35)^5)+$J$25-$J$26-$J$27)/$J$29 -> 307.95228
B37: 0.065 | C37: =((SUMPRODUCT($B$8:$F$8,1/(1+C$35)^$B$7:$F$7)+($F$8*(1+$B37)/(C$35-$B37))/(1+C$35)^5)+$B$25-$B$26-$B$27)/$B$29 -> 31.105863 | D37: =((SUMPRODUCT($B$8:$F$8,1/(1+D$35)^$B$7:$F$7)+($F$8*(1+$B37)/(D$35-$B37))/(1+D$35)^5)+$B$25-$B$26-$B$27)/$B$29 -> 10.928784 | E37: =((SUMPRODUCT($B$8:$F$8,1/(1+E$35)^$B$7:$F$7)+($F$8*(1+$B37)/(E$35-$B37))/(1+E$35)^5)+$B$25-$B$26-$B$27)/$B$29 -> -1.7229192 | F37: =((SUMPRODUCT($B$8:$F$8,1/(1+F$35)^$B$7:$F$7)+($F$8*(1+$B37)/(F$35-$B37))/(1+F$35)^5)+$B$25-$B$26-$B$27)/$B$29 -> -10.329668 | G37: =((SUMPRODUCT($B$8:$F$8,1/(1+G$35)^$B$7:$F$7)+($F$8*(1+$B37)/(G$35-$B37))/(1+G$35)^5)+$B$25-$B$26-$B$27)/$B$29 -> -16.515317 | J37: 13 | K37: =((SUMPRODUCT($J$8:$N$8,1/(1+K$35)^$J$7:$N$7)+($J$4*$J37)/(1+K$35)^5)+$J$25-$J$26-$J$27)/$J$29 -> 412.08199 | L37: =((SUMPRODUCT($J$8:$N$8,1/(1+L$35)^$J$7:$N$7)+($J$4*$J37)/(1+L$35)^5)+$J$25-$J$26-$J$27)/$J$29 -> 391.91495 | M37: =((SUMPRODUCT($J$8:$N$8,1/(1+M$35)^$J$7:$N$7)+($J$4*$J37)/(1+M$35)^5)+$J$25-$J$26-$J$27)/$J$29 -> 372.81739 | N37: =((SUMPRODUCT($J$8:$N$8,1/(1+N$35)^$J$7:$N$7)+($J$4*$J37)/(1+N$35)^5)+$J$25-$J$26-$J$27)/$J$29 -> 354.72405 | O37: =((SUMPRODUCT($J$8:$N$8,1/(1+O$35)^$J$7:$N$7)+($J$4*$J37)/(1+O$35)^5)+$J$25-$J$26-$J$27)/$J$29 -> 337.57414
B38: 0.07 | C38: =((SUMPRODUCT($B$8:$F$8,1/(1+C$35)^$B$7:$F$7)+($F$8*(1+$B38)/(C$35-$B38))/(1+C$35)^5)+$B$25-$B$26-$B$27)/$B$29 -> 44.774778 | D38: =((SUMPRODUCT($B$8:$F$8,1/(1+D$35)^$B$7:$F$7)+($F$8*(1+$B38)/(D$35-$B38))/(1+D$35)^5)+$B$25-$B$26-$B$27)/$B$29 -> 18.618843 | E38: =((SUMPRODUCT($B$8:$F$8,1/(1+E$35)^$B$7:$F$7)+($F$8*(1+$B38)/(E$35-$B38))/(1+E$35)^5)+$B$25-$B$26-$B$27)/$B$29 -> 3.1331993 | F38: =((SUMPRODUCT($B$8:$F$8,1/(1+F$35)^$B$7:$F$7)+($F$8*(1+$B38)/(F$35-$B38))/(1+F$35)^5)+$B$25-$B$26-$B$27)/$B$29 -> -7.0250926 | G38: =((SUMPRODUCT($B$8:$F$8,1/(1+G$35)^$B$7:$F$7)+($F$8*(1+$B38)/(G$35-$B38))/(1+G$35)^5)+$B$25-$B$26-$B$27)/$B$29 -> -14.145497 | J38: 14 | K38: =((SUMPRODUCT($J$8:$N$8,1/(1+K$35)^$J$7:$N$7)+($J$4*$J38)/(1+K$35)^5)+$J$25-$J$26-$J$27)/$J$29 -> 447.49585 | L38: =((SUMPRODUCT($J$8:$N$8,1/(1+L$35)^$J$7:$N$7)+($J$4*$J38)/(1+L$35)^5)+$J$25-$J$26-$J$27)/$J$29 -> 425.76207 | M38: =((SUMPRODUCT($J$8:$N$8,1/(1+M$35)^$J$7:$N$7)+($J$4*$J38)/(1+M$35)^5)+$J$25-$J$26-$J$27)/$J$29 -> 405.18022 | N38: =((SUMPRODUCT($J$8:$N$8,1/(1+N$35)^$J$7:$N$7)+($J$4*$J38)/(1+N$35)^5)+$J$25-$J$26-$J$27)/$J$29 -> 385.68002 | O38: =((SUMPRODUCT($J$8:$N$8,1/(1+O$35)^$J$7:$N$7)+($J$4*$J38)/(1+O$35)^5)+$J$25-$J$26-$J$27)/$J$29 -> 367.196
B39: 0.075 | C39: =((SUMPRODUCT($B$8:$F$8,1/(1+C$35)^$B$7:$F$7)+($F$8*(1+$B39)/(C$35-$B39))/(1+C$35)^5)+$B$25-$B$26-$B$27)/$B$29 -> 63.911258 | D39: =((SUMPRODUCT($B$8:$F$8,1/(1+D$35)^$B$7:$F$7)+($F$8*(1+$B39)/(D$35-$B39))/(1+D$35)^5)+$B$25-$B$26-$B$27)/$B$29 -> 28.506061 | E39: =((SUMPRODUCT($B$8:$F$8,1/(1+E$35)^$B$7:$F$7)+($F$8*(1+$B39)/(E$35-$B39))/(1+E$35)^5)+$B$25-$B$26-$B$27)/$B$29 -> 9.0684553 | F39: =((SUMPRODUCT($B$8:$F$8,1/(1+F$35)^$B$7:$F$7)+($F$8*(1+$B39)/(F$35-$B39))/(1+F$35)^5)+$B$25-$B$26-$B$27)/$B$29 -> -3.1196851 | G39: =((SUMPRODUCT($B$8:$F$8,1/(1+G$35)^$B$7:$F$7)+($F$8*(1+$B39)/(G$35-$B39))/(1+G$35)^5)+$B$25-$B$26-$B$27)/$B$29 -> -11.41109 | J39: 15 | K39: =((SUMPRODUCT($J$8:$N$8,1/(1+K$35)^$J$7:$N$7)+($J$4*$J39)/(1+K$35)^5)+$J$25-$J$26-$J$27)/$J$29 -> 482.9097 | L39: =((SUMPRODUCT($J$8:$N$8,1/(1+L$35)^$J$7:$N$7)+($J$4*$J39)/(1+L$35)^5)+$J$25-$J$26-$J$27)/$J$29 -> 459.60919 | M39: =((SUMPRODUCT($J$8:$N$8,1/(1+M$35)^$J$7:$N$7)+($J$4*$J39)/(1+M$35)^5)+$J$25-$J$26-$J$27)/$J$29 -> 437.54305 | N39: =((SUMPRODUCT($J$8:$N$8,1/(1+N$35)^$J$7:$N$7)+($J$4*$J39)/(1+N$35)^5)+$J$25-$J$26-$J$27)/$J$29 -> 416.63599 | O39: =((SUMPRODUCT($J$8:$N$8,1/(1+O$35)^$J$7:$N$7)+($J$4*$J39)/(1+O$35)^5)+$J$25-$J$26-$J$27)/$J$29 -> 396.81786
B40: 0.08 | C40: =((SUMPRODUCT($B$8:$F$8,1/(1+C$35)^$B$7:$F$7)+($F$8*(1+$B40)/(C$35-$B40))/(1+C$35)^5)+$B$25-$B$26-$B$27)/$B$29 -> 92.615978 | D40: =((SUMPRODUCT($B$8:$F$8,1/(1+D$35)^$B$7:$F$7)+($F$8*(1+$B40)/(D$35-$B40))/(1+D$35)^5)+$B$25-$B$26-$B$27)/$B$29 -> 41.689018 | E40: =((SUMPRODUCT($B$8:$F$8,1/(1+E$35)^$B$7:$F$7)+($F$8*(1+$B40)/(E$35-$B40))/(1+E$35)^5)+$B$25-$B$26-$B$27)/$B$29 -> 16.487525 | F40: =((SUMPRODUCT($B$8:$F$8,1/(1+F$35)^$B$7:$F$7)+($F$8*(1+$B40)/(F$35-$B40))/(1+F$35)^5)+$B$25-$B$26-$B$27)/$B$29 -> 1.5668038 | G40: =((SUMPRODUCT($B$8:$F$8,1/(1+G$35)^$B$7:$F$7)+($F$8*(1+$B40)/(G$35-$B40))/(1+G$35)^5)+$B$25-$B$26-$B$27)/$B$29 -> -8.2209474 | J40: 16 | K40: =((SUMPRODUCT($J$8:$N$8,1/(1+K$35)^$J$7:$N$7)+($J$4*$J40)/(1+K$35)^5)+$J$25-$J$26-$J$27)/$J$29 -> 518.32355 | L40: =((SUMPRODUCT($J$8:$N$8,1/(1+L$35)^$J$7:$N$7)+($J$4*$J40)/(1+L$35)^5)+$J$25-$J$26-$J$27)/$J$29 -> 493.45631 | M40: =((SUMPRODUCT($J$8:$N$8,1/(1+M$35)^$J$7:$N$7)+($J$4*$J40)/(1+M$35)^5)+$J$25-$J$26-$J$27)/$J$29 -> 469.90588 | N40: =((SUMPRODUCT($J$8:$N$8,1/(1+N$35)^$J$7:$N$7)+($J$4*$J40)/(1+N$35)^5)+$J$25-$J$26-$J$27)/$J$29 -> 447.59195 | O40: =((SUMPRODUCT($J$8:$N$8,1/(1+O$35)^$J$7:$N$7)+($J$4*$J40)/(1+O$35)^5)+$J$25-$J$26-$J$27)/$J$29 -> 426.43973

Sheet Football field
B1: Metric | C1: Min | D1: Width | E1: Max | F1: Mid | G1: Weights | H1: Product
B2: EV/Sales | C2: ='Relative Valuation'!X23 -> 822.79254 | D2: =E2-C2 -> 907.36841 | E2: ='Relative Valuation'!X24 -> 1730.161 | F2: ='Relative Valuation'!X22 -> 1281.5207 | G2: 0 | H2: =F2*G2 -> 0
B3: EV/EBITDA | C3: ='Relative Valuation'!Z23 -> 4613.6337 | D3: =E3-C3 -> 2153.3197 | E3: ='Relative Valuation'!Z24 -> 6766.9533 | F3: ='Relative Valuation'!Z22 -> 951.82483 | G3: 0.2 | H3: =F3*G3 -> 190.36497
B4: EV/EBIT | C4: ='Relative Valuation'!Y23 -> 5761.6971 | D4: =E4-C4 -> 3520.9267 | E4: ='Relative Valuation'!Y24 -> 9282.6238 | F4: ='Relative Valuation'!Y22 -> 941.61963 | G4: 0 | H4: =F4*G4 -> 0
B5: P/E | C5: ='Relative Valuation'!AA23 -> 304.9423 | D5: =E5-C5 -> 1214.0343 | E5: ='Relative Valuation'!AA24 -> 1518.9766 | F5: ='Relative Valuation'!AA22 -> 1168.406 | G5: 0 | H5: =F5*G5 -> 0
B6: P/B | C6: ='Relative Valuation'!AB23 -> 1244.5341 | D6: =E6-C6 -> 876.94676 | E6: ='Relative Valuation'!AB24 -> 2121.4809 | F6: ='Relative Valuation'!AB22 -> 1606.4371 | G6: 0 | H6: =F6*G6 -> 0
B7: DCF - TV as Stable growth | C7: ='Perpetual growth Vs EVEBITDA'!G36 -> -18.58891 | D7: =E7-C7 -> 111.20489 | E7: ='Perpetual growth Vs EVEBITDA'!C40 -> 92.615978 | F7: ='Perpetual growth Vs EVEBITDA'!B30 -> 26.732497 | G7: 0 | H7: =F7*G7 -> 0
B8: DCF - TV as Av EV/EBITDA | C8: ='Perpetual growth Vs EVEBITDA'!O36 -> 307.95228 | D8: =E8-C8 -> 210.37128 | E8: ='Perpetual growth Vs EVEBITDA'!K40 -> 518.32355 | F8: ='Perpetual growth Vs EVEBITDA'!J30 -> 319.60225 | G8: 0.8 | H8: =F8*G8 -> 255.6818
B9: 52 Week High/Low | C9: ='Relative Valuation'!O13 -> 280 | D9: =E9-C9 -> 407.2 | E9: ='Relative Valuation'!N13 -> 687.2 | F9: ='Relative Valuation'!Q13 -> 581.35 | G9: 0 | H9: =F9*G9 -> 0
B10: Average | C10: =AVERAGE(C3:C9) -> 1784.8815 | E10: =AVERAGE(E3:E9) -> 2998.3106 | G10: =SUM(G2:G9) -> 1 | H10: =SUM(H3:H9) -> 446.04676
B13: Current market price | C13: ='Relative Valuation'!Q13 -> 581.35
B14: Target Price | C14: =H10 -> 446.04676
